Workbook

Sheet Master
A4: Report Of | B4: XT INDIA
A5: From Date | B5: 46113
A6: To Date | B6: 46142 | C6: =UPPER(TEXT(B6,"MMM-YY")) -> APR-26
A8: Sr No | B8: Name of the Report | C8: Link
A10: 1 | B10: Petty Cash | C10: Petty Cash
A12: 2 | B12: Cheque Issued | C12: Cheque issued
A14: 3 | B14: Bank Book | C14: Bank book
A16: 4 | B16: Bank Statement | C16: Bank Statement
A18: 5 | B18: Direct Expenses - ICE | C18: DE-ICE
A20: 6 | B20: Direct Expenses - XT | C20: DE-XT
A22: 7 | B22: General Expenses | C22: General
A24: 8 | B24: Employees Loan Repayment | C24: Employees Loan Repayment
A26: 9 | B26: Inter Company Transfer | C26: Inter Company Transfer
A28: 10 | B28: Crew on Board | C28: CB
A30: 11 | B30: Cost Report | C30: CR
A32: 12 | B32: Consolidated Cost Report | C32: Consolidated CR

Sheet Cheque issued
B2: DBS | C2: Cheque issued for the month of APR 2026
B4: DATE | C4: CHEQUE NO | D4: PARTICULARS | E4: AMOUNT | F4: Type of Exp | G4: Nature of Expenses
B5: 46134 | C5: 000016 | D5: Universal Currency Exchange (I) Pvt Ltd - 16 BY IWCLG/000016/UNIVERSAL CURRENCY EXCHAN/HDFC BANK LTD. | E5: 113050 | F5: Travelling Expenses | G5: Bill no. 6200155 dt. 20.04.26 USD 1200 for rate 93.90 to vessel visit - Cape med
D7: TOTAL | E7: =SUM(E5:E6) -> 113050
B10: AXIS | C10: Cheque issued for the month of APR 2026
B12: DATE | C12: CHEQUE NO | D12: PARTICULARS | E12: AMOUNT | F12: Type of Exp | G12: Nature of Expenses
D13: No cheque issued during the month | E13: 0
D15: TOTAL | E15: =SUM(E13:E14) -> 0

Sheet Petty Cash
B2: XT SHIPS MANAGEMENT INDIA PVT LTD
B6: XT Ships Management India Pvt.Ltd.
B7: Petty Cash for the month of APR 2026
B8: DATE | C8: NAME | E8: AMT Recevd in USD | F8: Amt Rece | G8: Amt paid | H8: Balance
D10: Bal Cd fwd of 31.03.26 | H10: 5145
B11: 01.04.26 | C11: Santhana Clyobas Prosper Rajiv | D11: Being paid for transport services for spare carried to Vessel Blue Sky. Remaining excess amount handed over to India office & same has been credited to ICE DA. | F11: 3400 | G11: 0 | H11: =H10+F11 -> 8545
B12: 07.04.26 | C12: Cash Paid | D12: Airtel sim service fee, lunch expenses paid towards chair old & new pick up on Saturday, sanjay towards MIDC for Knife pick up | G12: 1151 | H12: =H11-G12 -> 7394
B13: 12.04.26 | C13: Bajrang Auto Service | D13: Petrol expenses | G13: 1000 | H13: =H12-G13 -> 6394
B14: 14.04.26 | C14: Siddhivinayak Medical | D14: sanitary pad Siddhivinayak medical | G14: 565 | H14: =H13-G14 -> 5829
B15: 14.04.26 | C15: Sanjay | D15: ambedkar jayanti closed tso sanjay brought fruits | G15: 870 | H15: =H14-G15 -> 4959
B16: 14.04.26 | C16: Cash Paid | D16: dishwash salt & Liquid set | G16: 1201 | H16: =H15-G16 -> 3758
B17: 16.04.26 | C17: Cash Paid | D17: Lunch for officer | G17: 340 | H17: =H16-G17 -> 3418
B18: 20.04.26 | C18: Sai Palace Hotel | D18: Lunch for cadet & officer | G18: 624 | H18: =H17-G18 -> 2794
B19: 21.04.26 | C19: Sai Palace Hotel | D19: Lunch for cadet & officer | G19: 624 | H19: =H18-G19 -> 2170
B20: 28.04.26 | C20: We Fast | D20: Conversion letter to Axis bank | G20: 420 | H20: =H19-G20 -> 1750
B21: 28.04.26 | C21: Sai Palace Hotel | D21: Rohit Suthar & officer | G21: 851 | H21: =H20-G21 -> 899
B22: 30.04.26 | C22: Sai Palace Hotel | D22: Rohit Suthar & officer | G22: 926 | H22: =H21-G22 -> -27
B23: 30.04.26 | C23: Axis Bank 6132 | D23: (No narration in Tally - Contra 4: cash withdrawn from Axis Bank 455010200006132) | F23: 20000 | G23: 0 | H23: =H22+F23 -> 19973
E28: =E10 -> 0 | G28: =SUM(G11:G27) -> 8572

Sheet DE-XT
A1: XT Ships Management India Pvt.Ltd. | P1: 26 APR
P2: XT
A5: ="XT MANAGEMENT INC - for the month of "&Master!C6 -> XT MANAGEMENT INC - for the month of APR-26
B7: Company Name | C7: Total Amount (INR) | D7: Total Amount (USD)
B8: XT | C8: =$J$156 -> 3036049.3 | D8: =$L$156 -> 31977.533
B9: ICE | C9: ='DE-ICE'!C9 -> 918550 | D9: ='DE-ICE'!D9 -> 9674.7318
B10: Grand Total | C10: =SUM(C8:C9) -> 3954599.3 | D10: =SUM(D8:D9) -> 41652.265
A12: SR | B12: NAME | C12: RANK | D12: VESSEL To /From | E12: TYPE OF EXPENSE | F12: BOOKED BY | G12: BILL RECEIVED DATE | H12: NAME OF COMPANY | I12: Inv no. | J12: Taxable Amount | K12: Exch rate as on 04.05.2026 | L12: Amount in USD | M12: GST | N12: Invoice Amount | O12: Eligibility | P12: DOC REF NO
A13: 1 | E13: Amount transferred from DBS AC 0001 towards Cash advance as per instructions from principals (USD 1100) | G13: 46113 | H13: Vincent Alexander | I13: 1 | J13: 102531 | K13: =Forex!$C$2 -> 94.9432 | L13: =J13/K13 -> 1079.9194 | M13: 0 | N13: =J13+M13 -> 102531 | O13: Non-GST | P13: 26 APR /XT/1186
A14: 2 | E14: JAN TO MAR 26 - PAID on 15.04.26 | G14: 46127 | H14: Seafarers Welfare Fund Society | I14: 3 | J14: 372967 | K14: =Forex!$C$2 -> 94.9432 | L14: =J14/K14 -> 3928.3171 | M14: 0 | N14: =J14+M14 -> 372967 | O14: Non-GST | P14: 26 APR /XT/2
A15: 3 | E15: Cook training & orientation program with room stay from 10.04.26 to 14.04.26 | G15: 46120 | H15: SIR Mohamed Yusuf Seamen Welfare Foundation | I15: CAT-26-27/6 | J15: 367950 | K15: =Forex!$C$2 -> 94.9432 | L15: =J15/K15 -> 3875.475 | M15: 66231 | N15: =J15+M15 -> 434181 | O15: Eligible | P15: 26 APR /XT/3
A16: 4 | E16: 20908 dt. 08.04.26 IKEA 365 + Knife S3 for Cook training pragramme Reimb | G16: 46120 | H16: IKEA | I16: 20908 | J16: 21049 | K16: =Forex!$C$2 -> 94.9432 | L16: =J16/K16 -> 221.70097 | M16: 0 | N16: =J16+M16 -> 21049 | O16: Non-GST | P16: 26 APR /XT/4
A17: 5 | E17: Cook Cap & Apron for Trainee Cooks - 20 Nos | G17: 46125 | H17: Best Marine Pvt Ltd | I17: 2627-AD364 | J17: 16188 | K17: =Forex!$C$2 -> 94.9432 | L17: =J17/K17 -> 170.50194 | M17: 0 | N17: =J17+M17 -> 16188 | O17: Non-GST | P17: 26 APR /XT/5
A18: 6 | E18: Courier charges for receiving Mannuals from Synergy office Chennai to Mumbai - India office - 25 Boxes for vessel - MH Arpeggio 13 & MH Adagio 12 against AWB no. D3504359612 | G18: 46132 | H18: Emmar Associates | I18: EA0042/26-27 | J18: 21000 | K18: =Forex!$C$2 -> 94.9432 | L18: =J18/K18 -> 221.18488 | M18: 3780 | N18: =J18+M18 -> 24780 | O18: Eligible | P18: 26 APR /XT/6
A19: 7 | E19: Medical signed off on 13.12.25 due to backache & severe pain in RT leg & hip joint - Sea bird consultation dt/ 18.02.26 , physiotherapy sessions & medications from 18.02.26 to 04.04.26 | G19: 46129 | H19: DIVYA KUMARI PASANTKUMAR TANDEL | I19: 4 | J19: 17307.76 | K19: =Forex!$C$2 -> 94.9432 | L19: =J19/K19 -> 182.29594 | M19: 0 | N19: =J19+M19 -> 17307.76 | O19: Non-GST | P19: 26 APR /XT/7
A20: 8 | E20: Amount transferred from DBS AC 0001 towards Cash advance as per instructions from principals (USD 1057.50) | G20: 46142 | H20: Sujesh Aravindan | I20: 5 | J20: 98569.58 | K20: =Forex!$C$2 -> 94.9432 | L20: =J20/K20 -> 1038.1953 | M20: 0 | N20: =J20+M20 -> 98569.58 | O20: Non-GST | P20: 26 APR /XT/8
A21: 9 | E21: Medical sigend for Ottis media, done left tympanoplasty. Dr. consultation charges & lab test dt. 03.01.26 to 31.03.26 | G21: 46142 | H21: Sea Bird Medicare Pvt. Ltd. | I21: SB/PNI/2627/021 | J21: 3750 | K21: =Forex!$C$2 -> 94.9432 | L21: =J21/K21 -> 39.497299 | M21: 0 | N21: =J21+M21 -> 3750 | O21: Non-GST | P21: 26 APR /XT/9
A22: 10 | E22: Professional fees for board training at Green Forest at Lisas from 21.02.26 to 24.02.26 traveling cost from 19.02.26 to 20.02.26 | G22: 46122 | H22: Shanker Das | I22: 8 | J22: 199100 | K22: =Forex!$C$2 -> 94.9432 | L22: =J22/K22 -> 2097.0433 | M22: 0 | N22: =J22+M22 -> 199100 | O22: Non-GST | P22: 26 APR /XT/10
A23: 11 | E23: Bill no P00417 dt. 24.04.26 Go pro purchase for parwinder singh , same has been handed over to CC ajinkya badekar at sea bird medicare Centre while PJM on 25.04.26 | G23: 46140 | H23: Swiggy | I23: P00417 | J23: 16011 | K23: =Forex!$C$2 -> 94.9432 | L23: =J23/K23 -> 168.63767 | M23: 0 | N23: =J23+M23 -> 16011 | O23: Non-GST | P23: 26 APR /XT/11
A24: 12 | E24: Reimbursment expenses for seafarers signed on/off | G24: 46121 | H24: Creditors for Travelling | I24: 6 | J24: 970593 | K24: =Forex!$C$2 -> 94.9432 | L24: =J24/K24 -> 10222.881 | M24: 0 | N24: =J24+M24 -> 970593 | O24: Non-GST | P24: 626 APR /XT/12
... A138: 126 | E138: REMITTANCE CHARGES - GST ON Fx 0853IT0517861 C317368OCP040126 XT SHIPS MANA XT SHIPS MANAGEMENT INDIA USD 689062.76 at INR93.2100000000 UETR Ref:7953f2b8-08c7-4e89-be58-cb51bcc0691c | G138: 46114 | H138: DBS Bank Ltd | I138: NA | J138: 10800 | K138: =Forex!$C$2 -> 94.9432 | L138: =J138/K138 -> 113.75222 | M138: 0 | N138: =J138+M138 -> 10800 | O138: Non-GST | P138: Payment 2 dt. 02.04.26
A156: Total | J156: =SUM(J13:J155) -> 3036049.3 | L156: =SUM(L13:L155) -> 31977.533 | M156: =SUM(M13:M155) -> 72784.48 | N156: =SUM(N13:N155) -> 3108833.8

Sheet DE-ICE
A1: =UPPER(" XT Ships Management India Pvt.Ltd.") -> XT SHIPS MANAGEMENT INDIA PVT.LTD. | P1: 26 APR
P2: ICE
A5: ="International Crewing Experts Inc. - for the month of "&Master!C6 -> International Crewing Experts Inc. - for the month of APR-26
B7: Company Name | C7: Total Amount (INR) | D7: Total Amount (USD)
B8: XT | C8: ='DE-XT'!C8 -> 3036049.3 | D8: ='DE-XT'!D8 -> 31977.533
B9: ICE | C9: =$J$80 -> 918550 | D9: =$L$80 -> 9674.7318
B10: Grand Total | C10: =SUM(C8:C9) -> 3954599.3 | D10: =SUM(D8:D9) -> 41652.265
A12: SR.NO | B12: NAME | C12: RANK | D12: VESSEL To /From | E12: TYPE OF EXPENSE | F12: BOOKED BY | G12: BILL RECEIVED DATE | H12: NAME OF COMPANY | I12: Inv no. | J12: Taxable Amount | K12: Exch rate as on 04.05.2026 | L12: Amount in USD | M12: GST | N12: Invoice Amount | O12: Eligibility | P12: Doc No
A13: 1 | E13: Fruit basket to the crew residence as a Get Well Soon gesture for speedy recovery & well wishes Tarkeshwar Singh | G13: 46142 | H13: Creative Gifting Solutions Pvt Ltd | I13: CGS/2026-27/14 | J13: 2000 | K13: =Forex!$C$2 -> 94.9432 | L13: =J13/K13 -> 21.065226 | M13: 0 | N13: =J13+M13 -> 2000 | O13: Non-GST | P13: =+$P$1&"/"&$P$2&"/"&A13 -> 26 APR/ICE/1
A14: 2 | E14: Fruit basket to the crew residence as a Get Well Soon gesture for speedy recovery & well wishes Kiran Kumar | G14: 46142 | H14: Creative Gifting Solutions Pvt Ltd | I14: CGS/2026-27/14 | J14: 2000 | K14: =Forex!$C$2 -> 94.9432 | L14: =J14/K14 -> 21.065226 | M14: 0 | N14: =J14+M14 -> 2000 | O14: Non-GST | P14: =+$P$1&"/"&$P$2&"/"&A14 -> 26 APR/ICE/2
A15: 3 | E15: JAN TO MAR 26 - PAID on 15.04.26 | G15: 46127 | H15: Seafarers Welfare Fund Society | I15: 3 | J15: 372083 | K15: =Forex!$C$2 -> 94.9432 | L15: =J15/K15 -> 3919.0063 | M15: 0 | N15: =J15+M15 -> 372083 | O15: Non-GST | P15: =+$P$1&"/"&$P$2&"/"&A15 -> 26 APR/ICE/3
A16: 4 | E16: Being paid for transport services for spare carried to Vessel Blue Sky. Remaining excess amount handed over to India office & same has been credited to ICE DA. Santhana Clyobas Prosper Rajiv | G16: 46127 | H16: Santhana Clyobas Prosper Rajiv | I16: 2 | J16: -3400 | K16: =Forex!$C$2 -> 94.9432 | L16: =J16/K16 -> -35.810885 | M16: 0 | N16: =J16+M16 -> -3400 | O16: Non-GST | P16: =+$P$1&"/"&$P$2&"/"&A16 -> 26 APR/ICE/4
A17: 5 | E17: Course fees towards LCHS dt. 29.04.26 | G17: 46142 | H17: Prakriti Marine Service | I17: PMS/IND/2026-020 | J17: 14500 | K17: =Forex!$C$2 -> 94.9432 | L17: =J17/K17 -> 152.72289 | M17: 2610 | N17: =J17+M17 -> 17110 | O17: Eligible | P17: =+$P$1&"/"&$P$2&"/"&A17 -> 26 APR/ICE/5
A18: 6 | E18: Netherland visa charges 9360/- VFS 2662/-appointment 1770/- Print 150/- Ticket 500/- Service fee 750/- GST 135-/ | G18: 46142 | H18: ATPI India Private Ltd | I18: 16616007 | J18: 15192 | K18: =Forex!$C$2 -> 94.9432 | L18: =J18/K18 -> 160.01146 | M18: 135 | N18: =J18+M18 -> 15327 | O18: Eligible | P18: =+$P$1&"/"&$P$2&"/"&A18 -> 26 APR/ICE/6
A19: 7 | E19: Insurance cancellation charges | G19: 46142 | H19: ATPI India Private Ltd | I19: 16616009 | J19: 350 | K19: =Forex!$C$2 -> 94.9432 | L19: =J19/K19 -> 3.6864146 | M19: 0 | N19: =J19+M19 -> 350 | O19: Non-GST | P19: =+$P$1&"/"&$P$2&"/"&A19 -> 26 APR/ICE/7
A20: 8 | E20: Netherland visa charges 9360/- VFS 1325/-appointment 1770/- Service fee 750/- GST 135-/ | G20: 46142 | H20: ATPI India Private Ltd | I20: 16615661 | J20: 13205 | K20: =Forex!$C$2 -> 94.9432 | L20: =J20/K20 -> 139.08316 | M20: 135 | N20: =J20+M20 -> 13340 | O20: Eligible | P20: =+$P$1&"/"&$P$2&"/"&A20 -> 26 APR/ICE/8
A21: 9 | E21: Insurance cancellation charges | G21: 46142 | H21: ATPI India Private Ltd | I21: 16615664 | J21: 350 | K21: =Forex!$C$2 -> 94.9432 | L21: =J21/K21 -> 3.6864146 | M21: 0 | N21: =J21+M21 -> 350 | O21: Non-GST | P21: =+$P$1&"/"&$P$2&"/"&A21 -> 26 APR/ICE/9
A22: 10 | E22: Belgium Visa 9270/- VFS appointment 2575/- VFS service 1445/- Print 20/- service fee 750/- GST 135/- | G22: 46142 | H22: ATPI India Private Ltd | I22: 16615489 | J22: 14060 | K22: =Forex!$C$2 -> 94.9432 | L22: =J22/K22 -> 148.08854 | M22: 135 | N22: =J22+M22 -> 14195 | O22: Eligible | P22: =+$P$1&"/"&$P$2&"/"&A22 -> 26 APR/ICE/10
A23: 11 | E23: Insurance cancellation charges | G23: 46142 | H23: ATPI India Private Ltd | I23: 16593579 | J23: 350 | K23: =Forex!$C$2 -> 94.9432 | L23: =J23/K23 -> 3.6864146 | M23: 0 | N23: =J23+M23 -> 350 | O23: Non-GST | P23: =+$P$1&"/"&$P$2&"/"&A23 -> 26 APR/ICE/11
A24: 12 | E24: Belgium Visa 9270/- VFS appointment 2575/- VFS service 1445/- Print 20/- service fee 750/- GST 135/- | G24: 46142 | H24: ATPI India Private Ltd | I24: 16615547 | J24: 14060 | K24: =Forex!$C$2 -> 94.9432 | L24: =J24/K24 -> 148.08854 | M24: 135 | N24: =J24+M24 -> 14195 | O24: Eligible | P24: =+$P$1&"/"&$P$2&"/"&A24 -> 26 APR/ICE/12
... A61: 49 | E61: Prejoning medical expenses dt. 05.03.26 Liberia Flag | G61: 46142 | H61: Sea Bird Medicare Pvt. Ltd. | I61: SB/PEME2627/0054 | J61: 3000 | K61: =Forex!$C$2 -> 94.9432 | L61: =J61/K61 -> 31.59784 | M61: 0 | N61: =J61+M61 -> 3000 | O61: Non-GST | P61: =+$P$1&"/"&$P$2&"/"&A61 -> 26 APR/ICE/49
A62: 50 | E62: REMITTANCE CHARGES - GST ON Fx 0853IT0517991 IH0304003743479 XT SHIPS MANAG XT SHIPS MANAGEMENT INDIA PRIVATE L USD 661177.49 at INR92.2212000000 UETR Ref:18ff3daa-e309-4f86-8567-516a07923557 | G62: 46120 | H62: DBS Bank Ltd | I62: NA | J62: 10800 | K62: =Forex!$C$2 -> 94.9432 | L62: =J62/K62 -> 113.75222 | M62: 0 | N62: =J62+M62 -> 10800 | O62: Non-GST | P62: Payment 211 dt. 08.04.26
A80: Total | J80: =SUM(J13:J79) -> 918550 | L80: =SUM(L13:L79) -> 9674.7318 | M80: =SUM(M13:M79) -> 4030 | N80: =SUM(N13:N79) -> 922580

Sheet Bank book-AXIS 
B3: AXIS BANK STATEMENT - A/c 455010200006132 (01.04.2026 to 12.05.2026; balance as on 30.04.2026 Rs 4,36,445.38)

Sheet Bank Book- DBS
A1: Account Details for : | B1: XT SHIPS MANAGEMENT INDIA PRIVATE LIMITED 8853210000030001 INR
A2: Statement as at : | B2: 01-Apr-2026 | C2: To : | D2: 30-Apr-2026
A3: Opening Balance : | B3: 5961993.1
A4: Ledger Balance : | B4: 7261701.3
A5: Available Balance : | B5: 7261701.3
A6: Date | B6: Value Date | C6: Transaction Description 1 | D6: Transaction Description 2 | E6: Debit | F6: Credit | G6: Running Balance
A7: 01-Apr-2026 | B7: 01-Apr-2026 | C7: TRANSFER | D7: NEFT 0811OP6171943970 Global Traders AXIS BANK UTIB0001062 REF Bill 780 dt. 30.03.26 Chair 52pcs Global Traders INR 141128 | E7: 141128 | G7: 5820865.1
A8: 02-Apr-2026 | B8: 02-Apr-2026 | C8: TRANSFER | D8: REMITTANCE CHARGES - GST ON Fx 0853IT0517861 C317368OCP040126 XT SHIPS MANA XT SHIPS MANAGEMENT INDIA USD 689062.76 at INR93.2100000000 UETR Ref:7953f2b8-08c7-4e89-be58-cb51bcc0691c | E8: 10800 | G8: 5810065.1
A9: 02-Apr-2026 | B9: 02-Apr-2026 | C9: TRANSFER | D9: NEFT 0811OP6172030374 XT Ships Management India Pv AXIS BANK UTIB0000004 REF TDS PF MAR 26 XT Ships Management India Pvt Ltd INR 2650000 | E9: 2650000 | G9: 3160065.1
A10: 06-Apr-2026 | B10: 06-Apr-2026 | C10: TRANSFER | D10: NEFT 0811OP6172226661 MOHAMMED SHAHID NAUSHAD BORK IDBI BANK IBKL0000574 REF MOHAMMED SHAHID NAUSHAD BORKAR INR 17020 | E10: 17020 | G10: 3143045.1
A11: 06-Apr-2026 | B11: 06-Apr-2026 | C11: TRANSFER | D11: NEFT 0811OP6172226665 EDWIN VINOTH M STATE BANK OF INDIA SBIN000931 REF EDWIN VINOTH M INR 3324 | E11: 3324 | G11: 3139721.1
A12: 06-Apr-2026 | B12: 06-Apr-2026 | C12: TRANSFER | D12: NEFT 0811OP6172226660 Pranshu Gupta ICICI BANK LIMITED ICIC0007237 REF Pranshu Gupta INR 3983 | E12: 3983 | G12: 3135738.1
A13: 06-Apr-2026 | B13: 06-Apr-2026 | C13: TRANSFER | D13: NEFT 0811OP6172226684 Hitesh Kumar Ninganiya STATE BANK OF INDIA SBIN000239 REF Hitesh Kumar Ninganiya INR 3240 | E13: 3240 | G13: 3132498.1
A14: 06-Apr-2026 | B14: 06-Apr-2026 | C14: TRANSFER | D14: NEFT 0811OP6172226693 ARUN DINAKAR ICICI BANK LIMITED ICIC0000807 REF ARUN DINAKAR INR 5404 | E14: 5404 | G14: 3127094.1
A15: 06-Apr-2026 | B15: 06-Apr-2026 | C15: TRANSFER | D15: NEFT 0811OP6172226690 Jorawar singh PUNJAB NATIONAL BANK PUNB00745 REF Jorawar singh INR 4650 | E15: 4650 | G15: 3122444.1
A16: 06-Apr-2026 | B16: 06-Apr-2026 | C16: TRANSFER | D16: NEFT 0811OP6172226678 Gopinath A STATE BANK OF INDIA SBIN000966 REF Gopinath A INR 3500 | E16: 3500 | G16: 3118944.1
A17: 06-Apr-2026 | B17: 06-Apr-2026 | C17: TRANSFER | D17: NEFT 0811OP6172226694 Manju bisht AXIS BANK UTIB0000093 REF Manju bisht INR 6865 | E17: 6865 | G17: 3112079.1
A18: 06-Apr-2026 | B18: 06-Apr-2026 | C18: TRANSFER | D18: NEFT 0811OP6172226675 Dinny Abraham ICICI BANK LIMITED ICIC0001952 REF Dinny Abraham INR 11778 | E18: 11778 | G18: 3100301.1
... A205: 06-Apr-2026 | B205: 06-Apr-2026 | C205: TRANSFER | D205: NEFT 0811OP6172226868 Tanmay Anil More BANK OF BARODA BARB0TISGAO REF Tanmay Anil More INR 1300 | E205: 1300 | G205: 2105924.1
A206: 06-Apr-2026 | B206: 06-Apr-2026 | C206: TRANSFER | D206: NEFT RETURN 0811OP6172226867 XT SHIPS MANAGEMENT I 0811OP6172226867 AXIS BANK NOT COMPLIANT Org Txn dated 2026 04 06 17:08:46.9 Arun Nadumane INR 2500 | F206: 2500 | G206: 2108424.1
A207: 06-Apr-2026 | B207: 06-Apr-2026 | C207: TRANSFER | D207: NEFT RETURN 0811OP6172226711 XT SHIPS MANAGEMENT I 0811OP6172226711 BANK OF BAROD INCORRECT ACCOUNT NUMBER Org Txn dated 2026 04 06 Mehul Kumar BARB0BALODA INR 4411 | F207: 4411 | G207: 2112835.1
A208: 06-Apr-2026 | B208: 06-Apr-2026 | C208: TRANSFER | D208: NEFT RETURN 0811OP6172226746 XT SHIPS MANAGEMENT I 0811OP6172226746 CANARA BANK INCORRECT ACCOUNT NUMBER Org Txn dated 2026 04 06 SUGIRTHA J INR 4410 | F208: 4410 | G208: 2117245.1
A209: 06-Apr-2026 | B209: 06-Apr-2026 | C209: TRANSFER | D209: NEFT RETURN 0811OP6172226725 XT SHIPS MANAGEMENT I 0811OP6172226725 STANDARD CHAR NOT COMPLIANT Org Txn dated 2026 04 06 17:37:26.3 Shubham Sanjay Chavan INR 15540 | F209: 15540 | G209: 2132785.1
A210: 06-Apr-2026 | B210: 06-Apr-2026 | C210: TRANSFER | D210: NEFT RETURN 0811OP6172226724 XT SHIPS MANAGEMENT I 0811OP6172226724 STANDARD CHAR NOT COMPLIANT Org Txn dated 2026 04 06 17:39:09.5 Shubham Sanjay Chavan INR 700 | F210: 700 | G210: 2133485.1
A211: 06-Apr-2026 | B211: 06-Apr-2026 | C211: TRANSFER | D211: NEFT RETURN 0811OP6172226681 XT SHIPS MANAGEMENT I 0811OP6172226681 HSBC BANK NOT COMPLIANT Org Txn dated 2026 04 06 17:42:51.4 Edwin Santhis INR 15540 | F211: 15540 | G211: 2149025.1
A212: 06-Apr-2026 | B212: 06-Apr-2026 | C212: TRANSFER | D212: NEFT RETURN 0811OP6172226823 XT SHIPS MANAGEMENT I 0811OP6172226823 HDFC BANK NOT COMPLIANT Org Txn dated 2026 04 06 18:24:03.2 Parthkumar Kamleshbhai Darji INR 4350 | F212: 4350 | G212: 2153375.1
A213: 06-Apr-2026 | B213: 06-Apr-2026 | C213: TRANSFER | D213: NEFT 0811OP6172226768 Ankush kumar CANARA BANK CNRB0002063 REF Ankush kumar INR 3600 | E213: 3600 | G213: 2149775.1
A214: 06-Apr-2026 | B214: 06-Apr-2026 | C214: TRANSFER | D214: NEFT 0811OP6172226769 Ankush kumar CANARA BANK CNRB0002063 REF Ankush kumar INR 3600 | E214: 3600 | G214: 2146175.1
A215: 06-Apr-2026 | B215: 06-Apr-2026 | C215: TRANSFER | D215: NEFT 0811OP6172226701 Hitesh Kumar Ninganiya STATE BANK OF INDIA SBIN000239 REF Hitesh Kumar Ninganiya INR 4600 | E215: 4600 | G215: 2141575.1
A216: 06-Apr-2026 | B216: 06-Apr-2026 | C216: TRANSFER | D216: NEFT 0811OP6172226700 Hitesh Kumar Ninganiya STATE BANK OF INDIA SBIN000239 REF Hitesh Kumar Ninganiya INR 4600 | E216: 4600 | G216: 2136975.1
A217: 07-Apr-2026 | B217: 07-Apr-2026 | C217: TRANSFER | D217: NEFT 0811OP6172334374 Dilip Thore BANK OF INDIA BKID0000176 REF office shifting work And Sat Sunday attend f Dilip Thore INR 5000 | E217: 5000 | G217: 2131975.1
A218: 07-Apr-2026 | B218: 07-Apr-2026 | C218: TRANSFER | D218: NEFT 0811OP6172334377 Aaradhya Enterprises MAHANAGAR COOPERATIVE BANK MCB REF 070426 6MM acrylic box cover for XT Maritime Aaradhya Enterprises INR 10000 | E218: 10000 | G218: 2121975.1
A219: 07-Apr-2026 | B219: 07-Apr-2026 | C219: TRANSFER | D219: NEFT 0811OP6172334373 Sanjay Joshi BANK OF INDIA BKID0001202 REF office shifting work And Sat Sunday attend f Sanjay Joshi INR 5000 | E219: 5000 | G219: 2116975.1
A220: 07-Apr-2026 | B220: 07-Apr-2026 | C220: TRANSFER | D220: NEFT 0811OP6172334372 SCENIUZ INFORMATION TECHNOLO AXIS BANK UTIB0000328 REF SCENIUZ2627001 dt 010426 Data AnalystDesign A SCENIUZ INFORMATION TECHNOLOGY PRIV INR 139200 | E220: 139200 | G220: 1977775.1
A221: 07-Apr-2026 | B221: 07-Apr-2026 | C221: TRANSFER | D221: NEFT 0811OP6172334375 Tata Teleservices M Ltd STANDARD CHARTERED BANK SCBL00 REF Account number 991640709 is nearing 9446 of th Tata Teleservices M Ltd INR 26544 | E221: 26544 | G221: 1951231.1
A222: 07-Apr-2026 | B222: 07-Apr-2026 | C222: TRANSFER | D222: NEFT 0811OP6172334376 Anil Kumar Sood AXIS BANK UTIB0000455 REF Bharatkosh for renewing licence RPSL receipt n Anil Kumar Sood INR 40477.64 | E222: 40477.64 | G222: 1910753.4
A223: 07-Apr-2026 | B223: 07-Apr-2026 | C223: TRANSFER | D223: NEFT 0811OP6172334371 Max Computers SARASWAT COOPERATIVE BANK LIMI REF MAX20264503 dt 020326 monitor armsportsaccess Max Computers INR 524628 | E223: 524628 | G223: 1386125.4
A224: 08-Apr-2026 | B224: 08-Apr-2026 | C224: TRANSFER | D224: REMITTANCE CHARGES - GST ON Fx 0853IT0517991 IH0304003743479 XT SHIPS MANAG XT SHIPS MANAGEMENT INDIA PRIVATE L USD 661177.49 at INR92.2212000000 UETR Ref:18ff3daa-e309-4f86-8567-516a07923557 | E224: 10800 | G224: 1375325.4
... A232: 10-Apr-2026 | B232: 10-Apr-2026 | C232: TRANSFER | D232: NEFT 0811OP6172524584 Indian Register of Shipping BANK OF BARODA BARB0POWBOM REF RPSL Annual audit 2025 advance Invoice pendin Indian Register of Shipping INR 24190 | E232: 24190 | G232: 762106.74
A233: 10-Apr-2026 | B233: 10-Apr-2026 | C233: TRANSFER | D233: TRANSFER 0853RF0606406 XT SHIPS MANAGEMENT INDIA PRIV XT SHIPS MANAGEMENT INDIA PRIVATE L INR 3281127.35 at USD92.3195000000 | F233: 3281127.4 | G233: 4043234.1
A234: 10-Apr-2026 | B234: 10-Apr-2026 | C234: TRANSFER | D234: REMITTANCE CHARGES - GST ON Fx 0853RF0606406 Conversion 35541 XT SHIPS MANA XT SHIPS MANAGEMENT INDIA PRIVATE L INR 3281127.35 at USD92.3195000000 | E234: 1400.6 | G234: 4041833.5
A235: 13-Apr-2026 | B235: 13-Apr-2026 | C235: TRANSFER | D235: NEFT 0811OP6172644297 Rahul Pawar STATE BANK OF INDIA SBIN000188 REF 1355 dt. 10.04.26 Food reimb towards purchase Rahul Pawar INR 4116 | E235: 4116 | G235: 4037717.5
A236: 14-Apr-2026 | B236: 14-Apr-2026 | C236: TRANSFER | D236: NEFT 0811OP6172720789 Space Creation KOTAK MAHINDRA BANK LIMITED KK REF Space creation Space Creation INR 2000000 | E236: 2000000 | G236: 2037717.5
A237: 15-Apr-2026 | B237: 15-Apr-2026 | C237: TRANSFER | D237: RTGS 0853OI6008350972 SEAFARERS WELFARE FUND SOCIE CANARA BANK CNRB0000239 REF- SWFS JAN-MAR 26 /SWFS JAN 26 TO MAR 26 SEAFARERS WELFARE FUND SOCIETY INR 745050 | E237: 745050 | G237: 1292667.5
A238: 17-Apr-2026 | B238: 17-Apr-2026 | C238: TRANSFER | D238: NEFT 0811OP6172889481 Adani Electricity Mumbai Ltd HDFC BANK HDFC0004989 REF Bill no. 100581704220 dt. 13.04.26 for Mar 26 Adani Electricity Mumbai Ltd INR 60050 | E238: 60050 | G238: 1232617.5
A239: 20-Apr-2026 | B239: 20-Apr-2026 | C239: TRANSFER | D239: Term Deposit-8853260420049595-XT SHIPS MANAGEMENT INDIA PRIVATE LIMITED | E239: 500000 | G239: 732617.49
A240: 21-Apr-2026 | B240: 21-Apr-2026 | C240: TRANSFER | D240: NEFT 0811OP6173042979 TIMES EDUTECH AND EVENTS LIM HDFC BANK HDFC0000060 REF Sujeet Course IIMI CPPM (project Management) TIMES EDUTECH AND EVENTS LIMITED INR 51840 | E240: 51840 | G240: 680777.49
A241: 21-Apr-2026 | B241: 21-Apr-2026 | C241: TRANSFER | D241: NEFT 0811OP6173043000 Tata Teleservices M Ltd STANDARD CHARTERED BANK SCBL00 REF 2172260641 dt. 03.04.26 for march 26 Tata Teleservices M Ltd INR 24190 | E241: 24190 | G241: 656587.49
A242: 21-Apr-2026 | B242: 21-Apr-2026 | C242: TRANSFER | D242: NEFT 0811OP6173043065 DIVYA KUMARI PASANTKUMAR TAN INDIAN BANK IDIB000V059 REF Sea bird consultation dt 18.02.26 physiothera DIVYA KUMARI PASANTKUMAR TANDEL INR 17307.76 | E242: 17307.76 | G242: 639279.73
A243: 22-Apr-2026 | B243: 22-Apr-2026 | C243: TRANSFER | D243: 16 BY IWCLG/000016/UNIVERSAL CURRENCY EXCHAN/HDFC BANK LTD. | E243: 113050 | G243: 526229.73
A244: 22-Apr-2026 | B244: 22-Apr-2026 | C244: TRANSFER | D244: REMITTANCE CHARGES - GST ON Fx 0853RF0606788 Convert 48259 XT SHIPS MANAGEM XT SHIPS MANAGEMENT INDIA PRIVATE L INR 4512602.57 at USD93.5080000000 | E244: 1622.27 | G244: 524607.46
A245: 22-Apr-2026 | B245: 22-Apr-2026 | C245: TRANSFER | D245: TRANSFER 0853RF0606788 XT SHIPS MANAGEMENT INDIA PRIV XT SHIPS MANAGEMENT INDIA PRIVATE L INR 4512602.57 at USD93.5080000000 | F245: 4512602.6 | G245: 5037210
A246: 23-Apr-2026 | B246: 23-Apr-2026 | C246: TRANSFER | D246: NEFT 0811OP6173108225 Bosscoder Software Services ICICI BANK LIMITED ICIC0000031 REF Course Data engineer for Yash sukati for the Bosscoder Software Services P Ltd INR 5000 | E246: 5000 | G246: 5032210
A247: 23-Apr-2026 | B247: 23-Apr-2026 | C247: TRANSFER | D247: NEFT 0811OP6173108284 Sir Mohamed Yusuf Seamen Wel INDUSIND BANK INDB0000599 REF CAT 26 27/6 dt. 21.04.26 cook training and ori Sir Mohamed Yusuf Seamen Welfare INR 397386 | E247: 397386 | G247: 4634824
A248: 24-Apr-2026 | B248: 24-Apr-2026 | C248: TRANSFER | D248: NEFT 0811OP6173174991 Shaikh Yaseen Ali SARASWAT COOPERATIVE BANK LIMI REF Friday Lunch 24.04.26 Shaikh Yaseen Ali INR 7400 | E248: 7400 | G248: 4627424
A249: 28-Apr-2026 | B249: 28-Apr-2026 | C249: TRANSFER | D249: NEFT 0811OP6173327460 Kanakia Hotels and Resorts P AXIS BANK UTIB0000328 REF Rohit Suthar booking 29.04.26 to 30.04.26 Kanakia Hotels and Resorts Pvt Ltd INR 13570 | E249: 13570 | G249: 4613854
A250: 30-Apr-2026 | B250: 30-Apr-2026 | C250: TRANSFER | D250: NEFT 0811OP6173423945 XT Ships Management India Pv AXIS BANK UTIB0000004 REF TDS additional payment FY 25 26 XT Ships Management India Pvt Ltd INR 90000 | E250: 90000 | G250: 4523854
A251: 30-Apr-2026 | B251: 30-Apr-2026 | C251: TRANSFER | D251: REMITTANCE CHARGES - GST ON Fx 0853RF0607076 Convert 113489 XT SHIPS MANAGE XT SHIPS MANAGEMENT INDIA PRIVATE L INR 10773000.07 at USD94.9255000000 | E251: 2749.14 | G251: 4521104.9
A252: 30-Apr-2026 | B252: 30-Apr-2026 | C252: TRANSFER | D252: TRANSFER 0853RF0607076 EBICT60430713396 XT SHIPS MANA XT SHIPS MANAGEMENT INDIA PRIVATE L INR 10773000.07 at USD94.9255000000 | F252: 10773000 | G252: 15294105
A253: 30-Apr-2026 | B253: 30-Apr-2026 | C253: TRANSFER | D253: NEFT 0811OP6173440706 Chandni Jaadwa ICICI BANK LIMITED ICIC0001000 REF Chandni Jaadwa INR 138553 | E253: 138553 | G253: 15155552
A254: 30-Apr-2026 | B254: 30-Apr-2026 | C254: TRANSFER | D254: NEFT 0811OP6173440716 Rahul Pawar ICICI BANK LIMITED ICIC0001212 REF Rahul Pawar INR 197454 | E254: 197454 | G254: 14958098
A255: 30-Apr-2026 | B255: 30-Apr-2026 | C255: TRANSFER | D255: NEFT 0811OP6173440727 Shilpa Rajpurkar IDBI BANK IBKL0000059 REF Shilpa Rajpurkar INR 88750 | E255: 88750 | G255: 14869348
A256: 30-Apr-2026 | B256: 30-Apr-2026 | C256: TRANSFER | D256: NEFT 0811OP6173440710 Nivedhana Sabesan HDFC BANK HDFC0001803 REF Nivedhana Sabesan INR 159729 | E256: 159729 | G256: 14709619
A257: 30-Apr-2026 | B257: 30-Apr-2026 | C257: TRANSFER | D257: NEFT 0811OP6173440721 Rutuja Raut AXIS BANK UTIB0000246 REF Rutuja Raut INR 72000 | E257: 72000 | G257: 14637619
A258: 30-Apr-2026 | B258: 30-Apr-2026 | C258: TRANSFER | D258: NEFT 0811OP6173440732 Udayaditya Bharat AXIS BANK UTIB0000125 REF Udayaditya Bharat INR 430666.44 | E258: 430666.44 | G258: 14206953
A259: 30-Apr-2026 | B259: 30-Apr-2026 | C259: TRANSFER | D259: NEFT 0811OP6173440715 Priti Agrawal HDFC BANK HDFC0000355 REF Priti Agrawal INR 106435 | E259: 106435 | G259: 14100518
A260: 30-Apr-2026 | B260: 30-Apr-2026 | C260: TRANSFER | D260: NEFT 0811OP6173440734 Vishwanath Balasubramanian STATE BANK OF INDIA SBIN005137 REF Vishwanath Balasubramanian INR 115760 | E260: 115760 | G260: 13984758
A261: 30-Apr-2026 | B261: 30-Apr-2026 | C261: TRANSFER | D261: NEFT 0811OP6173440725 Shabana Shaikh AXIS BANK UTIB0001346 REF Shabana Shaikh INR 78000 | E261: 78000 | G261: 13906758
A262: 30-Apr-2026 | B262: 30-Apr-2026 | C262: TRANSFER | D262: NEFT 0811OP6173440703 Anil Sood AXIS BANK UTIB0000455 REF Anil Sood INR 321341 | E262: 321341 | G262: 13585417
A263: 30-Apr-2026 | B263: 30-Apr-2026 | C263: TRANSFER | D263: NEFT 0811OP6173440722 Sagar Sonawane ICICI BANK LIMITED ICIC0001212 REF Sagar Sonawane INR 104017.65 | E263: 104017.65 | G263: 13481399
A264: 30-Apr-2026 | B264: 30-Apr-2026 | C264: TRANSFER | D264: NEFT 0811OP6173440707 Girish D Poojary ICICI BANK LIMITED ICIC0006414 REF Girish D Poojary INR 18600 | E264: 18600 | G264: 13462799
... A335: 30-Apr-2026 | B335: 30-Apr-2026 | C335: TRANSFER | D335: NEFT 0811OP6173442654 Vibrant Management Solutions IDBI BANK IBKL0000306 REF VMS2526184 dt 290326 Vibrant Management Solutions INR 25358 | E335: 25358 | G335: 7261701.3
A336: Printed By | B336: RENUKA@INXTSH01
A337: Printed On | B337: 08-May-2026 17:41:59

Sheet Inter Company Transfer
A1: ="Inter-Company Transfer for the month of "&Master!C6 -> Inter-Company Transfer for the month of APR-26
A2: Account Head | B2: Company Name | C2: Receipt/Payment in the books of XT | D2: Amount (INR) | E2: Remarks | F2: Transaction Date
B3: ASManagement Operations India Pvt Ltd | C3: Opening balance | D3: 27363.04 | E3: Outstanding as on 31 Mar 26 (Dr - receivable from ASM) | F3: 46112
B5: Petrol expenses - Ciaz car (Journal 9) | C5: Credit | D5: -2574.87 | E5: Petrol expenses dt. 19.04.26 for Ciaz Car Bajrang Auto Service | F5: 46131
B6: Swiggy - Go Pro purchase (Journal 2) | C6: Credit | D6: -16011 | E6: Bill no P00417 dt. 24.04.26 Go pro purchase for parwinder singh , same has been handed over to CC ajinkya badekar at sea bird medicare Centre while PJM on 25.04.26 | F6: 46140
B7: Airtel group bill - ASM users (Journal 7) | C7: Debit | D7: 3896 | E7: Airtel group bill MF2727I001683891 dt. 24.04.26 from 23.03.26 to 22.04.26User - Rohit Suthar User - Nair User - Priya | F7: 46142
B8: Airtel mobile bills - XT users (Journal 8) | C8: Credit | D8: -4517.46 | E8: Bill no. MF2727I000557247 dt. 09.04.26 for the period 08.03.26 to 07.04.26 Bill no. MF2727I000557544 dt. 09.04.26 for the period 08.03.26 to 07.04.26 Bill no. MF2727I001620777 dt. 24.04.26 for the period 23.03.26 to 22.04.26Bill no. MF2727I001506786 dt. 21.04.26 for the period 20.03.26 to 19.04.26 Bill no. MF2727I001271617 dt. 18.04.26 for the period 17.03.26 to 16.04.26 Bill no. MF2727I001506785 dt. 21.04.26 for the period 20.03.26 to 19.04.26 Bill no. MF2727I001190211 dt. 18.04.26 for the period 17.03.26 to 16.04.26 | F8: 46142
B9: Amazon balance - Go Pro (Journal 10) | C9: Credit | D9: -14990 | E9: Go pro purchase for parwinder singh , same has been amount credited to amazon balance money towards product not available as per order id 408-4163378-1768332 ( total 14990 - Rs 980 ordered as below entry & balance 14010 in XT Ships Amazon account ) 14010-980 order 170607 dt.28.04.26 Toy Metal avenger water bottle for Bipin's Son towards Get well soon dt. 28.04.26 | F9: 46142
C16: Closing balance | D16: =SUM(D3:D10) -> -6834.29

Sheet General
B1: Expenses done for the month of JAN 2026
B2: ACCOUNT HEAD | C2: Company Name | D2: Gross Amt.(Including GST) | E2: REMARKS | F2: BILL RECEIVED DATE | G2: TYPE OF EXPENSES INCLUDED | H2: CGST | I2: SGST | J2: IGST | K2: Net Amt. (Exluding GST)
B4: PROFESSIONAL FEES | C4: GSC Edge Consultancy Pvt Ltd | D4: =K4+SUM(H4:J4) -> 97350 | E4: Bill no. APR2601/26-27 dt. 01.04.26 Professional fees for the month APR 26 | F4: 46113 | G4: Professional Fees - 9982 | H4: 7425 | I4: 7425 | K4: 82500
B5: PROFESSIONAL FEES | C5: GSC Edge Consultancy Pvt Ltd | D5: =K5+SUM(H5:J5) -> 20650 | E5: Bill no.MAR2603/2025-26 dt. 31.03.26 Professional fees for filling & certification PAS6 for half year end 30.09.24, 31.03.25 & 30.09.25, DSC charges for capt anil Sood | F5: 46113 | G5: Professional Fees - 9982 | H5: 1575 | I5: 1575 | K5: 17500
B6: PROFESSIONAL FEES | C6: GSC Edge Consultancy Pvt Ltd | D6: =K6+SUM(H6:J6) -> 17700 | E6: Bill no. APR2603/2026-27 dt. 03.04.2026 Profeesional fees for change in address of new office under shop & establishment act | F6: 46115 | G6: Professional Fees - 9982 | H6: 1350 | I6: 1350 | K6: 15000
B7: PROFESSIONAL FEES | C7: Sceniuz Information Technology Pvt Ltd | D7: =K7+SUM(H7:J7) -> 141600 | E7: SCENIUZ/2627/001 dt. 01.04.26 Data Analyst-Design & Development services for 4month basic 120000x2% = 2400 | F7: 46113 | G7: Professional Fees - 998311 | H7: 10800 | I7: 10800 | K7: 120000
B8: PROFESSIONAL FEES | C8: Bigshare Services Pvt Ltd | D8: =K8+SUM(H8:J8) -> 5900 | E8: Bill no. RT/AP/3195/26-27 dt. 17.04.25 NSDL services - 12month | F8: 46129 | G8: Professional Fees - 9971 | H8: 450 | I8: 450 | K8: 5000
B9: PROFESSIONAL FEES | C9: Bigshare Services Pvt Ltd | D9: =K9+SUM(H9:J9) -> 983 | E9: Bill no. RT/AP/4467/25-26 dt. 21.04.25 NSDL services - 2month | F9: 46133 | G9: Professional Fees - 9971 | H9: 75 | I9: 75 | K9: 833
C10: SUB TOTAL | D10: =SUM(D4:D9) -> 284183
B12: COURIER CHARGES | C12: We Fast | D12: =K12+SUM(H12:J12) -> 420 | E12: Paid in cash towards ASM conversion letter | F12: 46140 | G12: Postage & Courier Exp - 996812 | K12: 420
B14: HOUSEKEEPING CHARGES | C14: Shine Edge Facility Management | D14: =K14+SUM(H14:J14) -> 47985.06 | E14: Bill no SE/HK/008/26-27 dt. 30.04.26 Housekeeping charges for the month Apr 26 for housekeeping - 2 boys | F14: 46142 | G14: House Keeping Expenses - 9985 | H14: 3659.88 | I14: 3659.88 | K14: 40665.3
B16: SECURITY CHARGES | C16: Vibrant Management Solutions | D16: =K16+SUM(H16:J16) -> 25575 | E16: Bill no VMS/26-27/002 dt. 30.04.26 Security charges for the mongh Apr 26 | F16: 46142 | G16: Security Charges | H16: 1950.6 | I16: 1950.6 | K16: 21673.8
B18: ADVERTISMENT | C18: Marex Media Pvt. Ltd. | D18: =K18+SUM(H18:J18) -> 8116 | E18: Bill no 21 dt. 28.04.26 advertisement for Apr 26 | F18: 46140 | G18: Advertisement - 998361 | H18: 619 | I18: 619 | K18: 6878
B20: PANTRY EXPENSES | C20: K.B.C Enterprises | D20: =K20+SUM(H20:J20) -> 124090 | E20: Bill no. 25-26/S00091 dt. 30.04.26 pantry expenses for the month Apr 26 | F20: 46142 | G20: Pantry Expenses | K20: 124090
B22: PRINTING & STATIONERY | C22: K.B.C Enterprises | D22: =K22+SUM(H22:J22) -> 10089 | E22: Bill no. 26-27/S00090 dt. 30.04.26 Stationery , Standee for cook program, visiiting cards, capt anil, ravindra, bipin, gopal, kapil, Uday | F22: 46142 | G22: Printing and Stationery -18% | H22: 769.5 | I22: 769.5 | K22: 8550
B24: ELECTRICITY CHARGES | C24: Adani Electricity | D24: =K24+SUM(H24:J24) -> 60050 | E24: Bill no. 100581704220 dt. 13.04.26 for Mar 26 Atrium office | F24: 46125 | G24: Electricity Expenses | K24: 60050
B26: TRAVEL EXPENSES | C26: Kaushal Tours & Travels | D26: =K26+SUM(H26:J26) -> 7361 | E26: Bill no. KT2526-000016 dt. 17.04.26 Capt Anil - Cook program & local | F26: 46129 | G26: Local Travelling Expenses - 9985 | K26: 7361
B27: TRAVEL EXPENSES | C27: Riya Travels and Tours India Pvt Ltd | D27: =K27+SUM(H27:J27) -> 13240 | E27: Bill no. ADH0426T0010195 dt. 27.04.26 travel from BOM-AMD dt. 30.04.26 for Rohit Suthar office visit | F27: 46139 | G27: Local Travelling Expenses | H27: 13.5 | I27: 13.5 | K27: 13213
B28: TRAVEL EXPENSES | C28: Riya Travels and Tours India Pvt Ltd | D28: =K28+SUM(H28:J28) -> 6403 | E28: Bill no. ADH0426T0011120 dt. 27.04.26 travel from AMD-BOM dt. 290.04.26 for Rohit Suthar office visit | F28: 46139 | G28: Local Travelling Expenses | H28: 13.5 | I28: 13.5 | K28: 6376
B29: TRAVEL EXPENSES | C29: Universal Currency Exchange (I) Pvt Ltd | D29: =K29+SUM(H29:J29) -> 113050 | E29: Bill no. 6200155 dt. 20.04.26 USD 1200 for rate 93.90 to vessel visit - Cape med | F29: 46132 | G29: Travelling Expenses | K29: 113050
C30: SUB TOTAL | D30: =SUM(D26:D29) -> 140054
B32: Health Insurance | C32: Care Health Insurance | D32: =K32+SUM(H32:J32) -> 43598 | E32: Shahina Mother - Sajida / 30940 USD 340 company share & 12658 / 3 month emi | F32: 46119 | G32: Health Insurance for Employees | K32: 43598
B33: Health Insurance | C33: Shahina Mohite (recovery) | D33: =K33+SUM(H33:J33) -> -12658 | E33: Shahina Mother - Sajida / 30940 USD 340 company share & 12658 / 3 month emi | F33: 46119 | G33: Health Insurance for Employees | K33: -12658
C34: SUB TOTAL | D34: =SUM(D32:D33) -> 30940
B36: Society Maintainance | C36: 215 Atrium Co op Premises Society Ltd | D36: =K36+SUM(H36:J36) -> 120874 | E36: 185 dt. 01.04.26 society Maintenance from 01.04.26 to 30.06.26 | F36: 46113 | G36: Society Maintenance Exp | H36: 9219 | I36: 9219 | K36: 102436
B37: Society Maintainance | C37: 215 Atrium Co op Premises Society Ltd | D37: =K37+SUM(H37:J37) -> 7000 | E37: 185 dt. 01.04.26 society Maintenance from 01.04.26 to 30.06.26 | F37: 46113 | G37: Water Charges | K37: 7000
C38: SUB TOTAL | D38: =SUM(D36:D37) -> 127874
B40: PROPERTY TAX | C40: 215 Atrium Co op Premises Society Ltd | D40: =K40+SUM(H40:J40) -> 6000 | E40: 185 dt. 01.04.26 society Maintenance from 01.04.26 to 30.06.26 | F40: 46113 | G40: Property Tax | K40: 6000
B42: PETROL EXPENSES | C42: Bajrang Auto Service | D42: =K42+SUM(H42:J42) -> 1000 | E42: Petrol expenses dt. 12.04.26 Paid in cash | F42: 46124 | G42: Petrol Expenses | K42: 1000
B43: PETROL EXPENSES | C43: Bajrang Auto Service (via ASM) | D43: =K43+SUM(H43:J43) -> 2574.87 | E43: Petrol expenses dt. 19.04.26 for Ciaz Car Bajrang Auto Service | F43: 46131 | G43: Petrol Expenses | K43: 2574.87
C44: SUB TOTAL | D44: =SUM(D42:D43) -> 3574.87
B46: OFFICE GENERAL EXPENSES | C46: Sanjay Joshi | D46: =K46+SUM(H46:J46) -> 5000 | E46: office shifting work Sat Sunday | F46: 46119 | G46: Office Expenses - URD | K46: 5000
B47: OFFICE GENERAL EXPENSES | C47: Dilip | D47: =K47+SUM(H47:J47) -> 5000 | E47: office shifting work Sat Sunday | F47: 46119 | G47: Office Expenses - URD | K47: 5000
B48: OFFICE GENERAL EXPENSES | C48: Cash Paid | D48: =K48+SUM(H48:J48) -> 1151 | E48: Airtel sim service fee, lunch expenses paid towards chair old & new pick up on Saturday, sanjay towards MIDC for Knife pick up | F48: 46119 | G48: Office Expenses - URD | K48: 1151
B49: OFFICE GENERAL EXPENSES | C49: Rahul Pawar (reimb) | D49: =K49+SUM(H49:J49) -> 4116 | E49: Bill no. 1355 dt. 10.04.26 Lunch with purchase team towards Sagar sonawane Farewell | F49: 46125 | G49: Office Expenses - URD | K49: 4116
B50: OFFICE GENERAL EXPENSES | C50: Cash Paid | D50: =K50+SUM(H50:J50) -> 565 | E50: sanitary pad Siddhivinayak medical | F50: 46126 | G50: Office Expenses - URD | K50: 565
B51: OFFICE GENERAL EXPENSES | C51: Cash Paid | D51: =K51+SUM(H51:J51) -> 870 | E51: ambedkar jayanti closed tso sanjay brought fruits | F51: 46126 | G51: Office Expenses - URD | K51: 870
B52: OFFICE GENERAL EXPENSES | C52: Cash Paid | D52: =K52+SUM(H52:J52) -> 1201 | E52: dishwash salt & Liquid set | F52: 46126 | G52: Office Expenses - URD | K52: 1201
B53: OFFICE GENERAL EXPENSES | C53: Cash Paid | D53: =K53+SUM(H53:J53) -> 340 | E53: Lunch for officer | F53: 46128 | G53: Office Expenses - URD | K53: 340
B54: OFFICE GENERAL EXPENSES | C54: Sai Palace Hotel | D54: =K54+SUM(H54:J54) -> 624 | E54: Lunch for cadet & officer paid in cash | F54: 46132 | G54: Office Expenses - URD | K54: 624
B55: OFFICE GENERAL EXPENSES | C55: Sai Palace Hotel | D55: =K55+SUM(H55:J55) -> 624 | E55: Lunch for cadet & officer paid in cash | F55: 46133 | G55: Office Expenses - URD | K55: 624
B56: OFFICE GENERAL EXPENSES | C56: Sai Palace Hotel | D56: =K56+SUM(H56:J56) -> 851 | E56: Bill no. 1712 dt. 29.04.26 lunch for officers - rohit | F56: 46141 | G56: Office Expenses - URD | K56: 851
B57: OFFICE GENERAL EXPENSES | C57: Sai Palace Hotel | D57: =K57+SUM(H57:J57) -> 926 | E57: Bill no. 1779 dt. 30.04.26 lunch for officers - rohit | F57: 46142 | G57: Office Expenses - URD | K57: 926
... B59: OFFICE GENERAL EXPENSES | C59: Sharadhha Fruits | D59: =K59+SUM(H59:J59) -> 7320 | E59: fruit from 10.04.26 to 28.4.26 | F59: 46142 | G59: Office Expenses - URD | K59: 7320
C60: SUB TOTAL | D60: =SUM(D46:D59) -> 49746
B62: OFFICE STAFF WELFARE | C62: Rashmi Foods Pvt Ltd | D62: =K62+SUM(H62:J62) -> 6136 | E62: Bill no. 1806 dt. 02.03.26 breakfast for employees | F62: 46113 | G62: Staff Welfare | K62: 6136
B63: OFFICE STAFF WELFARE | C63: Rashmi Foods Pvt Ltd | D63: =K63+SUM(H63:J63) -> 8231 | E63: Bill no. 1843 dt. 04.03.26 breakfast for employees | F63: 46118 | G63: Staff Welfare | K63: 8231
B64: OFFICE STAFF WELFARE | C64: Rashmi Foods Pvt Ltd | D64: =K64+SUM(H64:J64) -> 8231 | E64: Bill no. 1847 dt. 13.04.26 breakfast for employees | F64: 46125 | G64: Staff Welfare | K64: 8231
B65: OFFICE STAFF WELFARE | C65: Rashmi Foods Pvt Ltd | D65: =K65+SUM(H65:J65) -> 9146 | E65: Bill no. 1854 dt. 20.04.26 breakfast for employees | F65: 46132 | G65: Staff Welfare | K65: 9146
B66: OFFICE STAFF WELFARE | C66: Rashmi Foods Pvt Ltd | D66: =K66+SUM(H66:J66) -> 7169 | E66: Bill no. 1861 dt. 27.04.26 breakfast for employees | F66: 46139 | G66: Staff Welfare | K66: 7169
B67: OFFICE STAFF WELFARE | C67: Kanakia Hotels & Resorts Pvt Ltd | D67: =K67+SUM(H67:J67) -> 24447.5 | E67: Bill no. 1600989 & 983 dt. 29.04.26 Dinner with Rohit, Kapil & Ravindra Paid from Axis Bank | F67: 46141 | G67: Staff Welfare | K67: 24447.5
B68: OFFICE STAFF WELFARE | C68: Diplomat Wine Shop | D68: =K68+SUM(H68:J68) -> 9920 | E68: Paid towards ordered Beer & Juices for office staff for Happy Hours dt 29.04.26 | F68: 46141 | G68: Staff Welfare | K68: 9920
B69: OFFICE STAFF WELFARE | C69: Hatemi Caterers | D69: =K69+SUM(H69:J69) -> 7400 | E69: Bill 843 dt. 29.04.26 Lunch for Friday - office staff | F69: 46141 | G69: Staff Welfare | K69: 7400
B70: OFFICE STAFF WELFARE | C70: Diplomat Wine Shop | D70: =K70+SUM(H70:J70) -> 11120 | E70: Paid towards ordered Beer & Juices for office staff for Happy Hours dt 27.03.26 | F70: 46141 | G70: Staff Welfare | K70: 11120
B71: OFFICE STAFF WELFARE | C71: Domex Technical Info Pvt Ltd | D71: =K71+SUM(H71:J71) -> 9440 | E71: Bill no. DTI/Pschyo/26-27/7078 dt. 29.04.26 Workshop for POSH Session on 27th Apr 2026 in office area | F71: 46141 | G71: Staff Welfare | K71: 9440
B72: OFFICE STAFF WELFARE | C72: Sea Bird Medicare Pvt Ltd | D72: =K72+SUM(H72:J72) -> 2247 | E72: Bill no.0062 dt. 26.04.26 First Aid kit for office area | F72: 46142 | G72: Staff Welfare | K72: 2247
B73: OFFICE STAFF WELFARE | C73: ASM (inter-co) / Amazon | D73: =K73+SUM(H73:J73) -> 14990 | E73: Go pro purchase for parwinder singh , same has been amount credited to amazon balance money towards product not available as per order id 408-4163378-1768332 ( total 14990 - Rs 980 ordered as below entry & balance 14010 in XT Ships Amazon account ) 14010-980 order 170607 dt.28.04.26 Toy Metal avenger water bottle for Bipin's Son towards Get well soon dt. 28.04.26 | F73: 46142 | G73: Staff Welfare | K73: 14990
B74: OFFICE STAFF WELFARE | C74: Amazon (Payroll 58) | D74: =K74+SUM(H74:J74) -> 4660 | E74: BDAY GIFT CARD | F74: 46142 | G74: Gift Card for Employees | K74: 4660
C75: SUB TOTAL | D75: =SUM(D62:D74) -> 123137.5
B77: OFFICE EQUIPMENT EXPENSE | C77: Aaradhya Enterprises | D77: =K77+SUM(H77:J77) -> 10000 | E77: 07.04.26 6MM acrylic box cover for XT - Maritime Sextant demo | F77: 46119 | G77: Office Equipment Expense | K77: 10000
B79: REPAIR & MAINTANANCE | C79: Shubham Engineering Mep Solutions Pvt Ltd | D79: =K79+SUM(H79:J79) -> 110920 | E79: electrical works | F79: 46136 | G79: Office Internal Repairs/ Maintenance | H79: 8460 | I79: 8460 | K79: 94000
B81: OFFICE INTERNET CHARGES | C81: Bharti Airtel | D81: =K81+SUM(H81:J81) -> 47200 | E81: 15314 dt.09.04.26 for 01.04.26 to 30.04.26 | F81: 46142 | G81: Office Internet Expenses | H81: 3600 | I81: 3600 | K81: 40000
B82: OFFICE INTERNET CHARGES | C82: Bharti Airtel | D82: =K82+SUM(H82:J82) -> 19011 | E82: 15314 dt.09.04.26 for 01.04.26 to 30.04.26 | F82: 46142 | G82: Office Internet Expenses | H82: 1450 | I82: 1450 | K82: 16111
C83: SUB TOTAL | D83: =SUM(D81:D82) -> 66211
B85: MOBILE & TELEPHONE CHARGES | C85: Tata Teleservices Ltd | D85: =K85+SUM(H85:J85) -> 24190 | E85: 2172260641 dt. 03.04.26 for Mar 26 landline ac no. 991640709 | F85: 46115 | G85: Telephone & Mobile Charges - Other | K85: 24190
B86: MOBILE & TELEPHONE CHARGES | C86: Bharti Airtel | D86: =K86+SUM(H86:J86) -> 26360.02 | E86: Airtel group bill MF2727I001683891 dt. 24.04.26 from 23.03.26 to 22.04.26 | F86: 46136 | G86: Telephone & Mobile Charges - 998413 | H86: 2010.51 | I86: 2010.51 | K86: 22339
B87: MOBILE & TELEPHONE CHARGES | C87: ASM (inter-co) | D87: =K87+SUM(H87:J87) -> -3896 | E87: Airtel group bill MF2727I001683891 dt. 24.04.26 from 23.03.26 to 22.04.26User - Rohit Suthar User - Nair User - Priya | F87: 46142 | G87: Telephone & Mobile Charges - 998413 | K87: -3896
B88: MOBILE & TELEPHONE CHARGES | C88: ASM (inter-co) | D88: =K88+SUM(H88:J88) -> 4517.46 | E88: Bill no. MF2727I000557247 dt. 09.04.26 for the period 08.03.26 to 07.04.26 Bill no. MF2727I000557544 dt. 09.04.26 for the period 08.03.26 to 07.04.26 Bill no. MF2727I001620777 dt. 24.04.26 for the period 23.03.26 to 22.04.26Bill no. MF2727I001506786 dt. 21.04.26 for the period 20.03.26 to 19.04.26 Bill no. MF2727I001271617 dt. 18.04.26 for the period 17.03.26 to 16.04.26 Bill no. MF2727I001506785 dt. 21.04.26 for the period 20.03.26 to 19.04.26 Bill no. MF2727I001190211 dt. 18.04.26 for the period 17.03.26 to 16.04.26 | F88: 46142 | G88: Telephone & Mobile Charges - Other | K88: 4517.46
C89: SUB TOTAL | D89: =SUM(D85:D88) -> 51171.48
B91: HOTEL EXPENSES | C91: Kanakia Hotels & Resorts Pvt Ltd | D91: =K91+SUM(H91:J91) -> 13570 | E91: 94348287 dt. 28.04.26 Rohit Suthar Booking from 29.04.26 to 30.04.26 Hotel stay | F91: 46140 | G91: Hotel Stay - General Expenses | H91: 1035 | I91: 1035 | K91: 11500
B93: COURSE FEES | C93: Times Edutech and Events Ltd | D93: =K93+SUM(H93:J93) -> 56640 | E93: Prof no. PROF/012 dt. 13.04.26 3rd installment 48000 GST 8640=56640 tds deducted 10 % 4800/-on 48000 basic Sujeet Course - IIMI CPPM (project Managementt)INDORE | F93: 46125 | G93: Online-Course Fees | H93: 4320 | I93: 4320 | K93: 48000
B95: LICENSES & RENEWALS | C95: Bharatkosh | D95: =K95+SUM(H95:J95) -> 40477.64 | E95: Bharatkosh for change of address for RPSL paid on portal Pao shipping mumbai, dt. 08.04.26 Reimb to Capt Anil sood | F95: 46119 | G95: Licenses & Renewals | K95: 40477.64
B96: LICENSES & RENEWALS | C96: Bharatkosh | D96: =K96+SUM(H96:J96) -> 40477.64 | E96: Bharatkosh for renewing licence RPSL receipt no. 0704260018109 paid on portal Pao shipping mumbai, dt. 07.04.26 Reimb to capt anil sood | F96: 46120 | G96: Licenses & Renewals | K96: 40477.64
C97: SUB TOTAL | D97: =SUM(D95:D96) -> 80955.28
B99: ROC FEES | C99: GSC Edge Consultancy Pvt Ltd | D99: =K99+SUM(H99:J99) -> 11700 | E99: Bill no.MAR2603/2025-26 dt. 31.03.26 Professional fees for filling & certification PAS6 for half year end 30.09.24, 31.03.25 & 30.09.25, DSC charges for capt anil Sood | F99: 46113 | G99: ROC Fees | K99: 11700
B101: NETWORKING WORKS | C101: Shubham Engineering Mep Solutions Pvt Ltd | D101: =K101+SUM(H101:J101) -> 863966.5 | E101: server room works | F101: 46136 | G101: Networking Works | H101: 65895.75 | I101: 65895.75 | K101: 732175
B103: PENALTY & CHARGES | C103: EPFO | D103: =K103+SUM(H103:J103) -> 11479 | E103: INB/948000395/EPFO PAYMENT AXIS BANK/NA- PF RELATED | F103: 46121 | G103: Penalty & Charges | K103: 11479
B105: STAFF SALARY | C105: Bipin Jani | D105: =K105+SUM(H105:J105) -> 585408 | E105: APR 26 | F105: 46142 | G105: Payroll 56 - gross earnings | K105: 585408
B106: STAFF SALARY | C106: Amit Shinde | D106: =K106+SUM(H106:J106) -> 112350 | E106: APR 26 | F106: 46142 | G106: Payroll 56 - gross earnings | K106: 112350
B107: STAFF SALARY | C107: Gopal Mishra | D107: =K107+SUM(H107:J107) -> 384174 | E107: APR 26 | F107: 46142 | G107: Payroll 56 - gross earnings | K107: 384174
B108: STAFF SALARY | C108: Rahul Pawar | D108: =K108+SUM(H108:J108) -> 270500 | E108: APR 26 | F108: 46142 | G108: Payroll 56 - gross earnings | K108: 270500
B109: STAFF SALARY | C109: Captain Anil Sood | D109: =K109+SUM(H109:J109) -> 411615 | E109: APR 26 | F109: 46142 | G109: Payroll 56 - gross earnings | K109: 411615
B110: STAFF SALARY | C110: Rajendra Pawar | D110: =K110+SUM(H110:J110) -> 120750 | E110: APR 26 | F110: 46142 | G110: Payroll 56 - gross earnings | K110: 120750
B111: STAFF SALARY | C111: Sampada Shimge | D111: =K111+SUM(H111:J111) -> 68000 | E111: APR 26 | F111: 46142 | G111: Payroll 56 - gross earnings | K111: 68000
B112: STAFF SALARY | C112: Sunny Palav | D112: =K112+SUM(H112:J112) -> 130000 | E112: APR 26 | F112: 46142 | G112: Payroll 56 - gross earnings | K112: 130000
B113: STAFF SALARY | C113: Rohan Gawde | D113: =K113+SUM(H113:J113) -> 181500 | E113: APR 26 | F113: 46142 | G113: Payroll 56 - gross earnings | K113: 181500
B114: STAFF SALARY | C114: Sujeet Singh | D114: =K114+SUM(H114:J114) -> 130000 | E114: APR 26 | F114: 46142 | G114: Payroll 56 - gross earnings | K114: 130000
B115: STAFF SALARY | C115: Pratik Shiposkar | D115: =K115+SUM(H115:J115) -> 80000 | E115: APR 26 | F115: 46142 | G115: Payroll 56 - gross earnings | K115: 80000
... B139: STAFF SALARY | C139: Sumit Mandavkar | D139: =K139+SUM(H139:J139) -> 99751 | E139: APR 26 | F139: 46142 | G139: Payroll 56 - gross earnings | K139: 99751
C140: SUB TOTAL | D140: =SUM(D105:D139) -> 6259754
B142: LEAVE ENCASHMENT | C142: Sagar Sonawane | D142: =K142+SUM(H142:J142) -> 51003 | E142: Sagar Sonawane left the organization, his last working day was 14 April, to be paid till 14 April, leave encashment to be done for total 11 days. Rs 8389/- to be deducted from him for buying old iPhone. Full and Final pay voucher to be prepared. | F142: 46142 | G142: Leave Salary | K142: 51003
B144: REIMBURSMENT | C144: Ashwini Yadav | D144: =K144+SUM(H144:J144) -> 1666 | E144: APR 26 | F144: 46142 | G144: Reimbursements to Employees (Payroll 56) | K144: 1666
B145: REIMBURSMENT | C145: Chandni Jaadwa | D145: =K145+SUM(H145:J145) -> 3000 | E145: APR 26 | F145: 46142 | G145: Reimbursements to Employees (Payroll 56) | K145: 3000
B146: REIMBURSMENT | C146: Pratik Kondvilkar | D146: =K146+SUM(H146:J146) -> 3297 | E146: APR 26 | F146: 46142 | G146: Reimbursements to Employees (Payroll 56) | K146: 3297
B147: REIMBURSMENT | C147: Pratik Shiposkar | D147: =K147+SUM(H147:J147) -> 4000 | E147: APR 26 | F147: 46142 | G147: Reimbursements to Employees (Payroll 56) | K147: 4000
B148: REIMBURSMENT | C148: Rahul Pawar | D148: =K148+SUM(H148:J148) -> 10000 | E148: APR 26 | F148: 46142 | G148: Reimbursements to Employees (Payroll 56) | K148: 10000
B149: REIMBURSMENT | C149: Renuka Shetty | D149: =K149+SUM(H149:J149) -> 3600 | E149: APR 26 | F149: 46142 | G149: Reimbursements to Employees (Payroll 56) | K149: 3600
B150: REIMBURSMENT | C150: Sampada Shimge | D150: =K150+SUM(H150:J150) -> 900 | E150: APR 26 | F150: 46142 | G150: Reimbursements to Employees (Payroll 56) | K150: 900
B151: REIMBURSMENT | C151: Shilpa Rajpurkar | D151: =K151+SUM(H151:J151) -> 750 | E151: APR 26 | F151: 46142 | G151: Reimbursements to Employees (Payroll 56) | K151: 750
B152: REIMBURSMENT | C152: Yash Sukati | D152: =K152+SUM(H152:J152) -> 1877 | E152: APR 26 | F152: 46142 | G152: Reimbursements to Employees (Payroll 56) | K152: 1877
...

Sheet CR
A1: XT Ships Management India Private Limited
A5: General Expenses - Profit and Loss Account
A6: Head of expenses | B6: =Master!C6 -> APR-26 | D6: Pivot for Man Day Exepnses (Excluding Assets Purchased) | G6: Pivot for other than Manday Expenses & Assets
A7: PROFESSIONAL FEES | B7: =SUMIF(General!$B$4:$B$172,A7,General!$K$4:$K$172) -> 240833 | D7: Source: live SUMIF links to General sheet (pivot tables replaced)
A8: COURIER CHARGES | B8: =SUMIF(General!$B$4:$B$172,A8,General!$K$4:$K$172) -> 420
A9: HOUSEKEEPING CHARGES | B9: =SUMIF(General!$B$4:$B$172,A9,General!$K$4:$K$172) -> 40665.3
A10: SECURITY CHARGES | B10: =SUMIF(General!$B$4:$B$172,A10,General!$K$4:$K$172) -> 21673.8
A11: ADVERTISMENT | B11: =SUMIF(General!$B$4:$B$172,A11,General!$K$4:$K$172) -> 6878
A12: PANTRY EXPENSES | B12: =SUMIF(General!$B$4:$B$172,A12,General!$K$4:$K$172) -> 124090
A13: PRINTING & STATIONERY | B13: =SUMIF(General!$B$4:$B$172,A13,General!$K$4:$K$172) -> 8550
A14: ELECTRICITY CHARGES | B14: =SUMIF(General!$B$4:$B$172,A14,General!$K$4:$K$172) -> 60050
A15: TRAVEL EXPENSES | B15: =SUMIF(General!$B$4:$B$172,A15,General!$K$4:$K$172) -> 140000
A16: Health Insurance | B16: =SUMIF(General!$B$4:$B$172,A16,General!$K$4:$K$172) -> 30940
A17: Society Maintainance | B17: =SUMIF(General!$B$4:$B$172,A17,General!$K$4:$K$172) -> 109436
A18: PROPERTY TAX | B18: =SUMIF(General!$B$4:$B$172,A18,General!$K$4:$K$172) -> 6000
A19: PETROL EXPENSES | B19: =SUMIF(General!$B$4:$B$172,A19,General!$K$4:$K$172) -> 3574.87
... A36: EMPLOYER CONTRIBUTION TO PF | B36: =SUMIF(General!$B$4:$B$172,A36,General!$K$4:$K$172) -> 66299
A39: UTLIZED FOR TAX PAYMENT (TDS) OF XT/ASM
A40: PF XT/ASM | B40: 0
A41: INCOME TAX OF XT
A42: Total | B42: =SUM(B7:B41) -> 8514846.2
A45: ASSETS
A46: Purchase of Asset (Other than Office) | B46: =General!C226 -> 31380
A47: Purchase of Asset (Office Interior)
A49: Sale of Asset (Office)
A51: Depreciation (on all Assets) | B51: =General!K181 -> 539519
A53: Direct Expenses | B53: =Master!C6 -> APR-26
A54: Company name | B54: Total
A55: ICE | B55: ='DE-ICE'!C9 -> 918550
A56: XT | B56: ='DE-XT'!C8 -> 3036049.3
A57: Grand Total | B57: =SUM(B55:B56) -> 3954599.3
A58: General Expenses - Cost(without Depreciation) | B58: =$B$42 -> 8514846.2
A59: Grand Total | B59: =B57+B58 -> 12469446
A61: Mandays | B61: No of crew days
A62: ICE | B62: =+#REF! -> #REF!
A63: XT | B63: =+#REF! -> #REF!
A64: Total | B64: =SUM(B62:B63) -> #REF!
A66: Cost / Mandays INR | B66: =IFERROR(B58/B64,"Pending CB") -> Pending CB
A68: Foreign Exchenge Rate1$ = INR | B68: =Forex!C2 -> 94.9432
A70: Total Cost / Mandays USD | B70: =IFERROR(B66/B68,"Pending CB") -> Pending CB

Sheet Consolidated CR
A1: XT Ships Management India Private Limited
A7: General Expenses - Profit and Loss Account
A8: Head of expenses/Month | B8: 45748 | C8: 45778 | D8: 45809 | E8: 45839 | F8: 45870 | G8: 45901 | H8: 45931 | I8: 45962 | J8: 45992 | K8: 46023 | L8: 46054 | M8: 46082 | N8: Total
A9: ADVERTISMENT | B9: 92183.5 | C9: 65878 | D9: 25628 | E9: 59378 | F9: 6878 | G9: 25628 | H9: 6878 | I9: 59378 | J9: 25628 | K9: 271878 | L9: 52978 | M9: 50628 | N9: =SUM(B9:M9) -> 742941.5
A10: AMC | H10: 158363.06 | N10: =SUM(B10:M10) -> 158363.06
A11: BANK CHARGES | B11: 4922 | C11: 37459.36 | D11: 4184.48 | E11: 4663.24 | F11: 162711.33 | G11: 3272.36 | H11: 4997.04 | I11: 3006.31 | J11: 13406.06 | K11: 5737.37 | L11: 3904.75 | M11: 6715.56 | N11: =SUM(B11:M11) -> 254979.86
A12: COMPUTER EXPENSE | B12: 2550 | F12: 3715.3 | N12: =SUM(B12:M12) -> 6265.3
A13: COURIER CHARGES | B13: 793 | C13: 14928.7 | D13: 1217 | E13: 47157.72 | F13: 669 | G13: 6425 | H13: 25814.763 | I13: 9156 | J13: 13441.441 | K13: 35231.39 | L13: 380 | M13: 26514.6 | N13: =SUM(B13:M13) -> 181728.61
A14: ELECTRICITY CHARGES | C14: 64940 | D14: 61970 | E14: 63232.64 | F14: 56676.27 | G14: 49720 | H14: 55460 | I14: 55450 | J14: 52840 | K14: 65940 | L14: 46160 | M14: 212530 | N14: =SUM(B14:M14) -> 784918.91
A15: HOUSEKEEPING CHARGES | B15: 40665.3 | C15: 40665.3 | D15: 40665.3 | E15: 40665.3 | F15: 40665.3 | G15: 40665.32 | H15: 40665.3 | I15: 40665.3 | J15: 39353.44 | K15: 40665.3 | L15: 40665.3 | M15: 40665.3 | N15: =SUM(B15:M15) -> 486671.76
A16: LEAVE ENCASHMENT | M16: 80136 | N16: =SUM(B16:M16) -> 80136
A17: MOBILE & TELEPHONE CHARGES | B17: 45008.34 | C17: 35309.04 | D17: 44166.24 | E17: 36764.55 | F17: 36819.898 | G17: 35338.49 | H17: 33827.23 | I17: 48612 | J17: 37320.87 | K17: 37049.42 | L17: 48298.79 | M17: 32772 | N17: =SUM(B17:M17) -> 471286.87
A18: OFFICE GENERAL EXPENSES | B18: 89900 | C18: 40893 | D18: 49996 | E18: 52820.49 | F18: 53495 | G18: 39907.3 | H18: 23149.5 | I18: 19727 | J18: 86911.9 | K18: 83850.09 | L18: 41416 | M18: 102591.92 | N18: =SUM(B18:M18) -> 684658.2
A19: OFFICE INTERNET CHARGES | B19: 228625 | E19: 228625 | H19: 228625 | K19: 228625 | L19: 6801 | M19: 173942 | N19: =SUM(B19:M19) -> 1095243
A20: OFFICE STAFF WELFARE | B20: 85381 | C20: 82507 | D20: 62189 | E20: 83841 | F20: 49695 | G20: 48789 | H20: =2660449-8844 -> 2651605 | I20: 191625 | J20: 293956 | K20: 102528 | L20: 93799 | M20: 315883 | N20: =SUM(B20:M20) -> 4061798
A21: PANTRY EXPENSES | B21: 101089 | C21: 86855 | D21: 115524 | E21: 126941 | F21: 127422 | G21: 107877 | H21: 108296 | I21: 102506 | J21: 110064 | K21: 108960 | L21: 106448 | M21: 99919 | N21: =SUM(B21:M21) -> 1301901
A22: PETROL EXPENSES | B22: 2827.67 | C22: 2455.9 | D22: 2797.65 | E22: 3682.73 | F22: 2960.74 | G22: 3164.54 | H22: 2928.67 | I22: 2864.19 | J22: 5266.04 | K22: 6360.96 | L22: 3329.84 | M22: 2812.14 | N22: =SUM(B22:M22) -> 41451.07
A23: PRINTING & STATIONERY | B23: 6176.54 | C23: 41897.1 | D23: 5542.44 | E23: 10434.5 | F23: 3725.3 | G23: 8822.44 | H23: 8000 | I23: 8979.6 | J23: 3714.48 | K23: 4160.2 | L23: 23544 | M23: 63592 | N23: =SUM(B23:M23) -> 188588.6
A24: PROFESSIONAL FEES | B24: 109860 | C24: 106690 | D24: 482955 | E24: 216626 | F24: 82500 | G24: 82500 | H24: 546287 | I24: 88500 | J24: 202500 | K24: 107500 | L24: 158751 | M24: 165000 | N24: =SUM(B24:M24) -> 2349669
A25: PROPERTY TAX | F25: 23887 | L25: 371807 | N25: =SUM(B25:M25) -> 395694
A26: REIMBURSMENT | B26: 30754 | C26: 38931 | D26: 23995 | E26: 76480 | F26: 36415 | G26: 56371 | H26: 60499 | I26: 79086 | J26: 94859 | K26: 68510 | L26: 46159 | M26: 67736 | N26: =SUM(B26:M26) -> 679795
A27: NOC CHARGES | N27: =SUM(B27:M27) -> 0
A28: SECURITY CHARGES | B28: 21673.8 | C28: 21673.8 | D28: 21673.8 | E28: 21673.8 | F28: 21673.8 | G28: 21673.8 | H28: 21673.8 | I28: 21673.8 | J28: 21673.8 | K28: 21673.8 | L28: 21673.3 | M28: 21673.3 | N28: =SUM(B28:M28) -> 260084.6
A29: STAFF SALARY | B29: 8373712.4 | C29: 5831990 | D29: 6195778 | E29: 6127899.7 | F29: 5865330 | G29: 5804141 | H29: 6267589 | I29: 6204827.3 | J29: 6786960.3 | K29: 7820976.5 | L29: 6948415 | M29: 6627749 | N29: =SUM(B29:M29) -> 78855368
A30: TRAVEL EXPENSES | B30: 21902 | C30: 188444 | D30: 32328 | E30: 34129 | F30: 5913 | G30: 15825 | H30: 89323.85 | I30: 161278 | J30: 35695 | K30: 8582 | L30: 10175 | M30: 125133 | N30: =SUM(B30:M30) -> 728727.85
A31: EMPLOYER CONTRIBUTION TO PF | B31: 69841 | C31: 66342 | D31: 73441 | E31: 72123 | F31: 70263 | G31: 69649 | H31: 64351 | I31: 68743 | J31: 64915 | K31: 61260 | L31: 68099 | M31: 66449 | N31: =SUM(B31:M31) -> 815476
A32: OFFICE EQUIPMENT EXPENSE | F32: 4250 | L32: 29546 | N32: =SUM(B32:M32) -> 33796
A33: COURSE FEES | C33: 33898 | F33: 11440.68 | H33: 11278 | I33: 55000 | J33: 20788.98 | L33: 55000 | M33: 91200 | N33: =SUM(B33:M33) -> 278605.66
A34: HOTEL EXPENSES | B34: 60900 | E34: 38500 | H34: 42051 | I34: 15965 | N34: =SUM(B34:M34) -> 157416
A35: Health Insurance | B35: -3224 | C35: 56856 | D35: -3224 | K35: 14229 | N35: =SUM(B35:M35) -> 64637
A36: REPAIR & MAINTANANCE | H36: 9953 | J36: 91698.36 | N36: =SUM(B36:M36) -> 101651.36
A37: COMPUTER Consumables | C37: 351.64 | E37: 3126.3 | G37: 16143.22 | I37: 1948.3 | J37: 37298.3 | K37: 750 | L37: 25597.04 | M37: 18786 | N37: =SUM(B37:M37) -> 104000.8
A38: BUSINESS PROMOTION | D38: 89954.5 | E38: 5342 | H38: 104184.27 | I38: 23584.02 | K38: 42554 | L38: 74892.84 | M38: 15169 | N38: =SUM(B38:M38) -> 355680.63
A39: OFFICE RENT | C39: 140000 | D39: 428500 | E39: 420000 | F39: 420000 | G39: 420000 | H39: 420000 | I39: 420000 | J39: 420000 | K39: 420000 | L39: 420000 | M39: 210000 | N39: =SUM(B39:M39) -> 4138500
A40: OFFICE INSURANCE | G40: 22032 | N40: =SUM(B40:M40) -> 22032
A41: STAFF MEDICAL INSURANCE | B41: -29625 | E41: 23860 | F41: -11474 | H41: 1159867 | L41: 27178 | N41: =SUM(B41:M41) -> 1169806
A42: STAFF BONUS | H42: 4604615.9
A43: PEST CONTROL | C43: 3000 | N43: =SUM(B43:M43) -> 3000
A44: PARKING | H44: 5000
A45: SOCIETY MAINTAINANCE | C45: 35188.27 | I45: 233752 | K45: 117045.98 | N45: =SUM(B45:M45) -> 385986.25
A46: CAR INSURANCE | C46: 6436 | N46: =SUM(B46:M46) -> 6436
A47: Rent Income | B47: -75000 | C47: -75000 | D47: -1247312 | E47: -1247312 | F47: -1247312 | G47: -1247312 | H47: -1247312 | I47: -1002850 | J47: -25000 | K47: -25000 | L47: -25000 | M47: -25000 | N47: =SUM(B47:M47) -> -7489410
A48: CURRENCY EXCHANGE | I48: 71827 | N48: =SUM(B48:M48) -> 71827
A49: Foreign Exchange Difference | N49: =SUM(B49:M49) -> 0
A50: Misc Expenses | L50: 0.8 | M50: 2343.83 | N50: =SUM(B50:M50) -> 2344.63
A51: DONATION | B51: 10000 | G51: 10000 | H51: 5000 | N51: =SUM(B51:M51) -> 25000
A52: Office Car Insurance | N52: =SUM(B52:M52) -> 0
A53: NSDL Charges | B53: 5000 | N53: =SUM(B53:M53) -> 5000
A54: Interest On TDS | C54: 1000 | N54: =SUM(B54:M54) -> 1000
A55: Grand Total for Manday expenses | B55: =SUM(B9:B54) -> 9295915.6 | C55: =SUM(C9:C54) -> 6969589.1 | D55: =SUM(D9:D54) -> 6511969.4 | E55: =SUM(E9:E54) -> 6550653.9 | F55: =SUM(F9:F54) -> 5828319.6 | G55: =SUM(G9:G54) -> 5640632.5 | H55: =SUM(H9:H54) -> 15512970 | I55: =SUM(I9:I54) -> 6985303.9 | ... M55: =SUM(M9:M54) -> 8594940.7 | N55: =SUM(B55:M55) -> 98672672
A57: Other Disclosures : (Capital assets)
A59: Purchase on New office (215 Atrium) Capitalised
A60: Office Agreement value | C60: 172585000 | N60: =SUM(B60:M60) -> 172585000
A61: NOC Charges | C61: 448468 | N61: =SUM(B61:M61) -> 448468
A62: Professional Fees | C62: 117756 | D62: 350000 | N62: =SUM(B62:M62) -> 467756
A63: ROC charges and Stamp Duty | C63: 10670123 | N63: =SUM(B63:M63) -> 10670123
A64: Brokerage | D64: 1950000 | N64: =SUM(B64:M64) -> 1950000
A65: Other Expenses | D65: 400 | N65: =SUM(B65:M65) -> 400
A66: Office Interior | J66: 7434000 | K66: 8673000 | N66: =SUM(B66:M66) -> 16107000
A67: Atrium office deposit | N67: =SUM(B67:M67) -> 0
A68: Sale of Pinnacle Office | N68: =SUM(B68:M68) -> 0
A69: Sale Price | C69: -55000000 | N69: =SUM(B69:M69) -> -55000000
A70: NOC Charges | C70: 444445 | N70: =SUM(B70:M70) -> 444445
A71: Professional Fees | C71: 700000 | N71: =SUM(B71:M71) -> 700000
A73: Add: Provision for Depreciation | B73: 343731 | C73: 343731 | D73: 343731 | E73: 343731 | F73: 343731 | G73: 421953 | H73: 421953 | I73: 421953 | J73: 521953 | K73: 521953 | L73: 521953 | M73: 521953 | N73: =SUM(B73:M73) -> 5072326
A74: Final Total of expenses (Including Depreciation) | B74: =B55+B73 -> 9639646.6 | C74: =C55+C73 -> 7313320.1 | D74: =D55+D73 -> 6855700.4 | E74: =E55+E73 -> 6894384.9 | F74: =F55+F73 -> 6172050.6 | G74: =G55+G73 -> 6062585.5 | H74: =H55+H73 -> 15934923 | I74: =I55+I73 -> 7407256.9 | ... N74: =N55+N73 -> 1.03745e+08
A76: Direct Expenses
A77: Company name
A78: ICE | B78: 612315 | C78: 1843057.4 | D78: 3246907.4 | E78: 1597275.4 | F78: 600112.33 | G78: 786142.26 | H78: 2497768 | I78: 910296 | J78: 638029 | K78: 515039 | L78: 956215 | M78: 634864 | N78: =SUM(B78:M78) -> 14838021
A79: XT | B79: 2673237.4 | C79: 2590323.9 | D79: 5879298.3 | E79: 2672471.9 | F79: 2000549.5 | G79: 1863175.6 | H79: 2145590.6 | I79: 4340811.7 | J79: 2518088.2 | K79: 2640161 | L79: 1560586 | M79: 6144428.5 | N79: =SUM(B79:M79) -> 37028723
A80: Grand Total | B80: =SUM(B78:B79) -> 3285552.4 | C80: =SUM(C78:C79) -> 4433381.3 | D80: =SUM(D78:D79) -> 9126205.8 | E80: =SUM(E78:E79) -> 4269747.3 | F80: =SUM(F78:F79) -> 2600661.9 | G80: =SUM(G78:G79) -> 2649317.9 | H80: =SUM(H78:H79) -> 4643358.7 | I80: =SUM(I78:I79) -> 5251107.7 | ... M80: =SUM(M78:M79) -> 6779292.5 | N80: =SUM(B80:M80) -> 51866743
A81: General Expenses - Cost | B81: =B55 -> 9295915.6 | C81: =C55 -> 6969589.1 | D81: =D55 -> 6511969.4 | E81: =E55 -> 6550653.9 | F81: =F55 -> 5828319.6 | G81: =G55 -> 5640632.5 | H81: =H55 -> 15512970 | I81: =I55 -> 6985303.9 | ... M81: =M55 -> 8594940.7 | N81: =SUM(B81:M81) -> 98672672
A82: Grand Total | B82: =B80+B81 -> 12581468 | C82: =C80+C81 -> 11402970 | D82: =D80+D81 -> 15638175 | E82: =E80+E81 -> 10820401 | F82: =F80+F81 -> 8428981.5 | G82: =G80+G81 -> 8289950.4 | H82: =H80+H81 -> 20156329 | I82: =I80+I81 -> 12236412 | ... M82: =M80+M81 -> 15374233 | N82: =SUM(B82:M82) -> 1.5053942e+08
A84: Mandays
A85: ICE | B85: 7110 | C85: 6689 | D85: 6613 | E85: 7168 | F85: 7411 | G85: 7703 | H85: 7390 | I85: 7179 | J85: 7302 | K85: 7385 | N85: =SUM(B85:M85) -> 71950
A86: XT | B86: 7498 | C86: 7436 | D86: 7742 | E86: 8008 | F86: 8274 | G86: 8079 | H86: 7656 | I86: 7724 | J86: 7326 | K86: 7343 | N86: =SUM(B86:M86) -> 77086
A87: Total | B87: =SUM(B85:B86) -> 14608 | C87: =SUM(C85:C86) -> 14125 | D87: =SUM(D85:D86) -> 14355 | E87: =SUM(E85:E86) -> 15176 | F87: =SUM(F85:F86) -> 15685 | G87: =SUM(G85:G86) -> 15782 | H87: =SUM(H85:H86) -> 15046 | I87: =SUM(I85:I86) -> 14903 | ... N87: =SUM(N85:N86) -> 149036
A89: Cost / Mandays INR | B89: =IFERROR(B81/B87,"") -> 636.35786 | C89: =IFERROR(C81/C87,"") -> 493.42224 | D89: =IFERROR(D81/D87,"") -> 453.63772 | E89: =IFERROR(E81/E87,"") -> 431.64562 | F89: =IFERROR(F81/F87,"") -> 371.58557 | G89: =IFERROR(G81/G87,"") -> 357.40923 | H89: =IFERROR(H81/H87,"") -> 1031.0362 | I89: =IFERROR(I81/I87,"") -> 468.71797 | ... N89: =IFERROR(N81/N87,"") -> 662.07273
A91: Foreign Exchange Rate1$ = INR | B91: 83.8568 | C91: 85.4353 | D91: 85.6179 | E91: 87.3519 | F91: 88.2576 | G91: 88.6778 | H91: 88.7932 | I91: 89.7436 | J91: 89.9792 | K91: 91.6443 | L91: 91.4514 | M91: 93.2088 | N91: =AVERAGE(B91:M91) -> 88.66815
A93: Total Cost / Mandays USD | B93: =IFERROR(B89/B91,"") -> 7.5886256 | C93: =IFERROR(C89/C91,"") -> 5.7753907 | D93: =IFERROR(D89/D91,"") -> 5.2983981 | E93: =IFERROR(E89/E91,"") -> 4.9414566 | F93: =IFERROR(F89/F91,"") -> 4.2102387 | G93: =IFERROR(G89/G91,"") -> 4.0304251 | H93: =IFERROR(H89/H91,"") -> 11.611657 | I93: =IFERROR(I89/I91,"") -> 5.2228567 | ... N93: =IFERROR(N89/N91,"") -> 7.4668608
O94: =N93*10% -> 0.74668608
O95: =N93+O94 -> 8.2135469

Sheet Employees Loan Repayment
B2: Employee Loan Repayment for the month of APR 2026
B3: ACCOUNT HEAD | C3: Employee Name | D3: AMOUNT (INR) | E3: REMARKS | F3: Transaction Date | G3: TYPE OF PAYMENT | H3: Remarks | I3: Original Loan amount | J3: Date of Loan | K3: Dedcution Month | L3: Number of installements | M3: Total amount dedcuted | N3: Outstanding amount | O3: REMARKS
B4: LOAN INSTALLMENT | C4: Shahina Mohite | D4: 13700 | E4: Deducted from Salary | F4: 46142 | G4: Monthly Loan Repayment | H4: Nil | I4: 500000 | J4: 45536 | K4: 46113 | L4: 19 | M4: =6800+(D4*L4) -> 267100 | N4: =I4-M4 -> 232900
B5: LOAN INSTALLMENT | C5: Amit Shinde | D5: 12000 | E5: Deducted from Salary | F5: 46142 | G5: Monthly Loan Repayment | H5: Nil | I5: 432000 | J5: 45505 | K5: 46113 | L5: 21 | M5: =L5*D5 -> 252000 | N5: =I5-M5 -> 180000
B6: LOAN INSTALLMENT | C6: Pratik Shiposkar | D6: 10000 | E6: Deducted from Salary | F6: 46142 | G6: Monthly Loan Repayment | H6: Nil | I6: 400000 | J6: 45505 | K6: 46113 | L6: 21 | M6: =L6*D6 -> 210000 | N6: =I6-M6 -> 190000
B7: LOAN INSTALLMENT | C7: Sumit Mandavkar | D7: 23400 | E7: Deducted from Salary | F7: 46142 | G7: Monthly Loan Repayment | H7: Nil | I7: =842400+342000 -> 1184400 | J7: 45627 | K7: 46113 | L7: 17 | M7: =L7*D7 -> 397800 | N7: =I7-M7 -> 786600 | O7: 36 monthly deductions of 23400/- Rs starting from December 2024 payroll.
B8: LOAN INSTALLMENT | C8: Sandesh Patil | D8: 10000 | E8: Deducted from Salary | F8: 46142 | G8: Monthly Loan Repayment | H8: Nil | I8: 200000 | J8: 45901 | K8: 46113 | L8: 8 | M8: =L8*D8 -> 80000 | N8: =I8-M8 -> 120000 | O8: Sandesh Patil was given a loan of 2 Lakh Rs, deductions in 20 instalments of 10,000/- Rs each. First instalment of 10,000/- Rs to be deducted in September 2025.
B9: LOAN INSTALLMENT | C9: Rahul Pawar | D9: 35000 | E9: Deducted from Salary | F9: 46142 | G9: Monthly Loan Repayment | H9: Nil | I9: 700000 | J9: 45992 | K9: 46113 | L9: 5 | M9: =L9*D9 -> 175000 | N9: =I9-M9 -> 525000 | O9: Rahul Pawar was given a loan of 7 Lakh Rs, loan to be paid back in 20 monthly instalments of 35000/- Rs each starting from December 2025
B10: LOAN INSTALLMENT | C10: Pratik Kondvilkar | D10: 10000 | E10: Deducted from Salary | F10: 46142 | G10: Monthly Loan Repayment | H10: Nil | I10: 300000 | J10: 45992 | K10: 46113 | L10: 5 | M10: =L10*D10 -> 50000 | N10: =I10-M10 -> 250000 | O10: Pratik Kondvilkar was given a loan of 3 Lakhs in November, monthly deductions of 10000/- Rs to start from December 2025.
B11: LOAN INSTALLMENT | C11: Shivram R. Singh | D11: 20000 | E11: Deducted from Salary | F11: 46142 | G11: Monthly Loan Repayment | H11: Nil | I11: 400000 | J11: 46023 | K11: 46113 | L11: 3 | M11: =L11*D11 -> 60000 | N11: =I11-M11 -> 340000 | O11: Loan of 4,00,000; 20 monthly instalments of 20,000 from Feb-26 (Tally Payroll 48 narration)
B12: LOAN INSTALLMENT | C12: Rohan Gawde | D12: 16600 | E12: Deducted from Salary | F12: 46142 | G12: Monthly Loan Repayment | H12: Nil | I12: 400000 | J12: 46023 | K12: 46113 | L12: 3 | M12: =18200+D12*(L12-1) -> 51400 | N12: =I12-M12 -> 348600 | O12: Loan of 4,00,000: first deduction 18,200 in Feb-26, balance in 23 instalments of 16,600 from Mar-26 (Tally Payroll 48 narration)
B13: LOAN INSTALLMENT | C13: Sampada Shimge | D13: 15000 | E13: Deducted from Salary | F13: 46142 | G13: Monthly Loan Repayment | H13: Nil | I13: 150000 | J13: 46080 | K13: 46113 | L13: 2 | M13: =L13*D13 -> 30000 | N13: =I13-M13 -> 120000 | O13: Sampada was given a loan of 150,000/- Rs. To be paid back in 10 instalments of 15,000/- Rs each, first deduction of 15,000/- Rs to start from March 2026. (Tally Payroll 45 narration; disbursed from DBS on 27.02.26)
C14: SUB TOTAL | D14: =SUM(D4:D13) -> 165700 | I14: =SUM(I4:I13) -> 4666400 | M14: =SUM(M4:M13) -> 1573300 | N14: =SUM(N4:N13) -> 3093100
C16: Source: Tally Payroll voucher 54 dt. 30.04.26 (narration: APR 26) - Loan to Employees Cr 1,65,700. No loan disbursed in Apr-26. Sunny Palav loan fully recovered in Mar-26.

Sheet Forex
B2: INR/$ | C2: 94.9432
B4: USD amounts for Apr-26 service-charge invoices not yet raised in Tally - to be entered
C5: $ | D5: Rs
B6: ICE | D6: =ROUND(C6*C2,0) -> 0
B7: XT | D7: =ROUND(C7*C2,0) -> 0
B10: RBI screenshot (USD, 04.05.2026 = 94.9432) saved at: C:\Users\Prasanna\AppData\Local\Temp\claude-chrome-screenshots-6P8S4V\screenshot-1790594104620-2.jpg - paste here (shows USD 04/05/2026 = 94.9432)
R28: =C2 -> 94.9432
