Workbook

Sheet Start Here
A1: SURL Audit Tool — Final Capstone Prototype
A2: Fictional training dataset. This is an audit-support tool; all exceptions require auditor validation and conclusion.
A4: Section | B4: Purpose | C4: What to do | D4: Output | E4: Important limitation
A5: 1. Inputs & assumptions | B5: Set period, materiality and approved sampling parameters. | C5: Review Inputs tab and replace example values with engagement-approved values. | D5: Documented planning assumptions | E5: No universal sample size is determined by materiality/population count alone.
A6: 2. Four sample cases | B6: Test inclusion/exclusion logic using four controlled scenarios. | C6: See Test Cases and fictional invoice PDF. | D6: Expected outcome for each case | E6: Four invoices are only for prototype testing; not an adequate audit sample by themselves.
A7: 3. Population files | B7: Use YE AP aging, subsequent disbursements, subsequent AP aging, unprocessed invoices and trial balance. | C7: Replace sample data with approved/redacted client data; reconcile each population. | D7: Population counts and values | E7: Two core files alone do not establish completeness of all liabilities.
A8: 4. Auto sample selection | B8: Risk flags, large items, unmatched items and date buckets are surfaced. | C8: Review Sample Selection tab and approve/override selection. | D8: Suggested sample list | E8: Non-statistical risk-based selection unless a separate approved statistical method is implemented.
A9: 5. Invoice testing | B9: Document invoice, PO, receipt/service evidence, ledger trace and conclusion. | C9: Complete Invoice Testing tab and cross-reference supporting docs. | D9: Audit evidence trail | E9: Do not conclude unrecorded liability based only on payment date or AI flag.
A10: 6. Workpaper conclusion | B10: Summarise procedures, exceptions, follow-up and review. | C10: Complete Workpaper Summary and reviewer fields. | D10: Workpaper ready for review | E10: Engagement auditor must approve methodology and final conclusion.

Sheet Inputs
A1: Engagement Inputs
A2: Illustrative defaults only; replace with approved values. The sample size helper is planning support, not a substitute for professional judgment.
A4: Parameter | B4: Value | C4: Purpose / guidance | D4: Notes
A5: Entity | B5: Sample Co. Ltd. | C5: Fictional training entity
A6: Period start | B6: 45658 | C6: Start of audit period | D6: Date
A7: Year-end date | B7: 46022 | C7: Reporting date | D7: Date
A8: Subsequent search start | B8: 46023 | C8: First day after year-end | D8: Date
A9: Subsequent search end | B9: 46112 | C9: Illustrative 90-day search window; align with report date and methodology | D9: Date
A10: Overall materiality | B10: 250000 | C10: Approved financial statement materiality | D10: Currency
A11: Performance materiality | B11: 175000 | C11: Approved engagement planning value | D11: Currency
A12: SURL tolerable misstatement | B12: 100000 | C12: Procedure-specific tolerable misstatement approved by engagement team | D12: Currency
A13: Individually significant threshold | B13: 50000 | C13: Risk-screening threshold; set based on methodology | D13: Currency
A14: Confidence factor (planning only) | B14: 1 | C14: Placeholder for non-statistical planning; not a statistical confidence factor | D14: Do not use for statistical inference
A15: Population count | B15: =COUNTA(Disbursements!A5:A500) | C15: Calculated from disbursement population | D15: Formula
A16: Disbursement population value | B16: =SUM(Disbursements!F5:F500) | C16: Calculated from disbursement population | D16: Formula
A17: Illustrative base coverage rate | B17: 0.25 | C17: Non-statistical planning knob; review with auditor, do not treat as standard | D17: 0–1
A18: Planning sample count (helper) | B18: =MIN(B15,MAX(4,ROUNDUP(B15*B17,0))) | C18: Illustrative floor of 4 plus selected coverage rate; not an audit-standard formula | D18: Formula
A19: Days bucket 1 | B19: 30 | C19: Date coverage bucket boundary | D19: Days
A20: Days bucket 2 | B20: 60 | C20: Date coverage bucket boundary | D20: Days

Sheet YE AP Aging
A1: Year-End AP Aging
A2: Open AP invoice population as at 31-Dec-2025. Reconcile total to AP subledger and GL control account.
A4: Vendor ID | B4: Vendor Name | C4: Invoice No. | D4: Invoice Date | E4: Receipt / Service Date | F4: Invoice Amount | G4: Open Balance YE | H4: GL Account | I4: Status / Notes
A5: V001 | B5: Northstar Office Supplies | C5: NS-251188 | D5: 46001 | E5: 46006 | F5: 12500 | G5: 12500 | H5: 2000-AP | I5: Included at YE
A6: V002 | B6: Metro Utilities | C6: MU-DEC25 | D6: 46019 | E6: 46022 | F6: 18400 | G6: 18400 | H6: 2000-AP | I6: Included at YE
A7: V003 | B7: Apex IT Services | C7: APX-4491 | D7: 46011 | E7: 46013 | F7: 48500 | G7: 48500 | H7: 2000-AP | I7: Included at YE
A8: V004 | B8: Greenline Logistics | C8: GL-9822 | D8: 46020 | E8: 46024 | F8: 27600 | G8: 27600 | H8: 2000-AP | I8: Included at YE
A9: V005 | B9: BrightBuild Maintenance | C9: BB-7720 | D9: 46009 | E9: 46011 | F9: 63000 | G9: 63000 | H9: 2000-AP | I9: Included at YE
A10: V006 | B10: Summit Marketing | C10: SM-1044 | D10: 45991 | E10: 45993 | F10: 22000 | G10: 22000 | H10: 2000-AP | I10: Included at YE
A11: V007 | B11: CloudNine Software | C11: C9-DEC25 | D11: 45992 | E11: 45992 | F11: 96000 | G11: 96000 | H11: 2000-AP | I11: Included at YE
A12: V008 | B12: Pioneer Packaging | C12: PP-8890 | D12: 46013 | E12: 46015 | F12: 15800 | G12: 15800 | H12: 2000-AP | I12: Included at YE

Sheet Disbursements
A1: Subsequent Bank Disbursement Register
A2: Payments after year-end. Full fictional population; select samples from the full listing after reconciling to source.
A4: Payment ID | B4: Payment Date | C4: Vendor ID | D4: Vendor Name | E4: Invoice Ref | F4: Payment Amount | G4: Method | H4: Description
A5: D001 | B5: 46030 | C5: V001 | D5: Northstar Office Supplies | E5: NS-251188 | F5: 12500 | G5: ACH | H5: Payment for year-end AP item
A6: D002 | B6: 46034 | C6: V021 | D6: Delta Electric | E6: DE-5510 | F6: 38700 | G6: ACH | H6: Invoice not in year-end AP aging; December service
A7: D003 | B7: 46042 | C7: V022 | D7: Crown Legal LLP | E7: CL-DEC25 | F7: 92000 | G7: Wire | H7: Invoice not in year-end AP aging; December legal services
A8: D004 | B8: 46058 | C8: V023 | D8: Prime Janitorial | E8: PJ-0106 | F8: 14500 | G8: ACH | H8: January service; post-period expense
A9: D005 | B9: 46067 | C9: V003 | D9: Apex IT Services | E9: APX-4491 | F9: 48500 | G9: ACH | H9: Payment for year-end AP item
A10: D006 | B10: 46099 | C10: V024 | D10: Beacon Consulting | E10: BC-882 | F10: 57000 | G10: Wire | H10: Potential omitted December milestone; invoice reference requires evidence
A11: D007 | B11: 46050 | C11: V004 | D11: Greenline Logistics | E11: GL-9822 | F11: 27600 | G11: ACH | H11: Payment for year-end AP item
A12: D008 | B12: 46080 | C12: V008 | D12: Pioneer Packaging | E12: PP-8890 | F12: 7900 | G12: ACH | H12: Partial payment of year-end AP item
A13: D009 | B13: 46086 | C13: V025 | D13: Orion HVAC | E13: OH-DEC25 | F13: 108000 | G13: Wire | H13: December maintenance; not in year-end AP aging
A14: D010 | B14: 46103 | C14: V026 | D14: January Rent | E14: JR-0126 | F14: 25000 | G14: ACH | H14: January rent; post-period expense

Sheet Subsequent AP Aging
A1: Subsequent AP Aging
A2: Illustrative AP open item listing as at 31-Mar-2026. Helps identify items remaining open and subsequent settlement; does not replace YE AP aging.
A4: Vendor ID | B4: Vendor Name | C4: Invoice No. | D4: Invoice Date | E4: Receipt / Service Date | F4: Invoice Amount | G4: Open Balance 31-Mar | H4: Payment Date if settled | I4: Status / Notes
A5: V001 | B5: Northstar Office Supplies | C5: NS-251188 | D5: 46001 | E5: 46006 | F5: 12500 | G5: 0 | H5: 46030 | I5: Paid in full
A6: V002 | B6: Metro Utilities | C6: MU-DEC25 | D6: 46019 | E6: 46022 | F6: 18400 | G6: 0 | H6: 46034 | I6: Paid in full
A7: V003 | B7: Apex IT Services | C7: APX-4491 | D7: 46011 | E7: 46013 | F7: 48500 | G7: 0 | H7: 46067 | I7: Paid in full
A8: V004 | B8: Greenline Logistics | C8: GL-9822 | D8: 46020 | E8: 46024 | F8: 27600 | G8: 0 | H8: 46050 | I8: Paid in full
A9: V005 | B9: BrightBuild Maintenance | C9: BB-7720 | D9: 46009 | E9: 46011 | F9: 63000 | G9: 0 | I9: Still open at subsequent date
A10: V006 | B10: Summit Marketing | C10: SM-1044 | D10: 45991 | E10: 45993 | F10: 22000 | G10: 0 | H10: 46055 | I10: Paid in full
A11: V007 | B11: CloudNine Software | C11: C9-DEC25 | D11: 45992 | E11: 45992 | F11: 96000 | G11: 0 | H11: 46062 | I11: Paid in full
A12: V008 | B12: Pioneer Packaging | C12: PP-8890 | D12: 46013 | E12: 46015 | F12: 15800 | G12: 7900 | H12: 46080 | I12: Partially paid; remaining balance 7,900
A13: V021 | B13: Delta Electric | C13: DE-5510 | D13: 46011 | E13: 46011 | F13: 38700 | G13: 0 | H13: 46034 | I13: Potential omitted liability; not in YE AP
A14: V022 | B14: Crown Legal LLP | C14: CL-DEC25 | D14: 46022 | E14: 46022 | F14: 92000 | G14: 0 | H14: 46042 | I14: Potential omitted liability; not in YE AP
A15: V023 | B15: Prime Janitorial | C15: PJ-0106 | D15: 46053 | E15: 46053 | F15: 14500 | G15: 0 | H15: 46058 | I15: Post-period service
A16: V024 | B16: Beacon Consulting | C16: BC-882 | D16: 46009 | E16: 46009 | F16: 57000 | G16: 0 | H16: 46099 | I16: Potential omitted liability; investigate ledger
A17: V025 | B17: Orion HVAC | C17: OH-DEC25 | D17: 46022 | E17: 46022 | F17: 108000 | G17: 0 | H17: 46086 | I17: Potential omitted liability; investigate ledger
A18: V026 | B18: January Rent | C18: JR-0126 | D18: 46023 | E18: 46023 | F18: 25000 | G18: 0 | H18: 46103 | I18: Post-period expense

Sheet Unprocessed Invoices
A1: Unprocessed Invoices & Vouchers
A2: Post-year-end invoices / vouchers received or processed after YE. Include date received, service/receipt date and posting status.
A4: Voucher ID | B4: Vendor ID | C4: Vendor Name | D4: Invoice No. | E4: Date Received | F4: Amount | G4: Receipt / Service Date | H4: Description | I4: Initial Screen
A5: U001 | B5: V021 | C5: Delta Electric | D5: DE-5510 | E5: 46026 | F5: 38700 | G5: 46011 | H5: December electrical repairs; not posted at YE | I5: Potential SURL
A6: U002 | B6: V022 | C6: Crown Legal LLP | D6: CL-DEC25 | E6: 46029 | F6: 92000 | G6: 46022 | H6: Legal services through YE; not posted at YE | I6: Potential SURL
A7: U003 | B7: V023 | C7: Prime Janitorial | D7: PJ-0106 | E7: 46055 | F7: 14500 | G7: 46053 | H7: January cleaning service | I7: Post-period
A8: U004 | B8: V024 | C8: Beacon Consulting | D8: BC-882 | E8: 46037 | F8: 57000 | G8: 46009 | H8: December milestone; acceptance evidence needed | I8: Potential SURL
A9: U005 | B9: V025 | C9: Orion HVAC | D9: OH-DEC25 | E9: 46065 | F9: 108000 | G9: 46022 | H9: December maintenance; inspect service report | I9: Potential SURL
A10: U006 | B10: V026 | C10: January Rent | D10: JR-0126 | E10: 46103 | F10: 25000 | G10: 46023 | H10: January rent | I10: Post-period

Sheet Trial Balance
A1: Trial Balance at YE
A2: Fictional trial balance as at 31-Dec-2025. Agree AP and accrual accounts to the ledgers and investigate relevant expense accounts.
A4: Account No. | B4: Account Name | C4: Classification | D4: Debit | E4: Credit
A5: 1000 | B5: Cash and cash equivalents | C5: Asset | D5: 1250000 | E5: 0
A6: 1200 | B6: Accounts receivable | C6: Asset | D6: 845000 | E6: 0
A7: 1500 | B7: Inventory | C7: Asset | D7: 620000 | E7: 0
A8: 1600 | B8: Property, plant and equipment | C8: Asset | D8: 1800000 | E8: 0
A9: 2000 | B9: Accounts payable | C9: Liability | D9: 0 | E9: 253800
A10: 2100 | B10: Accrued expenses | C10: Liability | D10: 0 | E10: 95000
A11: 2200 | B11: Payroll liabilities | C11: Liability | D11: 0 | E11: 42000
A12: 3000 | B12: Share capital | C12: Equity | D12: 0 | E12: 500000
A13: 3100 | B13: Retained earnings | C13: Equity | D13: 0 | E13: 2414200
A14: 4000 | B14: Revenue | C14: Income | D14: 0 | E14: 3500000
A15: 5000 | B15: Cost of goods sold | C15: Expense | D15: 1650000 | E15: 0
A16: 6100 | B16: Utilities expense | C16: Expense | D16: 125000 | E16: 0
... A20: 6500 | B20: IT expense | C20: Expense | D20: 95000 | E20: 0

Sheet Test Cases
A1: Four Controlled Test Cases
A2: These four scenarios are for testing the tool's inclusion/exclusion logic only. They are not an audit sample.
A4: Case ID | B4: Scenario | C4: Vendor ID | D4: Vendor | E4: Invoice | F4: Amount | G4: Receipt / Service Date | H4: Payment Date | I4: Test facts | J4: Expected tool treatment | K4: Reason
A5: TC-01 | B5: Included / recorded liability | C5: V001 | D5: Northstar Office Supplies | E5: NS-251188 | F5: 12500 | G5: 46006 | H5: 46030 | I5: Present in YE AP aging and paid subsequently. | J5: Should be treated as recorded at YE; clear if ledger tie-out confirms. | K5: Included at YE; subsequent payment settlement.
A6: TC-02 | B6: Potential omitted liability | C6: V021 | D6: Delta Electric | E6: DE-5510 | F6: 38700 | G6: 46011 | H6: 46034 | I6: Not in YE AP aging; invoice/service evidence says December work. | J6: Flag as potential SURL; inspect invoice, service evidence and GL/accruals. | K6: Potential omitted liability; not confirmed until ledger search and evidence.
A7: TC-03 | B7: Excluded / post-period expense | C7: V023 | D7: Prime Janitorial | E7: PJ-0106 | F7: 14500 | G7: 46053 | H7: 46058 | I7: Service date is January 2026, after year-end. | J7: Exclude from YE liability population unless other evidence shows pre-year-end service. | K7: Post-period service; not YE liability on current evidence.
A8: TC-04 | B8: Unclear / partial or unsupported | C8: V024 | D8: Beacon Consulting | E8: BC-882 | F8: 57000 | G8: 46009 | H8: 46099 | I8: Potential December milestone; invoice/acceptance and GL trace need corroboration. | J8: Flag for follow-up; do not conclude until contract, acceptance evidence and ledger search are reviewed. | K8: Unresolved; obtain contract, milestone acceptance and GL/accrual trace.

Sheet Sample Selection
A1: Suggested Sample Selection
A2: Formula-based risk screen. The four controlled test cases are separate from this population sample. Validate the complete population and sampling approach.
A4: Payment ID | B4: Payment Date | C4: Days after YE | D4: Vendor | E4: Invoice Ref | F4: Amount | G4: YE AP match? | H4: Unprocessed match? | I4: Risk flag | J4: Above threshold? | K4: Date bucket | L4: Suggested selection? | M4: Rationale
A5: =Disbursements!A5 | B5: =Disbursements!B5 | C5: =B5-Inputs!$B$7 | D5: =Disbursements!D5 | E5: =Disbursements!E5 | F5: =Disbursements!F5 | G5: =IF(COUNTIFS('YE AP Aging'!$B$5:$B$500,D5,'YE AP Aging'!$C$5:$C$500,E5)>0,"Yes","No") | H5: =IF(COUNTIFS('Unprocessed Invoices'!$C$5:$C$500,D5,'Unprocessed Invoices'!$D$5:$D$500,E5)>0,"Yes","No") | I5: =IF(OR(G5="No",H5="Yes",COUNTIF($E$5:E5,E5)>1),"Review","Routine") | J5: =IF(F5>=Inputs!$B$13,"Yes","No") | K5: =IF(C5<=Inputs!$B$19,"0-30 days",IF(C5<=Inputs!$B$20,"31-60 days","61+ days")) | L5: =IF(OR(I5="Review",J5="Yes",MOD(ROW()-5,3)=0),"SELECT","") | M5: =IF(L5="SELECT",IF(I5="Review","Unmatched / voucher link / duplicate flag",IF(J5="Yes","Above individually significant threshold","Date/population coverage")),"Not auto-selected; auditor may add")
A6: =Disbursements!A6 | B6: =Disbursements!B6 | C6: =B6-Inputs!$B$7 | D6: =Disbursements!D6 | E6: =Disbursements!E6 | F6: =Disbursements!F6 | G6: =IF(COUNTIFS('YE AP Aging'!$B$5:$B$500,D6,'YE AP Aging'!$C$5:$C$500,E6)>0,"Yes","No") | H6: =IF(COUNTIFS('Unprocessed Invoices'!$C$5:$C$500,D6,'Unprocessed Invoices'!$D$5:$D$500,E6)>0,"Yes","No") | I6: =IF(OR(G6="No",H6="Yes",COUNTIF($E$5:E6,E6)>1),"Review","Routine") | J6: =IF(F6>=Inputs!$B$13,"Yes","No") | K6: =IF(C6<=Inputs!$B$19,"0-30 days",IF(C6<=Inputs!$B$20,"31-60 days","61+ days")) | L6: =IF(OR(I6="Review",J6="Yes",MOD(ROW()-5,3)=0),"SELECT","") | M6: =IF(L6="SELECT",IF(I6="Review","Unmatched / voucher link / duplicate flag",IF(J6="Yes","Above individually significant threshold","Date/population coverage")),"Not auto-selected; auditor may add")
A7: =Disbursements!A7 | B7: =Disbursements!B7 | C7: =B7-Inputs!$B$7 | D7: =Disbursements!D7 | E7: =Disbursements!E7 | F7: =Disbursements!F7 | G7: =IF(COUNTIFS('YE AP Aging'!$B$5:$B$500,D7,'YE AP Aging'!$C$5:$C$500,E7)>0,"Yes","No") | H7: =IF(COUNTIFS('Unprocessed Invoices'!$C$5:$C$500,D7,'Unprocessed Invoices'!$D$5:$D$500,E7)>0,"Yes","No") | I7: =IF(OR(G7="No",H7="Yes",COUNTIF($E$5:E7,E7)>1),"Review","Routine") | J7: =IF(F7>=Inputs!$B$13,"Yes","No") | K7: =IF(C7<=Inputs!$B$19,"0-30 days",IF(C7<=Inputs!$B$20,"31-60 days","61+ days")) | L7: =IF(OR(I7="Review",J7="Yes",MOD(ROW()-5,3)=0),"SELECT","") | M7: =IF(L7="SELECT",IF(I7="Review","Unmatched / voucher link / duplicate flag",IF(J7="Yes","Above individually significant threshold","Date/population coverage")),"Not auto-selected; auditor may add")
A8: =Disbursements!A8 | B8: =Disbursements!B8 | C8: =B8-Inputs!$B$7 | D8: =Disbursements!D8 | E8: =Disbursements!E8 | F8: =Disbursements!F8 | G8: =IF(COUNTIFS('YE AP Aging'!$B$5:$B$500,D8,'YE AP Aging'!$C$5:$C$500,E8)>0,"Yes","No") | H8: =IF(COUNTIFS('Unprocessed Invoices'!$C$5:$C$500,D8,'Unprocessed Invoices'!$D$5:$D$500,E8)>0,"Yes","No") | I8: =IF(OR(G8="No",H8="Yes",COUNTIF($E$5:E8,E8)>1),"Review","Routine") | J8: =IF(F8>=Inputs!$B$13,"Yes","No") | K8: =IF(C8<=Inputs!$B$19,"0-30 days",IF(C8<=Inputs!$B$20,"31-60 days","61+ days")) | L8: =IF(OR(I8="Review",J8="Yes",MOD(ROW()-5,3)=0),"SELECT","") | M8: =IF(L8="SELECT",IF(I8="Review","Unmatched / voucher link / duplicate flag",IF(J8="Yes","Above individually significant threshold","Date/population coverage")),"Not auto-selected; auditor may add")
A9: =Disbursements!A9 | B9: =Disbursements!B9 | C9: =B9-Inputs!$B$7 | D9: =Disbursements!D9 | E9: =Disbursements!E9 | F9: =Disbursements!F9 | G9: =IF(COUNTIFS('YE AP Aging'!$B$5:$B$500,D9,'YE AP Aging'!$C$5:$C$500,E9)>0,"Yes","No") | H9: =IF(COUNTIFS('Unprocessed Invoices'!$C$5:$C$500,D9,'Unprocessed Invoices'!$D$5:$D$500,E9)>0,"Yes","No") | I9: =IF(OR(G9="No",H9="Yes",COUNTIF($E$5:E9,E9)>1),"Review","Routine") | J9: =IF(F9>=Inputs!$B$13,"Yes","No") | K9: =IF(C9<=Inputs!$B$19,"0-30 days",IF(C9<=Inputs!$B$20,"31-60 days","61+ days")) | L9: =IF(OR(I9="Review",J9="Yes",MOD(ROW()-5,3)=0),"SELECT","") | M9: =IF(L9="SELECT",IF(I9="Review","Unmatched / voucher link / duplicate flag",IF(J9="Yes","Above individually significant threshold","Date/population coverage")),"Not auto-selected; auditor may add")
A10: =Disbursements!A10 | B10: =Disbursements!B10 | C10: =B10-Inputs!$B$7 | D10: =Disbursements!D10 | E10: =Disbursements!E10 | F10: =Disbursements!F10 | G10: =IF(COUNTIFS('YE AP Aging'!$B$5:$B$500,D10,'YE AP Aging'!$C$5:$C$500,E10)>0,"Yes","No") | H10: =IF(COUNTIFS('Unprocessed Invoices'!$C$5:$C$500,D10,'Unprocessed Invoices'!$D$5:$D$500,E10)>0,"Yes","No") | I10: =IF(OR(G10="No",H10="Yes",COUNTIF($E$5:E10,E10)>1),"Review","Routine") | J10: =IF(F10>=Inputs!$B$13,"Yes","No") | K10: =IF(C10<=Inputs!$B$19,"0-30 days",IF(C10<=Inputs!$B$20,"31-60 days","61+ days")) | L10: =IF(OR(I10="Review",J10="Yes",MOD(ROW()-5,3)=0),"SELECT","") | M10: =IF(L10="SELECT",IF(I10="Review","Unmatched / voucher link / duplicate flag",IF(J10="Yes","Above individually significant threshold","Date/population coverage")),"Not auto-selected; auditor may add")
A11: =Disbursements!A11 | B11: =Disbursements!B11 | C11: =B11-Inputs!$B$7 | D11: =Disbursements!D11 | E11: =Disbursements!E11 | F11: =Disbursements!F11 | G11: =IF(COUNTIFS('YE AP Aging'!$B$5:$B$500,D11,'YE AP Aging'!$C$5:$C$500,E11)>0,"Yes","No") | H11: =IF(COUNTIFS('Unprocessed Invoices'!$C$5:$C$500,D11,'Unprocessed Invoices'!$D$5:$D$500,E11)>0,"Yes","No") | I11: =IF(OR(G11="No",H11="Yes",COUNTIF($E$5:E11,E11)>1),"Review","Routine") | J11: =IF(F11>=Inputs!$B$13,"Yes","No") | K11: =IF(C11<=Inputs!$B$19,"0-30 days",IF(C11<=Inputs!$B$20,"31-60 days","61+ days")) | L11: =IF(OR(I11="Review",J11="Yes",MOD(ROW()-5,3)=0),"SELECT","") | M11: =IF(L11="SELECT",IF(I11="Review","Unmatched / voucher link / duplicate flag",IF(J11="Yes","Above individually significant threshold","Date/population coverage")),"Not auto-selected; auditor may add")
A12: =Disbursements!A12 | B12: =Disbursements!B12 | C12: =B12-Inputs!$B$7 | D12: =Disbursements!D12 | E12: =Disbursements!E12 | F12: =Disbursements!F12 | G12: =IF(COUNTIFS('YE AP Aging'!$B$5:$B$500,D12,'YE AP Aging'!$C$5:$C$500,E12)>0,"Yes","No") | H12: =IF(COUNTIFS('Unprocessed Invoices'!$C$5:$C$500,D12,'Unprocessed Invoices'!$D$5:$D$500,E12)>0,"Yes","No") | I12: =IF(OR(G12="No",H12="Yes",COUNTIF($E$5:E12,E12)>1),"Review","Routine") | J12: =IF(F12>=Inputs!$B$13,"Yes","No") | K12: =IF(C12<=Inputs!$B$19,"0-30 days",IF(C12<=Inputs!$B$20,"31-60 days","61+ days")) | L12: =IF(OR(I12="Review",J12="Yes",MOD(ROW()-5,3)=0),"SELECT","") | M12: =IF(L12="SELECT",IF(I12="Review","Unmatched / voucher link / duplicate flag",IF(J12="Yes","Above individually significant threshold","Date/population coverage")),"Not auto-selected; auditor may add")
A13: =Disbursements!A13 | B13: =Disbursements!B13 | C13: =B13-Inputs!$B$7 | D13: =Disbursements!D13 | E13: =Disbursements!E13 | F13: =Disbursements!F13 | G13: =IF(COUNTIFS('YE AP Aging'!$B$5:$B$500,D13,'YE AP Aging'!$C$5:$C$500,E13)>0,"Yes","No") | H13: =IF(COUNTIFS('Unprocessed Invoices'!$C$5:$C$500,D13,'Unprocessed Invoices'!$D$5:$D$500,E13)>0,"Yes","No") | I13: =IF(OR(G13="No",H13="Yes",COUNTIF($E$5:E13,E13)>1),"Review","Routine") | J13: =IF(F13>=Inputs!$B$13,"Yes","No") | K13: =IF(C13<=Inputs!$B$19,"0-30 days",IF(C13<=Inputs!$B$20,"31-60 days","61+ days")) | L13: =IF(OR(I13="Review",J13="Yes",MOD(ROW()-5,3)=0),"SELECT","") | M13: =IF(L13="SELECT",IF(I13="Review","Unmatched / voucher link / duplicate flag",IF(J13="Yes","Above individually significant threshold","Date/population coverage")),"Not auto-selected; auditor may add")
A14: =Disbursements!A14 | B14: =Disbursements!B14 | C14: =B14-Inputs!$B$7 | D14: =Disbursements!D14 | E14: =Disbursements!E14 | F14: =Disbursements!F14 | G14: =IF(COUNTIFS('YE AP Aging'!$B$5:$B$500,D14,'YE AP Aging'!$C$5:$C$500,E14)>0,"Yes","No") | H14: =IF(COUNTIFS('Unprocessed Invoices'!$C$5:$C$500,D14,'Unprocessed Invoices'!$D$5:$D$500,E14)>0,"Yes","No") | I14: =IF(OR(G14="No",H14="Yes",COUNTIF($E$5:E14,E14)>1),"Review","Routine") | J14: =IF(F14>=Inputs!$B$13,"Yes","No") | K14: =IF(C14<=Inputs!$B$19,"0-30 days",IF(C14<=Inputs!$B$20,"31-60 days","61+ days")) | L14: =IF(OR(I14="Review",J14="Yes",MOD(ROW()-5,3)=0),"SELECT","") | M14: =IF(L14="SELECT",IF(I14="Review","Unmatched / voucher link / duplicate flag",IF(J14="Yes","Above individually significant threshold","Date/population coverage")),"Not auto-selected; auditor may add")
A16: CAUTION | B16: This is a risk-based screening helper, not a statistically representative sample or a validated sample-size calculation. The engagement team must approve selection methodology, population completeness, sample size and any random selection.

Sheet Invoice Testing
A1: Invoice Testing Workpaper
A2: Complete for each selected item; attach or cross-reference invoice, PO/contract, receiving/service evidence, payment proof and GL/AP search.
A4: Sample ID | B4: Case / Payment ID | C4: Vendor | D4: Invoice Ref | E4: Amount | F4: Invoice obtained? | G4: PO / contract? | H4: Receipt/service evidence? | I4: Receipt/service date | J4: Related to YE? | K4: YE AP/accrual found? | L4: GL account / trace | M4: Duplicate / partial check | N4: Exception amount | O4: Exception / follow-up | P4: Conclusion | Q4: Reviewer/date
A5: S01 | B5: TC-01 | C5: Northstar Office Supplies | D5: NS-251188 | E5: 12500 | F5: Pending | G5: Pending | H5: Pending | I5: 46006 | J5: Pending | K5: Pending | M5: Pending | N5: 0 | P5: Pending
A6: S02 | B6: TC-02 | C6: Delta Electric | D6: DE-5510 | E6: 38700 | F6: Pending | G6: Pending | H6: Pending | I6: 46011 | J6: Pending | K6: Pending | M6: Pending | N6: 0 | P6: Pending
A7: S03 | B7: TC-03 | C7: Prime Janitorial | D7: PJ-0106 | E7: 14500 | F7: Pending | G7: Pending | H7: Pending | I7: 46053 | J7: Pending | K7: Pending | M7: Pending | N7: 0 | P7: Pending
A8: S04 | B8: TC-04 | C8: Beacon Consulting | D8: BC-882 | E8: 57000 | F8: Pending | G8: Pending | H8: Pending | I8: 46009 | J8: Pending | K8: Pending | M8: Pending | N8: 0 | P8: Pending

Sheet Workpaper Summary
A1: SURL Workpaper — Planning, Results & Conclusion
A2: Fill out preparer/reviewer fields and cross-reference evidence. This is a draft template for auditor review.
A4: Section | B4: Field | C4: Value / Formula | D4: Evidence reference / explanation | E4: Prepared by/date | F4: Reviewer/date
A5: Objective | B5: Audit objective | C5: Search for liabilities relating to the audit period that may have been omitted or recorded in the wrong period.
A6: Scope | B6: Audit period | C6: =Inputs!B6 | D6: Inputs tab
A7: Scope | B7: Year-end date | C7: =Inputs!B7 | D7: Inputs tab
A8: Population | B8: YE AP aging count | C8: =COUNTA('YE AP Aging'!A5:A500) | D8: Reconcile to AP subledger
A9: Population | B9: YE AP aging open balance | C9: =SUM('YE AP Aging'!G5:G500) | D9: Reconcile to AP control account / GL
A10: Population | B10: Subsequent disbursement count | C10: =COUNTA(Disbursements!A5:A500) | D10: Reconcile to bank/cash disbursement report
A11: Population | B11: Subsequent disbursement value | C11: =SUM(Disbursements!F5:F500) | D11: Reconcile to bank and cash disbursement GL
A12: Population | B12: Subsequent AP aging count | C12: =COUNTA('Subsequent AP Aging'!A5:A500) | D12: Tie to AP subledger as of subsequent date
A13: Population | B13: Unprocessed invoice count | C13: =COUNTA('Unprocessed Invoices'!A5:A500) | D13: Agree to AP system report / invoice register
A14: Population | B14: Trial balance total debits | C14: =SUM('Trial Balance'!D5:D500) | D14: Tie to signed trial balance
A15: Population | B15: Trial balance total credits | C15: =SUM('Trial Balance'!E5:E500) | D15: Tie to signed trial balance
A16: Sampling | B16: Suggested selected payments | C16: =COUNTIF('Sample Selection'!L5:L500,"SELECT") | D16: Selection helper; review and document rationale
A17: Sampling | B17: Selected payment value | C17: =SUMIF('Sample Selection'!L5:L500,"SELECT",'Sample Selection'!F5:F500) | D17: Coverage is descriptive, not a sufficiency criterion
A18: Materiality | B18: Overall materiality | C18: =Inputs!B10 | D18: Approved planning memo
A19: Materiality | B19: Performance materiality | C19: =Inputs!B11 | D19: Approved planning memo
A20: Materiality | B20: SURL tolerable misstatement | C20: =Inputs!B12 | D20: Approved procedure-specific threshold
A21: Procedures | B21: YE AP aging reconciled? | C21: Yes / No / N/A | D21: Document differences and resolution
A22: Procedures | B22: Subsequent disbursement listing reconciled? | C22: Yes / No / N/A | D22: Document source, date range, reconciliation
A23: Procedures | B23: Subsequent AP aging tested? | C23: Yes / No / N/A | D23: Use as complementary source, not replacement for YE aging
A24: Procedures | B24: Unprocessed invoices/vouchers tested? | C24: Yes / No / N/A | D24: Trace invoice/service/receipt dates and search ledger
A25: Procedures | B25: Unmatched receiving reports / open POs considered? | C25: Yes / No / N/A | D25: Document sources considered
A26: Results | B26: Exceptions identified (count) | C26: Enter count | D26: Cross-reference Invoice Testing
A27: Results | B27: Potential omitted liability amount | C27: Enter amount | D27: Evidence-based; avoid double counting the same invoice across sources
A28: Conclusion | B28: Conclusion | C28: Draft only — based on procedures performed and evidence obtained, determine whether additional procedures or adjustment are required. | D28: Must be completed by auditor and reviewed

Sheet Procedure Guide
A1: Procedure Guide — SURL
A2: Use with applicable auditing standards and the firm's methodology. Not a substitute for professional judgment.
A4: Topic | B4: Procedure / decision | C4: Documentation expected | D4: Key caution
A5: Year-end AP aging | B5: Obtain full aging as of reporting date; agree totals to AP subledger and GL control account; investigate unusual balances, credit balances and cut-off. | C5: Population count/value, reconciliation, differences and resolution. | D5: Recorded AP testing does not by itself find omitted liabilities.
A6: Subsequent disbursements | B6: Obtain full listing from year-end to appropriate cutoff/report date; reconcile to bank statements, cash disbursement journal and GL where possible. | C6: Source, date window, population count/value, reconciliation, selection method. | D6: Payment date alone does not prove period relevance.
A7: Subsequent AP aging | B7: Obtain AP aging as of a later date to identify items still open and settlements; trace relevant items back to YE and source docs. | C7: Subsequent balance, invoice date, receipt/service date, posting and settlement dates. | D7: Useful corroborative source, not a replacement for year-end AP aging.
A8: Unprocessed invoices | B8: Obtain invoices received/processed after YE, voucher hold/unmatched register, unmatched receiving reports and relevant vendor statements. | C8: Date received, invoice date, goods receipt/service date, posting date and ledger trace. | D8: Can identify unpaid or unprocessed obligations missed by payment search.
A9: Trial balance | B9: Tie AP control and accrual accounts to ledgers; scan relevant expense accounts and unusual journal entries; search for liabilities posted to other accounts. | C9: TB date, AP/accrual account totals, reconciliations and unusual entries. | D9: The TB must be balanced and agree to the ledger; do not infer completeness from balance alone.
A10: Materiality | B10: Use approved overall materiality, performance materiality and SURL tolerable misstatement; set a documented individually significant threshold. | C10: Planning memo references and rationale. | D10: Do not automatically change materiality based on payment date.
A11: Sample size | B11: Determine whether specific-item, non-statistical or statistical sampling is appropriate. Consider population, tolerable misstatement, expected error, risk and other substantive evidence. | C11: Sampling objective, population, sample method, factors, rationale and selected items. | D11: No universal formula using only materiality and population count. Statistical inference requires a valid statistical design.
A12: Date window | B12: Consider reporting date, audit report date, payment cycle, risks and available evidence; date buckets help ensure temporal coverage. | C12: Why the start/end date is appropriate; whether later window added more risk coverage. | D12: A later payment may settle an old liability; an early payment may relate to post-period services.
A13: Include / exclude | B13: Include as potential SURL when goods/services relate to the audit period and no year-end liability is identified. Exclude post-period goods/services unless other facts indicate a YE obligation. Escalate uncertain cases. | C13: Invoice, PO/contract, receiving/service evidence, AP/accrual/GL search and conclusion. | D13: Distinguish potential exception from confirmed unrecorded liability.
A14: Duplicate / partial payment | B14: Compare vendor, invoice number, amount, payment history and open balance; investigate repeated refs and split/partial payments. | C14: Payment-to-invoice reconciliation and remaining balance calculation. | D14: Duplicates are not automatically omitted liabilities; they may indicate payment error or data issue.
A15: Conclusion | B15: Aggregate exceptions without double counting and evaluate against tolerable misstatement/materiality and qualitative factors; expand work when warranted. | C15: Exception log, proposed adjustment, follow-up and reviewer sign-off. | D15: Tool-generated flags are not final audit judgments.
