Workbook

Sheet ReadMe
B2: Tax & Labour-Code Compliance Tracker
B3: ICAI AICA Level 2 Capstone Project
B6: What this workbook is
C7: A single source of truth for every recurring tax / GST / labour-code compliance,
C8: who owns it, when it is due, and whether it has been paid & completed.
C9: An n8n workflow reads the 'Task Instances' sheet daily to send escalating reminder emails,
C10: a dashboard reads it to show Due / Completed / Overdue by department, and a month-end
C11: script reads it to generate a PDF report and compare payments against the Trial Balance.
B13: Sheet guide
B14: Task Templates | C14: The master catalogue of compliance TYPES (e.g. 'GSTR-3B'). Add a new row here
C15: any time a new compliance needs to be tracked - this is how you 'keep adding to the list'.
C16: Mark Active = Y and re-run generate_instances.py (or the n8n 'Regenerate Instances' workflow)
C17: to create actual due-date rows in Task Instances for the current financial year.
B18: Users | C18: Directory of users, their supervisor and department HOD, with email addresses.
C19: REPLACE the placeholder names/emails (yellow) with your real team before going live.
B20: Task Instances | C20: One row per actual due date in the FY. This is the live working sheet:
C21: the user keys in Amount Paid, Payment Date, and ticks Task Complete when done.
C22: Status, Days To Due and Reminder Stage are formulas - do not overtype them.
B23: Trial Balance | C23: Paste/upload the monthly trial balance (GL Code, GL Name, Balance, Period).
B24: Variance Report | C24: Auto-compares actual tax paid (from Task Instances) to the Trial Balance
C25: GL balance for the same GL code & period, and flags any difference.
B27: Due Pattern syntax (Task Templates column E)
B28: M:d | C28: Monthly, due on day d of every month, e.g. M:7 = 7th of every month
B29: Q:d@m1,m2,m3,m4 | C29: Quarterly, due on day d in the given 4 months, e.g. Q:15@5,7,10,1
B30: H:d1@m1;d2@m2 | C30: Half-yearly, different day/month pairs, e.g. H:30@4;31@10
B31: A:d@m | C31: Annual, due on day d of month m, e.g. A:31@10 = 31 October
C32: Months are calendar month numbers (1=Jan...12=Dec). The FY used is Apr-Mar; a month
C33: of 1-3 (Jan-Mar) is placed in the following calendar year automatically.
B35: Reminder / escalation logic (implemented in the n8n workflow)
B36: Stage 1 | C36: Due date - 2 days: email to the assigned User only.
B37: Stage 2 | C37: Due date - 1 day, if not yet paid/completed: email to User, CC Supervisor.
B38: Stage 3 | C38: On the due date, if still not paid/completed: email to User, Supervisor and HOD,
C39: and repeated every day thereafter until Amount Paid is filled AND Task Complete = Y.
C40: Frequency of the whole cycle (monthly/quarterly/annual) is taken automatically from
C41: the Periodicity of the task in Task Templates / Task Instances.

Sheet Users
A1: Name | B1: Email | C1: Department | D1: Role | E1: Reports To (Email)
A2: Ritesh Garodia | B2: riteshgarodia@yahoo.com | C2: Direct Tax | D2: User | E2: garodia1.ritesh@gmail.com
A3: Ritesh Garodia | B3: riteshgarodia@yahoo.com | C3: GST | D3: User | E3: garodia1.ritesh@gmail.com
A4: Ritesh Garodia | B4: riteshgarodia@yahoo.com | C4: Payroll | D4: User | E4: garodia1.ritesh@gmail.com
A5: Ritesh Garodia | B5: garodia1.ritesh@gmail.com | C5: All | D5: Supervisor | E5: garodia1.ritesh@gmail.com
A6: Ritesh Garodia | B6: garodia1.ritesh@gmail.com | C6: All | D6: HOD
A8: Demo setup: only the account holder's own two email addresses are used across all roles (User = riteshgarodia@yahoo.com, Supervisor/HOD = garodia1.ritesh@gmail.com). Replace with real team emails when this moves from demo to production.

Sheet Task Templates
A1: Task ID | B1: Compliance Name | C1: Department | D1: Periodicity | E1: Due Pattern | F1: GL Code | G1: Assigned User Email | H1: Supervisor Email | I1: Active (Y/N) | J1: Notes | K1: <-- Add new compliance items below the last row. Set Active = Y, then re-run generate_instances.py to create this FY's due dates for it.
A2: DT-01 | B2: TDS/TCS Payment (Monthly) | C2: Direct Tax | D2: Monthly | E2: M:7 | F2: TDS-PAY | G2: riteshgarodia@yahoo.com | H2: garodia1.ritesh@gmail.com | I2: Y | J2: Source file
A3: DT-02 | B3: TCS Return (Quarterly) | C3: Direct Tax | D3: Quarterly | E3: Q:15@5,7,10,1 | F3: TCS-RET | G3: riteshgarodia@yahoo.com | H3: garodia1.ritesh@gmail.com | I3: Y | J3: Source file
A4: DT-03 | B4: TDS Return (Quarterly) | C4: Direct Tax | D4: Quarterly | E4: Q:31@5,7,10,1 | F4: TDS-RET | G4: riteshgarodia@yahoo.com | H4: garodia1.ritesh@gmail.com | I4: Y | J4: Source file
A5: DT-04 | B5: Form 61/62 (Half-Yearly) | C5: Direct Tax | D5: Half-Yearly | E5: H:30@4;31@10 | F5: F61-62 | G5: riteshgarodia@yahoo.com | H5: garodia1.ritesh@gmail.com | I5: Y | J5: Source file
A6: DT-05 | B6: Tax Audit | C6: Direct Tax | D6: Annual | E6: A:31@10 | F6: TAX-AUD | G6: riteshgarodia@yahoo.com | H6: garodia1.ritesh@gmail.com | I6: Y | J6: Source file: 'Tax Audit- MMFSL'
A7: DT-06 | B7: Form 3CEB | C7: Direct Tax | D7: Annual | E7: A:31@10 | F7: F3CEB | G7: riteshgarodia@yahoo.com | H7: garodia1.ritesh@gmail.com | I7: Y | J7: Source file
A8: DT-07 | B8: Income Tax Return | C8: Direct Tax | D8: Annual | E8: A:30@11 | F8: ITR | G8: riteshgarodia@yahoo.com | H8: garodia1.ritesh@gmail.com | I8: Y | J8: Source file
A9: DT-08 | B9: Form 67 - FTC (if any) | C9: Direct Tax | D9: Annual | E9: A:30@11 | F9: F67-FTC | G9: riteshgarodia@yahoo.com | H9: garodia1.ritesh@gmail.com | I9: Y | J9: Source file
A10: DT-09 | B10: Issue of TDS/TCS Certificate | C10: Direct Tax | D10: Quarterly | E10: Q:15@5,7,10,1 | F10: TDS-CERT | G10: riteshgarodia@yahoo.com | H10: garodia1.ritesh@gmail.com | I10: Y | J10: Source file
A11: DT-10 | B11: SFT Return - 61B | C11: Direct Tax | D11: Annual | E11: A:31@5 | F11: SFT61B | G11: riteshgarodia@yahoo.com | H11: garodia1.ritesh@gmail.com | I11: Y | J11: Source file
A12: DT-11 | B12: FATCA/CRS Compliance | C12: Direct Tax | D12: Annual | E12: A:31@5 | F12: FATCA | G12: riteshgarodia@yahoo.com | H12: garodia1.ritesh@gmail.com | I12: Y | J12: Source file
A13: DT-12 | B13: Advance Tax Payment | C13: Direct Tax | D13: Quarterly | E13: Q:15@6,9,12,3 | F13: ADV-TAX | G13: riteshgarodia@yahoo.com | H13: garodia1.ritesh@gmail.com | I13: Y | J13: Source file
... A30: PR-09 | B30: PF Annual Return (Form 3A/6A) | C30: Payroll | D30: Annual | E30: A:30@4 | F30: PF-ANN | G30: riteshgarodia@yahoo.com | H30: garodia1.ritesh@gmail.com | I30: Y | J30: Standard set

Sheet Task Instances
A1: Instance ID | B1: Task ID | C1: Compliance Name | D1: Department | E1: Periodicity | F1: Due Date | G1: Assigned User Email | H1: Assigned User Name | I1: Supervisor Email | J1: Supervisor Name | K1: HOD Email | L1: HOD Name | M1: GL Code | N1: Amount Due | O1: Amount Paid | P1: Payment Date | Q1: Task Complete (Y/N) | R1: Days To Due | S1: Status | T1: Reminder Stage | U1: Last Reminder Sent | V1: Remarks
A2: DT-01-20260407 | B2: DT-01 | C2: TDS/TCS Payment (Monthly) | D2: Direct Tax | E2: Monthly | F2: 46119 | G2: riteshgarodia@yahoo.com | H2: =IFERROR(INDEX(Users!$A:$A,MATCH($G2,Users!$B:$B,0)),"") -> Ritesh Garodia | I2: garodia1.ritesh@gmail.com | J2: =IFERROR(INDEX(Users!$A:$A,MATCH($I2,Users!$B:$B,0)),"") -> Ritesh Garodia | K2: =Users!$B$6 -> garodia1.ritesh@gmail.com | L2: =Users!$A$6 -> Ritesh Garodia | M2: TDS-PAY | Q2: N | R2: =$F2-TODAY() -> -166 | S2: =IF($Q2="Y","Completed",IF(TODAY()>$F2,"Overdue","Pending")) -> Overdue | T2: =IF($Q2="Y","-",IF($R2<=0,"Stage 3 - Final/Daily (due or overdue)",IF($R2=1,"Stage 2 - T-1 (CC Supervisor)",IF($R2=2,"Stage 1 - T-2","Not yet due")))) -> Stage 3 - Final/Daily (due or overdue)
A3: DT-01-20260507 | B3: DT-01 | C3: TDS/TCS Payment (Monthly) | D3: Direct Tax | E3: Monthly | F3: 46149 | G3: riteshgarodia@yahoo.com | H3: =IFERROR(INDEX(Users!$A:$A,MATCH($G3,Users!$B:$B,0)),"") -> Ritesh Garodia | I3: garodia1.ritesh@gmail.com | J3: =IFERROR(INDEX(Users!$A:$A,MATCH($I3,Users!$B:$B,0)),"") -> Ritesh Garodia | K3: =Users!$B$6 -> garodia1.ritesh@gmail.com | L3: =Users!$A$6 -> Ritesh Garodia | M3: TDS-PAY | Q3: N | R3: =$F3-TODAY() -> -136 | S3: =IF($Q3="Y","Completed",IF(TODAY()>$F3,"Overdue","Pending")) -> Overdue | T3: =IF($Q3="Y","-",IF($R3<=0,"Stage 3 - Final/Daily (due or overdue)",IF($R3=1,"Stage 2 - T-1 (CC Supervisor)",IF($R3=2,"Stage 1 - T-2","Not yet due")))) -> Stage 3 - Final/Daily (due or overdue)
A4: DT-01-20260607 | B4: DT-01 | C4: TDS/TCS Payment (Monthly) | D4: Direct Tax | E4: Monthly | F4: 46180 | G4: riteshgarodia@yahoo.com | H4: =IFERROR(INDEX(Users!$A:$A,MATCH($G4,Users!$B:$B,0)),"") -> Ritesh Garodia | I4: garodia1.ritesh@gmail.com | J4: =IFERROR(INDEX(Users!$A:$A,MATCH($I4,Users!$B:$B,0)),"") -> Ritesh Garodia | K4: =Users!$B$6 -> garodia1.ritesh@gmail.com | L4: =Users!$A$6 -> Ritesh Garodia | M4: TDS-PAY | Q4: N | R4: =$F4-TODAY() -> -105 | S4: =IF($Q4="Y","Completed",IF(TODAY()>$F4,"Overdue","Pending")) -> Overdue | T4: =IF($Q4="Y","-",IF($R4<=0,"Stage 3 - Final/Daily (due or overdue)",IF($R4=1,"Stage 2 - T-1 (CC Supervisor)",IF($R4=2,"Stage 1 - T-2","Not yet due")))) -> Stage 3 - Final/Daily (due or overdue)
A5: DT-01-20260707 | B5: DT-01 | C5: TDS/TCS Payment (Monthly) | D5: Direct Tax | E5: Monthly | F5: 46210 | G5: riteshgarodia@yahoo.com | H5: =IFERROR(INDEX(Users!$A:$A,MATCH($G5,Users!$B:$B,0)),"") -> Ritesh Garodia | I5: garodia1.ritesh@gmail.com | J5: =IFERROR(INDEX(Users!$A:$A,MATCH($I5,Users!$B:$B,0)),"") -> Ritesh Garodia | K5: =Users!$B$6 -> garodia1.ritesh@gmail.com | L5: =Users!$A$6 -> Ritesh Garodia | M5: TDS-PAY | Q5: N | R5: =$F5-TODAY() -> -75 | S5: =IF($Q5="Y","Completed",IF(TODAY()>$F5,"Overdue","Pending")) -> Overdue | T5: =IF($Q5="Y","-",IF($R5<=0,"Stage 3 - Final/Daily (due or overdue)",IF($R5=1,"Stage 2 - T-1 (CC Supervisor)",IF($R5=2,"Stage 1 - T-2","Not yet due")))) -> Stage 3 - Final/Daily (due or overdue)
A6: DT-01-20260807 | B6: DT-01 | C6: TDS/TCS Payment (Monthly) | D6: Direct Tax | E6: Monthly | F6: 46241 | G6: riteshgarodia@yahoo.com | H6: =IFERROR(INDEX(Users!$A:$A,MATCH($G6,Users!$B:$B,0)),"") -> Ritesh Garodia | I6: garodia1.ritesh@gmail.com | J6: =IFERROR(INDEX(Users!$A:$A,MATCH($I6,Users!$B:$B,0)),"") -> Ritesh Garodia | K6: =Users!$B$6 -> garodia1.ritesh@gmail.com | L6: =Users!$A$6 -> Ritesh Garodia | M6: TDS-PAY | Q6: N | R6: =$F6-TODAY() -> -44 | S6: =IF($Q6="Y","Completed",IF(TODAY()>$F6,"Overdue","Pending")) -> Overdue | T6: =IF($Q6="Y","-",IF($R6<=0,"Stage 3 - Final/Daily (due or overdue)",IF($R6=1,"Stage 2 - T-1 (CC Supervisor)",IF($R6=2,"Stage 1 - T-2","Not yet due")))) -> Stage 3 - Final/Daily (due or overdue)
A7: DT-01-20260907 | B7: DT-01 | C7: TDS/TCS Payment (Monthly) | D7: Direct Tax | E7: Monthly | F7: 46272 | G7: riteshgarodia@yahoo.com | H7: =IFERROR(INDEX(Users!$A:$A,MATCH($G7,Users!$B:$B,0)),"") -> Ritesh Garodia | I7: garodia1.ritesh@gmail.com | J7: =IFERROR(INDEX(Users!$A:$A,MATCH($I7,Users!$B:$B,0)),"") -> Ritesh Garodia | K7: =Users!$B$6 -> garodia1.ritesh@gmail.com | L7: =Users!$A$6 -> Ritesh Garodia | M7: TDS-PAY | Q7: N | R7: =$F7-TODAY() -> -13 | S7: =IF($Q7="Y","Completed",IF(TODAY()>$F7,"Overdue","Pending")) -> Overdue | T7: =IF($Q7="Y","-",IF($R7<=0,"Stage 3 - Final/Daily (due or overdue)",IF($R7=1,"Stage 2 - T-1 (CC Supervisor)",IF($R7=2,"Stage 1 - T-2","Not yet due")))) -> Stage 3 - Final/Daily (due or overdue)
A8: DT-01-20261007 | B8: DT-01 | C8: TDS/TCS Payment (Monthly) | D8: Direct Tax | E8: Monthly | F8: 46302 | G8: riteshgarodia@yahoo.com | H8: =IFERROR(INDEX(Users!$A:$A,MATCH($G8,Users!$B:$B,0)),"") -> Ritesh Garodia | I8: garodia1.ritesh@gmail.com | J8: =IFERROR(INDEX(Users!$A:$A,MATCH($I8,Users!$B:$B,0)),"") -> Ritesh Garodia | K8: =Users!$B$6 -> garodia1.ritesh@gmail.com | L8: =Users!$A$6 -> Ritesh Garodia | M8: TDS-PAY | Q8: N | R8: =$F8-TODAY() -> 17 | S8: =IF($Q8="Y","Completed",IF(TODAY()>$F8,"Overdue","Pending")) -> Pending | T8: =IF($Q8="Y","-",IF($R8<=0,"Stage 3 - Final/Daily (due or overdue)",IF($R8=1,"Stage 2 - T-1 (CC Supervisor)",IF($R8=2,"Stage 1 - T-2","Not yet due")))) -> Not yet due
A9: DT-01-20261107 | B9: DT-01 | C9: TDS/TCS Payment (Monthly) | D9: Direct Tax | E9: Monthly | F9: 46333 | G9: riteshgarodia@yahoo.com | H9: =IFERROR(INDEX(Users!$A:$A,MATCH($G9,Users!$B:$B,0)),"") -> Ritesh Garodia | I9: garodia1.ritesh@gmail.com | J9: =IFERROR(INDEX(Users!$A:$A,MATCH($I9,Users!$B:$B,0)),"") -> Ritesh Garodia | K9: =Users!$B$6 -> garodia1.ritesh@gmail.com | L9: =Users!$A$6 -> Ritesh Garodia | M9: TDS-PAY | Q9: N | R9: =$F9-TODAY() -> 48 | S9: =IF($Q9="Y","Completed",IF(TODAY()>$F9,"Overdue","Pending")) -> Pending | T9: =IF($Q9="Y","-",IF($R9<=0,"Stage 3 - Final/Daily (due or overdue)",IF($R9=1,"Stage 2 - T-1 (CC Supervisor)",IF($R9=2,"Stage 1 - T-2","Not yet due")))) -> Not yet due
A10: DT-01-20261207 | B10: DT-01 | C10: TDS/TCS Payment (Monthly) | D10: Direct Tax | E10: Monthly | F10: 46363 | G10: riteshgarodia@yahoo.com | H10: =IFERROR(INDEX(Users!$A:$A,MATCH($G10,Users!$B:$B,0)),"") -> Ritesh Garodia | I10: garodia1.ritesh@gmail.com | J10: =IFERROR(INDEX(Users!$A:$A,MATCH($I10,Users!$B:$B,0)),"") -> Ritesh Garodia | K10: =Users!$B$6 -> garodia1.ritesh@gmail.com | L10: =Users!$A$6 -> Ritesh Garodia | M10: TDS-PAY | Q10: N | R10: =$F10-TODAY() -> 78 | S10: =IF($Q10="Y","Completed",IF(TODAY()>$F10,"Overdue","Pending")) -> Pending | T10: =IF($Q10="Y","-",IF($R10<=0,"Stage 3 - Final/Daily (due or overdue)",IF($R10=1,"Stage 2 - T-1 (CC Supervisor)",IF($R10=2,"Stage 1 - T-2","Not yet due")))) -> Not yet due
A11: DT-01-20270107 | B11: DT-01 | C11: TDS/TCS Payment (Monthly) | D11: Direct Tax | E11: Monthly | F11: 46394 | G11: riteshgarodia@yahoo.com | H11: =IFERROR(INDEX(Users!$A:$A,MATCH($G11,Users!$B:$B,0)),"") -> Ritesh Garodia | I11: garodia1.ritesh@gmail.com | J11: =IFERROR(INDEX(Users!$A:$A,MATCH($I11,Users!$B:$B,0)),"") -> Ritesh Garodia | K11: =Users!$B$6 -> garodia1.ritesh@gmail.com | L11: =Users!$A$6 -> Ritesh Garodia | M11: TDS-PAY | Q11: N | R11: =$F11-TODAY() -> 109 | S11: =IF($Q11="Y","Completed",IF(TODAY()>$F11,"Overdue","Pending")) -> Pending | T11: =IF($Q11="Y","-",IF($R11<=0,"Stage 3 - Final/Daily (due or overdue)",IF($R11=1,"Stage 2 - T-1 (CC Supervisor)",IF($R11=2,"Stage 1 - T-2","Not yet due")))) -> Not yet due
A12: DT-01-20270207 | B12: DT-01 | C12: TDS/TCS Payment (Monthly) | D12: Direct Tax | E12: Monthly | F12: 46425 | G12: riteshgarodia@yahoo.com | H12: =IFERROR(INDEX(Users!$A:$A,MATCH($G12,Users!$B:$B,0)),"") -> Ritesh Garodia | I12: garodia1.ritesh@gmail.com | J12: =IFERROR(INDEX(Users!$A:$A,MATCH($I12,Users!$B:$B,0)),"") -> Ritesh Garodia | K12: =Users!$B$6 -> garodia1.ritesh@gmail.com | L12: =Users!$A$6 -> Ritesh Garodia | M12: TDS-PAY | Q12: N | R12: =$F12-TODAY() -> 140 | S12: =IF($Q12="Y","Completed",IF(TODAY()>$F12,"Overdue","Pending")) -> Pending | T12: =IF($Q12="Y","-",IF($R12<=0,"Stage 3 - Final/Daily (due or overdue)",IF($R12=1,"Stage 2 - T-1 (CC Supervisor)",IF($R12=2,"Stage 1 - T-2","Not yet due")))) -> Not yet due
A13: DT-01-20270307 | B13: DT-01 | C13: TDS/TCS Payment (Monthly) | D13: Direct Tax | E13: Monthly | F13: 46453 | G13: riteshgarodia@yahoo.com | H13: =IFERROR(INDEX(Users!$A:$A,MATCH($G13,Users!$B:$B,0)),"") -> Ritesh Garodia | I13: garodia1.ritesh@gmail.com | J13: =IFERROR(INDEX(Users!$A:$A,MATCH($I13,Users!$B:$B,0)),"") -> Ritesh Garodia | K13: =Users!$B$6 -> garodia1.ritesh@gmail.com | L13: =Users!$A$6 -> Ritesh Garodia | M13: TDS-PAY | Q13: N | R13: =$F13-TODAY() -> 168 | S13: =IF($Q13="Y","Completed",IF(TODAY()>$F13,"Overdue","Pending")) -> Pending | T13: =IF($Q13="Y","-",IF($R13<=0,"Stage 3 - Final/Daily (due or overdue)",IF($R13=1,"Stage 2 - T-1 (CC Supervisor)",IF($R13=2,"Stage 1 - T-2","Not yet due")))) -> Not yet due
... A146: PR-09-20260430 | B146: PR-09 | C146: PF Annual Return (Form 3A/6A) | D146: Payroll | E146: Annual | F146: 46142 | G146: riteshgarodia@yahoo.com | H146: =IFERROR(INDEX(Users!$A:$A,MATCH($G146,Users!$B:$B,0)),"") -> Ritesh Garodia | I146: garodia1.ritesh@gmail.com | J146: =IFERROR(INDEX(Users!$A:$A,MATCH($I146,Users!$B:$B,0)),"") -> Ritesh Garodia | K146: =Users!$B$6 -> garodia1.ritesh@gmail.com | L146: =Users!$A$6 -> Ritesh Garodia | M146: PF-ANN | Q146: N | R146: =$F146-TODAY() -> -143 | S146: =IF($Q146="Y","Completed",IF(TODAY()>$F146,"Overdue","Pending")) -> Overdue | T146: =IF($Q146="Y","-",IF($R146<=0,"Stage 3 - Final/Daily (due or overdue)",IF($R146=1,"Stage 2 - T-1 (CC Supervisor)",IF($R146=2,"Stage 1 - T-2","Not yet due")))) -> Stage 3 - Final/Daily (due or overdue)

Sheet Trial Balance
A1: Period (mmm-yyyy) | B1: GL Code | C1: GL Name | D1: TB Balance (Dr)
A2: Apr-2026 | B2: GSTR3B | C2: GST Payable - Output | D2: 125000
A3: Apr-2026 | B3: TDS-PAY | C3: TDS Payable - Contractors | D3: 48000
A4: Apr-2026 | B4: PF-PAY | C4: PF Payable | D4: 62000
A6: Example rows above (yellow) - replace with your actual monthly Trial Balance export. GL Code must match the GL Code used in Task Templates for that compliance.

Sheet Variance Report
A1: Period (mmm-yyyy) | B1: GL Code | C1: GL Name | D1: Trial Balance Amount | E1: Actual Amount Paid (Task Instances) | F1: Variance (TB - Paid) | G1: Flag
A2: ='Trial Balance'!A2 -> Apr-2026 | B2: ='Trial Balance'!B2 -> GSTR3B | C2: ='Trial Balance'!C2 -> GST Payable - Output | D2: ='Trial Balance'!D2 -> 125000 | E2: =SUMPRODUCT(('Task Instances'!$M$2:$M$147=$B2)*(TEXT('Task Instances'!$P$2:$P$147,"mmm-yyyy")=$A2)*'Task Instances'!$O$2:$O$147) -> 0 | F2: =$D2-$E2 -> 125000 | G2: =IF(ABS($F2)<=1,"OK","VARIANCE") -> VARIANCE
A3: ='Trial Balance'!A3 -> Apr-2026 | B3: ='Trial Balance'!B3 -> TDS-PAY | C3: ='Trial Balance'!C3 -> TDS Payable - Contractors | D3: ='Trial Balance'!D3 -> 48000 | E3: =SUMPRODUCT(('Task Instances'!$M$2:$M$147=$B3)*(TEXT('Task Instances'!$P$2:$P$147,"mmm-yyyy")=$A3)*'Task Instances'!$O$2:$O$147) -> 0 | F3: =$D3-$E3 -> 48000 | G3: =IF(ABS($F3)<=1,"OK","VARIANCE") -> VARIANCE
A4: ='Trial Balance'!A4 -> Apr-2026 | B4: ='Trial Balance'!B4 -> PF-PAY | C4: ='Trial Balance'!C4 -> PF Payable | D4: ='Trial Balance'!D4 -> 62000 | E4: =SUMPRODUCT(('Task Instances'!$M$2:$M$147=$B4)*(TEXT('Task Instances'!$P$2:$P$147,"mmm-yyyy")=$A4)*'Task Instances'!$O$2:$O$147) -> 0 | F4: =$D4-$E4 -> 62000 | G4: =IF(ABS($F4)<=1,"OK","VARIANCE") -> VARIANCE
A6: This report auto-populates once the Trial Balance sheet is filled and Task Instances have Amount Paid + Payment Date keyed in for the same period/GL Code.
