Workbook

Sheet README
A1: DTRS – Dummy Organisation and Master Data
A2: Company: Sample Manufacturing Industries Pvt Ltd (SMIPL) – FICTITIOUS. All names, codes and emails are invented for development, testing and the ICAI course submission.
A3: Companion to: BRD – Department Task & Review System (DTRS), v0.1
A5: Sheets
A6: Departments – 15 units with HOD and live headcount (formula)
A7: Levels – standard designation levels L1–L6
A8: Employees – 100 users with reporting line (Reports To), system roles and plant. This is the bulk-upload format for the Admin console.
A9: Access_Matrix – capability × role, as in BRD section 5
A10: Categories – task / request categories with default form and proposed turnaround (BRD section 7)
A11: Recurring_Templates – sample recurring tasks per department
A12: Sample_Tasks – 60 dummy tasks for testing dashboards; Days Overdue is a formula against the As-of date below
A13: Requests – sample requests between departments
... A20: Reports To holds the Employee Code of the immediate senior; the CEO has none. Reports To Name is a lookup formula.
A22: As-of date (used by Sample_Tasks) | B22: 46317

Sheet Departments
A1: Dept Code | B1: Department | C1: HOD Emp Code | D1: HOD Name | E1: Headcount | F1: Scored in KPI
A2: MGT | B2: Management office | C2: E101 | D2: =IFERROR(INDEX(Employees!$B$2:$B$101,MATCH(C2,Employees!$A$2:$A$101,0)),"") -> Arjun Raman | E2: =COUNTIFS(Employees!$E$2:$E$101,A2,Employees!$M$2:$M$101,"Active") -> 3 | F2: No (management office)
A3: FIN | B3: Finance & Accounts | C3: E104 | D3: =IFERROR(INDEX(Employees!$B$2:$B$101,MATCH(C3,Employees!$A$2:$A$101,0)),"") -> Divya Iyer | E3: =COUNTIFS(Employees!$E$2:$E$101,A3,Employees!$M$2:$M$101,"Active") -> 12 | F3: Yes
A4: HRA | B4: HR & Admin | C4: E116 | D4: =IFERROR(INDEX(Employees!$B$2:$B$101,MATCH(C4,Employees!$A$2:$A$101,0)),"") -> Revathi Pillai | E4: =COUNTIFS(Employees!$E$2:$E$101,A4,Employees!$M$2:$M$101,"Active") -> 7 | F4: Yes
A5: PUR | B5: Purchase | C5: E123 | D5: =IFERROR(INDEX(Employees!$B$2:$B$101,MATCH(C5,Employees!$A$2:$A$101,0)),"") -> Senthil Varma | E5: =COUNTIFS(Employees!$E$2:$E$101,A5,Employees!$M$2:$M$101,"Active") -> 6 | F5: Yes
A6: STR | B6: Stores | C6: E129 | D6: =IFERROR(INDEX(Employees!$B$2:$B$101,MATCH(C6,Employees!$A$2:$A$101,0)),"") -> Dinesh Murugan | E6: =COUNTIFS(Employees!$E$2:$E$101,A6,Employees!$M$2:$M$101,"Active") -> 6 | F6: Yes
A7: LOG | B7: Logistics | C7: E135 | D7: =IFERROR(INDEX(Employees!$B$2:$B$101,MATCH(C7,Employees!$A$2:$A$101,0)),"") -> Naveen Balan | E7: =COUNTIFS(Employees!$E$2:$E$101,A7,Employees!$M$2:$M$101,"Active") -> 5 | F7: Yes
A8: PRD | B8: Production | C8: E140 | D8: =IFERROR(INDEX(Employees!$B$2:$B$101,MATCH(C8,Employees!$A$2:$A$101,0)),"") -> Ramya Thomas | E8: =COUNTIFS(Employees!$E$2:$E$101,A8,Employees!$M$2:$M$101,"Active") -> 16 | F8: Yes
A9: QAD | B9: Quality | C9: E156 | D9: =IFERROR(INDEX(Employees!$B$2:$B$101,MATCH(C9,Employees!$A$2:$A$101,0)),"") -> Lakshmi Shetty | E9: =COUNTIFS(Employees!$E$2:$E$101,A9,Employees!$M$2:$M$101,"Active") -> 8 | F9: Yes
A10: MNT | B10: Maintenance | C10: E164 | D10: =IFERROR(INDEX(Employees!$B$2:$B$101,MATCH(C10,Employees!$A$2:$A$101,0)),"") -> Deepa Subramani | E10: =COUNTIFS(Employees!$E$2:$E$101,A10,Employees!$M$2:$M$101,"Active") -> 9 | F10: Yes
A11: SAM | B11: Sales & Marketing | C11: E173 | D11: =IFERROR(INDEX(Employees!$B$2:$B$101,MATCH(C11,Employees!$A$2:$A$101,0)),"") -> Senthil Rao | E11: =COUNTIFS(Employees!$E$2:$E$101,A11,Employees!$M$2:$M$101,"Active") -> 10 | F11: Yes
A12: PRJ | B12: Projects & Engineering | C12: E183 | D12: =IFERROR(INDEX(Employees!$B$2:$B$101,MATCH(C12,Employees!$A$2:$A$101,0)),"") -> Rajesh Sekar | E12: =COUNTIFS(Employees!$E$2:$E$101,A12,Employees!$M$2:$M$101,"Active") -> 5 | F12: Yes
A13: ITD | B13: Information Technology | C13: E188 | D13: =IFERROR(INDEX(Employees!$B$2:$B$101,MATCH(C13,Employees!$A$2:$A$101,0)),"") -> Aishwarya Joseph | E13: =COUNTIFS(Employees!$E$2:$E$101,A13,Employees!$M$2:$M$101,"Active") -> 3 | F13: Yes
... A16: IAD | B16: Internal Audit | C16: E198 | D16: =IFERROR(INDEX(Employees!$B$2:$B$101,MATCH(C16,Employees!$A$2:$A$101,0)),"") -> Mythili Natarajan | E16: =COUNTIFS(Employees!$E$2:$E$101,A16,Employees!$M$2:$M$101,"Active") -> 3 | F16: Yes
D17: Total | E17: =SUM(E2:E16) -> 100

Sheet Levels
A1: Level | B1: Designation | C1: Typical DTRS role
A2: L6 | B2: CEO | C2: Management Viewer; reviews HODs; vouches scorecards
A3: L5 | B3: Department Head (HOD) | C3: Owns department; reviews L4/L3; handles incoming requests
A4: L4 | B4: Deputy Manager | C4: Section lead; reviews L3
A5: L3 | B5: Assistant Manager | C5: Team lead; reviews L2
A6: L2 | B6: Senior Executive | C6: Doer; first-level reviewer of L1
A7: L1 | B7: Executive | C7: Doer

Sheet Categories
A1: Code | B1: Category | C1: Typical examples | D1: Default form | E1: Proposed turnaround
A2: DR | B2: Data / information request | C2: Sales data by branch, GRN copies, payroll inputs | D2: Request | E2: 2 working days
A3: CF | B3: Confirmation / verification | C3: Balance confirmation, stock count confirmation, bank details check | D3: Request | E3: 2 working days
A4: AP | B4: Approval / sign-off | C4: Payment approval, rate approval, budget sign-off | D4: Request | E4: 1 working day
A5: MD | B5: Master data creation / change | C5: New vendor / customer / material code in SAP; bank detail change | D5: Request | E5: 1 working day
A6: DS | B6: Data compilation / sorting / cleansing | C6: Vendor list cleansing, invoice sorting by age, plant data consolidation | D6: Task | E6: 3 working days
A7: RC | B7: Reconciliation | C7: Bank, vendor, GST 2B, inter-company, TDS | D7: Task | E7: 5 working days
A8: RP | B8: Report / MIS preparation | C8: Monthly P&L, ageing report, production report | D8: Task | E8: As per report calendar
A9: TX | B9: Transaction processing | C9: Payment release, invoice booking, journal entries | D9: Task | E9: 2 working days
A10: DC | B10: Document drafting / review | C10: Agreements, Board notes, letters, job descriptions | D10: Task | E10: 5 working days
A11: CO | B11: Statutory compliance / filing | C11: GST, TDS, PF, ESI, ROC returns | D11: Task | E11: Before statutory due date
A12: AU | B12: Audit query / observation closure | C12: Internal or statutory audit queries | D12: Task | E12: 7 working days
... A16: OT | B16: Other | C16: Anything not covered above (description mandatory) | D16: Task | E16: As agreed
A18: Task = work to be done, reviewed by a senior. Request = asks for data, confirmation or approval; the requester confirms closure. Turnaround values (yellow) are proposals pending management approval. Admin may add department-wise sub-categories.

Sheet Employees
A1: Emp Code | B1: Employee Name | C1: Designation | D1: Level | E1: Dept Code | F1: Department | G1: Section | H1: Plant | I1: Reports To (Emp Code) | J1: Reports To Name | K1: Email | L1: System Roles | M1: Status
A2: E101 | B2: Arjun Raman | C2: Chief Executive Officer | D2: L6 | E2: MGT | F2: Management office | H2: HO | J2: =IF(I2="","– (top of tree)",IFERROR(INDEX($B$2:$B$101,MATCH(I2,$A$2:$A$101,0)),"CHECK: code not found")) -> – (top of tree) | K2: arjun.raman@samplemfg.example | L2: Employee; Reviewer; Management Viewer | M2: Active
A3: E102 | B3: Priya Rao | C3: Assistant Manager – MIS (DTRS Administrator) | D3: L3 | E3: MGT | F3: Management office | H3: HO | I3: E101 | J3: =IF(I3="","– (top of tree)",IFERROR(INDEX($B$2:$B$101,MATCH(I3,$A$2:$A$101,0)),"CHECK: code not found")) -> Arjun Raman | K3: priya.rao@samplemfg.example | L3: Employee; Functional Admin | M3: Active
A4: E103 | B4: Karthik Varma | C4: Executive Assistant to CEO | D4: L1 | E4: MGT | F4: Management office | H4: HO | I4: E101 | J4: =IF(I4="","– (top of tree)",IFERROR(INDEX($B$2:$B$101,MATCH(I4,$A$2:$A$101,0)),"CHECK: code not found")) -> Arjun Raman | K4: karthik.varma@samplemfg.example | L4: Employee | M4: Active
A5: E104 | B5: Divya Iyer | C5: Head – Finance & Legal | D5: L5 | E5: FIN | F5: Finance & Accounts | H5: HO | I5: E101 | J5: =IF(I5="","– (top of tree)",IFERROR(INDEX($B$2:$B$101,MATCH(I5,$A$2:$A$101,0)),"CHECK: code not found")) -> Arjun Raman | K5: divya.iyer@samplemfg.example | L5: Employee; Reviewer; HOD; Management Viewer | M5: Active
A6: E105 | B6: Suresh Shetty | C6: Deputy Manager – Accounts | D6: L4 | E6: FIN | F6: Finance & Accounts | G6: Accounts | H6: HO | I6: E104 | J6: =IF(I6="","– (top of tree)",IFERROR(INDEX($B$2:$B$101,MATCH(I6,$A$2:$A$101,0)),"CHECK: code not found")) -> Divya Iyer | K6: suresh.shetty@samplemfg.example | L6: Employee; Reviewer | M6: Active
A7: E106 | B7: Lakshmi Chandran | C7: Assistant Manager – Accounts | D7: L3 | E7: FIN | F7: Finance & Accounts | G7: Accounts | H7: HO | I7: E105 | J7: =IF(I7="","– (top of tree)",IFERROR(INDEX($B$2:$B$101,MATCH(I7,$A$2:$A$101,0)),"CHECK: code not found")) -> Suresh Shetty | K7: lakshmi.chandran@samplemfg.example | L7: Employee; Reviewer | M7: Active
A8: E107 | B8: Rahul Natarajan | C8: Senior Executive – Accounts | D8: L2 | E8: FIN | F8: Finance & Accounts | G8: Accounts | H8: HO | I8: E106 | J8: =IF(I8="","– (top of tree)",IFERROR(INDEX($B$2:$B$101,MATCH(I8,$A$2:$A$101,0)),"CHECK: code not found")) -> Lakshmi Chandran | K8: rahul.natarajan@samplemfg.example | L8: Employee; Reviewer | M8: Active
A9: E108 | B9: Meena Reddy | C9: Executive – Accounts | D9: L1 | E9: FIN | F9: Finance & Accounts | G9: Accounts | H9: HO | I9: E107 | J9: =IF(I9="","– (top of tree)",IFERROR(INDEX($B$2:$B$101,MATCH(I9,$A$2:$A$101,0)),"CHECK: code not found")) -> Rahul Natarajan | K9: meena.reddy@samplemfg.example | L9: Employee | M9: Active
A10: E109 | B10: Vignesh Murugan | C10: Executive – Accounts | D10: L1 | E10: FIN | F10: Finance & Accounts | G10: Accounts | H10: Plant-1 | I10: E107 | J10: =IF(I10="","– (top of tree)",IFERROR(INDEX($B$2:$B$101,MATCH(I10,$A$2:$A$101,0)),"CHECK: code not found")) -> Rahul Natarajan | K10: vignesh.murugan@samplemfg.example | L10: Employee | M10: Active
A11: E110 | B11: Anitha Krishnan | C11: Assistant Manager – Taxation | D11: L3 | E11: FIN | F11: Finance & Accounts | G11: Taxation | H11: HO | I11: E104 | J11: =IF(I11="","– (top of tree)",IFERROR(INDEX($B$2:$B$101,MATCH(I11,$A$2:$A$101,0)),"CHECK: code not found")) -> Divya Iyer | K11: anitha.krishnan@samplemfg.example | L11: Employee; Reviewer | M11: Active
A12: E111 | B12: Ramesh Nair | C12: Senior Executive – Taxation | D12: L2 | E12: FIN | F12: Finance & Accounts | G12: Taxation | H12: HO | I12: E110 | J12: =IF(I12="","– (top of tree)",IFERROR(INDEX($B$2:$B$101,MATCH(I12,$A$2:$A$101,0)),"CHECK: code not found")) -> Anitha Krishnan | K12: ramesh.nair@samplemfg.example | L12: Employee; Reviewer | M12: Active
A13: E112 | B13: Kavya Sekar | C13: Executive – Taxation | D13: L1 | E13: FIN | F13: Finance & Accounts | G13: Taxation | H13: HO | I13: E111 | J13: =IF(I13="","– (top of tree)",IFERROR(INDEX($B$2:$B$101,MATCH(I13,$A$2:$A$101,0)),"CHECK: code not found")) -> Ramesh Nair | K13: kavya.sekar@samplemfg.example | L13: Employee | M13: Active
A14: E113 | B14: Prakash Subramani | C14: Deputy Manager – Treasury & Finance | D14: L4 | E14: FIN | F14: Finance & Accounts | G14: Treasury & Finance | H14: HO | I14: E104 | J14: =IF(I14="","– (top of tree)",IFERROR(INDEX($B$2:$B$101,MATCH(I14,$A$2:$A$101,0)),"CHECK: code not found")) -> Divya Iyer | K14: prakash.subramani@samplemfg.example | L14: Employee; Reviewer | M14: Active
A15: E114 | B15: Deepa Sharma | C15: Senior Executive – Treasury | D15: L2 | E15: FIN | F15: Finance & Accounts | G15: Treasury & Finance | H15: HO | I15: E113 | J15: =IF(I15="","– (top of tree)",IFERROR(INDEX($B$2:$B$101,MATCH(I15,$A$2:$A$101,0)),"CHECK: code not found")) -> Prakash Subramani | K15: deepa.sharma@samplemfg.example | L15: Employee; Reviewer | M15: Active
A16: E115 | B16: Sanjay Balan | C16: Executive – Treasury | D16: L1 | E16: FIN | F16: Finance & Accounts | G16: Treasury & Finance | H16: HO | I16: E114 | J16: =IF(I16="","– (top of tree)",IFERROR(INDEX($B$2:$B$101,MATCH(I16,$A$2:$A$101,0)),"CHECK: code not found")) -> Deepa Sharma | K16: sanjay.balan@samplemfg.example | L16: Employee | M16: Active
A17: E116 | B17: Revathi Pillai | C17: Head – HR & Admin | D17: L5 | E17: HRA | F17: HR & Admin | H17: HO | I17: E101 | J17: =IF(I17="","– (top of tree)",IFERROR(INDEX($B$2:$B$101,MATCH(I17,$A$2:$A$101,0)),"CHECK: code not found")) -> Arjun Raman | K17: revathi.pillai@samplemfg.example | L17: Employee; Reviewer; HOD | M17: Active
A18: E117 | B18: Ganesh Joseph | C18: Deputy Manager – HR | D18: L4 | E18: HRA | F18: HR & Admin | G18: HR | H18: HO | I18: E116 | J18: =IF(I18="","– (top of tree)",IFERROR(INDEX($B$2:$B$101,MATCH(I18,$A$2:$A$101,0)),"CHECK: code not found")) -> Revathi Pillai | K18: ganesh.joseph@samplemfg.example | L18: Employee; Reviewer | M18: Active
A19: E118 | B19: Nithya Das | C19: Assistant Manager – HR | D19: L3 | E19: HRA | F19: HR & Admin | G19: HR | H19: HO | I19: E117 | J19: =IF(I19="","– (top of tree)",IFERROR(INDEX($B$2:$B$101,MATCH(I19,$A$2:$A$101,0)),"CHECK: code not found")) -> Ganesh Joseph | K19: nithya.das@samplemfg.example | L19: Employee; Reviewer | M19: Active
A20: E119 | B20: Ashok Menon | C20: Senior Executive – HR | D20: L2 | E20: HRA | F20: HR & Admin | G20: HR | H20: Plant-1 | I20: E118 | J20: =IF(I20="","– (top of tree)",IFERROR(INDEX($B$2:$B$101,MATCH(I20,$A$2:$A$101,0)),"CHECK: code not found")) -> Nithya Das | K20: ashok.menon@samplemfg.example | L20: Employee; Reviewer | M20: Active
A21: E120 | B21: Swathi Thomas | C21: Executive – HR | D21: L1 | E21: HRA | F21: HR & Admin | G21: HR | H21: Plant-2 | I21: E119 | J21: =IF(I21="","– (top of tree)",IFERROR(INDEX($B$2:$B$101,MATCH(I21,$A$2:$A$101,0)),"CHECK: code not found")) -> Ashok Menon | K21: swathi.thomas@samplemfg.example | L21: Employee | M21: Active
A22: E121 | B22: Manoj Raman | C22: Assistant Manager – Admin | D22: L3 | E22: HRA | F22: HR & Admin | G22: Admin | H22: HO | I22: E116 | J22: =IF(I22="","– (top of tree)",IFERROR(INDEX($B$2:$B$101,MATCH(I22,$A$2:$A$101,0)),"CHECK: code not found")) -> Revathi Pillai | K22: manoj.raman@samplemfg.example | L22: Employee; Reviewer | M22: Active
A23: E122 | B23: Pooja Rao | C23: Executive – Admin | D23: L1 | E23: HRA | F23: HR & Admin | G23: Admin | H23: HO | I23: E121 | J23: =IF(I23="","– (top of tree)",IFERROR(INDEX($B$2:$B$101,MATCH(I23,$A$2:$A$101,0)),"CHECK: code not found")) -> Manoj Raman | K23: pooja.rao@samplemfg.example | L23: Employee | M23: Active
A24: E123 | B24: Senthil Varma | C24: Head – Purchase | D24: L5 | E24: PUR | F24: Purchase | H24: HO | I24: E101 | J24: =IF(I24="","– (top of tree)",IFERROR(INDEX($B$2:$B$101,MATCH(I24,$A$2:$A$101,0)),"CHECK: code not found")) -> Arjun Raman | K24: senthil.varma@samplemfg.example | L24: Employee; Reviewer; HOD | M24: Active
A25: E124 | B25: Harini Iyer | C25: Assistant Manager – Purchase | D25: L3 | E25: PUR | F25: Purchase | H25: HO | I25: E123 | J25: =IF(I25="","– (top of tree)",IFERROR(INDEX($B$2:$B$101,MATCH(I25,$A$2:$A$101,0)),"CHECK: code not found")) -> Senthil Varma | K25: harini.iyer@samplemfg.example | L25: Employee; Reviewer | M25: Active
A26: E125 | B26: Vinod Shetty | C26: Senior Executive – Purchase | D26: L2 | E26: PUR | F26: Purchase | H26: HO | I26: E124 | J26: =IF(I26="","– (top of tree)",IFERROR(INDEX($B$2:$B$101,MATCH(I26,$A$2:$A$101,0)),"CHECK: code not found")) -> Harini Iyer | K26: vinod.shetty@samplemfg.example | L26: Employee; Reviewer | M26: Active
A27: E126 | B27: Sowmya Chandran | C27: Senior Executive – Purchase | D27: L2 | E27: PUR | F27: Purchase | H27: Plant-2 | I27: E124 | J27: =IF(I27="","– (top of tree)",IFERROR(INDEX($B$2:$B$101,MATCH(I27,$A$2:$A$101,0)),"CHECK: code not found")) -> Harini Iyer | K27: sowmya.chandran@samplemfg.example | L27: Employee; Reviewer | M27: Active
A28: E127 | B28: Balaji Natarajan | C28: Executive – Purchase | D28: L1 | E28: PUR | F28: Purchase | H28: HO | I28: E125 | J28: =IF(I28="","– (top of tree)",IFERROR(INDEX($B$2:$B$101,MATCH(I28,$A$2:$A$101,0)),"CHECK: code not found")) -> Vinod Shetty | K28: balaji.natarajan@samplemfg.example | L28: Employee | M28: Active
A29: E128 | B29: Janani Reddy | C29: Executive – Purchase | D29: L1 | E29: PUR | F29: Purchase | H29: Plant-2 | I29: E126 | J29: =IF(I29="","– (top of tree)",IFERROR(INDEX($B$2:$B$101,MATCH(I29,$A$2:$A$101,0)),"CHECK: code not found")) -> Sowmya Chandran | K29: janani.reddy@samplemfg.example | L29: Employee | M29: Active
A30: E129 | B30: Dinesh Murugan | C30: Manager – Stores (HOD) | D30: L5 | E30: STR | F30: Stores | H30: Plant-1 | I30: E101 | J30: =IF(I30="","– (top of tree)",IFERROR(INDEX($B$2:$B$101,MATCH(I30,$A$2:$A$101,0)),"CHECK: code not found")) -> Arjun Raman | K30: dinesh.murugan@samplemfg.example | L30: Employee; Reviewer; HOD | M30: Active
A31: E130 | B31: Keerthana Krishnan | C31: Senior Executive – Stores | D31: L2 | E31: STR | F31: Stores | H31: Plant-1 | I31: E129 | J31: =IF(I31="","– (top of tree)",IFERROR(INDEX($B$2:$B$101,MATCH(I31,$A$2:$A$101,0)),"CHECK: code not found")) -> Dinesh Murugan | K31: keerthana.krishnan@samplemfg.example | L31: Employee; Reviewer | M31: Active
A32: E131 | B32: Mohan Nair | C32: Senior Executive – Stores | D32: L2 | E32: STR | F32: Stores | H32: Plant-2 | I32: E129 | J32: =IF(I32="","– (top of tree)",IFERROR(INDEX($B$2:$B$101,MATCH(I32,$A$2:$A$101,0)),"CHECK: code not found")) -> Dinesh Murugan | K32: mohan.nair@samplemfg.example | L32: Employee; Reviewer | M32: Active
A33: E132 | B33: Sangeetha Sekar | C33: Executive – Stores | D33: L1 | E33: STR | F33: Stores | H33: Plant-1 | I33: E130 | J33: =IF(I33="","– (top of tree)",IFERROR(INDEX($B$2:$B$101,MATCH(I33,$A$2:$A$101,0)),"CHECK: code not found")) -> Keerthana Krishnan | K33: sangeetha.sekar@samplemfg.example | L33: Employee | M33: Active
A34: E133 | B34: Rajesh Subramani | C34: Executive – Stores | D34: L1 | E34: STR | F34: Stores | H34: Plant-1 | I34: E130 | J34: =IF(I34="","– (top of tree)",IFERROR(INDEX($B$2:$B$101,MATCH(I34,$A$2:$A$101,0)),"CHECK: code not found")) -> Keerthana Krishnan | K34: rajesh.subramani@samplemfg.example | L34: Employee | M34: Active
A35: E134 | B35: Bhavani Sharma | C35: Executive – Stores | D35: L1 | E35: STR | F35: Stores | H35: Plant-2 | I35: E131 | J35: =IF(I35="","– (top of tree)",IFERROR(INDEX($B$2:$B$101,MATCH(I35,$A$2:$A$101,0)),"CHECK: code not found")) -> Mohan Nair | K35: bhavani.sharma@samplemfg.example | L35: Employee | M35: Active
... A41: E140 | B41: Ramya Thomas | C41: Head – Production | D41: L5 | E41: PRD | F41: Production | H41: Plant-1 | I41: E101 | J41: =IF(I41="","– (top of tree)",IFERROR(INDEX($B$2:$B$101,MATCH(I41,$A$2:$A$101,0)),"CHECK: code not found")) -> Arjun Raman | K41: ramya.thomas@samplemfg.example | L41: Employee; Reviewer; HOD | M41: Active
A42: E141 | B42: Vijay Raman | C42: Deputy Manager – Production (Plant 1) | D42: L4 | E42: PRD | F42: Production | G42: Plant 1 | H42: Plant-1 | I42: E140 | J42: =IF(I42="","– (top of tree)",IFERROR(INDEX($B$2:$B$101,MATCH(I42,$A$2:$A$101,0)),"CHECK: code not found")) -> Ramya Thomas | K42: vijay.raman@samplemfg.example | L42: Employee; Reviewer | M42: Active
A43: E142 | B43: Gayathri Rao | C43: Assistant Manager – Production (Plant 1) | D43: L3 | E43: PRD | F43: Production | G43: Plant 1 | H43: Plant-1 | I43: E141 | J43: =IF(I43="","– (top of tree)",IFERROR(INDEX($B$2:$B$101,MATCH(I43,$A$2:$A$101,0)),"CHECK: code not found")) -> Vijay Raman | K43: gayathri.rao@samplemfg.example | L43: Employee; Reviewer | M43: Active
A44: E143 | B44: Kumar Varma | C44: Senior Executive – Production (Shift A) | D44: L2 | E44: PRD | F44: Production | G44: Plant 1 | H44: Plant-1 | I44: E142 | J44: =IF(I44="","– (top of tree)",IFERROR(INDEX($B$2:$B$101,MATCH(I44,$A$2:$A$101,0)),"CHECK: code not found")) -> Gayathri Rao | K44: kumar.varma@samplemfg.example | L44: Employee; Reviewer | M44: Active
A45: E144 | B45: Nandhini Iyer | C45: Senior Executive – Production (Shift B) | D45: L2 | E45: PRD | F45: Production | G45: Plant 1 | H45: Plant-1 | I45: E142 | J45: =IF(I45="","– (top of tree)",IFERROR(INDEX($B$2:$B$101,MATCH(I45,$A$2:$A$101,0)),"CHECK: code not found")) -> Gayathri Rao | K45: nandhini.iyer@samplemfg.example | L45: Employee; Reviewer | M45: Active
A46: E145 | B46: Sathish Shetty | C46: Executive – Production | D46: L1 | E46: PRD | F46: Production | G46: Plant 1 | H46: Plant-1 | I46: E143 | J46: =IF(I46="","– (top of tree)",IFERROR(INDEX($B$2:$B$101,MATCH(I46,$A$2:$A$101,0)),"CHECK: code not found")) -> Kumar Varma | K46: sathish.shetty@samplemfg.example | L46: Employee | M46: Active
A47: E146 | B47: Preethi Chandran | C47: Executive – Production | D47: L1 | E47: PRD | F47: Production | G47: Plant 1 | H47: Plant-1 | I47: E144 | J47: =IF(I47="","– (top of tree)",IFERROR(INDEX($B$2:$B$101,MATCH(I47,$A$2:$A$101,0)),"CHECK: code not found")) -> Nandhini Iyer | K47: preethi.chandran@samplemfg.example | L47: Employee | M47: Active
A48: E147 | B48: Arun Natarajan | C48: Executive – Production | D48: L1 | E48: PRD | F48: Production | G48: Plant 1 | H48: Plant-1 | I48: E143 | J48: =IF(I48="","– (top of tree)",IFERROR(INDEX($B$2:$B$101,MATCH(I48,$A$2:$A$101,0)),"CHECK: code not found")) -> Kumar Varma | K48: arun.natarajan@samplemfg.example | L48: Employee | M48: Active
A49: E148 | B49: Mythili Reddy | C49: Executive – Production | D49: L1 | E49: PRD | F49: Production | G49: Plant 1 | H49: Plant-1 | I49: E144 | J49: =IF(I49="","– (top of tree)",IFERROR(INDEX($B$2:$B$101,MATCH(I49,$A$2:$A$101,0)),"CHECK: code not found")) -> Nandhini Iyer | K49: mythili.reddy@samplemfg.example | L49: Employee | M49: Active
A50: E149 | B50: Siva Murugan | C50: Deputy Manager – Production (Plant 2) | D50: L4 | E50: PRD | F50: Production | G50: Plant 2 | H50: Plant-2 | I50: E140 | J50: =IF(I50="","– (top of tree)",IFERROR(INDEX($B$2:$B$101,MATCH(I50,$A$2:$A$101,0)),"CHECK: code not found")) -> Ramya Thomas | K50: siva.murugan@samplemfg.example | L50: Employee; Reviewer | M50: Active
A51: E150 | B51: Varsha Krishnan | C51: Assistant Manager – Production (Plant 2) | D51: L3 | E51: PRD | F51: Production | G51: Plant 2 | H51: Plant-2 | I51: E149 | J51: =IF(I51="","– (top of tree)",IFERROR(INDEX($B$2:$B$101,MATCH(I51,$A$2:$A$101,0)),"CHECK: code not found")) -> Siva Murugan | K51: varsha.krishnan@samplemfg.example | L51: Employee; Reviewer | M51: Active
A52: E151 | B52: Arjun Thomas | C52: Senior Executive – Production (Shift A) | D52: L2 | E52: PRD | F52: Production | G52: Plant 2 | H52: Plant-2 | I52: E150 | J52: =IF(I52="","– (top of tree)",IFERROR(INDEX($B$2:$B$101,MATCH(I52,$A$2:$A$101,0)),"CHECK: code not found")) -> Varsha Krishnan | K52: arjun.thomas@samplemfg.example | L52: Employee; Reviewer | M52: Active
A53: E152 | B53: Priya Raman | C53: Senior Executive – Production (Shift B) | D53: L2 | E53: PRD | F53: Production | G53: Plant 2 | H53: Plant-2 | I53: E150 | J53: =IF(I53="","– (top of tree)",IFERROR(INDEX($B$2:$B$101,MATCH(I53,$A$2:$A$101,0)),"CHECK: code not found")) -> Varsha Krishnan | K53: priya.raman@samplemfg.example | L53: Employee; Reviewer | M53: Active
... A56: E155 | B56: Suresh Iyer | C56: Executive – Production | D56: L1 | E56: PRD | F56: Production | G56: Plant 2 | H56: Plant-2 | I56: E151 | J56: =IF(I56="","– (top of tree)",IFERROR(INDEX($B$2:$B$101,MATCH(I56,$A$2:$A$101,0)),"CHECK: code not found")) -> Arjun Thomas | K56: suresh.iyer@samplemfg.example | L56: Employee | M56: Active
A57: E156 | B57: Lakshmi Shetty | C57: Head – Quality | D57: L5 | E57: QAD | F57: Quality | H57: Plant-1 | I57: E101 | J57: =IF(I57="","– (top of tree)",IFERROR(INDEX($B$2:$B$101,MATCH(I57,$A$2:$A$101,0)),"CHECK: code not found")) -> Arjun Raman | K57: lakshmi.shetty@samplemfg.example | L57: Employee; Reviewer; HOD | M57: Active
A58: E157 | B58: Rahul Chandran | C58: Deputy Manager – Quality | D58: L4 | E58: QAD | F58: Quality | H58: Plant-1 | I58: E156 | J58: =IF(I58="","– (top of tree)",IFERROR(INDEX($B$2:$B$101,MATCH(I58,$A$2:$A$101,0)),"CHECK: code not found")) -> Lakshmi Shetty | K58: rahul.chandran@samplemfg.example | L58: Employee; Reviewer | M58: Active
A59: E158 | B59: Meena Natarajan | C59: Assistant Manager – Quality | D59: L3 | E59: QAD | F59: Quality | H59: Plant-1 | I59: E157 | J59: =IF(I59="","– (top of tree)",IFERROR(INDEX($B$2:$B$101,MATCH(I59,$A$2:$A$101,0)),"CHECK: code not found")) -> Rahul Chandran | K59: meena.natarajan@samplemfg.example | L59: Employee; Reviewer | M59: Active
A60: E159 | B60: Vignesh Reddy | C60: Senior Executive – QC | D60: L2 | E60: QAD | F60: Quality | H60: Plant-1 | I60: E158 | J60: =IF(I60="","– (top of tree)",IFERROR(INDEX($B$2:$B$101,MATCH(I60,$A$2:$A$101,0)),"CHECK: code not found")) -> Meena Natarajan | K60: vignesh.reddy@samplemfg.example | L60: Employee; Reviewer | M60: Active
A61: E160 | B61: Anitha Murugan | C61: Senior Executive – QA | D61: L2 | E61: QAD | F61: Quality | H61: Plant-2 | I61: E158 | J61: =IF(I61="","– (top of tree)",IFERROR(INDEX($B$2:$B$101,MATCH(I61,$A$2:$A$101,0)),"CHECK: code not found")) -> Meena Natarajan | K61: anitha.murugan@samplemfg.example | L61: Employee; Reviewer | M61: Active
A62: E161 | B62: Ramesh Krishnan | C62: Executive – QC Lab | D62: L1 | E62: QAD | F62: Quality | H62: Plant-1 | I62: E159 | J62: =IF(I62="","– (top of tree)",IFERROR(INDEX($B$2:$B$101,MATCH(I62,$A$2:$A$101,0)),"CHECK: code not found")) -> Vignesh Reddy | K62: ramesh.krishnan@samplemfg.example | L62: Employee | M62: Active
A63: E162 | B63: Kavya Nair | C63: Executive – QC Lab | D63: L1 | E63: QAD | F63: Quality | H63: Plant-1 | I63: E159 | J63: =IF(I63="","– (top of tree)",IFERROR(INDEX($B$2:$B$101,MATCH(I63,$A$2:$A$101,0)),"CHECK: code not found")) -> Vignesh Reddy | K63: kavya.nair@samplemfg.example | L63: Employee | M63: Active
A64: E163 | B64: Prakash Sekar | C64: Executive – QA | D64: L1 | E64: QAD | F64: Quality | H64: Plant-2 | I64: E160 | J64: =IF(I64="","– (top of tree)",IFERROR(INDEX($B$2:$B$101,MATCH(I64,$A$2:$A$101,0)),"CHECK: code not found")) -> Anitha Murugan | K64: prakash.sekar@samplemfg.example | L64: Employee | M64: Active
A65: E164 | B65: Deepa Subramani | C65: Head – Maintenance | D65: L5 | E65: MNT | F65: Maintenance | H65: Plant-1 | I65: E101 | J65: =IF(I65="","– (top of tree)",IFERROR(INDEX($B$2:$B$101,MATCH(I65,$A$2:$A$101,0)),"CHECK: code not found")) -> Arjun Raman | K65: deepa.subramani@samplemfg.example | L65: Employee; Reviewer; HOD | M65: Active
A66: E165 | B66: Sanjay Sharma | C66: Deputy Manager – Maintenance | D66: L4 | E66: MNT | F66: Maintenance | H66: Plant-1 | I66: E164 | J66: =IF(I66="","– (top of tree)",IFERROR(INDEX($B$2:$B$101,MATCH(I66,$A$2:$A$101,0)),"CHECK: code not found")) -> Deepa Subramani | K66: sanjay.sharma@samplemfg.example | L66: Employee; Reviewer | M66: Active
A67: E166 | B67: Revathi Balan | C67: Assistant Manager – Mechanical | D67: L3 | E67: MNT | F67: Maintenance | G67: Mechanical | H67: Plant-1 | I67: E165 | J67: =IF(I67="","– (top of tree)",IFERROR(INDEX($B$2:$B$101,MATCH(I67,$A$2:$A$101,0)),"CHECK: code not found")) -> Sanjay Sharma | K67: revathi.balan@samplemfg.example | L67: Employee; Reviewer | M67: Active
A68: E167 | B68: Ganesh Pillai | C68: Assistant Manager – Electrical | D68: L3 | E68: MNT | F68: Maintenance | G68: Electrical | H68: Plant-1 | I68: E165 | J68: =IF(I68="","– (top of tree)",IFERROR(INDEX($B$2:$B$101,MATCH(I68,$A$2:$A$101,0)),"CHECK: code not found")) -> Sanjay Sharma | K68: ganesh.pillai@samplemfg.example | L68: Employee; Reviewer | M68: Active
A69: E168 | B69: Nithya Joseph | C69: Senior Executive – Mechanical | D69: L2 | E69: MNT | F69: Maintenance | G69: Mechanical | H69: Plant-1 | I69: E166 | J69: =IF(I69="","– (top of tree)",IFERROR(INDEX($B$2:$B$101,MATCH(I69,$A$2:$A$101,0)),"CHECK: code not found")) -> Revathi Balan | K69: nithya.joseph@samplemfg.example | L69: Employee; Reviewer | M69: Active
A70: E169 | B70: Ashok Das | C70: Senior Executive – Electrical | D70: L2 | E70: MNT | F70: Maintenance | G70: Electrical | H70: Plant-2 | I70: E167 | J70: =IF(I70="","– (top of tree)",IFERROR(INDEX($B$2:$B$101,MATCH(I70,$A$2:$A$101,0)),"CHECK: code not found")) -> Ganesh Pillai | K70: ashok.das@samplemfg.example | L70: Employee; Reviewer | M70: Active
A71: E170 | B71: Swathi Menon | C71: Executive – Mechanical | D71: L1 | E71: MNT | F71: Maintenance | G71: Mechanical | H71: Plant-1 | I71: E168 | J71: =IF(I71="","– (top of tree)",IFERROR(INDEX($B$2:$B$101,MATCH(I71,$A$2:$A$101,0)),"CHECK: code not found")) -> Nithya Joseph | K71: swathi.menon@samplemfg.example | L71: Employee | M71: Active
A72: E171 | B72: Manoj Thomas | C72: Executive – Mechanical | D72: L1 | E72: MNT | F72: Maintenance | G72: Mechanical | H72: Plant-2 | I72: E168 | J72: =IF(I72="","– (top of tree)",IFERROR(INDEX($B$2:$B$101,MATCH(I72,$A$2:$A$101,0)),"CHECK: code not found")) -> Nithya Joseph | K72: manoj.thomas@samplemfg.example | L72: Employee | M72: Active
A73: E172 | B73: Pooja Raman | C73: Executive – Electrical | D73: L1 | E73: MNT | F73: Maintenance | G73: Electrical | H73: Plant-2 | I73: E169 | J73: =IF(I73="","– (top of tree)",IFERROR(INDEX($B$2:$B$101,MATCH(I73,$A$2:$A$101,0)),"CHECK: code not found")) -> Ashok Das | K73: pooja.raman@samplemfg.example | L73: Employee | M73: Active
A74: E173 | B74: Senthil Rao | C74: Head – Sales & Marketing | D74: L5 | E74: SAM | F74: Sales & Marketing | H74: HO | I74: E101 | J74: =IF(I74="","– (top of tree)",IFERROR(INDEX($B$2:$B$101,MATCH(I74,$A$2:$A$101,0)),"CHECK: code not found")) -> Arjun Raman | K74: senthil.rao@samplemfg.example | L74: Employee; Reviewer; HOD | M74: Active
A75: E174 | B75: Harini Varma | C75: Deputy Manager – Sales | D75: L4 | E75: SAM | F75: Sales & Marketing | H75: HO | I75: E173 | J75: =IF(I75="","– (top of tree)",IFERROR(INDEX($B$2:$B$101,MATCH(I75,$A$2:$A$101,0)),"CHECK: code not found")) -> Senthil Rao | K75: harini.varma@samplemfg.example | L75: Employee; Reviewer | M75: Active
A76: E175 | B76: Vinod Iyer | C76: Assistant Manager – Sales (South) | D76: L3 | E76: SAM | F76: Sales & Marketing | G76: South | H76: HO | I76: E174 | J76: =IF(I76="","– (top of tree)",IFERROR(INDEX($B$2:$B$101,MATCH(I76,$A$2:$A$101,0)),"CHECK: code not found")) -> Harini Varma | K76: vinod.iyer@samplemfg.example | L76: Employee; Reviewer | M76: Active
A77: E176 | B77: Sowmya Shetty | C77: Assistant Manager – Sales (North) | D77: L3 | E77: SAM | F77: Sales & Marketing | G77: North | H77: HO | I77: E174 | J77: =IF(I77="","– (top of tree)",IFERROR(INDEX($B$2:$B$101,MATCH(I77,$A$2:$A$101,0)),"CHECK: code not found")) -> Harini Varma | K77: sowmya.shetty@samplemfg.example | L77: Employee; Reviewer | M77: Active
A78: E177 | B78: Balaji Chandran | C78: Senior Executive – Sales (South) | D78: L2 | E78: SAM | F78: Sales & Marketing | G78: South | H78: HO | I78: E175 | J78: =IF(I78="","– (top of tree)",IFERROR(INDEX($B$2:$B$101,MATCH(I78,$A$2:$A$101,0)),"CHECK: code not found")) -> Vinod Iyer | K78: balaji.chandran@samplemfg.example | L78: Employee; Reviewer | M78: Active
A79: E178 | B79: Janani Natarajan | C79: Senior Executive – Sales (North) | D79: L2 | E79: SAM | F79: Sales & Marketing | G79: North | H79: HO | I79: E176 | J79: =IF(I79="","– (top of tree)",IFERROR(INDEX($B$2:$B$101,MATCH(I79,$A$2:$A$101,0)),"CHECK: code not found")) -> Sowmya Shetty | K79: janani.natarajan@samplemfg.example | L79: Employee; Reviewer | M79: Active
A80: E179 | B80: Dinesh Reddy | C80: Executive – Sales (South) | D80: L1 | E80: SAM | F80: Sales & Marketing | G80: South | H80: HO | I80: E177 | J80: =IF(I80="","– (top of tree)",IFERROR(INDEX($B$2:$B$101,MATCH(I80,$A$2:$A$101,0)),"CHECK: code not found")) -> Balaji Chandran | K80: dinesh.reddy@samplemfg.example | L80: Employee | M80: Active
A81: E180 | B81: Keerthana Murugan | C81: Executive – Sales (South) | D81: L1 | E81: SAM | F81: Sales & Marketing | G81: South | H81: HO | I81: E177 | J81: =IF(I81="","– (top of tree)",IFERROR(INDEX($B$2:$B$101,MATCH(I81,$A$2:$A$101,0)),"CHECK: code not found")) -> Balaji Chandran | K81: keerthana.murugan@samplemfg.example | L81: Employee | M81: Active
A82: E181 | B82: Mohan Krishnan | C82: Executive – Sales (North) | D82: L1 | E82: SAM | F82: Sales & Marketing | G82: North | H82: HO | I82: E178 | J82: =IF(I82="","– (top of tree)",IFERROR(INDEX($B$2:$B$101,MATCH(I82,$A$2:$A$101,0)),"CHECK: code not found")) -> Janani Natarajan | K82: mohan.krishnan@samplemfg.example | L82: Employee | M82: Active
A83: E182 | B83: Sangeetha Nair | C83: Executive – Sales (North) | D83: L1 | E83: SAM | F83: Sales & Marketing | G83: North | H83: HO | I83: E178 | J83: =IF(I83="","– (top of tree)",IFERROR(INDEX($B$2:$B$101,MATCH(I83,$A$2:$A$101,0)),"CHECK: code not found")) -> Janani Natarajan | K83: sangeetha.nair@samplemfg.example | L83: Employee | M83: Active
A84: E183 | B84: Rajesh Sekar | C84: Head – Projects & Engineering | D84: L5 | E84: PRJ | F84: Projects & Engineering | H84: HO | I84: E101 | J84: =IF(I84="","– (top of tree)",IFERROR(INDEX($B$2:$B$101,MATCH(I84,$A$2:$A$101,0)),"CHECK: code not found")) -> Arjun Raman | K84: rajesh.sekar@samplemfg.example | L84: Employee; Reviewer; HOD | M84: Active
A85: E184 | B85: Bhavani Subramani | C85: Assistant Manager – Projects | D85: L3 | E85: PRJ | F85: Projects & Engineering | H85: Plant-2 | I85: E183 | J85: =IF(I85="","– (top of tree)",IFERROR(INDEX($B$2:$B$101,MATCH(I85,$A$2:$A$101,0)),"CHECK: code not found")) -> Rajesh Sekar | K85: bhavani.subramani@samplemfg.example | L85: Employee; Reviewer | M85: Active
A86: E185 | B86: Naveen Sharma | C86: Senior Executive – Projects | D86: L2 | E86: PRJ | F86: Projects & Engineering | H86: Plant-2 | I86: E184 | J86: =IF(I86="","– (top of tree)",IFERROR(INDEX($B$2:$B$101,MATCH(I86,$A$2:$A$101,0)),"CHECK: code not found")) -> Bhavani Subramani | K86: naveen.sharma@samplemfg.example | L86: Employee; Reviewer | M86: Active
A87: E186 | B87: Shalini Balan | C87: Executive – Projects (Civil) | D87: L1 | E87: PRJ | F87: Projects & Engineering | H87: Plant-2 | I87: E185 | J87: =IF(I87="","– (top of tree)",IFERROR(INDEX($B$2:$B$101,MATCH(I87,$A$2:$A$101,0)),"CHECK: code not found")) -> Naveen Sharma | K87: shalini.balan@samplemfg.example | L87: Employee | M87: Active
A88: E187 | B88: Gopal Pillai | C88: Executive – Projects (Mechanical) | D88: L1 | E88: PRJ | F88: Projects & Engineering | H88: Plant-2 | I88: E185 | J88: =IF(I88="","– (top of tree)",IFERROR(INDEX($B$2:$B$101,MATCH(I88,$A$2:$A$101,0)),"CHECK: code not found")) -> Naveen Sharma | K88: gopal.pillai@samplemfg.example | L88: Employee | M88: Active
A89: E188 | B89: Aishwarya Joseph | C89: Manager – IT (HOD) | D89: L5 | E89: ITD | F89: Information Technology | H89: HO | I89: E101 | J89: =IF(I89="","– (top of tree)",IFERROR(INDEX($B$2:$B$101,MATCH(I89,$A$2:$A$101,0)),"CHECK: code not found")) -> Arjun Raman | K89: aishwarya.joseph@samplemfg.example | L89: Employee; Reviewer; HOD; IT Admin | M89: Active
A90: E189 | B90: Hari Das | C90: Senior Executive – IT | D90: L2 | E90: ITD | F90: Information Technology | H90: HO | I90: E188 | J90: =IF(I90="","– (top of tree)",IFERROR(INDEX($B$2:$B$101,MATCH(I90,$A$2:$A$101,0)),"CHECK: code not found")) -> Aishwarya Joseph | K90: hari.das@samplemfg.example | L90: Employee; Reviewer; IT Admin | M90: Active
A91: E190 | B91: Ramya Menon | C91: Executive – IT Support | D91: L1 | E91: ITD | F91: Information Technology | H91: Plant-1 | I91: E189 | J91: =IF(I91="","– (top of tree)",IFERROR(INDEX($B$2:$B$101,MATCH(I91,$A$2:$A$101,0)),"CHECK: code not found")) -> Hari Das | K91: ramya.menon@samplemfg.example | L91: Employee | M91: Active
A92: E191 | B92: Vijay Thomas | C92: Company Secretary (HOD) | D92: L5 | E92: LEG | F92: Legal & Secretarial | H92: HO | I92: E101 | J92: =IF(I92="","– (top of tree)",IFERROR(INDEX($B$2:$B$101,MATCH(I92,$A$2:$A$101,0)),"CHECK: code not found")) -> Arjun Raman | K92: vijay.thomas@samplemfg.example | L92: Employee; Reviewer; HOD | M92: Active
A93: E192 | B93: Gayathri Raman | C93: Assistant Manager – Legal | D93: L3 | E93: LEG | F93: Legal & Secretarial | H93: HO | I93: E191 | J93: =IF(I93="","– (top of tree)",IFERROR(INDEX($B$2:$B$101,MATCH(I93,$A$2:$A$101,0)),"CHECK: code not found")) -> Vijay Thomas | K93: gayathri.raman@samplemfg.example | L93: Employee; Reviewer | M93: Active
A94: E193 | B94: Kumar Rao | C94: Executive – Secretarial | D94: L1 | E94: LEG | F94: Legal & Secretarial | H94: HO | I94: E192 | J94: =IF(I94="","– (top of tree)",IFERROR(INDEX($B$2:$B$101,MATCH(I94,$A$2:$A$101,0)),"CHECK: code not found")) -> Gayathri Raman | K94: kumar.rao@samplemfg.example | L94: Employee | M94: Active
A95: E194 | B95: Nandhini Varma | C95: Head – EHS | D95: L5 | E95: EHS | F95: Environment, Health & Safety | H95: Plant-1 | I95: E101 | J95: =IF(I95="","– (top of tree)",IFERROR(INDEX($B$2:$B$101,MATCH(I95,$A$2:$A$101,0)),"CHECK: code not found")) -> Arjun Raman | K95: nandhini.varma@samplemfg.example | L95: Employee; Reviewer; HOD | M95: Active
... A101: E200 | B101: Varsha Murugan | C101: Executive – Internal Audit | D101: L1 | E101: IAD | F101: Internal Audit | H101: HO | I101: E199 | J101: =IF(I101="","– (top of tree)",IFERROR(INDEX($B$2:$B$101,MATCH(I101,$A$2:$A$101,0)),"CHECK: code not found")) -> Siva Reddy | K101: varsha.murugan@samplemfg.example | L101: Employee | M101: Active

Sheet Access_Matrix
A1: Capability | B1: Employee | C1: Reviewer | D1: HOD | E1: Mgmt Viewer | F1: Functional Admin | G1: IT Admin | H1: Auditor
A2: View own tasks | B2: Y | C2: Y | D2: Y | E2: Y | F2: Y | G2: Y | H2: Y
A3: View reportees' tasks (whole sub-tree) | B3: – | C3: Own sub-tree | D3: Own dept | E3: All | F3: – | G3: – | H3: All (read)
A4: Create and assign tasks / requests | B4: To self; to a peer or one level up (same dept) | C4: To sub-tree; to a peer or one level up (same dept) | D4: Within dept | E4: To HODs | F4: – | G4: – | H4: –
A5: Review / return / close a junior's task | B5: – | C5: Direct reportees | D5: Dept | E5: HOD tasks | F5: – | G5: – | H5: –
A6: Approve due-date extension | B6: – | C6: Direct reportees | D6: Dept | E6: HOD tasks | F6: – | G6: – | H6: –
A7: Raise request to another department | B7: Y | C7: Y | D7: Y | E7: Y | F7: – | G7: – | H7: –
A8: Accept and assign incoming request | B8: – | C8: If SPOC | D8: Y | E8: – | F8: – | G8: – | H8: –
A9: Department dashboard and scorecard | B9: – | C9: Own team | D9: Own dept | E9: All depts | F9: – | G9: – | H9: All (read)
A10: HOD monthly self-review | B10: – | C10: – | D10: Y | E10: – | F10: – | G10: – | H10: –
A11: Vouch / sign off scorecard | B11: – | C11: – | D11: – | E11: Y | F11: – | G11: – | H11: –
A12: Maintain masters, hierarchy, rules, templates | B12: – | C12: – | D12: – | E12: Approves key changes | F12: Y (maker) | G12: – | H12: –
... A15: View audit trail | B15: – | C15: – | D15: Own dept | E15: All | F15: Config changes | G15: Technical logs | H15: All

Sheet Recurring_Templates
A1: Template ID | B1: Dept | C1: Section | D1: Task | E1: Frequency | F1: Due Rule | G1: Due Parameter | H1: Doer (Emp Code) | I1: Reviewer (Emp Code) | J1: Priority | K1: Evidence Required
A2: RT-01 | B2: FIN | C2: Accounts | D2: Monthly P&L and Balance Sheet to management | E2: Monthly | F2: Nth working day | G2: 4 | H2: E107 | I2: E105 | J2: High | K2: Yes
A3: RT-02 | B3: FIN | C3: Accounts | D3: Debtors and creditors ageing review | E3: Weekly | F3: Weekday | G3: Monday | H3: E108 | I3: E107 | J3: Medium | K3: Yes
A4: RT-03 | B4: FIN | C4: Taxation | D4: Monthly GST return preparation and filing | E4: Monthly | F4: Fixed day | G4: Per current GST due date | H4: E111 | I4: E110 | J4: Critical | K4: Yes
A5: RT-04 | B5: FIN | C5: Taxation | D5: TDS deposit for previous month | E5: Monthly | F5: Fixed day | G5: Per current TDS due date | H5: E112 | I5: E111 | J5: Critical | K5: Yes
A6: RT-05 | B6: FIN | C6: Treasury & Finance | D6: Monthly loan status summary | E6: Monthly | F6: Nth working day | G6: 5 | H6: E114 | I6: E113 | J6: Medium | K6: Yes
A7: RT-06 | B7: HRA | C7: HR | D7: Payroll inputs to Finance | E7: Monthly | F7: Fixed day | G7: 25 | H7: E119 | I7: E118 | J7: High | K7: Yes
A8: RT-07 | B8: HRA | C8: HR | D8: PF and ESI remittance | E8: Monthly | F8: Fixed day | G8: Per current PF/ESI due date | H8: E119 | I8: E118 | J8: Critical | K8: Yes
A9: RT-08 | B9: PUR | D9: Open PO and pending GRN review | E9: Fortnightly | F9: Fixed day | G9: 1 and 16 | H9: E125 | I9: E124 | J9: Medium | K9: No
A10: RT-09 | B10: STR | D10: Non-moving inventory report | E10: Monthly | F10: Nth working day | G10: 5 | H10: E130 | I10: E129 | J10: Medium | K10: Yes
A11: RT-10 | B11: LOG | D11: Freight cost and on-time dispatch report | E11: Monthly | F11: Nth working day | G11: 3 | H11: E137 | I11: E136 | J11: Medium | K11: Yes
A12: RT-11 | B12: PRD | C12: Plant 1 | D12: Daily production and downtime report | E12: Daily | F12: Same day | G12: — | H12: E143 | I12: E142 | J12: High | K12: Yes
A13: RT-12 | B13: PRD | C13: Plant 2 | D13: Daily production and downtime report | E13: Daily | F13: Same day | G13: — | H13: E151 | I13: E150 | J13: High | K13: Yes
A14: RT-13 | B14: QAD | D14: Customer complaint closure review | E14: Weekly | F14: Weekday | G14: Friday | H14: E159 | I14: E158 | J14: High | K14: Yes
A15: RT-14 | B15: MNT | C15: Mechanical | D15: Preventive maintenance schedule compliance | E15: Monthly | F15: Nth working day | G15: 3 | H15: E168 | I15: E166 | J15: High | K15: Yes
A16: RT-15 | B16: SAM | D16: Sales vs target and collection review | E16: Monthly | F16: Nth working day | G16: 2 | H16: E177 | I16: E175 | J16: High | K16: Yes
A17: RT-16 | B17: PRJ | D17: Project progress and fund utilisation report | E17: Fortnightly | F17: Weekday | G17: Saturday | H17: E185 | I17: E184 | J17: Medium | K17: Yes
A18: RT-17 | B18: ITD | D18: Backup restore test | E18: Quarterly | F18: Offset from period end | G18: 15 days after quarter end | H18: E189 | I18: E188 | J18: High | K18: Yes
A19: RT-18 | B19: LEG | D19: Statutory compliance certificate to Board | E19: Quarterly | F19: Offset from period end | G19: 15 days after quarter end | H19: E192 | I19: E191 | J19: Critical | K19: Yes
A20: RT-19 | B20: EHS | D20: Plant safety inspection | E20: Monthly | F20: Last working day | G20: — | H20: E195 | I20: E194 | J20: High | K20: Yes
A21: RT-20 | B21: IAD | D21: Internal audit observations follow-up | E21: Monthly | F21: Nth working day | G21: 7 | H21: E199 | I21: E198 | J21: Medium | K21: Yes
A23: Note: statutory due dates (GST, TDS, PF, ESI) are not hard-coded here; the Functional Admin enters them from current notifications each year.

Sheet Sample_Tasks
A1: Task ID | B1: Title | C1: Type | D1: Dept | E1: Section | F1: Doer Code | G1: Doer Name | H1: Reviewer Code | I1: Priority | J1: Status | K1: Start Date | L1: Original Due Date | M1: Revised Due Date | N1: Completion Date | O1: Days Overdue | P1: On Time? | Q1: Category | R1: Raised On | S1: Raised By (Emp Code)
A2: T-0001 | B2: Bank reconciliation – all accounts | C2: Assigned | D2: FIN | E2: Treasury & Finance | F2: E114 | G2: Deepa Sharma | H2: E113 | I2: High | J2: Closed | K2: 46287 | L2: 46294 | N2: 46293 | O2: =IF(J2="Closed",0,MAX(0,README!$B$22-IF(M2="",L2,M2))) -> 0 | P2: =IF(J2="Closed",IF(N2<=IF(M2="",L2,M2),"Yes","No"),"–") -> Yes | Q2: RC | R2: 46285 | S2: E113
A3: T-0002 | B3: Fixed asset register update | C3: Assigned | D3: FIN | E3: Treasury & Finance | F3: E115 | G3: Sanjay Balan | H3: E114 | I3: Low | J3: Returned for Rework | K3: 46286 | L3: 46314 | O3: =IF(J3="Closed",0,MAX(0,README!$B$22-IF(M3="",L3,M3))) -> 3 | P3: =IF(J3="Closed",IF(N3<=IF(M3="",L3,M3),"Yes","No"),"–") -> – | Q3: DS | R3: 46286 | S3: E114
A4: T-0003 | B4: Vendor balance confirmation follow-up | C4: Assigned | D4: FIN | E4: Taxation | F4: E110 | G4: Anitha Krishnan | H4: E104 | I4: High | J4: Accepted | K4: 46282 | L4: 46289 | O4: =IF(J4="Closed",0,MAX(0,README!$B$22-IF(M4="",L4,M4))) -> 28 | P4: =IF(J4="Closed",IF(N4<=IF(M4="",L4,M4),"Yes","No"),"–") -> – | Q4: CF | R4: 46281 | S4: E104
A5: T-0004 | B5: Revise payment document cycle to 2 days a week | C5: Self-initiated | D5: FIN | E5: Taxation | F5: E112 | G5: Kavya Sekar | H5: E111 | I5: High | J5: Submitted for Review | K5: 46281 | L5: 46305 | O5: =IF(J5="Closed",0,MAX(0,README!$B$22-IF(M5="",L5,M5))) -> 12 | P5: =IF(J5="Closed",IF(N5<=IF(M5="",L5,M5),"Yes","No"),"–") -> – | Q5: FU | R5: 46279 | S5: E112
A6: T-0005 | B6: Loan sanction documentation – term loan | C6: Assigned | D6: FIN | E6: Treasury & Finance | F6: E115 | G6: Sanjay Balan | H6: E114 | I6: Low | J6: Submitted for Review | K6: 46314 | L6: 46334 | O6: =IF(J6="Closed",0,MAX(0,README!$B$22-IF(M6="",L6,M6))) -> 0 | P6: =IF(J6="Closed",IF(N6<=IF(M6="",L6,M6),"Yes","No"),"–") -> – | Q6: FU | R6: 46314 | S6: E114
A7: T-0006 | B7: Budget vs actual commentary | C7: Assigned | D7: FIN | E7: Accounts | F7: E108 | G7: Meena Reddy | H7: E107 | I7: High | J7: Closed | K7: 46280 | L7: 46292 | N7: 46293 | O7: =IF(J7="Closed",0,MAX(0,README!$B$22-IF(M7="",L7,M7))) -> 0 | P7: =IF(J7="Closed",IF(N7<=IF(M7="",L7,M7),"Yes","No"),"–") -> No | Q7: RP | R7: 46279 | S7: E107
A8: T-0007 | B8: Revise JDs per new structure | C8: Assigned | D8: HRA | E8: HR | F8: E117 | G8: Ganesh Joseph | H8: E116 | I8: Critical | J8: Accepted | K8: 46301 | L8: 46311 | O8: =IF(J8="Closed",0,MAX(0,README!$B$22-IF(M8="",L8,M8))) -> 6 | P8: =IF(J8="Closed",IF(N8<=IF(M8="",L8,M8),"Yes","No"),"–") -> – | Q8: DC | R8: 46299 | S8: E116
A9: T-0008 | B9: Revise JDs per new structure (follow-up) | C9: Self-initiated | D9: HRA | E9: HR | F9: E118 | G9: Nithya Das | H9: E117 | I9: Medium | J9: Closed | K9: 46302 | L9: 46328 | N9: 46316 | O9: =IF(J9="Closed",0,MAX(0,README!$B$22-IF(M9="",L9,M9))) -> 0 | P9: =IF(J9="Closed",IF(N9<=IF(M9="",L9,M9),"Yes","No"),"–") -> Yes | Q9: DC | R9: 46302 | S9: E118
A10: T-0009 | B10: Induction for new joinees | C10: Self-initiated | D10: HRA | E10: HR | F10: E120 | G10: Swathi Thomas | H10: E119 | I10: Medium | J10: Accepted | K10: 46287 | L10: 46306 | O10: =IF(J10="Closed",0,MAX(0,README!$B$22-IF(M10="",L10,M10))) -> 11 | P10: =IF(J10="Closed",IF(N10<=IF(M10="",L10,M10),"Yes","No"),"–") -> – | Q10: FU | R10: 46286 | S10: E120
A11: T-0010 | B11: Induction for new joinees (follow-up) | C11: Self-initiated | D11: HRA | E11: Admin | F11: E122 | G11: Pooja Rao | H11: E121 | I11: Critical | J11: Submitted for Review | K11: 46303 | L11: 46328 | O11: =IF(J11="Closed",0,MAX(0,README!$B$22-IF(M11="",L11,M11))) -> 0 | P11: =IF(J11="Closed",IF(N11<=IF(M11="",L11,M11),"Yes","No"),"–") -> – | Q11: FU | R11: 46301 | S11: E122
A12: T-0011 | B12: Canteen contract renewal | C12: Assigned | D12: HRA | F12: E116 | G12: Revathi Pillai | H12: E101 | I12: Critical | J12: Accepted | K12: 46294 | L12: 46310 | O12: =IF(J12="Closed",0,MAX(0,README!$B$22-IF(M12="",L12,M12))) -> 7 | P12: =IF(J12="Closed",IF(N12<=IF(M12="",L12,M12),"Yes","No"),"–") -> – | Q12: DC | R12: 46294 | S12: E101
A13: T-0012 | B13: Canteen contract renewal (follow-up) | C13: Assigned | D13: HRA | E13: HR | F13: E119 | G13: Ashok Menon | H13: E118 | I13: Medium | J13: Closed | K13: 46297 | L13: 46318 | N13: 46316 | O13: =IF(J13="Closed",0,MAX(0,README!$B$22-IF(M13="",L13,M13))) -> 0 | P13: =IF(J13="Closed",IF(N13<=IF(M13="",L13,M13),"Yes","No"),"–") -> Yes | Q13: DC | R13: 46296 | S13: E118
A14: T-0013 | B14: Rate contract renewal – packing material | C14: Self-initiated | D14: PUR | F14: E124 | G14: Harini Iyer | H14: E123 | I14: High | J14: Accepted | K14: 46297 | L14: 46326 | O14: =IF(J14="Closed",0,MAX(0,README!$B$22-IF(M14="",L14,M14))) -> 0 | P14: =IF(J14="Closed",IF(N14<=IF(M14="",L14,M14),"Yes","No"),"–") -> – | Q14: DC | R14: 46295 | S14: E124
A15: T-0014 | B15: Rate contract renewal – packing material (follow-up) | C15: Assigned | D15: PUR | F15: E124 | G15: Harini Iyer | H15: E123 | I15: Medium | J15: Submitted for Review | K15: 46314 | L15: 46344 | O15: =IF(J15="Closed",0,MAX(0,README!$B$22-IF(M15="",L15,M15))) -> 0 | P15: =IF(J15="Closed",IF(N15<=IF(M15="",L15,M15),"Yes","No"),"–") -> – | Q15: DC | R15: 46314 | S15: E123
A16: T-0015 | B16: Vendor evaluation – Q2 | C16: Assigned | D16: PUR | F16: E126 | G16: Sowmya Chandran | H16: E124 | I16: High | J16: Returned for Rework | K16: 46297 | L16: 46324 | O16: =IF(J16="Closed",0,MAX(0,README!$B$22-IF(M16="",L16,M16))) -> 0 | P16: =IF(J16="Closed",IF(N16<=IF(M16="",L16,M16),"Yes","No"),"–") -> – | Q16: DS | R16: 46296 | S16: E124
A17: T-0016 | B17: Vendor evaluation – Q2 (follow-up) | C17: Assigned | D17: PUR | F17: E125 | G17: Vinod Shetty | H17: E124 | I17: Medium | J17: Open | K17: 46283 | L17: 46297 | O17: =IF(J17="Closed",0,MAX(0,README!$B$22-IF(M17="",L17,M17))) -> 20 | P17: =IF(J17="Closed",IF(N17<=IF(M17="",L17,M17),"Yes","No"),"–") -> – | Q17: DS | R17: 46281 | S17: E124
A18: T-0017 | B18: Physical stock verification – Plant 1 | C18: Self-initiated | D18: STR | F18: E131 | G18: Mohan Nair | H18: E129 | I18: Medium | J18: In Progress | K18: 46284 | L18: 46297 | O18: =IF(J18="Closed",0,MAX(0,README!$B$22-IF(M18="",L18,M18))) -> 20 | P18: =IF(J18="Closed",IF(N18<=IF(M18="",L18,M18),"Yes","No"),"–") -> – | Q18: PI | R18: 46284 | S18: E131
A19: T-0018 | B19: Physical stock verification – Plant 1 (follow-up) | C19: Assigned | D19: STR | F19: E130 | G19: Keerthana Krishnan | H19: E129 | I19: Medium | J19: On Hold | K19: 46311 | L19: 46330 | O19: =IF(J19="Closed",0,MAX(0,README!$B$22-IF(M19="",L19,M19))) -> 0 | P19: =IF(J19="Closed",IF(N19<=IF(M19="",L19,M19),"Yes","No"),"–") -> – | Q19: PI | R19: 46310 | S19: E129
A20: T-0019 | B20: Bin location relabelling | C20: Self-initiated | D20: STR | F20: E130 | G20: Keerthana Krishnan | H20: E129 | I20: Medium | J20: Returned for Rework | K20: 46295 | L20: 46325 | O20: =IF(J20="Closed",0,MAX(0,README!$B$22-IF(M20="",L20,M20))) -> 0 | P20: =IF(J20="Closed",IF(N20<=IF(M20="",L20,M20),"Yes","No"),"–") -> – | Q20: DS | R20: 46293 | S20: E130
A21: T-0020 | B21: Bin location relabelling (follow-up) | C21: Assigned | D21: STR | F21: E134 | G21: Bhavani Sharma | H21: E131 | I21: High | J21: Closed | K21: 46307 | L21: 46332 | N21: 46316 | O21: =IF(J21="Closed",0,MAX(0,README!$B$22-IF(M21="",L21,M21))) -> 0 | P21: =IF(J21="Closed",IF(N21<=IF(M21="",L21,M21),"Yes","No"),"–") -> Yes | Q21: DS | R21: 46307 | S21: E131
A22: T-0021 | B22: Transporter rate revision | C22: Assigned | D22: LOG | F22: E139 | G22: Hari Menon | H22: E137 | I22: High | J22: Open | K22: 46311 | L22: 46320 | O22: =IF(J22="Closed",0,MAX(0,README!$B$22-IF(M22="",L22,M22))) -> 0 | P22: =IF(J22="Closed",IF(N22<=IF(M22="",L22,M22),"Yes","No"),"–") -> – | Q22: DC | R22: 46310 | S22: E137
A23: T-0022 | B23: Transporter rate revision (follow-up) | C23: Assigned | D23: LOG | F23: E136 | G23: Shalini Pillai | H23: E135 | I23: Medium | J23: Accepted | K23: 46307 | L23: 46333 | O23: =IF(J23="Closed",0,MAX(0,README!$B$22-IF(M23="",L23,M23))) -> 0 | P23: =IF(J23="Closed",IF(N23<=IF(M23="",L23,M23),"Yes","No"),"–") -> – | Q23: DC | R23: 46305 | S23: E135
A24: T-0023 | B24: Dispatch delay root-cause | C24: Assigned | D24: LOG | F24: E139 | G24: Hari Menon | H24: E137 | I24: High | J24: Closed | K24: 46309 | L24: 46332 | N24: 46316 | O24: =IF(J24="Closed",0,MAX(0,README!$B$22-IF(M24="",L24,M24))) -> 0 | P24: =IF(J24="Closed",IF(N24<=IF(M24="",L24,M24),"Yes","No"),"–") -> Yes | Q24: IS | R24: 46309 | S24: E137
A25: T-0024 | B25: Dispatch delay root-cause (follow-up) | C25: Assigned | D25: LOG | F25: E135 | G25: Naveen Balan | H25: E101 | I25: Medium | J25: Closed | K25: 46314 | L25: 46329 | N25: 46316 | O25: =IF(J25="Closed",0,MAX(0,README!$B$22-IF(M25="",L25,M25))) -> 0 | P25: =IF(J25="Closed",IF(N25<=IF(M25="",L25,M25),"Yes","No"),"–") -> Yes | Q25: IS | R25: 46313 | S25: E101
A26: T-0025 | B26: Reduce changeover time on Line 2 | C26: Assigned | D26: PRD | E26: Plant 1 | F26: E145 | G26: Sathish Shetty | H26: E143 | I26: Low | J26: Closed | K26: 46309 | L26: 46316 | N26: 46316 | O26: =IF(J26="Closed",0,MAX(0,README!$B$22-IF(M26="",L26,M26))) -> 0 | P26: =IF(J26="Closed",IF(N26<=IF(M26="",L26,M26),"Yes","No"),"–") -> Yes | Q26: PI | R26: 46307 | S26: E143
A27: T-0026 | B27: Reduce changeover time on Line 2 (follow-up) | C27: Self-initiated | D27: PRD | E27: Plant 1 | F27: E143 | G27: Kumar Varma | H27: E142 | I27: High | J27: Returned for Rework | K27: 46299 | L27: 46326 | O27: =IF(J27="Closed",0,MAX(0,README!$B$22-IF(M27="",L27,M27))) -> 0 | P27: =IF(J27="Closed",IF(N27<=IF(M27="",L27,M27),"Yes","No"),"–") -> – | Q27: PI | R27: 46299 | S27: E143
A28: T-0027 | B28: Shift-wise OEE dashboard | C28: Self-initiated | D28: PRD | E28: Plant 1 | F28: E144 | G28: Nandhini Iyer | H28: E142 | I28: Critical | J28: Returned for Rework | K28: 46303 | L28: 46315 | O28: =IF(J28="Closed",0,MAX(0,README!$B$22-IF(M28="",L28,M28))) -> 2 | P28: =IF(J28="Closed",IF(N28<=IF(M28="",L28,M28),"Yes","No"),"–") -> – | Q28: RP | R28: 46302 | S28: E144
A29: T-0028 | B29: Shift-wise OEE dashboard (follow-up) | C29: Assigned | D29: PRD | E29: Plant 2 | F29: E150 | G29: Varsha Krishnan | H29: E149 | I29: Medium | J29: Accepted | K29: 46311 | L29: 46318 | O29: =IF(J29="Closed",0,MAX(0,README!$B$22-IF(M29="",L29,M29))) -> 0 | P29: =IF(J29="Closed",IF(N29<=IF(M29="",L29,M29),"Yes","No"),"–") -> – | Q29: RP | R29: 46309 | S29: E149
A30: T-0029 | B30: Operator skill matrix update | C30: Assigned | D30: PRD | E30: Plant 1 | F30: E147 | G30: Arun Natarajan | H30: E143 | I30: Critical | J30: In Progress | K30: 46283 | L30: 46297 | O30: =IF(J30="Closed",0,MAX(0,README!$B$22-IF(M30="",L30,M30))) -> 20 | P30: =IF(J30="Closed",IF(N30<=IF(M30="",L30,M30),"Yes","No"),"–") -> – | Q30: DS | R30: 46283 | S30: E143
A31: T-0030 | B31: Operator skill matrix update (follow-up) | C31: Assigned | D31: PRD | E31: Plant 2 | F31: E155 | G31: Suresh Iyer | H31: E151 | I31: High | J31: In Progress | K31: 46284 | L31: 46308 | O31: =IF(J31="Closed",0,MAX(0,README!$B$22-IF(M31="",L31,M31))) -> 9 | P31: =IF(J31="Closed",IF(N31<=IF(M31="",L31,M31),"Yes","No"),"–") -> – | Q31: DS | R31: 46283 | S31: E151
A32: T-0031 | B32: Customer complaint #CC-114 CAPA | C32: Self-initiated | D32: QAD | F32: E163 | G32: Prakash Sekar | H32: E160 | I32: Medium | J32: Closed | K32: 46315 | L32: 46327 | N32: 46316 | O32: =IF(J32="Closed",0,MAX(0,README!$B$22-IF(M32="",L32,M32))) -> 0 | P32: =IF(J32="Closed",IF(N32<=IF(M32="",L32,M32),"Yes","No"),"–") -> Yes | Q32: IS | R32: 46313 | S32: E163
A33: T-0032 | B33: Customer complaint #CC-114 CAPA (follow-up) | C33: Self-initiated | D33: QAD | F33: E159 | G33: Vignesh Reddy | H33: E158 | I33: Medium | J33: Submitted for Review | K33: 46314 | L33: 46344 | O33: =IF(J33="Closed",0,MAX(0,README!$B$22-IF(M33="",L33,M33))) -> 0 | P33: =IF(J33="Closed",IF(N33<=IF(M33="",L33,M33),"Yes","No"),"–") -> – | Q33: IS | R33: 46314 | S33: E159
A34: T-0033 | B34: Calibration of lab instruments | C34: Assigned | D34: QAD | F34: E162 | G34: Kavya Nair | H34: E159 | I34: Critical | J34: Returned for Rework | K34: 46303 | L34: 46324 | O34: =IF(J34="Closed",0,MAX(0,README!$B$22-IF(M34="",L34,M34))) -> 0 | P34: =IF(J34="Closed",IF(N34<=IF(M34="",L34,M34),"Yes","No"),"–") -> – | Q34: CO | R34: 46302 | S34: E159
A35: T-0034 | B35: Calibration of lab instruments (follow-up) | C35: Self-initiated | D35: QAD | F35: E159 | G35: Vignesh Reddy | H35: E158 | I35: Low | J35: Closed | K35: 46294 | L35: 46303 | N35: 46299 | O35: =IF(J35="Closed",0,MAX(0,README!$B$22-IF(M35="",L35,M35))) -> 0 | P35: =IF(J35="Closed",IF(N35<=IF(M35="",L35,M35),"Yes","No"),"–") -> Yes | Q35: CO | R35: 46292 | S35: E159
A36: T-0035 | B36: Compressor overhaul | C36: Self-initiated | D36: MNT | E36: Electrical | F36: E167 | G36: Ganesh Pillai | H36: E165 | I36: High | J36: Accepted | K36: 46294 | L36: 46301 | O36: =IF(J36="Closed",0,MAX(0,README!$B$22-IF(M36="",L36,M36))) -> 16 | P36: =IF(J36="Closed",IF(N36<=IF(M36="",L36,M36),"Yes","No"),"–") -> – | Q36: IS | R36: 46294 | S36: E167
A37: T-0036 | B37: Compressor overhaul (follow-up) | C37: Assigned | D37: MNT | F37: E164 | G37: Deepa Subramani | H37: E101 | I37: Critical | J37: Open | K37: 46294 | L37: 46303 | O37: =IF(J37="Closed",0,MAX(0,README!$B$22-IF(M37="",L37,M37))) -> 14 | P37: =IF(J37="Closed",IF(N37<=IF(M37="",L37,M37),"Yes","No"),"–") -> – | Q37: IS | R37: 46293 | S37: E101
A38: T-0037 | B38: Spare parts criticality list | C38: Assigned | D38: MNT | E38: Electrical | F38: E172 | G38: Pooja Raman | H38: E169 | I38: Low | J38: On Hold | K38: 46295 | L38: 46310 | O38: =IF(J38="Closed",0,MAX(0,README!$B$22-IF(M38="",L38,M38))) -> 7 | P38: =IF(J38="Closed",IF(N38<=IF(M38="",L38,M38),"Yes","No"),"–") -> – | Q38: DS | R38: 46293 | S38: E169
A39: T-0038 | B39: Spare parts criticality list (follow-up) | C39: Assigned | D39: MNT | E39: Mechanical | F39: E166 | G39: Revathi Balan | H39: E165 | I39: High | J39: On Hold | K39: 46310 | L39: 46324 | O39: =IF(J39="Closed",0,MAX(0,README!$B$22-IF(M39="",L39,M39))) -> 0 | P39: =IF(J39="Closed",IF(N39<=IF(M39="",L39,M39),"Yes","No"),"–") -> – | Q39: DS | R39: 46310 | S39: E165
A40: T-0039 | B40: Dealer meet planning – South | C40: Assigned | D40: SAM | F40: E174 | G40: Harini Varma | H40: E173 | I40: Medium | J40: Closed | K40: 46286 | L40: 46314 | N40: 46315 | O40: =IF(J40="Closed",0,MAX(0,README!$B$22-IF(M40="",L40,M40))) -> 0 | P40: =IF(J40="Closed",IF(N40<=IF(M40="",L40,M40),"Yes","No"),"–") -> No | Q40: PI | R40: 46285 | S40: E173
A41: T-0040 | B41: Dealer meet planning – South (follow-up) | C41: Assigned | D41: SAM | E41: South | F41: E180 | G41: Keerthana Murugan | H41: E177 | I41: Medium | J41: Accepted | K41: 46283 | L41: 46311 | O41: =IF(J41="Closed",0,MAX(0,README!$B$22-IF(M41="",L41,M41))) -> 6 | P41: =IF(J41="Closed",IF(N41<=IF(M41="",L41,M41),"Yes","No"),"–") -> – | Q41: PI | R41: 46281 | S41: E177
A42: T-0041 | B42: Price list revision | C42: Assigned | D42: SAM | E42: North | F42: E178 | G42: Janani Natarajan | H42: E176 | I42: Low | J42: Submitted for Review | K42: 46286 | L42: 46300 | O42: =IF(J42="Closed",0,MAX(0,README!$B$22-IF(M42="",L42,M42))) -> 17 | P42: =IF(J42="Closed",IF(N42<=IF(M42="",L42,M42),"Yes","No"),"–") -> – | Q42: DS | R42: 46286 | S42: E176
A43: T-0042 | B43: Price list revision (follow-up) | C43: Assigned | D43: SAM | E43: South | F43: E180 | G43: Keerthana Murugan | H43: E177 | I43: Medium | J43: In Progress | K43: 46288 | L43: 46308 | O43: =IF(J43="Closed",0,MAX(0,README!$B$22-IF(M43="",L43,M43))) -> 9 | P43: =IF(J43="Closed",IF(N43<=IF(M43="",L43,M43),"Yes","No"),"–") -> – | Q43: DS | R43: 46287 | S43: E177
A44: T-0043 | B44: New warehouse – civil progress | C44: Assigned | D44: PRJ | F44: E184 | G44: Bhavani Subramani | H44: E183 | I44: Critical | J44: Returned for Rework | K44: 46284 | L44: 46305 | O44: =IF(J44="Closed",0,MAX(0,README!$B$22-IF(M44="",L44,M44))) -> 12 | P44: =IF(J44="Closed",IF(N44<=IF(M44="",L44,M44),"Yes","No"),"–") -> – | Q44: RP | R44: 46282 | S44: E183
A45: T-0044 | B45: New warehouse – civil progress (follow-up) | C45: Assigned | D45: PRJ | F45: E187 | G45: Gopal Pillai | H45: E185 | I45: Medium | J45: Submitted for Review | K45: 46280 | L45: 46289 | O45: =IF(J45="Closed",0,MAX(0,README!$B$22-IF(M45="",L45,M45))) -> 28 | P45: =IF(J45="Closed",IF(N45<=IF(M45="",L45,M45),"Yes","No"),"–") -> – | Q45: RP | R45: 46280 | S45: E185
A46: T-0045 | B46: Capex proposal – solar rooftop | C46: Assigned | D46: PRJ | F46: E186 | G46: Shalini Balan | H46: E185 | I46: Medium | J46: Closed | K46: 46310 | L46: 46323 | N46: 46316 | O46: =IF(J46="Closed",0,MAX(0,README!$B$22-IF(M46="",L46,M46))) -> 0 | P46: =IF(J46="Closed",IF(N46<=IF(M46="",L46,M46),"Yes","No"),"–") -> Yes | Q46: PI | R46: 46309 | S46: E185
A47: T-0046 | B47: Capex proposal – solar rooftop (follow-up) | C47: Assigned | D47: PRJ | F47: E183 | G47: Rajesh Sekar | H47: E101 | I47: Medium | J47: On Hold | K47: 46304 | L47: 46319 | O47: =IF(J47="Closed",0,MAX(0,README!$B$22-IF(M47="",L47,M47))) -> 0 | P47: =IF(J47="Closed",IF(N47<=IF(M47="",L47,M47),"Yes","No"),"–") -> – | Q47: PI | R47: 46302 | S47: E101
A48: T-0047 | B48: Antivirus renewal | C48: Assigned | D48: ITD | F48: E190 | G48: Ramya Menon | H48: E189 | I48: High | J48: On Hold | K48: 46315 | L48: 46343 | O48: =IF(J48="Closed",0,MAX(0,README!$B$22-IF(M48="",L48,M48))) -> 0 | P48: =IF(J48="Closed",IF(N48<=IF(M48="",L48,M48),"Yes","No"),"–") -> – | Q48: DC | R48: 46315 | S48: E189
A49: T-0048 | B49: Antivirus renewal (follow-up) | C49: Self-initiated | D49: ITD | F49: E189 | G49: Hari Das | H49: E188 | I49: Low | J49: In Progress | K49: 46293 | L49: 46301 | O49: =IF(J49="Closed",0,MAX(0,README!$B$22-IF(M49="",L49,M49))) -> 16 | P49: =IF(J49="Closed",IF(N49<=IF(M49="",L49,M49),"Yes","No"),"–") -> – | Q49: DC | R49: 46292 | S49: E189
A50: T-0049 | B50: Email migration plan | C50: Self-initiated | D50: ITD | F50: E188 | G50: Aishwarya Joseph | H50: E101 | I50: Medium | J50: Open | K50: 46300 | L50: 46308 | O50: =IF(J50="Closed",0,MAX(0,README!$B$22-IF(M50="",L50,M50))) -> 9 | P50: =IF(J50="Closed",IF(N50<=IF(M50="",L50,M50),"Yes","No"),"–") -> – | Q50: PI | R50: 46298 | S50: E188
A51: T-0050 | B51: Email migration plan (follow-up) | C51: Self-initiated | D51: ITD | F51: E190 | G51: Ramya Menon | H51: E189 | I51: Critical | J51: Open | K51: 46313 | L51: 46325 | O51: =IF(J51="Closed",0,MAX(0,README!$B$22-IF(M51="",L51,M51))) -> 0 | P51: =IF(J51="Closed",IF(N51<=IF(M51="",L51,M51),"Yes","No"),"–") -> – | Q51: PI | R51: 46313 | S51: E190
A52: T-0051 | B52: Board meeting minutes – Q2 | C52: Self-initiated | D52: LEG | F52: E191 | G52: Vijay Thomas | H52: E101 | I52: High | J52: Accepted | K52: 46284 | L52: 46310 | O52: =IF(J52="Closed",0,MAX(0,README!$B$22-IF(M52="",L52,M52))) -> 7 | P52: =IF(J52="Closed",IF(N52<=IF(M52="",L52,M52),"Yes","No"),"–") -> – | Q52: DC | R52: 46283 | S52: E191
A53: T-0052 | B53: Board meeting minutes – Q2 (follow-up) | C53: Self-initiated | D53: LEG | F53: E192 | G53: Gayathri Raman | H53: E191 | I53: Low | J53: Submitted for Review | K53: 46287 | L53: 46312 | O53: =IF(J53="Closed",0,MAX(0,README!$B$22-IF(M53="",L53,M53))) -> 5 | P53: =IF(J53="Closed",IF(N53<=IF(M53="",L53,M53),"Yes","No"),"–") -> – | Q53: DC | R53: 46285 | S53: E192
A54: T-0053 | B54: Trademark renewal filing | C54: Self-initiated | D54: LEG | F54: E191 | G54: Vijay Thomas | H54: E101 | I54: Low | J54: In Progress | K54: 46285 | L54: 46305 | O54: =IF(J54="Closed",0,MAX(0,README!$B$22-IF(M54="",L54,M54))) -> 12 | P54: =IF(J54="Closed",IF(N54<=IF(M54="",L54,M54),"Yes","No"),"–") -> – | Q54: CO | R54: 46285 | S54: E191
A55: T-0054 | B55: Trademark renewal filing (follow-up) | C55: Assigned | D55: LEG | F55: E192 | G55: Gayathri Raman | H55: E191 | I55: Medium | J55: Closed | K55: 46296 | L55: 46309 | N55: 46308 | O55: =IF(J55="Closed",0,MAX(0,README!$B$22-IF(M55="",L55,M55))) -> 0 | P55: =IF(J55="Closed",IF(N55<=IF(M55="",L55,M55),"Yes","No"),"–") -> Yes | Q55: CO | R55: 46295 | S55: E191
A56: T-0055 | B56: Fire drill – Plant 2 | C56: Assigned | D56: EHS | F56: E195 | G56: Sathish Iyer | H56: E194 | I56: Medium | J56: Closed | K56: 46299 | L56: 46320 | N56: 46317 | O56: =IF(J56="Closed",0,MAX(0,README!$B$22-IF(M56="",L56,M56))) -> 0 | P56: =IF(J56="Closed",IF(N56<=IF(M56="",L56,M56),"Yes","No"),"–") -> Yes | Q56: PI | R56: 46297 | S56: E194
A57: T-0056 | B57: Fire drill – Plant 2 (follow-up) | C57: Self-initiated | D57: EHS | F57: E194 | G57: Nandhini Varma | H57: E101 | I57: Medium | J57: Submitted for Review | K57: 46284 | L57: 46308 | O57: =IF(J57="Closed",0,MAX(0,README!$B$22-IF(M57="",L57,M57))) -> 9 | P57: =IF(J57="Closed",IF(N57<=IF(M57="",L57,M57),"Yes","No"),"–") -> – | Q57: PI | R57: 46284 | S57: E194
A58: T-0057 | B58: Hazard identification refresh | C58: Assigned | D58: EHS | F58: E195 | G58: Sathish Iyer | H58: E194 | I58: Medium | J58: Submitted for Review | K58: 46302 | L58: 46311 | O58: =IF(J58="Closed",0,MAX(0,README!$B$22-IF(M58="",L58,M58))) -> 6 | P58: =IF(J58="Closed",IF(N58<=IF(M58="",L58,M58),"Yes","No"),"–") -> – | Q58: CO | R58: 46301 | S58: E194
A59: T-0058 | B59: Hazard identification refresh (follow-up) | C59: Self-initiated | D59: EHS | F59: E195 | G59: Sathish Iyer | H59: E194 | I59: Low | J59: Closed | K59: 46308 | L59: 46332 | N59: 46316 | O59: =IF(J59="Closed",0,MAX(0,README!$B$22-IF(M59="",L59,M59))) -> 0 | P59: =IF(J59="Closed",IF(N59<=IF(M59="",L59,M59),"Yes","No"),"–") -> Yes | Q59: CO | R59: 46306 | S59: E195
A60: T-0059 | B60: Audit of petty cash – Plant 1 | C60: Assigned | D60: IAD | F60: E198 | G60: Mythili Natarajan | H60: E101 | I60: Medium | J60: Accepted | K60: 46315 | L60: 46331 | O60: =IF(J60="Closed",0,MAX(0,README!$B$22-IF(M60="",L60,M60))) -> 0 | P60: =IF(J60="Closed",IF(N60<=IF(M60="",L60,M60),"Yes","No"),"–") -> – | Q60: PI | R60: 46315 | S60: E101
A61: T-0060 | B61: Audit of petty cash – Plant 1 (follow-up) | C61: Assigned | D61: IAD | F61: E198 | G61: Mythili Natarajan | H61: E101 | I61: Medium | J61: Returned for Rework | K61: 46286 | L61: 46316 | O61: =IF(J61="Closed",0,MAX(0,README!$B$22-IF(M61="",L61,M61))) -> 1 | P61: =IF(J61="Closed",IF(N61<=IF(M61="",L61,M61),"Yes","No"),"–") -> – | Q61: PI | R61: 46285 | S61: E101
A64: Summary (formulas)
A65: Total tasks | B65: =COUNTA(A2:A61) -> 60
A66: Closed | B66: =COUNTIF(J2:J61,"Closed") -> 15
A67: Closed on time | B67: =COUNTIF(P2:P61,"Yes") -> 13
A68: On-time completion % (K1, unweighted) | B68: =IFERROR(B67/B66,0) -> 0.86666667
A69: Open tasks overdue as at As-of date | B69: =COUNTIFS(J2:J61,"<>Closed",O2:O61,">0") -> 27

Sheet Requests
A1: Request ID | B1: From Dept | C1: To Dept | D1: Request | E1: Priority | F1: Raised On | G1: Need-by Date | H1: Acceptance | I1: Committed Date | J1: Status | K1: Category
A2: R-001 | B2: FIN | C2: PUR | D2: Provide PO copies for GRNI items older than 30 days | E2: High | F2: 46300 | G2: 46305 | H2: Accepted | I2: 46307 | J2: In Progress | K2: DR
A3: R-002 | B3: PRD | C3: MNT | D3: Repair hydraulic press – Line 2 | E3: Critical | F3: 46309 | G3: 46310 | H3: Accepted | I3: 46310 | J3: Closed – confirmed | K3: IS
A4: R-003 | B4: SAM | C4: FIN | D4: Credit limit enhancement for dealer D-0231 | E4: Medium | F4: 46303 | G4: 46310 | H4: Accepted | I4: 46309 | J4: Closed – confirmed | K4: AP
A5: R-004 | B5: HRA | C5: ITD | D5: Laptop and email for 4 new joinees | E5: Medium | F5: 46311 | G5: 46317 | H5: Pending acceptance | J5: Open | K5: MD
A6: R-005 | B6: QAD | C6: PUR | D6: Replace supplier for packing film after rejections | E6: High | F6: 46296 | G6: 46315 | H6: Accepted | I6: 46325 | J6: In Progress | K6: IS
A7: R-006 | B7: FIN | C7: HRA | D7: Payroll inputs for October | E7: High | F7: 46313 | G7: 46320 | H7: Accepted | I7: 46320 | J7: In Progress | K7: DR
A8: R-007 | B8: PRJ | C8: LEG | D8: Vet civil contractor agreement | E8: Medium | F8: 46298 | G8: 46305 | H8: Accepted | I8: 46307 | J8: Submitted – awaiting requester | K8: DC
A9: R-008 | B9: STR | C9: LOG | D9: Shift idle material from Plant 2 to Plant 1 | E9: Low | F9: 46304 | G9: 46315 | H9: Declined – need material list | J9: Returned to requester | K9: FU
A10: R-009 | B10: EHS | C10: MNT | D10: Install guard on conveyor C-4 | E10: Critical | F10: 46314 | G10: 46315 | H10: Accepted | I10: 46316 | J10: In Progress | K10: IS
A11: R-010 | B11: IAD | C11: FIN | D11: Share petty cash vouchers – Plant 1 | E11: Medium | F11: 46307 | G11: 46311 | H11: Accepted | I11: 46311 | J11: Closed – confirmed | K11: DR

Sheet KPI_Config
A1: Code | B1: Measure | C1: Formula | D1: Weight
A2: K1 | B2: On-time completion | C2: Tasks closed on/before applicable due date ÷ tasks closed | D2: 0.4
A3: K2 | B3: Overdue control | C3: 1 − (open overdue at month end ÷ open at month end) | D3: 0.2
A4: K3 | B4: First-time right | C4: Closed without rework ÷ closed | D4: 0.15
A5: K4 | B5: Responsiveness to other departments | C5: Avg of (accepted within time %) and (closed by committed date %) | D5: 0.15
A6: K5 | B6: Recurring and compliance adherence | C6: Recurring closed on time ÷ recurring due | D6: 0.1
C7: Total weight (must be 100%) | D7: =SUM(D2:D6) -> 1
A9: Priority weights
A10: Critical | B10: 3
A11: High | B11: 2
A12: Medium | B12: 1
A13: Low | B13: 1
A15: Score bands
A16: 90–100 | B16: Excellent | C16: Green
A17: 75–89 | B17: Good | C17: Light green
A18: 60–74 | B18: Needs attention | C18: Amber
A19: Below 60 | B19: Critical | C19: Red
A21: Minimum closed tasks for a score: 10 per month (below this, shown as 'insufficient data').
A22: Yellow cells are proposals pending management approval (BRD section 11).

Sheet Escalation_Rules
A1: Trigger | B1: Normal priority → notify | C1: Critical priority → notify
A2: 2 days before due | B2: Doer (reminder) | C2: Doer (reminder, 3 days before)
A3: On due date | B3: Doer | C3: Doer + reviewer
A4: 1 working day overdue | B4: Reviewer (immediate senior) | C4: HOD
A5: 3 working days overdue | B5: HOD | C5: Management Viewers
A6: 7 working days overdue | B6: Management Viewers | C6: Management Viewers (daily until closed)
A7: Request not accepted within acceptance time | B7: Receiving HOD | C7: Receiving HOD + Management Viewers
A8: Review pending > 2 days after submission | B8: Reviewer's own senior | C8: HOD
A10: Acceptance time by priority: Critical same day; High 1 working day; Medium 2; Low 3.

Sheet Holidays
A1: Date | B1: Holiday | C1: Applies to (HO / Plant-1 / Plant-2 / All)
A2: 46297 | B2: Gandhi Jayanti | C2: All
A3: 46315 | B3: Ayudha Pooja (sample) | C3: All
A4: 46334 | B4: Deepavali (sample) | C4: All
A5: 46381 | B5: Christmas | C5: HO
A6: 46402 | B6: Pongal (sample) | C6: All
A7: 46413 | B7: Republic Day | C7: All
A9: Dummy calendar for testing only; dates marked (sample) are placeholders. Replace with the company's notified holiday list.
