Workbook

Sheet Assumptions
A1: CMA DATA — TEST
A2: All amounts in ₹ Lakhs · generated by CMA Pro Builder
A4: Sales Growth % p.a. | B4: 10
A5: Cost Efficiency Boost % | B5: 0
A6: RM Consumed as % of Sales | B6: 0.352288
A7: Inventory Days | B7: 60
A8: Debtor Days | B8: 45
A9: Creditor Days | B9: 30
A10: Tax Rate % | B10: 25
A11: Dividend % of PAT | B11: 0
A12: Minimum Cash Balance | B12: 1
A13: CC Limit | B13: 50
A14: CC Interest Rate % | B14: 10.5
A15: Grant Month Index (0=Apr) | B15: 1
A16: Term Loan Amount | B16: 87.59
A19: Expense ratios (% of sales, from latest actual year)
A20: Power & Fuel | B20: 0.002797
A21: Direct Labour & Wages | B21: 0
A22: Salary & Employee Benefits | B22: 0.207368
A23: Freight & Cartage | B23: 0.00338
A24: Sales Promotion & Distribution | B24: 0.00771
A25: Travelling & Conveyance | B25: 0.003775
A26: Repairs & Maintenance | B26: 0.007109
A27: Professional Fees | B27: 0.045863
A28: Operating Expenses (General) | B28: 0.048796
A29: Other Expenses | B29: 0.150906
A30: Custom Expense 1 | B30: 0
A31: Custom Expense 2 | B31: 0
A32: Packing Charges | B32: 0.007293

Sheet Loan Schedule
A1: Month | B1: Date | C1: FY Index | D1: Opening | E1: EMI | F1: Interest | G1: Principal | H1: Closing
A2: 1 | B2: 2024-06-09 | C2: 1 | D2: 87.59 | E2: 0.66 | F2: 0.66 | G2: 0 | H2: 87.59
A3: 2 | B3: 2024-07-09 | C3: 1 | D3: 87.59 | E3: 0.66 | F3: 0.66 | G3: 0 | H3: 87.59
A4: 3 | B4: 2024-08-09 | C4: 1 | D4: 87.59 | E4: 0.66 | F4: 0.66 | G4: 0 | H4: 87.59
A5: 4 | B5: 2024-09-09 | C5: 1 | D5: 87.59 | E5: 0.66 | F5: 0.66 | G5: 0 | H5: 87.59
A6: 5 | B6: 2024-10-09 | C6: 1 | D6: 87.59 | E6: 0.66 | F6: 0.66 | G6: 0 | H6: 87.59
A7: 6 | B7: 2024-11-09 | C7: 1 | D7: 87.59 | E7: 0.66 | F7: 0.66 | G7: 0 | H7: 87.59
A8: 7 | B8: 2024-12-09 | C8: 1 | D8: 87.59 | E8: 1.45 | F8: 0.66 | G8: 0.79 | H8: 86.8
A9: 8 | B9: 2025-01-09 | C9: 1 | D9: 86.8 | E9: 1.45 | F9: 0.66 | G9: 0.79 | H9: 86.01
A10: 9 | B10: 2025-02-09 | C10: 1 | D10: 86.01 | E10: 1.45 | F10: 0.65 | G10: 0.8 | H10: 85.21
A11: 10 | B11: 2025-03-09 | C11: 1 | D11: 85.21 | E11: 1.45 | F11: 0.65 | G11: 0.81 | H11: 84.41
A12: 11 | B12: 2025-04-09 | C12: 2 | D12: 84.41 | E12: 1.45 | F12: 0.64 | G12: 0.81 | H12: 83.6
A13: 12 | B13: 2025-05-09 | C13: 2 | D13: 83.6 | E13: 1.45 | F13: 0.63 | G13: 0.82 | H13: 82.78
... A88: 87 | B88: 2031-08-09 | C88: 8 | D88: 1.44 | E88: 1.45 | F88: 0.01 | G88: 1.44 | H88: 0

Sheet Depreciation
A1: Depreciation Schedule (WDV)
A2: Block | B2: 2023-24 | C2: 2024-25 | D2: 2025-26 | E2: 2026-27
A3: Plant & Machinery — Opening (15%) | B3: 50 | C3: =B6 | D3: =C6 | E3: =D6
A4: Plant & Machinery — Addition | B4: 0 | C4: 87.59 | D4: 0 | E4: 0
A5: Plant & Machinery — Depreciation | B5: =(B3+B4)*0.15 | C5: =(C3+C4)*0.15 | D5: =(D3+D4)*0.15 | E5: =(E3+E4)*0.15
A6: Plant & Machinery — Closing WDV | B6: =B3+B4-B5 | C6: =C3+C4-C5 | D6: =D3+D4-D5 | E6: =E3+E4-E5
A7: Furniture & Fixtures — Opening (10%) | B7: 0 | C7: =B10 | D7: =C10 | E7: =D10
A8: Furniture & Fixtures — Addition | B8: 0 | C8: 0 | D8: 0 | E8: 0
A9: Furniture & Fixtures — Depreciation | B9: =(B7+B8)*0.1 | C9: =(C7+C8)*0.1 | D9: =(D7+D8)*0.1 | E9: =(E7+E8)*0.1
A10: Furniture & Fixtures — Closing WDV | B10: =B7+B8-B9 | C10: =C7+C8-C9 | D10: =D7+D8-D9 | E10: =E7+E8-E9
A11: Building — Opening (10%) | B11: 0 | C11: =B14 | D11: =C14 | E11: =D14
A12: Building — Addition | B12: 0 | C12: 0 | D12: 0 | E12: 0
A13: Building — Depreciation | B13: =(B11+B12)*0.1 | C13: =(C11+C12)*0.1 | D13: =(D11+D12)*0.1 | E13: =(E11+E12)*0.1
A14: Building — Closing WDV | B14: =B11+B12-B13 | C14: =C11+C12-C13 | D14: =D11+D12-D13 | E14: =E11+E12-E13
A15: Computers — Opening (40%) | B15: 0 | C15: =B18 | D15: =C18 | E15: =D18
A16: Computers — Addition | B16: 0 | C16: 0 | D16: 0 | E16: 0
A17: Computers — Depreciation | B17: =(B15+B16)*0.4 | C17: =(C15+C16)*0.4 | D17: =(D15+D16)*0.4 | E17: =(E15+E16)*0.4
A18: Computers — Closing WDV | B18: =B15+B16-B17 | C18: =C15+C16-C17 | D18: =D15+D16-D17 | E18: =E15+E16-E17
A19: Other Asset 1 — Opening (15%) | B19: 0 | C19: =B22 | D19: =C22 | E19: =D22
A20: Other Asset 1 — Addition | B20: 0 | C20: 0 | D20: 0 | E20: 0
A21: Other Asset 1 — Depreciation | B21: =(B19+B20)*0.15 | C21: =(C19+C20)*0.15 | D21: =(D19+D20)*0.15 | E21: =(E19+E20)*0.15
A22: Other Asset 1 — Closing WDV | B22: =B19+B20-B21 | C22: =C19+C20-C21 | D22: =D19+D20-D21 | E22: =E19+E20-E21
A23: Other Asset 2 — Opening (15%) | B23: 0 | C23: =B26 | D23: =C26 | E23: =D26
A24: Other Asset 2 — Addition | B24: 0 | C24: 0 | D24: 0 | E24: 0
A25: Other Asset 2 — Depreciation | B25: =(B23+B24)*0.15 | C25: =(C23+C24)*0.15 | D25: =(D23+D24)*0.15 | E25: =(E23+E24)*0.15
A26: Other Asset 2 — Closing WDV | B26: =B23+B24-B25 | C26: =C23+C24-C25 | D26: =D23+D24-D25 | E26: =E23+E24-E25
A27: TOTAL DEPRECIATION | B27: =B5+B9+B13+B17+B21+B25 | C27: =C5+C9+C13+C17+C21+C25 | D27: =D5+D9+D13+D17+D21+D25 | E27: =E5+E9+E13+E17+E21+E25
A28: TOTAL NET BLOCK | B28: =B6+B10+B14+B18+B22+B26 | C28: =C6+C10+C14+C18+C22+C26 | D28: =D6+D10+D14+D18+D22+D26 | E28: =E6+E10+E14+E18+E22+E26

Sheet Operating Statement
A1: FORM-II : OPERATING STATEMENT
A2: For the year ended/ending 31st March · ₹ Lakhs
A3: Particulars | B3: 2023-24 (Actual) | C3: 2024-25 (Estimated) | D3: 2025-26 (Projected) | E3: 2026-27 (Projected)
A4: INCOME
A5: Gross Sales | B5: 342.79 | C5: =B5*(1+Assumptions!$B$4/100) | D5: =C5*(1+Assumptions!$B$4/100) | E5: =D5*(1+Assumptions!$B$4/100)
A6: Other Income | B6: 0 | C6: 0 | D6: 0 | E6: 0
A7: COST OF SALES
A8: Opening Stock | B8: 9 | C8: =B10 | D8: =C10 | E8: =D10
A9: Add: Purchases | B9: 121.76 | C9: =C11+C10-C8 | D9: =D11+D10-D8 | E9: =E11+E10-E8
A10: Less: Closing Stock | B10: 10 | C10: =C5/365*Assumptions!$B$7 | D10: =D5/365*Assumptions!$B$7 | E10: =E5/365*Assumptions!$B$7
A11: Raw Material Consumed | B11: =B8+B9-B10 | C11: =C5*Assumptions!$B$6*(1-Assumptions!$B$5/100) | D11: =D5*Assumptions!$B$6*(1-Assumptions!$B$5/100) | E11: =E5*Assumptions!$B$6*(1-Assumptions!$B$5/100)
A12: Power & Fuel | B12: 0.96 | C12: =C5*Assumptions!$B$20*(1-Assumptions!$B$5/100) | D12: =D5*Assumptions!$B$20*(1-Assumptions!$B$5/100) | E12: =E5*Assumptions!$B$20*(1-Assumptions!$B$5/100)
A13: Direct Labour & Wages | B13: 0 | C13: =C5*Assumptions!$B$21*(1-Assumptions!$B$5/100) | D13: =D5*Assumptions!$B$21*(1-Assumptions!$B$5/100) | E13: =E5*Assumptions!$B$21*(1-Assumptions!$B$5/100)
A14: Salary & Employee Benefits | B14: 71.08 | C14: =C5*Assumptions!$B$22*(1-Assumptions!$B$5/100) | D14: =D5*Assumptions!$B$22*(1-Assumptions!$B$5/100) | E14: =E5*Assumptions!$B$22*(1-Assumptions!$B$5/100)
A15: Freight & Cartage | B15: 1.16 | C15: =C5*Assumptions!$B$23*(1-Assumptions!$B$5/100) | D15: =D5*Assumptions!$B$23*(1-Assumptions!$B$5/100) | E15: =E5*Assumptions!$B$23*(1-Assumptions!$B$5/100)
A16: Sales Promotion & Distribution | B16: 2.64 | C16: =C5*Assumptions!$B$24*(1-Assumptions!$B$5/100) | D16: =D5*Assumptions!$B$24*(1-Assumptions!$B$5/100) | E16: =E5*Assumptions!$B$24*(1-Assumptions!$B$5/100)
A17: Travelling & Conveyance | B17: 1.29 | C17: =C5*Assumptions!$B$25*(1-Assumptions!$B$5/100) | D17: =D5*Assumptions!$B$25*(1-Assumptions!$B$5/100) | E17: =E5*Assumptions!$B$25*(1-Assumptions!$B$5/100)
A18: Repairs & Maintenance | B18: 2.44 | C18: =C5*Assumptions!$B$26*(1-Assumptions!$B$5/100) | D18: =D5*Assumptions!$B$26*(1-Assumptions!$B$5/100) | E18: =E5*Assumptions!$B$26*(1-Assumptions!$B$5/100)
A19: Professional Fees | B19: 15.72 | C19: =C5*Assumptions!$B$27*(1-Assumptions!$B$5/100) | D19: =D5*Assumptions!$B$27*(1-Assumptions!$B$5/100) | E19: =E5*Assumptions!$B$27*(1-Assumptions!$B$5/100)
A20: Operating Expenses (General) | B20: 16.73 | C20: =C5*Assumptions!$B$28*(1-Assumptions!$B$5/100) | D20: =D5*Assumptions!$B$28*(1-Assumptions!$B$5/100) | E20: =E5*Assumptions!$B$28*(1-Assumptions!$B$5/100)
A21: Other Expenses | B21: 51.73 | C21: =C5*Assumptions!$B$29*(1-Assumptions!$B$5/100) | D21: =D5*Assumptions!$B$29*(1-Assumptions!$B$5/100) | E21: =E5*Assumptions!$B$29*(1-Assumptions!$B$5/100)
A22: Custom Expense 1 | B22: 0 | C22: =C5*Assumptions!$B$30*(1-Assumptions!$B$5/100) | D22: =D5*Assumptions!$B$30*(1-Assumptions!$B$5/100) | E22: =E5*Assumptions!$B$30*(1-Assumptions!$B$5/100)
A23: Custom Expense 2 | B23: 0 | C23: =C5*Assumptions!$B$31*(1-Assumptions!$B$5/100) | D23: =D5*Assumptions!$B$31*(1-Assumptions!$B$5/100) | E23: =E5*Assumptions!$B$31*(1-Assumptions!$B$5/100)
A24: Packing Charges | B24: 2.5 | C24: =C5*Assumptions!$B$32*(1-Assumptions!$B$5/100) | D24: =D5*Assumptions!$B$32*(1-Assumptions!$B$5/100) | E24: =E5*Assumptions!$B$32*(1-Assumptions!$B$5/100)
A25: Total Expenses (incl. Power & Labour) | B25: =SUM(B12:B24) | C25: =SUM(C12:C24) | D25: =SUM(D12:D24) | E25: =SUM(E12:E24)
A26: PBDIT / EBITDA | B26: =B5+B6-B11-B25 | C26: =C5+C6-C11-C25 | D26: =D5+D6-D11-D25 | E26: =E5+E6-E11-E25
A27: Depreciation | B27: 16.45 | C27: =Depreciation!C27 | D27: =Depreciation!D27 | E27: =Depreciation!E27
A28: Interest — Cash Credit | B28: 3.8 | C28: =Assumptions!$B$13*Assumptions!$B$14/100*(12-Assumptions!$B$15)/12 | D28: =Assumptions!$B$13*Assumptions!$B$14/100 | E28: =Assumptions!$B$13*Assumptions!$B$14/100
A29: Interest — Term Loan | B29: 0 | C29: =SUMIF('Loan Schedule'!C:C,1,'Loan Schedule'!F:F) | D29: =SUMIF('Loan Schedule'!C:C,2,'Loan Schedule'!F:F) | E29: =SUMIF('Loan Schedule'!C:C,3,'Loan Schedule'!F:F)
A30: Bank Charges | B30: 0.74 | C30: 0.74 | D30: 0.74 | E30: 0.74
A31: Profit Before Tax | B31: =B26-B27-B28-B29-B30 | C31: =C26-C27-C28-C29-C30 | D31: =D26-D27-D28-D29-D30 | E31: =E26-E27-E28-E29-E30
A32: Provision for Tax | B32: 14.1 | C32: =MAX(0,C31*Assumptions!$B$10/100) | D32: =MAX(0,D31*Assumptions!$B$10/100) | E32: =MAX(0,E31*Assumptions!$B$10/100)
A33: Net Profit After Tax | B33: =B31-B32 | C33: =C31-C32 | D33: =D31-D32 | E33: =E31-E32
A34: Dividend | B34: 0 | C34: =MAX(0,C33*Assumptions!$B$11/100) | D34: =MAX(0,D33*Assumptions!$B$11/100) | E34: =MAX(0,E33*Assumptions!$B$11/100)
A35: Retained Profit | B35: =B33-B34 | C35: =C33-C34 | D35: =D33-D34 | E35: =E33-E34
A36: Net Cash Accrual (PAT + Dep) | B36: =B33+B27 | C36: =C33+C27 | D36: =D33+D27 | E36: =E33+E27

Sheet Balance Sheet
A1: FORM-III : ANALYSIS OF BALANCE SHEET
A3: Particulars | B3: 2023-24 (Actual) | C3: 2024-25 (Estimated) | D3: 2025-26 (Projected) | E3: 2026-27 (Projected)
A4: LIABILITIES
A5: Share Capital | B5: 50 | C5: 50 | D5: 50 | E5: 50
A6: Reserves & Surplus | B6: 25 | C6: =B6+'Operating Statement'!C35 | D6: =C6+'Operating Statement'!D35 | E6: =D6+'Operating Statement'!E35
A7: Net Worth | B7: =B5+B6 | C7: =C5+C6 | D7: =D5+D6 | E7: =E5+E6
A8: Term Loan (total o/s) | B8: 0 | C8: =Assumptions!$B$16-SUMIF('Loan Schedule'!C:C,"<="&1,'Loan Schedule'!G:G) | D8: =Assumptions!$B$16-SUMIF('Loan Schedule'!C:C,"<="&2,'Loan Schedule'!G:G) | E8: =Assumptions!$B$16-SUMIF('Loan Schedule'!C:C,"<="&3,'Loan Schedule'!G:G)
A9: of which CPLTD (next 12m) | B9: 0 | C9: =SUMIF('Loan Schedule'!C:C,2,'Loan Schedule'!G:G) | D9: =SUMIF('Loan Schedule'!C:C,3,'Loan Schedule'!G:G) | E9: =SUMIF('Loan Schedule'!C:C,4,'Loan Schedule'!G:G)
A10: Cash Credit | B10: 35 | C10: =Assumptions!$B$13 | D10: =Assumptions!$B$13 | E10: =Assumptions!$B$13
A11: Unsecured Loans | B11: 5 | C11: 5 | D11: 5 | E11: 5
A12: Creditors / Payables | B12: 18 | C12: ='Operating Statement'!C9/365*Assumptions!$B$9 | D12: ='Operating Statement'!D9/365*Assumptions!$B$9 | E12: ='Operating Statement'!E9/365*Assumptions!$B$9
A13: Other Current Liabilities | B13: 6 | C13: =B13*1.05 | D13: =C13*1.05 | E13: =D13*1.05
A14: GST Payable (current) | B14: 3 | C14: =B14*1.05 | D14: =C14*1.05 | E14: =D14*1.05
A15: TOTAL LIABILITIES | B15: =B5+B6+B8+B10+B11+B12+B13+B14 | C15: =C5+C6+C8+C10+C11+C12+C13+C14 | D15: =D5+D6+D8+D10+D11+D12+D13+D14 | E15: =E5+E6+E8+E10+E11+E12+E13+E14
A16: ASSETS
A17: Fixed Assets (Net Block) | B17: 72.5 | C17: =Depreciation!C28 | D17: =Depreciation!D28 | E17: =Depreciation!E28
A18: Deposits & Advances | B18: 3.5 | C18: 3.5 | D18: 3.5 | E18: 3.5
A19: Investments | B19: 0 | C19: 0 | D19: 0 | E19: 0
A20: Stock / Inventory | B20: 10 | C20: ='Operating Statement'!C10 | D20: ='Operating Statement'!D10 | E20: ='Operating Statement'!E10
A21: Debtors / Receivables | B21: 42 | C21: ='Operating Statement'!C5/365*Assumptions!$B$8 | D21: ='Operating Statement'!D5/365*Assumptions!$B$8 | E21: ='Operating Statement'!E5/365*Assumptions!$B$8
A22: Cash & Bank | B22: 8 | C22: =C15-(C17+C18+C19+C20+C21+C23+C24) | D22: =D15-(D17+D18+D19+D20+D21+D23+D24) | E22: =E15-(E17+E18+E19+E20+E21+E23+E24)
A23: Other Current Assets | B23: 2 | C23: 2 | D23: 2 | E23: 2
A24: GST Refund Due (current) | B24: 4 | C24: 4 | D24: 4 | E24: 4
A25: TOTAL ASSETS | B25: =SUM(B17:B24) | C25: =SUM(C17:C24) | D25: =SUM(D17:D24) | E25: =SUM(E17:E24)
A26: Difference (should be 0) | B26: =B15-B25 | C26: =C15-C25 | D26: =D15-D25 | E26: =E15-E25

Sheet Ratio Analysis
A1: KEY RATIOS
A3: Ratio | B3: 2023-24 | C3: 2024-25 | D3: 2025-26 | E3: 2026-27
A4: Current Ratio (norm ≥ 1.23) | B4: =IF(('Balance Sheet'!B10+'Balance Sheet'!B12+'Balance Sheet'!B13+'Balance Sheet'!B9+'Balance Sheet'!B14)=0,0,('Balance Sheet'!B20+'Balance Sheet'!B21+'Balance Sheet'!B22+'Balance Sheet'!B23+'Balance Sheet'!B24)/('Balance Sheet'!B10+'Balance Sheet'!B12+'Balance Sheet'!B13+'Balance Sheet'!B9+'Balance Sheet'!B14)) | C4: =IF(('Balance Sheet'!C10+'Balance Sheet'!C12+'Balance Sheet'!C13+'Balance Sheet'!C9+'Balance Sheet'!C14)=0,0,('Balance Sheet'!C20+'Balance Sheet'!C21+'Balance Sheet'!C22+'Balance Sheet'!C23+'Balance Sheet'!C24)/('Balance Sheet'!C10+'Balance Sheet'!C12+'Balance Sheet'!C13+'Balance Sheet'!C9+'Balance Sheet'!C14)) | D4: =IF(('Balance Sheet'!D10+'Balance Sheet'!D12+'Balance Sheet'!D13+'Balance Sheet'!D9+'Balance Sheet'!D14)=0,0,('Balance Sheet'!D20+'Balance Sheet'!D21+'Balance Sheet'!D22+'Balance Sheet'!D23+'Balance Sheet'!D24)/('Balance Sheet'!D10+'Balance Sheet'!D12+'Balance Sheet'!D13+'Balance Sheet'!D9+'Balance Sheet'!D14)) | E4: =IF(('Balance Sheet'!E10+'Balance Sheet'!E12+'Balance Sheet'!E13+'Balance Sheet'!E9+'Balance Sheet'!E14)=0,0,('Balance Sheet'!E20+'Balance Sheet'!E21+'Balance Sheet'!E22+'Balance Sheet'!E23+'Balance Sheet'!E24)/('Balance Sheet'!E10+'Balance Sheet'!E12+'Balance Sheet'!E13+'Balance Sheet'!E9+'Balance Sheet'!E14))
A5: DSCR (norm ≥ 1.75) | B5: =IF(('Operating Statement'!B29+SUMIF('Loan Schedule'!C:C,0,'Loan Schedule'!G:G))=0,0,('Operating Statement'!B33+'Operating Statement'!B27+'Operating Statement'!B29)/('Operating Statement'!B29+SUMIF('Loan Schedule'!C:C,0,'Loan Schedule'!G:G))) | C5: =IF(('Operating Statement'!C29+SUMIF('Loan Schedule'!C:C,1,'Loan Schedule'!G:G))=0,0,('Operating Statement'!C33+'Operating Statement'!C27+'Operating Statement'!C29)/('Operating Statement'!C29+SUMIF('Loan Schedule'!C:C,1,'Loan Schedule'!G:G))) | D5: =IF(('Operating Statement'!D29+SUMIF('Loan Schedule'!C:C,2,'Loan Schedule'!G:G))=0,0,('Operating Statement'!D33+'Operating Statement'!D27+'Operating Statement'!D29)/('Operating Statement'!D29+SUMIF('Loan Schedule'!C:C,2,'Loan Schedule'!G:G))) | E5: =IF(('Operating Statement'!E29+SUMIF('Loan Schedule'!C:C,3,'Loan Schedule'!G:G))=0,0,('Operating Statement'!E33+'Operating Statement'!E27+'Operating Statement'!E29)/('Operating Statement'!E29+SUMIF('Loan Schedule'!C:C,3,'Loan Schedule'!G:G)))
A6: Debt / Equity (norm ≤ 3.00) | B6: =IF('Balance Sheet'!B7=0,0,('Balance Sheet'!B8-'Balance Sheet'!B9+'Balance Sheet'!B11)/'Balance Sheet'!B7) | C6: =IF('Balance Sheet'!C7=0,0,('Balance Sheet'!C8-'Balance Sheet'!C9+'Balance Sheet'!C11)/'Balance Sheet'!C7) | D6: =IF('Balance Sheet'!D7=0,0,('Balance Sheet'!D8-'Balance Sheet'!D9+'Balance Sheet'!D11)/'Balance Sheet'!D7) | E6: =IF('Balance Sheet'!E7=0,0,('Balance Sheet'!E8-'Balance Sheet'!E9+'Balance Sheet'!E11)/'Balance Sheet'!E7)
A7: TOL / TNW (norm ≤ 4.50) | B7: =IF('Balance Sheet'!B7=0,0,('Balance Sheet'!B15-'Balance Sheet'!B7)/'Balance Sheet'!B7) | C7: =IF('Balance Sheet'!C7=0,0,('Balance Sheet'!C15-'Balance Sheet'!C7)/'Balance Sheet'!C7) | D7: =IF('Balance Sheet'!D7=0,0,('Balance Sheet'!D15-'Balance Sheet'!D7)/'Balance Sheet'!D7) | E7: =IF('Balance Sheet'!E7=0,0,('Balance Sheet'!E15-'Balance Sheet'!E7)/'Balance Sheet'!E7)
A8: Interest Coverage (norm ≥ 2.60) | B8: =IF(('Operating Statement'!B28+'Operating Statement'!B29+'Operating Statement'!B30)=0,0,('Operating Statement'!B31+('Operating Statement'!B28+'Operating Statement'!B29+'Operating Statement'!B30))/('Operating Statement'!B28+'Operating Statement'!B29+'Operating Statement'!B30)) | C8: =IF(('Operating Statement'!C28+'Operating Statement'!C29+'Operating Statement'!C30)=0,0,('Operating Statement'!C31+('Operating Statement'!C28+'Operating Statement'!C29+'Operating Statement'!C30))/('Operating Statement'!C28+'Operating Statement'!C29+'Operating Statement'!C30)) | D8: =IF(('Operating Statement'!D28+'Operating Statement'!D29+'Operating Statement'!D30)=0,0,('Operating Statement'!D31+('Operating Statement'!D28+'Operating Statement'!D29+'Operating Statement'!D30))/('Operating Statement'!D28+'Operating Statement'!D29+'Operating Statement'!D30)) | E8: =IF(('Operating Statement'!E28+'Operating Statement'!E29+'Operating Statement'!E30)=0,0,('Operating Statement'!E31+('Operating Statement'!E28+'Operating Statement'!E29+'Operating Statement'!E30))/('Operating Statement'!E28+'Operating Statement'!E29+'Operating Statement'!E30))
A9: Net Profit Ratio % | B9: =IF('Operating Statement'!B5=0,0,'Operating Statement'!B33/'Operating Statement'!B5*100) | C9: =IF('Operating Statement'!C5=0,0,'Operating Statement'!C33/'Operating Statement'!C5*100) | D9: =IF('Operating Statement'!D5=0,0,'Operating Statement'!D33/'Operating Statement'!D5*100) | E9: =IF('Operating Statement'!E5=0,0,'Operating Statement'!E33/'Operating Statement'!E5*100)
A10: Return on Investment % | B10: =IF(('Balance Sheet'!B7+'Balance Sheet'!B8)=0,0,'Operating Statement'!B33/('Balance Sheet'!B7+'Balance Sheet'!B8)*100) | C10: =IF(('Balance Sheet'!C7+'Balance Sheet'!C8)=0,0,'Operating Statement'!C33/('Balance Sheet'!C7+'Balance Sheet'!C8)*100) | D10: =IF(('Balance Sheet'!D7+'Balance Sheet'!D8)=0,0,'Operating Statement'!D33/('Balance Sheet'!D7+'Balance Sheet'!D8)*100) | E10: =IF(('Balance Sheet'!E7+'Balance Sheet'!E8)=0,0,'Operating Statement'!E33/('Balance Sheet'!E7+'Balance Sheet'!E8)*100)

Sheet MPBF & DP
A1: MAXIMUM PERMISSIBLE BANK FINANCE & DRAWING POWER
A3: Particulars | B3: 2023-24 | C3: 2024-25 | D3: 2025-26 | E3: 2026-27
A4: TANDON METHOD (Balance Sheet Method)
A5: Total Current Assets | B5: =('Balance Sheet'!B20+'Balance Sheet'!B21+'Balance Sheet'!B22+'Balance Sheet'!B23+'Balance Sheet'!B24) | C5: =('Balance Sheet'!C20+'Balance Sheet'!C21+'Balance Sheet'!C22+'Balance Sheet'!C23+'Balance Sheet'!C24) | D5: =('Balance Sheet'!D20+'Balance Sheet'!D21+'Balance Sheet'!D22+'Balance Sheet'!D23+'Balance Sheet'!D24) | E5: =('Balance Sheet'!E20+'Balance Sheet'!E21+'Balance Sheet'!E22+'Balance Sheet'!E23+'Balance Sheet'!E24)
A6: Other Current Liabilities (excl. bank) | B6: =('Balance Sheet'!B12+'Balance Sheet'!B13) | C6: =('Balance Sheet'!C12+'Balance Sheet'!C13) | D6: =('Balance Sheet'!D12+'Balance Sheet'!D13) | E6: =('Balance Sheet'!E12+'Balance Sheet'!E13)
A7: Working Capital Gap | B7: =('Balance Sheet'!B20+'Balance Sheet'!B21+'Balance Sheet'!B22+'Balance Sheet'!B23+'Balance Sheet'!B24)-('Balance Sheet'!B12+'Balance Sheet'!B13) | C7: =('Balance Sheet'!C20+'Balance Sheet'!C21+'Balance Sheet'!C22+'Balance Sheet'!C23+'Balance Sheet'!C24)-('Balance Sheet'!C12+'Balance Sheet'!C13) | D7: =('Balance Sheet'!D20+'Balance Sheet'!D21+'Balance Sheet'!D22+'Balance Sheet'!D23+'Balance Sheet'!D24)-('Balance Sheet'!D12+'Balance Sheet'!D13) | E7: =('Balance Sheet'!E20+'Balance Sheet'!E21+'Balance Sheet'!E22+'Balance Sheet'!E23+'Balance Sheet'!E24)-('Balance Sheet'!E12+'Balance Sheet'!E13)
A8: Less: 25% minimum margin of CA | B8: =0.25*('Balance Sheet'!B20+'Balance Sheet'!B21+'Balance Sheet'!B22+'Balance Sheet'!B23+'Balance Sheet'!B24) | C8: =0.25*('Balance Sheet'!C20+'Balance Sheet'!C21+'Balance Sheet'!C22+'Balance Sheet'!C23+'Balance Sheet'!C24) | D8: =0.25*('Balance Sheet'!D20+'Balance Sheet'!D21+'Balance Sheet'!D22+'Balance Sheet'!D23+'Balance Sheet'!D24) | E8: =0.25*('Balance Sheet'!E20+'Balance Sheet'!E21+'Balance Sheet'!E22+'Balance Sheet'!E23+'Balance Sheet'!E24)
A9: MPBF — Tandon | B9: =MAX(0,0.75*('Balance Sheet'!B20+'Balance Sheet'!B21+'Balance Sheet'!B22+'Balance Sheet'!B23+'Balance Sheet'!B24)-('Balance Sheet'!B12+'Balance Sheet'!B13)) | C9: =MAX(0,0.75*('Balance Sheet'!C20+'Balance Sheet'!C21+'Balance Sheet'!C22+'Balance Sheet'!C23+'Balance Sheet'!C24)-('Balance Sheet'!C12+'Balance Sheet'!C13)) | D9: =MAX(0,0.75*('Balance Sheet'!D20+'Balance Sheet'!D21+'Balance Sheet'!D22+'Balance Sheet'!D23+'Balance Sheet'!D24)-('Balance Sheet'!D12+'Balance Sheet'!D13)) | E9: =MAX(0,0.75*('Balance Sheet'!E20+'Balance Sheet'!E21+'Balance Sheet'!E22+'Balance Sheet'!E23+'Balance Sheet'!E24)-('Balance Sheet'!E12+'Balance Sheet'!E13))
A10: TURNOVER METHOD (Nayak Committee)
A11: Sales Turnover | B11: ='Operating Statement'!B5 | C11: ='Operating Statement'!C5 | D11: ='Operating Statement'!D5 | E11: ='Operating Statement'!E5
A12: 25% of Turnover | B12: =0.25*'Operating Statement'!B5 | C12: =0.25*'Operating Statement'!C5 | D12: =0.25*'Operating Statement'!D5 | E12: =0.25*'Operating Statement'!E5
A13: Less: 5% margin by promoter | B13: =0.05*'Operating Statement'!B5 | C13: =0.05*'Operating Statement'!C5 | D13: =0.05*'Operating Statement'!D5 | E13: =0.05*'Operating Statement'!E5
A14: MPBF — Turnover (20% of sales) | B14: =0.2*'Operating Statement'!B5 | C14: =0.2*'Operating Statement'!C5 | D14: =0.2*'Operating Statement'!D5 | E14: =0.2*'Operating Statement'!E5
A15: DRAWING POWER
A16: Stock after 25% margin | B16: ='Balance Sheet'!B20*(1-25/100) | C16: ='Balance Sheet'!C20*(1-25/100) | D16: ='Balance Sheet'!D20*(1-25/100) | E16: ='Balance Sheet'!E20*(1-25/100)
A17: Debtors (≤90d) after 40% margin | B17: =MIN('Balance Sheet'!B21,'Operating Statement'!B5/365*90)*(1-40/100) | C17: =MIN('Balance Sheet'!C21,'Operating Statement'!C5/365*90)*(1-40/100) | D17: =MIN('Balance Sheet'!D21,'Operating Statement'!D5/365*90)*(1-40/100) | E17: =MIN('Balance Sheet'!E21,'Operating Statement'!E5/365*90)*(1-40/100)
A18: Total Drawing Power | B18: ='Balance Sheet'!B20*(1-25/100)+MIN('Balance Sheet'!B21,'Operating Statement'!B5/365*90)*(1-40/100) | C18: ='Balance Sheet'!C20*(1-25/100)+MIN('Balance Sheet'!C21,'Operating Statement'!C5/365*90)*(1-40/100) | D18: ='Balance Sheet'!D20*(1-25/100)+MIN('Balance Sheet'!D21,'Operating Statement'!D5/365*90)*(1-40/100) | E18: ='Balance Sheet'!E20*(1-25/100)+MIN('Balance Sheet'!E21,'Operating Statement'!E5/365*90)*(1-40/100)
A19: CC Limit / Drawing | B19: ='Balance Sheet'!B10 | C19: ='Balance Sheet'!C10 | D19: ='Balance Sheet'!D10 | E19: ='Balance Sheet'!E10
