Workbook

Sheet Guide
A1: Year-End Adjustment Tracker & Automatic Income Tax Recomputation
A2: AICA Level 2 Capstone Project | CA T S Surendranath | Batch AICA-L2B101, Chennai | Dummy data only - no client data used in any AI tool
A4: HOW THE MODEL FLOWS
A5: 1 | B5: Settings: company name, financial year, tax rates and the 'Tax Nature' list (how much of each kind of expense is added back).
A6: 2 | B6: Trial_Balance: enter the unadjusted trial balance in column E (Debit = +, Credit = -). Adjusted balances calculate automatically.
A7: 3 | B7: Adjustments: every year-end entry goes here ONE line each - version (V1/V2/V3), Dr ledger, Cr ledger, amount, Include Y/N, Tax Nature.
A8: 4 | B8: Financial_Statements: P&L and Balance Sheet build themselves from the adjusted trial balance.
A9: 5 | B9: Tax_Computation: starts from PBT in the P&L, adds back disallowances by type, replaces book depreciation with tax depreciation, works out current tax and deferred tax.
A10: 6 | B10: Checks: 10 automatic reconciliation checks. All must show OK before the accounts are final.
A11: 7 | B11: Version_Log: shows how PBT and tax moved from Draft (V1) to Audit (V2) to Final (V3).
A12: 8 | B12: Time_Study: record your own manual vs. tool timings to measure time saved.
A13: 9 | B13: AI_Prompts: the prompts used with ChatGPT / Copilot / Claude to classify entries and build formulas.
A14: 10 | B14: AI_Live_Demo: four new entries to classify with AI live in the video, including two where the CA must check / correct the AI.
A15: COLOUR LEGEND
A16: Blue | B16: Blue text = input you type. Black text = formula (do not overwrite). Green text = link from another sheet.
A17: Yellow | B17: Yellow cells = the main inputs you change during the demo (Include Y/N, amounts, tax depreciation, timings).
A19: DEMO TIP
A20: Try | B20: On Adjustments, change 'Include' of A05 (gratuity) from Y to N. Watch PBT, tax, deferred tax and all checks update in seconds.
A21: Note | B21: Figures are for FY 2025-26 (AY 2026-27), so section references follow the Income-tax Act, 1961. From FY 2026-27 the Income-tax Act, 2025 applies with new section numbers.
A22: Note | B22: AI suggestions on tax treatment must always be verified by the Chartered Accountant before finalisation.

Sheet Settings
A1: Settings & Assumptions
A4: Company name | B4: Sunrise Textiles Pvt Ltd (dummy)
A5: Financial year | B5: FY 2025-26 (AY 2026-27)
A6: Tax regime | B6: Section 115BAA | C6: Domestic company opting for concessional rate
A7: Base tax rate | B7: 0.22 | C7: Sec 115BAA
A8: Surcharge | B8: 0.1 | C8: Flat 10% under 115BAA
A9: Health & education cess | B9: 0.04
A10: Effective tax rate | B10: =B7*(1+B8)*(1+B9) -> 0.25168
A13: TAX NATURE LIST (used by the Adjustments sheet)
A14: Tax Nature | B14: Add-back % | C14: Difference type | D14: Explanation (FY 2025-26, IT Act 1961)
A15: Allowable | B15: 0 | C15: None | D15: Fully deductible in the year; taxable income moves with book profit.
A16: Disallowed - 43B (Timing) | B16: 1 | C16: Timing | D16: Bonus/gratuity/leave etc. unpaid by due date of return - allowed when paid (sec 43B). Creates DTA.
A17: Disallowed - 40(a)(ia) 30% | B17: 0.3 | C17: Timing | D17: TDS not deducted/paid - 30% disallowed, allowed in year TDS is paid (sec 40(a)(ia)).
A18: Disallowed - Provision (Timing) | B18: 1 | C18: Timing | D18: General provisions e.g. doubtful debts - allowed only on actual write-off (sec 36(1)(vii)).
A19: Disallowed - Permanent | B19: 1 | C19: Permanent | D19: Never allowed: penalties (Expl. 1 to 37(1)), MSME delayed-payment interest (sec 23 MSMED Act), CSR.
A20: Book Depreciation | B20: 1 | C20: Replaced | D20: Book depreciation is added back in full and replaced by depreciation as per sec 32.

Sheet Trial_Balance
A1: Trial Balance - Unadjusted to Adjusted (Rs.)
A2: Debit = positive, Credit = negative. Only column E is input.
A4: Code | B4: Ledger | C4: Type | D4: FS Line | E4: Unadjusted (Dr+/Cr-) | F4: Adjustment Dr | G4: Adjustment Cr | H4: Adjusted (Dr+/Cr-)
A5: L01 | B5: Sales | C5: PL-Income | D5: Revenue from operations | E5: -50000000 | F5: =SUMIFS(Adjustments!$I:$I,Adjustments!$E:$E,A5,Adjustments!$J:$J,"Y") -> 0 | G5: =SUMIFS(Adjustments!$I:$I,Adjustments!$G:$G,A5,Adjustments!$J:$J,"Y") -> 0 | H5: =E5+F5-G5 -> -50000000
A6: L02 | B6: Interest income | C6: PL-Income | D6: Other income | E6: -800000 | F6: =SUMIFS(Adjustments!$I:$I,Adjustments!$E:$E,A6,Adjustments!$J:$J,"Y") -> 0 | G6: =SUMIFS(Adjustments!$I:$I,Adjustments!$G:$G,A6,Adjustments!$J:$J,"Y") -> 60000 | H6: =E6+F6-G6 -> -860000
A7: L03 | B7: Purchases & materials consumed | C7: PL-Expense | D7: Cost of materials consumed | E7: 28000000 | F7: =SUMIFS(Adjustments!$I:$I,Adjustments!$E:$E,A7,Adjustments!$J:$J,"Y") -> 450000 | G7: =SUMIFS(Adjustments!$I:$I,Adjustments!$G:$G,A7,Adjustments!$J:$J,"Y") -> 0 | H7: =E7+F7-G7 -> 28450000
A8: L04 | B8: Salaries, bonus & gratuity | C8: PL-Expense | D8: Employee benefits expense | E8: 6000000 | F8: =SUMIFS(Adjustments!$I:$I,Adjustments!$E:$E,A8,Adjustments!$J:$J,"Y") -> 1000000 | G8: =SUMIFS(Adjustments!$I:$I,Adjustments!$G:$G,A8,Adjustments!$J:$J,"Y") -> 0 | H8: =E8+F8-G8 -> 7000000
A9: L05 | B9: Interest on loans | C9: PL-Expense | D9: Finance costs | E9: 900000 | F9: =SUMIFS(Adjustments!$I:$I,Adjustments!$E:$E,A9,Adjustments!$J:$J,"Y") -> 80000 | G9: =SUMIFS(Adjustments!$I:$I,Adjustments!$G:$G,A9,Adjustments!$J:$J,"Y") -> 0 | H9: =E9+F9-G9 -> 980000
A10: L06 | B10: Depreciation | C10: PL-Expense | D10: Depreciation | E10: 1500000 | F10: =SUMIFS(Adjustments!$I:$I,Adjustments!$E:$E,A10,Adjustments!$J:$J,"Y") -> 350000 | G10: =SUMIFS(Adjustments!$I:$I,Adjustments!$G:$G,A10,Adjustments!$J:$J,"Y") -> 0 | H10: =E10+F10-G10 -> 1850000
A11: L07 | B11: Professional & consultancy fees | C11: PL-Expense | D11: Professional fees | E11: 1200000 | F11: =SUMIFS(Adjustments!$I:$I,Adjustments!$E:$E,A11,Adjustments!$J:$J,"Y") -> 450000 | G11: =SUMIFS(Adjustments!$I:$I,Adjustments!$G:$G,A11,Adjustments!$J:$J,"Y") -> 0 | H11: =E11+F11-G11 -> 1650000
A12: L08 | B12: Rent | C12: PL-Expense | D12: Rent | E12: 1800000 | F12: =SUMIFS(Adjustments!$I:$I,Adjustments!$E:$E,A12,Adjustments!$J:$J,"Y") -> 100000 | G12: =SUMIFS(Adjustments!$I:$I,Adjustments!$G:$G,A12,Adjustments!$J:$J,"Y") -> 0 | H12: =E12+F12-G12 -> 1900000
A13: L09 | B13: Power & fuel | C13: PL-Expense | D13: Power & fuel | E13: 2400000 | F13: =SUMIFS(Adjustments!$I:$I,Adjustments!$E:$E,A13,Adjustments!$J:$J,"Y") -> 0 | G13: =SUMIFS(Adjustments!$I:$I,Adjustments!$G:$G,A13,Adjustments!$J:$J,"Y") -> 0 | H13: =E13+F13-G13 -> 2400000
A14: L10 | B14: Other expenses | C14: PL-Expense | D14: Other expenses | E14: 1600000 | F14: =SUMIFS(Adjustments!$I:$I,Adjustments!$E:$E,A14,Adjustments!$J:$J,"Y") -> 275000 | G14: =SUMIFS(Adjustments!$I:$I,Adjustments!$G:$G,A14,Adjustments!$J:$J,"Y") -> 220000 | H14: =E14+F14-G14 -> 1655000
A15: L11 | B15: CSR expenditure | C15: PL-Expense | D15: CSR expenditure | E15: 200000 | F15: =SUMIFS(Adjustments!$I:$I,Adjustments!$E:$E,A15,Adjustments!$J:$J,"Y") -> 0 | G15: =SUMIFS(Adjustments!$I:$I,Adjustments!$G:$G,A15,Adjustments!$J:$J,"Y") -> 0 | H15: =E15+F15-G15 -> 200000
A16: L12 | B16: Property, plant & equipment (net) | C16: BS-Asset | D16: Property, plant & equipment | E16: 18000000 | F16: =SUMIFS(Adjustments!$I:$I,Adjustments!$E:$E,A16,Adjustments!$J:$J,"Y") -> 0 | G16: =SUMIFS(Adjustments!$I:$I,Adjustments!$G:$G,A16,Adjustments!$J:$J,"Y") -> 350000 | H16: =E16+F16-G16 -> 17650000
... A30: L26 | B30: Expenses payable & other liabilities | C30: BS-Liability | D30: Other current liabilities | E30: -1200000 | F30: =SUMIFS(Adjustments!$I:$I,Adjustments!$E:$E,A30,Adjustments!$J:$J,"Y") -> 0 | G30: =SUMIFS(Adjustments!$I:$I,Adjustments!$G:$G,A30,Adjustments!$J:$J,"Y") -> 230000 | H30: =E30+F30-G30 -> -1430000
B31: Total (must be zero) | E31: =SUM(E5:E30) -> 0 | F31: =SUM(F5:F30) -> 2885000 | G31: =SUM(G5:G30) -> 2885000 | H31: =SUM(H5:H30) -> 0

Sheet Adjustments
A1: Year-End Adjustment Register
A2: One line per entry. Inputs: B-E, G, I-K, P. Columns F, H and L-O, Q calculate automatically.
A4: No. | B4: Version | C4: Date | D4: Description | E4: Dr Ledger | F4: Dr Ledger Name | G4: Cr Ledger | H4: Cr Ledger Name | I4: Amount (Rs.) | J4: Include? (Y/N) | K4: Tax Nature | L4: Impact on PBT | M4: Tax add-back | N4: Impact on taxable income | O4: Impact on current tax | P4: AI suggestion / remarks | Q4: Difference type
A5: A01 | B5: V1 | C5: 2026-04-08 | D5: Depreciation on new looms added in Feb not charged | E5: L06 | F5: =IF(E5="","",IFERROR(INDEX(Trial_Balance!$B$5:$B$30,MATCH(E5,Trial_Balance!$A$5:$A$30,0)),"NOT FOUND")) -> Depreciation | G5: L12 | H5: =IF(G5="","",IFERROR(INDEX(Trial_Balance!$B$5:$B$30,MATCH(G5,Trial_Balance!$A$5:$A$30,0)),"NOT FOUND")) -> Property, plant & equipment (net) | I5: 350000 | J5: Y | K5: Book Depreciation | L5: =IF(AND(J5="Y",E5<>"",G5<>""),I5*(IF(LEFT(IFERROR(INDEX(Trial_Balance!$C$5:$C$30,MATCH(G5,Trial_Balance!$A$5:$A$30,0)),""),2)="PL",1,0)-IF(LEFT(IFERROR(INDEX(Trial_Balance!$C$5:$C$30,MATCH(E5,Trial_Balance!$A$5:$A$30,0)),""),2)="PL",1,0)),0) -> -350000 | M5: =IF(AND(L5<0,K5<>""),-L5*IFERROR(INDEX(Settings!$B$15:$B$20,MATCH(K5,Settings!$A$15:$A$20,0)),0),0) -> 350000 | N5: =L5+M5 -> 0 | O5: =N5*Settings!$B$10 -> 0 | P5: AI: Book depreciation correction. Added back in full; tax depreciation under sec 32 is computed separately (half rate - used < 180 days). | Q5: =IF(K5="","",IFERROR(INDEX(Settings!$C$15:$C$20,MATCH(K5,Settings!$A$15:$A$20,0)),"")) -> Replaced
A6: A02 | B6: V1 | C6: 2026-04-08 | D6: Insurance paid for Apr-Sep 2026 - prepaid portion | E6: L17 | F6: =IF(E6="","",IFERROR(INDEX(Trial_Balance!$B$5:$B$30,MATCH(E6,Trial_Balance!$A$5:$A$30,0)),"NOT FOUND")) -> Prepaid expenses | G6: L10 | H6: =IF(G6="","",IFERROR(INDEX(Trial_Balance!$B$5:$B$30,MATCH(G6,Trial_Balance!$A$5:$A$30,0)),"NOT FOUND")) -> Other expenses | I6: 120000 | J6: Y | K6: Allowable | L6: =IF(AND(J6="Y",E6<>"",G6<>""),I6*(IF(LEFT(IFERROR(INDEX(Trial_Balance!$C$5:$C$30,MATCH(G6,Trial_Balance!$A$5:$A$30,0)),""),2)="PL",1,0)-IF(LEFT(IFERROR(INDEX(Trial_Balance!$C$5:$C$30,MATCH(E6,Trial_Balance!$A$5:$A$30,0)),""),2)="PL",1,0)),0) -> 120000 | M6: =IF(AND(L6<0,K6<>""),-L6*IFERROR(INDEX(Settings!$B$15:$B$20,MATCH(K6,Settings!$A$15:$A$20,0)),0),0) -> 0 | N6: =L6+M6 -> 120000 | O6: =N6*Settings!$B$10 -> 30201.6 | P6: AI: Reverses expense of next year. Increases profit and taxable income equally; no add-back. | Q6: =IF(K6="","",IFERROR(INDEX(Settings!$C$15:$C$20,MATCH(K6,Settings!$A$15:$A$20,0)),"")) -> None
A7: A03 | B7: V1 | C7: 2026-04-10 | D7: Statutory audit fee provision (TDS deducted & paid) | E7: L07 | F7: =IF(E7="","",IFERROR(INDEX(Trial_Balance!$B$5:$B$30,MATCH(E7,Trial_Balance!$A$5:$A$30,0)),"NOT FOUND")) -> Professional & consultancy fees | G7: L26 | H7: =IF(G7="","",IFERROR(INDEX(Trial_Balance!$B$5:$B$30,MATCH(G7,Trial_Balance!$A$5:$A$30,0)),"NOT FOUND")) -> Expenses payable & other liabilities | I7: 150000 | J7: Y | K7: Allowable | L7: =IF(AND(J7="Y",E7<>"",G7<>""),I7*(IF(LEFT(IFERROR(INDEX(Trial_Balance!$C$5:$C$30,MATCH(G7,Trial_Balance!$A$5:$A$30,0)),""),2)="PL",1,0)-IF(LEFT(IFERROR(INDEX(Trial_Balance!$C$5:$C$30,MATCH(E7,Trial_Balance!$A$5:$A$30,0)),""),2)="PL",1,0)),0) -> -150000 | M7: =IF(AND(L7<0,K7<>""),-L7*IFERROR(INDEX(Settings!$B$15:$B$20,MATCH(K7,Settings!$A$15:$A$20,0)),0),0) -> 0 | N7: =L7+M7 -> -150000 | O7: =N7*Settings!$B$10 -> -37752 | P7: AI: Accrued expense with TDS complied - fully allowable. | Q7: =IF(K7="","",IFERROR(INDEX(Settings!$C$15:$C$20,MATCH(K7,Settings!$A$15:$A$20,0)),"")) -> None
A8: A04 | B8: V2 | C8: 2026-05-05 | D8: Bonus for FY 25-26 payable in Nov 2026 | E8: L04 | F8: =IF(E8="","",IFERROR(INDEX(Trial_Balance!$B$5:$B$30,MATCH(E8,Trial_Balance!$A$5:$A$30,0)),"NOT FOUND")) -> Salaries, bonus & gratuity | G8: L24 | H8: =IF(G8="","",IFERROR(INDEX(Trial_Balance!$B$5:$B$30,MATCH(G8,Trial_Balance!$A$5:$A$30,0)),"NOT FOUND")) -> Provision for employee benefits | I8: 400000 | J8: Y | K8: Disallowed - 43B (Timing) | L8: =IF(AND(J8="Y",E8<>"",G8<>""),I8*(IF(LEFT(IFERROR(INDEX(Trial_Balance!$C$5:$C$30,MATCH(G8,Trial_Balance!$A$5:$A$30,0)),""),2)="PL",1,0)-IF(LEFT(IFERROR(INDEX(Trial_Balance!$C$5:$C$30,MATCH(E8,Trial_Balance!$A$5:$A$30,0)),""),2)="PL",1,0)),0) -> -400000 | M8: =IF(AND(L8<0,K8<>""),-L8*IFERROR(INDEX(Settings!$B$15:$B$20,MATCH(K8,Settings!$A$15:$A$20,0)),0),0) -> 400000 | N8: =L8+M8 -> 0 | O8: =N8*Settings!$B$10 -> 0 | P8: AI: Bonus paid after due date of return - disallowed u/s 43B(c); allowed on payment. Timing difference -> DTA. | Q8: =IF(K8="","",IFERROR(INDEX(Settings!$C$15:$C$20,MATCH(K8,Settings!$A$15:$A$20,0)),"")) -> Timing
A9: A05 | B9: V2 | C9: 2026-05-05 | D9: Gratuity provision as per actuarial report | E9: L04 | F9: =IF(E9="","",IFERROR(INDEX(Trial_Balance!$B$5:$B$30,MATCH(E9,Trial_Balance!$A$5:$A$30,0)),"NOT FOUND")) -> Salaries, bonus & gratuity | G9: L24 | H9: =IF(G9="","",IFERROR(INDEX(Trial_Balance!$B$5:$B$30,MATCH(G9,Trial_Balance!$A$5:$A$30,0)),"NOT FOUND")) -> Provision for employee benefits | I9: 600000 | J9: Y | K9: Disallowed - 43B (Timing) | L9: =IF(AND(J9="Y",E9<>"",G9<>""),I9*(IF(LEFT(IFERROR(INDEX(Trial_Balance!$C$5:$C$30,MATCH(G9,Trial_Balance!$A$5:$A$30,0)),""),2)="PL",1,0)-IF(LEFT(IFERROR(INDEX(Trial_Balance!$C$5:$C$30,MATCH(E9,Trial_Balance!$A$5:$A$30,0)),""),2)="PL",1,0)),0) -> -600000 | M9: =IF(AND(L9<0,K9<>""),-L9*IFERROR(INDEX(Settings!$B$15:$B$20,MATCH(K9,Settings!$A$15:$A$20,0)),0),0) -> 600000 | N9: =L9+M9 -> 0 | O9: =N9*Settings!$B$10 -> 0 | P9: AI: Gratuity provision not paid to approved fund - sec 43B / 40A(7). Timing difference -> DTA. | Q9: =IF(K9="","",IFERROR(INDEX(Settings!$C$15:$C$20,MATCH(K9,Settings!$A$15:$A$20,0)),"")) -> Timing
A10: A06 | B10: V2 | C10: 2026-05-12 | D10: Consultancy fee booked - TDS not deducted | E10: L07 | F10: =IF(E10="","",IFERROR(INDEX(Trial_Balance!$B$5:$B$30,MATCH(E10,Trial_Balance!$A$5:$A$30,0)),"NOT FOUND")) -> Professional & consultancy fees | G10: L25 | H10: =IF(G10="","",IFERROR(INDEX(Trial_Balance!$B$5:$B$30,MATCH(G10,Trial_Balance!$A$5:$A$30,0)),"NOT FOUND")) -> Trade payables | I10: 300000 | J10: Y | K10: Disallowed - 40(a)(ia) 30% | L10: =IF(AND(J10="Y",E10<>"",G10<>""),I10*(IF(LEFT(IFERROR(INDEX(Trial_Balance!$C$5:$C$30,MATCH(G10,Trial_Balance!$A$5:$A$30,0)),""),2)="PL",1,0)-IF(LEFT(IFERROR(INDEX(Trial_Balance!$C$5:$C$30,MATCH(E10,Trial_Balance!$A$5:$A$30,0)),""),2)="PL",1,0)),0) -> -300000 | M10: =IF(AND(L10<0,K10<>""),-L10*IFERROR(INDEX(Settings!$B$15:$B$20,MATCH(K10,Settings!$A$15:$A$20,0)),0),0) -> 90000 | N10: =L10+M10 -> -210000 | O10: =N10*Settings!$B$10 -> -52852.8 | P10: AI: 30% disallowed u/s 40(a)(ia) until TDS is deducted and paid. Timing difference. | Q10: =IF(K10="","",IFERROR(INDEX(Settings!$C$15:$C$20,MATCH(K10,Settings!$A$15:$A$20,0)),"")) -> Timing
A11: A07 | B11: V2 | C11: 2026-05-12 | D11: Slow-moving yarn written down to NRV (AS 2) | E11: L03 | F11: =IF(E11="","",IFERROR(INDEX(Trial_Balance!$B$5:$B$30,MATCH(E11,Trial_Balance!$A$5:$A$30,0)),"NOT FOUND")) -> Purchases & materials consumed | G11: L13 | H11: =IF(G11="","",IFERROR(INDEX(Trial_Balance!$B$5:$B$30,MATCH(G11,Trial_Balance!$A$5:$A$30,0)),"NOT FOUND")) -> Inventory | I11: 450000 | J11: Y | K11: Allowable | L11: =IF(AND(J11="Y",E11<>"",G11<>""),I11*(IF(LEFT(IFERROR(INDEX(Trial_Balance!$C$5:$C$30,MATCH(G11,Trial_Balance!$A$5:$A$30,0)),""),2)="PL",1,0)-IF(LEFT(IFERROR(INDEX(Trial_Balance!$C$5:$C$30,MATCH(E11,Trial_Balance!$A$5:$A$30,0)),""),2)="PL",1,0)),0) -> -450000 | M11: =IF(AND(L11<0,K11<>""),-L11*IFERROR(INDEX(Settings!$B$15:$B$20,MATCH(K11,Settings!$A$15:$A$20,0)),0),0) -> 0 | N11: =L11+M11 -> -450000 | O11: =N11*Settings!$B$10 -> -113256 | P11: AI: Valuation at lower of cost or NRV is accepted for tax (ICDS II). Allowable. | Q11: =IF(K11="","",IFERROR(INDEX(Settings!$C$15:$C$20,MATCH(K11,Settings!$A$15:$A$20,0)),"")) -> None
A12: A08 | B12: V2 | C12: 2026-05-15 | D12: Provision for doubtful debts (ageing > 1 year) | E12: L10 | F12: =IF(E12="","",IFERROR(INDEX(Trial_Balance!$B$5:$B$30,MATCH(E12,Trial_Balance!$A$5:$A$30,0)),"NOT FOUND")) -> Other expenses | G12: L15 | H12: =IF(G12="","",IFERROR(INDEX(Trial_Balance!$B$5:$B$30,MATCH(G12,Trial_Balance!$A$5:$A$30,0)),"NOT FOUND")) -> Provision for doubtful debts | I12: 250000 | J12: Y | K12: Disallowed - Provision (Timing) | L12: =IF(AND(J12="Y",E12<>"",G12<>""),I12*(IF(LEFT(IFERROR(INDEX(Trial_Balance!$C$5:$C$30,MATCH(G12,Trial_Balance!$A$5:$A$30,0)),""),2)="PL",1,0)-IF(LEFT(IFERROR(INDEX(Trial_Balance!$C$5:$C$30,MATCH(E12,Trial_Balance!$A$5:$A$30,0)),""),2)="PL",1,0)),0) -> -250000 | M12: =IF(AND(L12<0,K12<>""),-L12*IFERROR(INDEX(Settings!$B$15:$B$20,MATCH(K12,Settings!$A$15:$A$20,0)),0),0) -> 250000 | N12: =L12+M12 -> 0 | O12: =N12*Settings!$B$10 -> 0 | P12: AI: General provision not allowed; deduction only on actual write-off u/s 36(1)(vii). Timing -> DTA. | Q12: =IF(K12="","",IFERROR(INDEX(Settings!$C$15:$C$20,MATCH(K12,Settings!$A$15:$A$20,0)),"")) -> Timing
A13: A09 | B13: V3 | C13: 2026-06-02 | D13: Interest on delayed payment to MSME supplier | E13: L05 | F13: =IF(E13="","",IFERROR(INDEX(Trial_Balance!$B$5:$B$30,MATCH(E13,Trial_Balance!$A$5:$A$30,0)),"NOT FOUND")) -> Interest on loans | G13: L26 | H13: =IF(G13="","",IFERROR(INDEX(Trial_Balance!$B$5:$B$30,MATCH(G13,Trial_Balance!$A$5:$A$30,0)),"NOT FOUND")) -> Expenses payable & other liabilities | I13: 80000 | J13: Y | K13: Disallowed - Permanent | L13: =IF(AND(J13="Y",E13<>"",G13<>""),I13*(IF(LEFT(IFERROR(INDEX(Trial_Balance!$C$5:$C$30,MATCH(G13,Trial_Balance!$A$5:$A$30,0)),""),2)="PL",1,0)-IF(LEFT(IFERROR(INDEX(Trial_Balance!$C$5:$C$30,MATCH(E13,Trial_Balance!$A$5:$A$30,0)),""),2)="PL",1,0)),0) -> -80000 | M13: =IF(AND(L13<0,K13<>""),-L13*IFERROR(INDEX(Settings!$B$15:$B$20,MATCH(K13,Settings!$A$15:$A$20,0)),0),0) -> 80000 | N13: =L13+M13 -> 0 | O13: =N13*Settings!$B$10 -> 0 | P13: AI: Sec 23 of MSMED Act - interest not deductible at any time. Permanent difference, no deferred tax. | Q13: =IF(K13="","",IFERROR(INDEX(Settings!$C$15:$C$20,MATCH(K13,Settings!$A$15:$A$20,0)),"")) -> Permanent
A14: A10 | B14: V3 | C14: 2026-06-02 | D14: Penalty for late filing (non-compensatory) | E14: L10 | F14: =IF(E14="","",IFERROR(INDEX(Trial_Balance!$B$5:$B$30,MATCH(E14,Trial_Balance!$A$5:$A$30,0)),"NOT FOUND")) -> Other expenses | G14: L16 | H14: =IF(G14="","",IFERROR(INDEX(Trial_Balance!$B$5:$B$30,MATCH(G14,Trial_Balance!$A$5:$A$30,0)),"NOT FOUND")) -> Cash & bank | I14: 25000 | J14: Y | K14: Disallowed - Permanent | L14: =IF(AND(J14="Y",E14<>"",G14<>""),I14*(IF(LEFT(IFERROR(INDEX(Trial_Balance!$C$5:$C$30,MATCH(G14,Trial_Balance!$A$5:$A$30,0)),""),2)="PL",1,0)-IF(LEFT(IFERROR(INDEX(Trial_Balance!$C$5:$C$30,MATCH(E14,Trial_Balance!$A$5:$A$30,0)),""),2)="PL",1,0)),0) -> -25000 | M14: =IF(AND(L14<0,K14<>""),-L14*IFERROR(INDEX(Settings!$B$15:$B$20,MATCH(K14,Settings!$A$15:$A$20,0)),0),0) -> 25000 | N14: =L14+M14 -> 0 | O14: =N14*Settings!$B$10 -> 0 | P14: AI: Penalty for offence/violation of law - Explanation 1 to sec 37(1). Permanent. (Interest on late GST is compensatory - verify separately.) | Q14: =IF(K14="","",IFERROR(INDEX(Settings!$C$15:$C$20,MATCH(K14,Settings!$A$15:$A$20,0)),"")) -> Permanent
A15: A11 | B15: V3 | C15: 2026-06-03 | D15: Interest accrued on fixed deposits | E15: L19 | F15: =IF(E15="","",IFERROR(INDEX(Trial_Balance!$B$5:$B$30,MATCH(E15,Trial_Balance!$A$5:$A$30,0)),"NOT FOUND")) -> Other current assets | G15: L02 | H15: =IF(G15="","",IFERROR(INDEX(Trial_Balance!$B$5:$B$30,MATCH(G15,Trial_Balance!$A$5:$A$30,0)),"NOT FOUND")) -> Interest income | I15: 60000 | J15: Y | K15: Allowable | L15: =IF(AND(J15="Y",E15<>"",G15<>""),I15*(IF(LEFT(IFERROR(INDEX(Trial_Balance!$C$5:$C$30,MATCH(G15,Trial_Balance!$A$5:$A$30,0)),""),2)="PL",1,0)-IF(LEFT(IFERROR(INDEX(Trial_Balance!$C$5:$C$30,MATCH(E15,Trial_Balance!$A$5:$A$30,0)),""),2)="PL",1,0)),0) -> 60000 | M15: =IF(AND(L15<0,K15<>""),-L15*IFERROR(INDEX(Settings!$B$15:$B$20,MATCH(K15,Settings!$A$15:$A$20,0)),0),0) -> 0 | N15: =L15+M15 -> 60000 | O15: =N15*Settings!$B$10 -> 15100.8 | P15: AI: Income accrued - taxable as income from other sources. Increases both profit and taxable income. | Q15: =IF(K15="","",IFERROR(INDEX(Settings!$C$15:$C$20,MATCH(K15,Settings!$A$15:$A$20,0)),"")) -> None
A16: A12 | B16: V3 | C16: 2026-06-03 | D16: Reclassify warehouse rent wrongly booked in Other exp. | E16: L08 | F16: =IF(E16="","",IFERROR(INDEX(Trial_Balance!$B$5:$B$30,MATCH(E16,Trial_Balance!$A$5:$A$30,0)),"NOT FOUND")) -> Rent | G16: L10 | H16: =IF(G16="","",IFERROR(INDEX(Trial_Balance!$B$5:$B$30,MATCH(G16,Trial_Balance!$A$5:$A$30,0)),"NOT FOUND")) -> Other expenses | I16: 100000 | J16: Y | K16: Allowable | L16: =IF(AND(J16="Y",E16<>"",G16<>""),I16*(IF(LEFT(IFERROR(INDEX(Trial_Balance!$C$5:$C$30,MATCH(G16,Trial_Balance!$A$5:$A$30,0)),""),2)="PL",1,0)-IF(LEFT(IFERROR(INDEX(Trial_Balance!$C$5:$C$30,MATCH(E16,Trial_Balance!$A$5:$A$30,0)),""),2)="PL",1,0)),0) -> 0 | M16: =IF(AND(L16<0,K16<>""),-L16*IFERROR(INDEX(Settings!$B$15:$B$20,MATCH(K16,Settings!$A$15:$A$20,0)),0),0) -> 0 | N16: =L16+M16 -> 0 | O16: =N16*Settings!$B$10 -> 0 | P16: AI: Reclassification within expenses - no impact on profit or tax. | Q16: =IF(K16="","",IFERROR(INDEX(Settings!$C$15:$C$20,MATCH(K16,Settings!$A$15:$A$20,0)),"")) -> None
... A20: A16 | B20: V3 | C20: 2026-06-05 | D20: LIVE DEMO: Donation to political party (by cheque) | E20: L10 | F20: =IF(E20="","",IFERROR(INDEX(Trial_Balance!$B$5:$B$30,MATCH(E20,Trial_Balance!$A$5:$A$30,0)),"NOT FOUND")) -> Other expenses | G20: L16 | H20: =IF(G20="","",IFERROR(INDEX(Trial_Balance!$B$5:$B$30,MATCH(G20,Trial_Balance!$A$5:$A$30,0)),"NOT FOUND")) -> Cash & bank | I20: 50000 | J20: N | K20: Disallowed - Permanent | L20: =IF(AND(J20="Y",E20<>"",G20<>""),I20*(IF(LEFT(IFERROR(INDEX(Trial_Balance!$C$5:$C$30,MATCH(G20,Trial_Balance!$A$5:$A$30,0)),""),2)="PL",1,0)-IF(LEFT(IFERROR(INDEX(Trial_Balance!$C$5:$C$30,MATCH(E20,Trial_Balance!$A$5:$A$30,0)),""),2)="PL",1,0)),0) -> 0 | M20: =IF(AND(L20<0,K20<>""),-L20*IFERROR(INDEX(Settings!$B$15:$B$20,MATCH(K20,Settings!$A$15:$A$20,0)),0),0) -> 0 | N20: =L20+M20 -> 0 | O20: =N20*Settings!$B$10 -> 0 | P20: LIVE DEMO entry - switch Include to Y in the video. AI: 80GGB not available under 115BAA. Permanent difference. | Q20: =IF(K20="","",IFERROR(INDEX(Settings!$C$15:$C$20,MATCH(K20,Settings!$A$15:$A$20,0)),"")) -> Permanent
F21: =IF(E21="","",IFERROR(INDEX(Trial_Balance!$B$5:$B$30,MATCH(E21,Trial_Balance!$A$5:$A$30,0)),"NOT FOUND")) | H21: =IF(G21="","",IFERROR(INDEX(Trial_Balance!$B$5:$B$30,MATCH(G21,Trial_Balance!$A$5:$A$30,0)),"NOT FOUND")) | L21: =IF(AND(J21="Y",E21<>"",G21<>""),I21*(IF(LEFT(IFERROR(INDEX(Trial_Balance!$C$5:$C$30,MATCH(G21,Trial_Balance!$A$5:$A$30,0)),""),2)="PL",1,0)-IF(LEFT(IFERROR(INDEX(Trial_Balance!$C$5:$C$30,MATCH(E21,Trial_Balance!$A$5:$A$30,0)),""),2)="PL",1,0)),0) -> 0 | M21: =IF(AND(L21<0,K21<>""),-L21*IFERROR(INDEX(Settings!$B$15:$B$20,MATCH(K21,Settings!$A$15:$A$20,0)),0),0) -> 0 | N21: =L21+M21 -> 0 | O21: =N21*Settings!$B$10 -> 0 | Q21: =IF(K21="","",IFERROR(INDEX(Settings!$C$15:$C$20,MATCH(K21,Settings!$A$15:$A$20,0)),""))
F22: =IF(E22="","",IFERROR(INDEX(Trial_Balance!$B$5:$B$30,MATCH(E22,Trial_Balance!$A$5:$A$30,0)),"NOT FOUND")) | H22: =IF(G22="","",IFERROR(INDEX(Trial_Balance!$B$5:$B$30,MATCH(G22,Trial_Balance!$A$5:$A$30,0)),"NOT FOUND")) | L22: =IF(AND(J22="Y",E22<>"",G22<>""),I22*(IF(LEFT(IFERROR(INDEX(Trial_Balance!$C$5:$C$30,MATCH(G22,Trial_Balance!$A$5:$A$30,0)),""),2)="PL",1,0)-IF(LEFT(IFERROR(INDEX(Trial_Balance!$C$5:$C$30,MATCH(E22,Trial_Balance!$A$5:$A$30,0)),""),2)="PL",1,0)),0) -> 0 | M22: =IF(AND(L22<0,K22<>""),-L22*IFERROR(INDEX(Settings!$B$15:$B$20,MATCH(K22,Settings!$A$15:$A$20,0)),0),0) -> 0 | N22: =L22+M22 -> 0 | O22: =N22*Settings!$B$10 -> 0 | Q22: =IF(K22="","",IFERROR(INDEX(Settings!$C$15:$C$20,MATCH(K22,Settings!$A$15:$A$20,0)),""))
F23: =IF(E23="","",IFERROR(INDEX(Trial_Balance!$B$5:$B$30,MATCH(E23,Trial_Balance!$A$5:$A$30,0)),"NOT FOUND")) | H23: =IF(G23="","",IFERROR(INDEX(Trial_Balance!$B$5:$B$30,MATCH(G23,Trial_Balance!$A$5:$A$30,0)),"NOT FOUND")) | L23: =IF(AND(J23="Y",E23<>"",G23<>""),I23*(IF(LEFT(IFERROR(INDEX(Trial_Balance!$C$5:$C$30,MATCH(G23,Trial_Balance!$A$5:$A$30,0)),""),2)="PL",1,0)-IF(LEFT(IFERROR(INDEX(Trial_Balance!$C$5:$C$30,MATCH(E23,Trial_Balance!$A$5:$A$30,0)),""),2)="PL",1,0)),0) -> 0 | M23: =IF(AND(L23<0,K23<>""),-L23*IFERROR(INDEX(Settings!$B$15:$B$20,MATCH(K23,Settings!$A$15:$A$20,0)),0),0) -> 0 | N23: =L23+M23 -> 0 | O23: =N23*Settings!$B$10 -> 0 | Q23: =IF(K23="","",IFERROR(INDEX(Settings!$C$15:$C$20,MATCH(K23,Settings!$A$15:$A$20,0)),""))
F24: =IF(E24="","",IFERROR(INDEX(Trial_Balance!$B$5:$B$30,MATCH(E24,Trial_Balance!$A$5:$A$30,0)),"NOT FOUND")) | H24: =IF(G24="","",IFERROR(INDEX(Trial_Balance!$B$5:$B$30,MATCH(G24,Trial_Balance!$A$5:$A$30,0)),"NOT FOUND")) | L24: =IF(AND(J24="Y",E24<>"",G24<>""),I24*(IF(LEFT(IFERROR(INDEX(Trial_Balance!$C$5:$C$30,MATCH(G24,Trial_Balance!$A$5:$A$30,0)),""),2)="PL",1,0)-IF(LEFT(IFERROR(INDEX(Trial_Balance!$C$5:$C$30,MATCH(E24,Trial_Balance!$A$5:$A$30,0)),""),2)="PL",1,0)),0) -> 0 | M24: =IF(AND(L24<0,K24<>""),-L24*IFERROR(INDEX(Settings!$B$15:$B$20,MATCH(K24,Settings!$A$15:$A$20,0)),0),0) -> 0 | N24: =L24+M24 -> 0 | O24: =N24*Settings!$B$10 -> 0 | Q24: =IF(K24="","",IFERROR(INDEX(Settings!$C$15:$C$20,MATCH(K24,Settings!$A$15:$A$20,0)),""))
F25: =IF(E25="","",IFERROR(INDEX(Trial_Balance!$B$5:$B$30,MATCH(E25,Trial_Balance!$A$5:$A$30,0)),"NOT FOUND")) | H25: =IF(G25="","",IFERROR(INDEX(Trial_Balance!$B$5:$B$30,MATCH(G25,Trial_Balance!$A$5:$A$30,0)),"NOT FOUND")) | L25: =IF(AND(J25="Y",E25<>"",G25<>""),I25*(IF(LEFT(IFERROR(INDEX(Trial_Balance!$C$5:$C$30,MATCH(G25,Trial_Balance!$A$5:$A$30,0)),""),2)="PL",1,0)-IF(LEFT(IFERROR(INDEX(Trial_Balance!$C$5:$C$30,MATCH(E25,Trial_Balance!$A$5:$A$30,0)),""),2)="PL",1,0)),0) -> 0 | M25: =IF(AND(L25<0,K25<>""),-L25*IFERROR(INDEX(Settings!$B$15:$B$20,MATCH(K25,Settings!$A$15:$A$20,0)),0),0) -> 0 | N25: =L25+M25 -> 0 | O25: =N25*Settings!$B$10 -> 0 | Q25: =IF(K25="","",IFERROR(INDEX(Settings!$C$15:$C$20,MATCH(K25,Settings!$A$15:$A$20,0)),""))
F26: =IF(E26="","",IFERROR(INDEX(Trial_Balance!$B$5:$B$30,MATCH(E26,Trial_Balance!$A$5:$A$30,0)),"NOT FOUND")) | H26: =IF(G26="","",IFERROR(INDEX(Trial_Balance!$B$5:$B$30,MATCH(G26,Trial_Balance!$A$5:$A$30,0)),"NOT FOUND")) | L26: =IF(AND(J26="Y",E26<>"",G26<>""),I26*(IF(LEFT(IFERROR(INDEX(Trial_Balance!$C$5:$C$30,MATCH(G26,Trial_Balance!$A$5:$A$30,0)),""),2)="PL",1,0)-IF(LEFT(IFERROR(INDEX(Trial_Balance!$C$5:$C$30,MATCH(E26,Trial_Balance!$A$5:$A$30,0)),""),2)="PL",1,0)),0) -> 0 | M26: =IF(AND(L26<0,K26<>""),-L26*IFERROR(INDEX(Settings!$B$15:$B$20,MATCH(K26,Settings!$A$15:$A$20,0)),0),0) -> 0 | N26: =L26+M26 -> 0 | O26: =N26*Settings!$B$10 -> 0 | Q26: =IF(K26="","",IFERROR(INDEX(Settings!$C$15:$C$20,MATCH(K26,Settings!$A$15:$A$20,0)),""))
F27: =IF(E27="","",IFERROR(INDEX(Trial_Balance!$B$5:$B$30,MATCH(E27,Trial_Balance!$A$5:$A$30,0)),"NOT FOUND")) | H27: =IF(G27="","",IFERROR(INDEX(Trial_Balance!$B$5:$B$30,MATCH(G27,Trial_Balance!$A$5:$A$30,0)),"NOT FOUND")) | L27: =IF(AND(J27="Y",E27<>"",G27<>""),I27*(IF(LEFT(IFERROR(INDEX(Trial_Balance!$C$5:$C$30,MATCH(G27,Trial_Balance!$A$5:$A$30,0)),""),2)="PL",1,0)-IF(LEFT(IFERROR(INDEX(Trial_Balance!$C$5:$C$30,MATCH(E27,Trial_Balance!$A$5:$A$30,0)),""),2)="PL",1,0)),0) -> 0 | M27: =IF(AND(L27<0,K27<>""),-L27*IFERROR(INDEX(Settings!$B$15:$B$20,MATCH(K27,Settings!$A$15:$A$20,0)),0),0) -> 0 | N27: =L27+M27 -> 0 | O27: =N27*Settings!$B$10 -> 0 | Q27: =IF(K27="","",IFERROR(INDEX(Settings!$C$15:$C$20,MATCH(K27,Settings!$A$15:$A$20,0)),""))
F28: =IF(E28="","",IFERROR(INDEX(Trial_Balance!$B$5:$B$30,MATCH(E28,Trial_Balance!$A$5:$A$30,0)),"NOT FOUND")) | H28: =IF(G28="","",IFERROR(INDEX(Trial_Balance!$B$5:$B$30,MATCH(G28,Trial_Balance!$A$5:$A$30,0)),"NOT FOUND")) | L28: =IF(AND(J28="Y",E28<>"",G28<>""),I28*(IF(LEFT(IFERROR(INDEX(Trial_Balance!$C$5:$C$30,MATCH(G28,Trial_Balance!$A$5:$A$30,0)),""),2)="PL",1,0)-IF(LEFT(IFERROR(INDEX(Trial_Balance!$C$5:$C$30,MATCH(E28,Trial_Balance!$A$5:$A$30,0)),""),2)="PL",1,0)),0) -> 0 | M28: =IF(AND(L28<0,K28<>""),-L28*IFERROR(INDEX(Settings!$B$15:$B$20,MATCH(K28,Settings!$A$15:$A$20,0)),0),0) -> 0 | N28: =L28+M28 -> 0 | O28: =N28*Settings!$B$10 -> 0 | Q28: =IF(K28="","",IFERROR(INDEX(Settings!$C$15:$C$20,MATCH(K28,Settings!$A$15:$A$20,0)),""))
D29: Total of included adjustments | I29: =SUMIFS(I5:I28,J5:J28,"Y") -> 2885000 | L29: =SUM(L5:L28) -> -2425000 | M29: =SUM(M5:M28) -> 1795000 | N29: =SUM(N5:N28) -> -630000 | O29: =SUM(O5:O28) -> -158558.4
D31: Versions: V1 = Draft (management), V2 = After audit observations, V3 = Final close. Blank rows are ready for new entries.

Sheet Financial_Statements
A1: Financial Statements (Rs.) - built automatically from the adjusted trial balance
A3: STATEMENT OF PROFIT AND LOSS | B3: Before adjustments | C3: After adjustments | D3: Change
A4: Revenue from operations | B4: =-SUMIFS(Trial_Balance!$E$5:$E$30,Trial_Balance!$D$5:$D$30,"Revenue from operations") -> 50000000 | C4: =-SUMIFS(Trial_Balance!$H$5:$H$30,Trial_Balance!$D$5:$D$30,"Revenue from operations") -> 50000000 | D4: =C4-B4 -> 0
A5: Other income | B5: =-SUMIFS(Trial_Balance!$E$5:$E$30,Trial_Balance!$D$5:$D$30,"Other income") -> 800000 | C5: =-SUMIFS(Trial_Balance!$H$5:$H$30,Trial_Balance!$D$5:$D$30,"Other income") -> 860000 | D5: =C5-B5 -> 60000
A6: Total income | B6: =SUM(B4:B5) -> 50800000 | C6: =SUM(C4:C5) -> 50860000 | D6: =SUM(D4:D5) -> 60000
A7: Cost of materials consumed | B7: =SUMIFS(Trial_Balance!$E$5:$E$30,Trial_Balance!$D$5:$D$30,"Cost of materials consumed") -> 28000000 | C7: =SUMIFS(Trial_Balance!$H$5:$H$30,Trial_Balance!$D$5:$D$30,"Cost of materials consumed") -> 28450000 | D7: =C7-B7 -> 450000
A8: Employee benefits expense | B8: =SUMIFS(Trial_Balance!$E$5:$E$30,Trial_Balance!$D$5:$D$30,"Employee benefits expense") -> 6000000 | C8: =SUMIFS(Trial_Balance!$H$5:$H$30,Trial_Balance!$D$5:$D$30,"Employee benefits expense") -> 7000000 | D8: =C8-B8 -> 1000000
A9: Finance costs | B9: =SUMIFS(Trial_Balance!$E$5:$E$30,Trial_Balance!$D$5:$D$30,"Finance costs") -> 900000 | C9: =SUMIFS(Trial_Balance!$H$5:$H$30,Trial_Balance!$D$5:$D$30,"Finance costs") -> 980000 | D9: =C9-B9 -> 80000
A10: Depreciation | B10: =SUMIFS(Trial_Balance!$E$5:$E$30,Trial_Balance!$D$5:$D$30,"Depreciation") -> 1500000 | C10: =SUMIFS(Trial_Balance!$H$5:$H$30,Trial_Balance!$D$5:$D$30,"Depreciation") -> 1850000 | D10: =C10-B10 -> 350000
A11: Professional fees | B11: =SUMIFS(Trial_Balance!$E$5:$E$30,Trial_Balance!$D$5:$D$30,"Professional fees") -> 1200000 | C11: =SUMIFS(Trial_Balance!$H$5:$H$30,Trial_Balance!$D$5:$D$30,"Professional fees") -> 1650000 | D11: =C11-B11 -> 450000
A12: Rent | B12: =SUMIFS(Trial_Balance!$E$5:$E$30,Trial_Balance!$D$5:$D$30,"Rent") -> 1800000 | C12: =SUMIFS(Trial_Balance!$H$5:$H$30,Trial_Balance!$D$5:$D$30,"Rent") -> 1900000 | D12: =C12-B12 -> 100000
A13: Power & fuel | B13: =SUMIFS(Trial_Balance!$E$5:$E$30,Trial_Balance!$D$5:$D$30,"Power & fuel") -> 2400000 | C13: =SUMIFS(Trial_Balance!$H$5:$H$30,Trial_Balance!$D$5:$D$30,"Power & fuel") -> 2400000 | D13: =C13-B13 -> 0
A14: Other expenses | B14: =SUMIFS(Trial_Balance!$E$5:$E$30,Trial_Balance!$D$5:$D$30,"Other expenses") -> 1600000 | C14: =SUMIFS(Trial_Balance!$H$5:$H$30,Trial_Balance!$D$5:$D$30,"Other expenses") -> 1655000 | D14: =C14-B14 -> 55000
A15: CSR expenditure | B15: =SUMIFS(Trial_Balance!$E$5:$E$30,Trial_Balance!$D$5:$D$30,"CSR expenditure") -> 200000 | C15: =SUMIFS(Trial_Balance!$H$5:$H$30,Trial_Balance!$D$5:$D$30,"CSR expenditure") -> 200000 | D15: =C15-B15 -> 0
A16: Total expenses | B16: =SUM(B7:B15) -> 43600000 | C16: =SUM(C7:C15) -> 46085000 | D16: =SUM(D7:D15) -> 2485000
A17: Profit before tax (PBT) | B17: =B6-B16 -> 7200000 | C17: =C6-C16 -> 4775000 | D17: =D6-D16 -> -2425000
A18: Current tax (from Tax_Computation) | C18: =Tax_Computation!C30 -> 1603200
A19: Deferred tax charge / (credit) | C19: =Tax_Computation!C40 -> -324667
A20: Profit after tax (PAT) | C20: =C17-C18-C19 -> 3496467
A22: BALANCE SHEET | C22: After adjustments
A23: EQUITY AND LIABILITIES
A24: Share capital | C24: =-SUMIFS(Trial_Balance!$H$5:$H$30,Trial_Balance!$D$5:$D$30,"Share capital") -> 5000000
A25: Reserves & surplus (opening + PAT) | C25: =-SUMIFS(Trial_Balance!$H$5:$H$30,Trial_Balance!$D$5:$D$30,"Reserves & surplus")+C20 -> 13996467
A26: Long-term borrowings | C26: =-SUMIFS(Trial_Balance!$H$5:$H$30,Trial_Balance!$D$5:$D$30,"Long-term borrowings") -> 8000000
A27: Deferred tax liability (net) (opening + charge) | C27: =-SUMIFS(Trial_Balance!$H$5:$H$30,Trial_Balance!$D$5:$D$30,"Deferred tax liability (net)")+C19 -> 75333
A28: Provision for employee benefits | C28: =-SUMIFS(Trial_Balance!$H$5:$H$30,Trial_Balance!$D$5:$D$30,"Provision for employee benefits") -> 1500000
A29: Trade payables | C29: =-SUMIFS(Trial_Balance!$H$5:$H$30,Trial_Balance!$D$5:$D$30,"Trade payables") -> 6800000
A30: Other current liabilities | C30: =-SUMIFS(Trial_Balance!$H$5:$H$30,Trial_Balance!$D$5:$D$30,"Other current liabilities") -> 1430000
A31: Provision for income tax (current year) | C31: =C18 -> 1603200
A32: Total equity and liabilities | C32: =SUM(C24:C31) -> 38405000
A34: ASSETS
A35: Property, plant & equipment | C35: =SUMIFS(Trial_Balance!$H$5:$H$30,Trial_Balance!$D$5:$D$30,"Property, plant & equipment") -> 17650000
A36: Inventories | C36: =SUMIFS(Trial_Balance!$H$5:$H$30,Trial_Balance!$D$5:$D$30,"Inventories") -> 7050000
A37: Trade receivables (net) | C37: =SUMIFS(Trial_Balance!$H$5:$H$30,Trial_Balance!$D$5:$D$30,"Trade receivables (net)") -> 8750000
A38: Cash & bank balances | C38: =SUMIFS(Trial_Balance!$H$5:$H$30,Trial_Balance!$D$5:$D$30,"Cash & bank balances") -> 2475000
A39: Prepaid expenses | C39: =SUMIFS(Trial_Balance!$H$5:$H$30,Trial_Balance!$D$5:$D$30,"Prepaid expenses") -> 420000
A40: Advance tax & TDS | C40: =SUMIFS(Trial_Balance!$H$5:$H$30,Trial_Balance!$D$5:$D$30,"Advance tax & TDS") -> 1400000
A41: Other current assets | C41: =SUMIFS(Trial_Balance!$H$5:$H$30,Trial_Balance!$D$5:$D$30,"Other current assets") -> 660000
A42: Total assets | C42: =SUM(C35:C41) -> 38405000
A43: Difference (must be zero) | C43: =C32-C42 -> 0

Sheet Tax_Computation
A1: Computation of Total Income & Tax (Rs.) - FY 2025-26 / AY 2026-27
A2: Recomputes automatically when any adjustment changes
B4: Particulars | C4: Amount | D4: Source / basis
B5: INPUT: Depreciation as per Income-tax Act (sec 32) | C5: 1900000 | D5: From tax depreciation schedule - type here
B7: Profit before tax as per P&L | C7: =Financial_Statements!C17 -> 4775000 | D7: Link: Financial_Statements
B8: Add:
B9: Depreciation as per books | C9: =SUMIFS(Trial_Balance!$H$5:$H$30,Trial_Balance!$D$5:$D$30,"Depreciation") -> 1850000 | D9: Adjusted trial balance
B10: CSR expenditure (Explanation 2 to sec 37(1)) | C10: =SUMIFS(Trial_Balance!$H$5:$H$30,Trial_Balance!$D$5:$D$30,"CSR expenditure") -> 200000 | D10: Adjusted trial balance
B11: Disallowed - 43B (Timing) | C11: =SUMIFS(Adjustments!$M$5:$M$28,Adjustments!$K$5:$K$28,"Disallowed - 43B (Timing)") -> 1000000 | D11: Adjustment register
B12: Disallowed - 40(a)(ia) 30% | C12: =SUMIFS(Adjustments!$M$5:$M$28,Adjustments!$K$5:$K$28,"Disallowed - 40(a)(ia) 30%") -> 90000 | D12: Adjustment register
B13: Disallowed - Provision (Timing) | C13: =SUMIFS(Adjustments!$M$5:$M$28,Adjustments!$K$5:$K$28,"Disallowed - Provision (Timing)") -> 250000 | D13: Adjustment register
B14: Disallowed - Permanent | C14: =SUMIFS(Adjustments!$M$5:$M$28,Adjustments!$K$5:$K$28,"Disallowed - Permanent") -> 105000 | D14: Adjustment register
B15: Total additions | C15: =SUM(C9:C14) -> 3495000
B17: Less:
B18: Depreciation as per Income-tax Act | C18: =C5 -> 1900000 | D18: Input above
B20: Total income (business income) | C20: =C7+C15-C18 -> 6370000
B21: Total income rounded off (sec 288A) | C21: =ROUND(C20/10,0)*10 -> 6370000 | D21: Nearest Rs. 10
B23: Tax calculation
B24: Income tax @ base rate | C24: =C21*Settings!B7 -> 1401400 | D24: Settings: 22%
B25: Surcharge | C25: =C24*Settings!B8 -> 140140 | D25: Settings: 10%
B26: Health & education cess | C26: =(C24+C25)*Settings!B9 -> 61661.6 | D26: Settings: 4%
B28: Total tax (unrounded) | C28: =SUM(C24:C26) -> 1603201.6
B30: CURRENT TAX (rounded, sec 288B) | C30: =ROUND(C28/10,0)*10 -> 1603200 | D30: Goes to P&L and Balance Sheet
B31: Less: Advance tax & TDS | C31: =SUMIFS(Trial_Balance!$H$5:$H$30,Trial_Balance!$D$5:$D$30,"Advance tax & TDS") -> 1400000 | D31: Adjusted trial balance
B32: Net tax payable / (refundable) | C32: =C30-C31 -> 203200
B34: Deferred tax (AS 22)
B35: Depreciation difference (tax - book): creates DTL if positive | C35: =C18-C9 -> 50000
B36: Timing disallowances (reverse later): creates DTA | C36: =-SUMIFS(Adjustments!$M$5:$M$28,Adjustments!$Q$5:$Q$28,"Timing") -> -1340000 | D36: Adjustment register
B37: Net timing difference for the year | C37: =C35+C36 -> -1290000
B38: Effective tax rate | C38: =Settings!$B$10 -> 0.25168 | D38: Settings
B40: DEFERRED TAX CHARGE / (CREDIT) | C40: =ROUND(C37*C38,0) -> -324667 | D40: Goes to P&L and Balance Sheet
B42: Total tax expense (current + deferred) | C42: =C30+C40 -> 1278533
B43: Effective tax rate on book profit | C43: =IFERROR(C42/C7,0) -> 0.2677556 | D43: Sense check

Sheet Checks
A1: Reconciliation Checks & Summary
A2: Every check must say OK before signing the accounts
A4: No. | B4: Check | C4: Difference | D4: Status
A5: 1 | B5: Unadjusted trial balance totals to zero | C5: =Trial_Balance!E31 -> 0 | D5: =IF(ABS(C5)<1,"OK","CHECK") -> OK
A6: 2 | B6: Adjusted trial balance totals to zero | C6: =Trial_Balance!H31 -> 0 | D6: =IF(ABS(C6)<1,"OK","CHECK") -> OK
A7: 3 | B7: Every included adjustment uses a valid ledger code (count of errors) | C7: =COUNTIFS(Adjustments!$J$5:$J$28,"Y",Adjustments!$F$5:$F$28,"NOT FOUND")+COUNTIFS(Adjustments!$J$5:$J$28,"Y",Adjustments!$H$5:$H$28,"NOT FOUND") -> 0 | D7: =IF(ABS(C7)<1,"OK","CHECK") -> OK
A8: 4 | B8: Every included adjustment has a Tax Nature (count missing) | C8: =COUNTIFS(Adjustments!$J$5:$J$28,"Y",Adjustments!$K$5:$K$28,"") -> 0 | D8: =IF(ABS(C8)<1,"OK","CHECK") -> OK
A9: 5 | B9: Balance Sheet tallies (Equity & liabilities - Assets) | C9: =Financial_Statements!C43 -> 0 | D9: =IF(ABS(C9)<1,"OK","CHECK") -> OK
A10: 6 | B10: PBT in tax computation = PBT in P&L | C10: =Tax_Computation!C7-Financial_Statements!C17 -> 0 | D10: =IF(ABS(C10)<1,"OK","CHECK") -> OK
A11: 7 | B11: Current tax in P&L = tax computation | C11: =Financial_Statements!C18-Tax_Computation!C30 -> 0 | D11: =IF(ABS(C11)<1,"OK","CHECK") -> OK
A12: 8 | B12: Provision for tax in Balance Sheet = tax computation | C12: =Financial_Statements!C31-Tax_Computation!C30 -> 0 | D12: =IF(ABS(C12)<1,"OK","CHECK") -> OK
A13: 9 | B13: Deferred tax: Balance Sheet movement = P&L charge | C13: =(Financial_Statements!C27+SUMIFS(Trial_Balance!$H$5:$H$30,Trial_Balance!$D$5:$D$30,"Deferred tax liability (net)"))-Financial_Statements!C19 -> 0 | D13: =IF(ABS(C13)<1,"OK","CHECK") -> OK
A14: 10 | B14: Sum of adjustment PBT impacts = Adjusted PBT - Unadjusted PBT | C14: =Adjustments!L29-(Financial_Statements!C17-Financial_Statements!B17) -> 0 | D14: =IF(ABS(C14)<1,"OK","CHECK") -> OK
B15: OVERALL STATUS | D15: =IF(COUNTIF(D5:D14,"OK")=10,"ALL OK","REVIEW") -> ALL OK
B18: KEY FIGURES
B19: Profit before tax - before adjustments | C19: =Financial_Statements!B17 -> 7200000
B20: Profit before tax - after adjustments | C20: =Financial_Statements!C17 -> 4775000
B21: Number of adjustments included | C21: =COUNTIFS(Adjustments!$J$5:$J$28,"Y",Adjustments!$A$5:$A$28,"<>") -> 12
B22: Total income (rounded) | C22: =Tax_Computation!C21 -> 6370000
B23: Current tax | C23: =Tax_Computation!C30 -> 1603200
B24: Deferred tax charge / (credit) | C24: =Tax_Computation!C40 -> -324667
B25: Net tax payable / (refundable) | C25: =Tax_Computation!C32 -> 203200
B26: Profit after tax | C26: =Financial_Statements!C20 -> 3496467

Sheet Version_Log
A1: Version Log - how profit and tax moved through each revision (Rs.)
A4: Version | B4: Stage | C4: No. of entries | D4: PBT impact | E4: Taxable income impact | F4: Current tax impact | G4: Cumulative PBT | H4: Cumulative taxable-income impact
A5: V0 | B5: Unadjusted trial balance | G5: =Financial_Statements!B17 -> 7200000 | H5: 0
A6: V1 | B6: Draft - management entries | C6: =COUNTIFS(Adjustments!$B$5:$B$28,A6,Adjustments!$J$5:$J$28,"Y") -> 3 | D6: =SUMIFS(Adjustments!$L$5:$L$28,Adjustments!$B$5:$B$28,A6) -> -380000 | E6: =SUMIFS(Adjustments!$N$5:$N$28,Adjustments!$B$5:$B$28,A6) -> -30000 | F6: =SUMIFS(Adjustments!$O$5:$O$28,Adjustments!$B$5:$B$28,A6) -> -7550.4 | G6: =G5+D6 -> 6820000 | H6: =H5+E6 -> -30000
A7: V2 | B7: After audit observations | C7: =COUNTIFS(Adjustments!$B$5:$B$28,A7,Adjustments!$J$5:$J$28,"Y") -> 5 | D7: =SUMIFS(Adjustments!$L$5:$L$28,Adjustments!$B$5:$B$28,A7) -> -2000000 | E7: =SUMIFS(Adjustments!$N$5:$N$28,Adjustments!$B$5:$B$28,A7) -> -660000 | F7: =SUMIFS(Adjustments!$O$5:$O$28,Adjustments!$B$5:$B$28,A7) -> -166108.8 | G7: =G6+D7 -> 4820000 | H7: =H6+E7 -> -690000
A8: V3 | B8: Final close | C8: =COUNTIFS(Adjustments!$B$5:$B$28,A8,Adjustments!$J$5:$J$28,"Y") -> 4 | D8: =SUMIFS(Adjustments!$L$5:$L$28,Adjustments!$B$5:$B$28,A8) -> -45000 | E8: =SUMIFS(Adjustments!$N$5:$N$28,Adjustments!$B$5:$B$28,A8) -> 60000 | F8: =SUMIFS(Adjustments!$O$5:$O$28,Adjustments!$B$5:$B$28,A8) -> 15100.8 | G8: =G7+D8 -> 4775000 | H8: =H7+E8 -> -630000
B9: Total | C9: =SUM(C6:C8) -> 12 | D9: =SUM(D6:D8) -> -2425000 | E9: =SUM(E6:E8) -> -630000 | F9: =SUM(F6:F8) -> -158558.4
B11: Reading this: each audit round changes profit, and the tax changes with it. Taxable-income impact differs from PBT impact because of disallowances (43B, 40(a)(ia), provisions, penalties).

Sheet Time_Study
A1: Time Study - Manual method vs. this tool (minutes per revision)
A2: Illustrative figures. REPLACE the yellow cells with your own timings from trying both methods.
A4: No. | B4: Task | C4: Manual (min) | D4: With tool (min) | E4: Time saved (min) | F4: Saving %
A5: 1 | B5: Pass entries and update trial balance | C5: 20 | D5: 5 | E5: =C5-D5 -> 15 | F5: =IFERROR(E5/C5,0) -> 0.75
A6: 2 | B6: Redraft P&L and Balance Sheet | C6: 30 | D6: 0 | E6: =C6-D6 -> 30 | F6: =IFERROR(E6/C6,0) -> 1
A7: 3 | B7: Identify tax treatment of each new entry | C7: 25 | D7: 5 | E7: =C7-D7 -> 20 | F7: =IFERROR(E7/C7,0) -> 0.8
A8: 4 | B8: Recompute total income and tax | C8: 30 | D8: 0 | E8: =C8-D8 -> 30 | F8: =IFERROR(E8/C8,0) -> 1
A9: 5 | B9: Recompute deferred tax | C9: 20 | D9: 0 | E9: =C9-D9 -> 20 | F9: =IFERROR(E9/C9,0) -> 1
A10: 6 | B10: Tie tax provision & DTL back to financial statements | C10: 15 | D10: 1 | E10: =C10-D10 -> 14 | F10: =IFERROR(E10/C10,0) -> 0.93333333
A11: 7 | B11: Explain changes to partner / client | C11: 20 | D11: 5 | E11: =C11-D11 -> 15 | F11: =IFERROR(E11/C11,0) -> 0.75
B12: Total per revision | C12: =SUM(C5:C11) -> 160 | D12: =SUM(D5:D11) -> 16 | E12: =SUM(E5:E11) -> 144 | F12: =IFERROR(E12/C12,0) -> 0.9
B13: Number of revisions in a typical close (V1, V2, V3) | C13: 3
B14: Total hours saved per client per year | C14: =E12*C13/60 -> 7.2

Sheet AI_Prompts
A1: AI Prompts used in this project
A2: Tools: ChatGPT / Microsoft Copilot / Claude. Always verify AI output.
A4: No. | B4: Purpose | C4: Prompt (copy-paste ready) | D4: How the output was used
A5: 1 | B5: Classify adjustments | C5: You are a Chartered Accountant in India. For FY 2025-26 (Income-tax Act, 1961), classify each year-end journal entry below into exactly one of: Allowable; Disallowed - 43B (Timing); Disallowed - 40(a)(ia) 30%; Disallowed - Provision (Timing); Disallowed - Permanent; Book Depreciation. Give the section reference and whether it creates a DTA, DTL or permanent difference. Return a table. Entries: [paste Description, Dr, Cr, Amount] | D5: Filled the 'Tax Nature' and 'AI suggestion' columns; each verified by me.
A6: 2 | B6: Map ledgers to FS lines | C6: Map these trial balance ledger names to Schedule III line items and tag each as PL-Income, PL-Expense, BS-Asset, BS-Liability or BS-Equity. Return as a table with columns Code, Ledger, Type, FS Line: [paste ledger list] | D6: Created the 'Type' and 'FS Line' columns of Trial_Balance.
A7: 3 | B7: Build Excel formulas | C7: Write an Excel formula (no XLOOKUP, must work in Excel 2016) that returns the total of column I in sheet 'Adjustments' where column E equals the ledger code in A5 and column J is 'Y'. | D7: Adjustment Dr / Cr columns in Trial_Balance.
A8: 4 | B8: Impact formula | C8: In Excel, an adjustment has Dr ledger in E5 and Cr ledger in G5. Ledger types are in Trial_Balance column C. Write a formula giving the impact on profit: +amount if the credit side is a P&L ledger, -amount if the debit side is a P&L ledger. | D8: 'Impact on PBT' column of Adjustments.
A9: 5 | B9: Reconciliation checks | C9: List the reconciliation checks a CA should perform between the final financial statements and the income-tax computation of a company at year end, and suggest an Excel formula for each. | D9: Designed the 10 checks in the Checks sheet.
A10: 6 | B10: Explain changes | C10: Using this version log [paste], write a 5-line note for the client explaining why profit and tax changed between the draft and final accounts, in simple language. | D10: Client communication; shown in the video demo.

Sheet AI_Live_Demo
A1: Live AI Demonstration - 4 new entries to classify with AI on camera
A2: Step 1: copy the prompt into ChatGPT / Copilot / Claude. Step 2: compare with the 'CA review' column. Step 3: on Adjustments rows 17-20, change Include from N to Y.
A4: No. | B4: New entry | C4: Dr | D4: Cr | E4: Amount (Rs.) | F4: Correct Tax Nature | G4: CA review point (what to check in the AI answer)
A5: A13 | B5: Leave encashment provision (unpaid) | C5: L04 | D5: L24 | E5: 150000 | F5: Disallowed - 43B (Timing) | G5: Straightforward: sec 43B(f), allowed on payment. Expect AI to get this right.
A6: A14 | B6: Interest on delayed GST payment | C6: L05 | D6: L26 | E6: 18000 | F6: Allowable | G6: WATCH: AI may call this a 'penalty'. Interest for delay is compensatory, not penal, so generally allowable u/s 37(1). Correct the AI if needed.
A7: A15 | B7: Agent commission - TDS u/s 194H not deducted | C7: L10 | D7: L25 | E7: 200000 | F7: Disallowed - 40(a)(ia) 30% | G7: 30% disallowed (Rs. 60,000), allowed in the year TDS is paid.
A8: A16 | B8: Donation to political party (by cheque) | C8: L10 | D8: L16 | E8: 50000 | F8: Disallowed - Permanent | G8: WATCH: AI may suggest deduction u/s 80GGB. But a company under 115BAA cannot claim Chapter VI-A deductions (except 80JJAA / 80M), so it is fully disallowed. This is the CA's judgement.
B10: PROMPT TO PASTE INTO THE AI TOOL
B11: You are a Chartered Accountant in India. The company is a domestic company that has opted for section 115BAA, FY 2025-26 (Income-tax Act, 1961). Classify each year-end entry below into exactly one of: Allowable; Disallowed - 43B (Timing); Disallowed - 40(a)(ia) 30%; Disallowed - Provision (Timing); Disallowed - Permanent; Book Depreciation. For each, give the section reference, the amount disallowed, and whether it creates a DTA or a permanent difference. Return a table. 1. Leave encashment provision (unpaid) Rs. 1,50,000 2. Interest on delayed GST payment Rs. 18,000 3. Agent commission Rs. 2,00,000 - TDS u/s 194H not deducted 4. Donation to political party by cheque Rs. 50,000
B13: EXPECTED RESULT after changing Include from N to Y for rows 17-20 of Adjustments
B14: Profit before tax | C14: 47,75,000 -> 43,57,000
B15: Total income | C15: 63,70,000 -> 62,12,000
B16: Current tax | C16: 16,03,200 -> 15,63,440
B17: Deferred tax credit | C17: 3,24,667 -> 3,77,520
B18: Checks | C18: Still ALL OK
B20: SECOND LIVE PROMPT - client note (paste the Version_Log table after it)
B21: Using this version log, write a 5-line note to the client's managing director explaining in simple language why profit and tax changed between the draft and the final accounts. Mention that many audit entries reduced profit but not tax because they are disallowed now and allowed later. [paste Version_Log]
B23: Note: AI answers vary between tools and runs. Whatever the AI says, the 'Correct Tax Nature' column is what goes into the model, after your review.
B25: TRAP 2 - Additional depreciation for a 115BAA company (ask the AI separately)
B26: Prompt: New looms costing Rs. 40,00,000 were bought and put to use in February 2026 (less than 180 days in the year). The company has opted for section 115BAA. Compute tax depreciation, including any additional depreciation available for new plant and machinery.
B27: Item | E27: AI's likely answer (Rs.) | F27: Correct answer (Rs.)
B28: Normal depreciation 15% x 1/2 | E28: 300000 | F28: 300000
B29: Additional depreciation 20% x 1/2 u/s 32(1)(iia) | E29: 400000 | F29: Not allowed (115BAA)
B30: Total depreciation | E30: 700000 | F30: 300000
B31: Tax understated if AI accepted (Rs. 4,00,000 x 25.168%) | E31: =ROUND(400000*Settings!$B$10,0) -> 100672
B33: Two-model test: run Trap 1 and Trap 2 on two different models in the ICAI AI Agent and compare. The model's tax depreciation input (Tax_Computation C5) already excludes additional depreciation.
