Workbook

Sheet Points to check
A1: Royal Orchid | K1: =35/2000 -> 0.0175
A3: Issues | D3: Strength | K3: 35000000
A4: 1 | B4: Case filed by Kamat hotels for use of its Brand name | D4: 1 | K4: =K3*13 -> 455000000
A5: =A4+1 -> 2 | B5: Increase in salary of chairmand by 15% despite no major performance of the company (AR 2019-20)- Salary Rs 2.73 crores | D5: =D4+1 -> 2 | K5: =K3*600 -> 21000000000
A6: =A5+1 -> 3 | B6: Loan from related party of Rs 1.05 crores @18% (AR 2019-20) | D6: 3 | K6: =K4/K5 -> 0.021666667
A7: =A6+1 -> 4 | B7: Complex ownership structure with multiple subsidiaries and risk in impairment in valueof investments | D7: =D6+1 -> 4
A8: =A7+1 -> 5 | D8: =D7+1 -> 5
A10: Threats | D10: Opportunities
A11: 1 | B11: Case filed by Kamat hotels for use of its Brand name | D11: 1 | E11: Indian domestic tourism to touch 2.8 bn by 2022 (AR 2019-20)
A12: =A11+1 -> 2 | B12: Age of promoter CK Baljee ( around 74), though younger family members have joined | D12: =D11+1 -> 2 | E12: Tourism sector to touch USD 460 bn by 2028
A13: =A12+1 -> 3 | D13: 3
A14: =A13+1 -> 4 | D14: =D13+1 -> 4
A15: =A14+1 -> 5 | D15: =D14+1 -> 5
D16: =D15+1 -> 6
A17: Revenue model
A18: 1 | B18: JV, leased and owned
A19: =A18+1 -> 2 | B19: Mangement contracts
A23: Other points
A24: 1 | B24: Total employees 1079 and contractual : 287
A26: Questions
A27: 1 | B27: Check subsidiaries balance sheet for any potential dimmuniation in value of investment and also loans given to subsidiaries
B28: a) Impairment of Rs 6 crores in subsidiaries in AR 2020-21
A29: =A27+1 -> 2 | B29: Recheck - other expenses details growth year on year
A30: =A29+1 -> 3 | B30: What is FD held for trade payable in FY 2019-20
A31: =A30+1 -> 4 | B31: Understand note 50 related to bifurcation of total assets in consolidated FS ( AR 2019-20)
A32: =A31+1 -> 5 | B32: Check status of "Ksheer Sagar Developers Private Limited" which has accumulated losses of around 60 crores as on March 31, 2022

Sheet Quarterly call
A1: Royal Orchid | D1: Check quarterly
A3: Q-2 - FY 2023-24 | E3: Hotel growth | F3: Hotels | G3: Keys
E4: FY 2019-20 | F4: 60 | G4: 4000
A5: S.No. | C5: Actual | E5: FY 2020-21 | F5: 70
A6: 1 | B6: Decrease in profits due to incresae in a) payroll cost, b) electrcity and gas expenses | E6: FY 2021-22 | F6: 75 | G6: 4600
A7: =A6+1 -> 2 | B7: 10-15% increase inn food and beverages business | E7: FY 2022-23 | F7: 95 | G7: 5600
A8: =A7+1 -> 3 | B8: a) Average room rate (JLO) - Rs 5,087 , average occupancy : 73% b) Average room rate (managed) - Rs 3,747, average occupancy : 54%
A9: =A8+1 -> 4 | B9: Revenue guidance of around 375 crores in FY 2023-24 | C9: 313 crores, 340 crores including jaipur
A10: =A9+1 -> 5 | B10: Revenue increase of 25 to 30% per annum
A11: =A10+1 -> 6 | B11: Negative point related to debentures and related party loan @ 14%
A13: Q-3 - FY 2023-24
A15: 1 | B15: a) Average room rate (JLO) - Rs 5,656 , average occupancy : 76% b) Average room rate (managed) - Rs 4,184, average occupancy : 63%
A16: =A15+1 -> 2 | B16: Total Keys : 5795
A17: =A16+1 -> 3 | B17: Renovation in Bangalore and goa
A20: Q-1 - FY 2024-25
A21: 1 | B21: Revenue guidance of around 375 crores in FY 2024-25 Rs 500 crores in fy 2025-26
A22: =A21+1 -> 2 | B22: Room renovations to continue till December 2024
A23: =A22+1 -> 3 | B23: Target to hit 200 hotels by Feb 2026, 100 crores PAT
A24: =A23+1 -> 4 | B24: Mumbai will be 300 room hotel and surat 288 room hotel
A25: =A24+1 -> 5

Sheet Summary
A1: Endurance Technologies
A3: S.No. | B3: Particulars
A4: 1 | B4: Quantitative Analysis
A5: a) | B5: Financials_Consol
B6: Financials_Standalone!A1
A8: b) | B8: Common Size Analysis - BS Conso
B9: Common Size Analysis - BS'!A1
A11: c) | B11: Common Size Analysis - PL Conso
B12: Common Size Analysis - PL'!A1
A14: d) | B14: Common Size Analysis - CFS Conso
B15: Common Size Analysis - CFS'!A1
A17: e) | B17: Ratio Analysis Conso
B18: Ratio Analysis'!A1
A20: f) | B20: Valuation Models DCF Conso
B21: Valuation Models DCF'!A1
A23: I | B23: Do reverse DCF to understand how stock market is valuing the company
A24: II | B24: Growth rate not above 20% in first 5 years and 10% for next 5 years
A25: III | B25: Terminal growth rate not above 2%
A26: IV | B26: Discount rate 12 % for stable companies and 15% for growth companies
A27: V | B27: Intrinsic value - share price should be 50-60% of Intrinsic value (MOS) | C27: Conso | D27: ='Valuation Models DCF_Conso'!$G$24 -> 0.23959941
C28: Standalone | D28: ='Valuation Models DCF'!$G$23 -> 0.42987019
A29: g) | B29: Valuation Models Residual eanin
A30: h) | B30: Valuation Models EPV
A31: i) | B31: Relative valuation Models (page 3, page 11 of module 41)
A33: =A4+1 -> 2 | B33: Read 5 years annual reports (module 21)
A34: a) | B34: Financials along with ratios and quantitative
A35: b) | B35: Chairman letter
A36: c) | B36: Financial results and highlights
A37: d) | B37: Segment revenue
A38: e) | B38: Director report
A39: f) | B39: Management discussion and analysis
A40: g) | B40: Reserves reconciliation
A42: =A33+1 -> 3 | B42: Notes inconsistencies in ratios - Module 26, 27 , 28
A43: a) | B43: Inventory high or low reason | C43: Ratio Analysis_Conso'!A1
A44: b) | B44: DTR- high or low reason | C44: Ratio Analysis'!A1
A45: c) | B45: Check current and quick ratio with inventory turnover ratio
A46: d) | B46: Compare ratio with competitors
A47: e) | B47: Page 6 - Module 27
A49: =A42+1 -> 4 | B49: Cash flow analysis
A50: a) | B50: Analyse where cash is generated and used in last 3-5 years
A51: b) | B51: Under each head observe major sources of cash generation and utlisation
A52: c) | B52: If cash inflow from operation activities then how is it consumed
A53: d) | B53: Is cash flow from operating activities enough to cover capex
A54: e) | B54: Is cash flow from operations Greater than net income
A55: f) | B55: Consistency of cash flows | D55: ='Common Size Analysis - CFS'!$A$45 -> 0.70452986
A56: g) | B56: Cash flow from investing activities where is it coming from operating or financing
A57: h) | B57: Financing nature of capital sources
A58: i) | B58: Calculate FCFF and FCFE | D58: ='Ratio Analysis_Conso'!$D$132 -> 237
D59: ='Ratio Analysis'!$D$130 -> 238
A61: =A49+1 -> 5 | B61: Competitors annual reports for 3-5 years Excel analysis
A62: =A61+1 -> 6 | B62: Analysis of ROE, Growth rate and cost of equity
A63: =A62+1 -> 7 | B63: DU pont analysis, growth rate > ROE, PE ratio, ROE and Growth rate cost of equity | C63: Conso | D63: ='Ratio Analysis_Conso'!D125 -> 0.13722372 | E63: Standalone | F63: ='Ratio Analysis'!$D$123 -> 0.16473895
A64: =A63+1 -> 8 | B64: Understanding of the revenue model
A65: =A64+1 -> 9 | B65: Contrarian views on the stock
A66: =A65+1 -> 10 | B66: SWOT Analysis of the company
A67: =A66+1 -> 11 | B67: Recent fillings with NSE
A68: =A67+1 -> 12 | B68: What is the total industry size (check competitors annual reports also)
A69: =A68+1 -> 13 | B69: 4 qtrs investors concall
A71: =A69+1 -> 14 | B71: Scuttlebutt approach of getting information
A72: a) | B72: Employees (linkedin, glassdoor)
A73: b) | B73: Competitors
A74: c) | B74: Vendors
A75: d) | B75: Customers (Online reviews)
A76: e) | B76: Government
A77: f) | B77: Service centres
A79: =A71+1 -> 15 | B79: Define margin of safety | C79: ='Valuation Models DCF'!$G$23 -> 0.42987019
A80: =A79+1 -> 16 | B80: Quarterly reading of financials (Checklist to prepare)
A81: =A80+1 -> 17 | B81: Call with the management
A83: =A81+1 -> 18 | B83: Is that company/industry in my circle of competence
A84: a) | B84: What are the key companies
A85: c) | B85: What drives their growth and profits
A86: d) | B86: Challenges they face
A87: e) | B87: Will this industry survive the nezxt 10 years in its current format | C87: Yes
A89: =A83+1 -> 19 | B89: Technical Analysis
A91: B) | B91: Qualitative Analysis
A92: =A83+1 -> 19 | B92: Michael Porters - 5 Pt analysis (Module 31, 32 and 33)
A93: =A92+1 -> 20 | B93: Financial Shenanigans checklist (module 29 and 30)
A94: =A93+1 -> 21 | B94: Same auditor for many years, audit fees comparison vs industry
A95: =A94+1 -> 22 | B95: Business Qualitative Assessment (Module 4, lesson 34)
A96: =A95+1 -> 23 | B96: Management Qualitiy Checklist
A97: =A96+1 -> 24 | B97: Behavioral Checklist
A98: =A97+1 -> 25 | B98: Investor Sin Checklist
A99: =A98+1 -> 26 | B99: Less is more checklist
A100: =A99+1 -> 27 | B100: 15 point analysis of philips fischer
A101: =A100+1 -> 28 | B101: Investor Checklist (Page 4, 43)
A102: =A101+1 -> 29 | B102: Stop loss
A103: =A102+1 -> 30 | B103: When to sell
A104: =A103+1 -> 31 | B104: Is the company a value trap
... A107: =A106+1 -> 34 | B107: Write a note on why you want to invest in the company
A108: a) | B108: The company appears profitable and has been consistently increasing its sales and profits.
A109: b) | B109: Its return on equity is also good and does not have any debt
A110: c) | B110: It appears that the holding company has appointed it as a distributor in india for its products and ensuring profit margins are maintained
A111: d) | B111: The mangement and its holding company do not appear aggressive enough to indian market are content on the growth they are achieving
A112: e) | B112: Further it is facing competition from its rivals and not able to scale up its business

Sheet SWOT
A1: Endurance Technologies | E1: To check
E2: 1
A3: Strength | C3: Weakness | E3: =E2+1 -> 2
A4: 1 | C4: 1 | E4: 3
A5: =A4+1 -> 2 | E5: =E4+1 -> 4
A6: 3 | E6: =E5+1 -> 5
A7: =A6+1 -> 4 | E7: 6
A8: =A7+1 -> 5 | E8: =E7+1 -> 7
E9: =E8+1 -> 8
E10: =E9+1 -> 9
E11: =E10+1 -> 10
A12: Opportunities | C12: Threats | E12: =E11+1 -> 11
A13: 1 | C13: 1
A14: =A13+1 -> 2 | C14: =C13+1 -> 2
A15: =A14+1 -> 3 | C15: =C14+1 -> 3
C16: =C15+1 -> 4
C17: =C16+1 -> 5

Sheet Quarterly reporting
A1: Endurance Technologies
A3: Q-4 Fy 2024-25
A4: 1
A5: =A4+1 -> 2
A7: =A5+1 -> 3
A8: =A7+1 -> 4
A9: =A8+1 -> 5
A10: =A9+1 -> 6
A11: =A10+1 -> 7
A12: =A11+1 -> 8
A13: =A12+1 -> 9
A17: Q-1 Fy 2025-26
A18: 1
A19: =A18+1 -> 2
A20: =A19+1 -> 3
A21: =A20+1 -> 4
A23: =A21+1 -> 5
A24: =A23+1 -> 6

Sheet Financials_Standalone
A1: Endurance Technologies
A3: Standalone Balance Sheet
A5: EQUITIES AND LIABILITIES
A6: SHAREHOLDER'S FUNDS | B6: Mar 25 | C6: Mar 24 | D6: 45016 | E6: 44651 | F6: 44286 | G6: 43921 | H6: 43555 | I6: 43190 | J6: 42825 | K6: 42460 | L6: 42094
A7: Equity Share Capital | B7: 140.66 | C7: 140.66 | D7: 140.66 | E7: 140.66 | F7: 140.66 | G7: 140.66 | H7: 140.66 | I7: 140.66 | J7: 140.66 | K7: 17.58
A8: Total Share Capital | B8: =SUM(B7) -> 140.66 | C8: =SUM(C7) -> 140.66 | D8: =SUM(D7) -> 140.66 | E8: =SUM(E7) -> 140.66 | F8: =SUM(F7) -> 140.66 | G8: =SUM(G7) -> 140.66 | H8: =SUM(H7) -> 140.66 | I8: =SUM(I7) -> 140.66 | ... L8: =SUM(L7) -> 0
A9: Reserves and Surplus | B9: 4207.35 | C9: 3664.66 | D9: 3190.28 | E9: 2866.19 | F9: 2567.59 | G9: 2176.1 | H9: 1939.29 | I9: 1651.6 | J9: 1422.4 | K9: 1324.88
A10: Total Reserves and Surplus | B10: =SUM(B9) -> 4207.35 | C10: =SUM(C9) -> 3664.66 | D10: =SUM(D9) -> 3190.28 | E10: =SUM(E9) -> 2866.19 | F10: =SUM(F9) -> 2567.59 | G10: =SUM(G9) -> 2176.1 | H10: =SUM(H9) -> 1939.29 | I10: =SUM(I9) -> 1651.6 | ... L10: =SUM(L9) -> 0
A11: Employees Stock Options/ share application money pending allotment
A12: Total Shareholders Funds | B12: =SUM(B10,B8) -> 4348.01 | C12: =SUM(C10,C8) -> 3805.32 | D12: =SUM(D10,D8) -> 3330.94 | E12: =SUM(E10,E8) -> 3006.85 | F12: =SUM(F10,F8) -> 2708.25 | G12: =SUM(G10,G8) -> 2316.76 | H12: =SUM(H10,H8)+H11 -> 2079.95 | I12: =SUM(I10,I8)+I11 -> 1792.26 | J12: =SUM(J10,J8)+J11 -> 1563.06 | K12: =SUM(K10,K8)+K11 -> 1342.46 | L12: =SUM(L10,L8)+L11 -> 0
A13: NON-CURRENT LIABILITIES
A14: Long Term Borrowings | B14: 0 | C14: 0 | D14: 0 | E14: 0 | F14: 2.73 | G14: 4.28 | H14: 2.98 | I14: 4.96 | J14: 19.85 | K14: 78.02
A15: Deferred Tax Liabilities [Net] | B15: 13.35 | C15: 13.8 | D15: 0 | E15: 0 | F15: 0 | G15: 7.37 | H15: 15.61 | I15: 1.08 | J15: 0 | K15: 0
A16: Other Long Term Liabilities | B16: 32.77 | C16: 18.79 | D16: 31.94 | E16: 29.94 | F16: 8.96 | G16: 10.75 | H16: 4.68 | I16: 3.08 | J16: 2.26 | K16: 2.79
A17: Long Term Provisions | B17: 3.6 | C17: 4.07 | D17: 6.04 | E17: 8.85 | F17: 21.07 | G17: 15.82 | H17: 6.28 | I17: 2.16 | J17: 16.54 | K17: 22.65
A18: Total Non-Current Liabilities | B18: =SUM(B14:B17) -> 49.72 | C18: =SUM(C14:C17) -> 36.66 | D18: =SUM(D14:D17) -> 37.98 | E18: =SUM(E14:E17) -> 38.79 | F18: =SUM(F14:F17) -> 32.76 | G18: =SUM(G14:G17) -> 38.22 | H18: =SUM(H14:H17) -> 29.55 | I18: =SUM(I14:I17) -> 11.28 | ... L18: =SUM(L14:L17) -> 0
A19: CURRENT LIABILITIES
A20: Short Term Borrowings | B20: 0 | C20: 0 | D20: 20 | E20: 31.7 | F20: 45 | G20: 146.1 | H20: 212 | I20: 178.27 | J20: 142.49 | K20: 68.78
A21: Trade Payables | B21: 815.01 | C21: 676.21 | D21: 566.45 | E21: 529.93 | F21: 526.84 | G21: 395.6 | H21: 520.76 | I21: 483.23 | J21: 347.95 | K21: 312.1
A22: Other Current Liabilities | B22: 157.15 | C22: 142.91 | D22: 121.04 | E22: 103.83 | F22: 94.9 | G22: 56.93 | H22: 91.27 | I22: 121.43 | J22: 135.67 | K22: 148.43
A23: Short Term Provisions | B23: 26.01 | C23: 24.21 | D23: 32.64 | E23: 28.25 | F23: 29.89 | G23: 29.25 | H23: 25.03 | I23: 19.04 | J23: 22.28 | K23: 16.5
A24: Total Current Liabilities | B24: =SUM(B20:B23) -> 998.17 | C24: =SUM(C20:C23) -> 843.33 | D24: =SUM(D20:D23) -> 740.13 | E24: =SUM(E20:E23) -> 693.71 | F24: =SUM(F20:F23) -> 696.63 | G24: =SUM(G20:G23) -> 627.88 | H24: =SUM(H20:H23) -> 849.06 | I24: =SUM(I20:I23) -> 801.97 | ... L24: =SUM(L20:L23) -> 0
A25: Total Capital And Liabilities | B25: =B12+B18+B24 -> 5395.9 | C25: =C12+C18+C24 -> 4685.31 | D25: =D12+D18+D24 -> 4109.05 | E25: =E12+E18+E24 -> 3739.35 | F25: =F12+F18+F24 -> 3437.64 | G25: =G12+G18+G24 -> 2982.86 | H25: =H12+H18+H24 -> 2958.56 | I25: =I12+I18+I24 -> 2605.51 | ... L25: =L12+L18+L24 -> 0
A27: ASSETS
A28: NON-CURRENT ASSETS
A29: Tangible Assets | B29: 1964.46 | C29: 1756.7 | D29: 1624.85 | E29: 1508.39 | F29: 1368.37 | G29: 1455.65 | H29: 1157.49 | I29: 957.13 | J29: 838.81 | K29: 916.52
A30: Intangible Assets | B30: 60.85 | C30: 44.45 | D30: 51.47 | E30: 56.56 | F30: 26.67 | G30: 3.25 | H30: 4.16 | I30: 5.7 | J30: 7.45 | K30: 6.83
A31: Capital Work-In-Progress | B31: 206.97 | C31: 102.27 | D31: 119.11 | E31: 83.78 | F31: 88.92 | G31: 61.22 | H31: 89.78 | I31: 50.52 | J31: 33.22 | K31: 46.39
A32: Intangible Assets Under Development | B32: 2.82 | C32: 17.69 | D32: 12.38 | E32: 5.4 | F32: 3.17 | G32: 19.5 | H32: 11.5 | I32: 4.78 | J32: 0.4 | K32: 0.55
A33: Fixed Assets | B33: =SUM(B29:B32) -> 2235.1 | C33: =SUM(C29:C32) -> 1921.11 | D33: =SUM(D29:D32) -> 1807.81 | E33: =SUM(E29:E32) -> 1654.13 | F33: =SUM(F29:F32) -> 1487.13 | G33: =SUM(G29:G32) -> 1539.62 | H33: =SUM(H29:H32) -> 1262.93 | I33: =SUM(I29:I32) -> 1018.13 | ... L33: =SUM(L29:L32) -> 0
A34: Non-Current Investments | B34: 521.97 | C34: 533.82 | D34: 524.82 | E34: 364.91 | F34: 364.91 | G34: 364.91 | H34: 365 | I34: 364.77 | J34: 364.71 | K34: 364.67
A35: Deferred Tax Assets [Net] | B35: 0 | C35: 0 | D35: 1.11 | E35: 3.82 | F35: 1.96 | G35: 0 | H35: 0 | I35: 0 | J35: 9.54 | K35: 10.53
A36: Long Term Loans And Advances | B36: 13.7 | C36: 10 | D36: 0 | E36: 0 | F36: 0 | G36: 0 | H36: 0 | I36: 0 | J36: 0 | K36: 26.09
A37: Other Non-Current Assets | B37: 76.06 | C37: 53.31 | D37: 48.67 | E37: 50.08 | F37: 37.25 | G37: 117.76 | H37: 225 | I37: 190.26 | J37: 171.41 | K37: 0.64
A38: Total Non-Current Assets | B38: =SUM(B34:B37) -> 611.73 | C38: =SUM(C34:C37) -> 597.13 | D38: =SUM(D34:D37) -> 574.6 | E38: =SUM(E34:E37) -> 418.81 | F38: =SUM(F34:F37) -> 404.12 | G38: =SUM(G34:G37) -> 482.67 | H38: =SUM(H34:H37) -> 590 | I38: =SUM(I34:I37) -> 555.03 | ... L38: =SUM(L34:L37) -> 0
A39: CURRENT ASSETS | B39: =B33+B38 -> 2846.83 | C39: =C33+C38 -> 2518.24 | D39: =D33+D38 -> 2382.41 | E39: =E33+E38 -> 2072.94 | F39: =F33+F38 -> 1891.25 | G39: =G33+G38 -> 2022.29 | H39: =H33+H38 -> 1852.93 | I39: =I33+I38 -> 1573.16 | ... L39: =L33+L38 -> 0
A40: Current Investments | B40: 518.37 | C40: 402.22 | D40: 267.87 | E40: 209.45 | F40: 169.93 | G40: 37.32 | H40: 34.82 | I40: 44.91 | J40: 31.64 | K40: 45.58
A41: Inventories | B41: 562.08 | C41: 481.71 | D41: 428.92 | E41: 366.68 | F41: 329.53 | G41: 265.83 | H41: 282.98 | I41: 246.62 | J41: 249.07 | K41: 195.31
A42: Trade Receivables | B42: 1132.25 | C42: 1068.44 | D42: 848.8 | E42: 801.09 | F42: 812.51 | G42: 473.76 | H42: 694.76 | I42: 706.57 | J42: 484.64 | K42: 316.51
A43: Cash And Cash Equivalents | B43: 92.19 | C43: 15.74 | D43: 42.73 | E43: 103.14 | F43: 34.29 | G43: 125.33 | H43: 30.43 | I43: 8.69 | J43: 2.98 | K43: 7.58
A44: Short Term Loans And Advances | B44: 3.36 | C44: 2 | D44: 1.48 | E44: 1.1 | F44: 1.26 | G44: 2.01 | H44: 2.1 | I44: 1.3 | J44: 1.62 | K44: 41.25
A45: Other Current assets | B45: 240.83 | C45: 196.96 | D45: 136.84 | E45: 184.93 | F45: 198.89 | G45: 56.35 | H45: 60.53 | I45: 24.26 | J45: 54.61 | K45: 13.3
A46: Total Current Assets | B46: =SUM(B40:B45) -> 2549.08 | C46: =SUM(C40:C45) -> 2167.07 | D46: =SUM(D40:D45) -> 1726.64 | E46: =SUM(E40:E45) -> 1666.39 | F46: =SUM(F40:F45) -> 1546.41 | G46: =SUM(G40:G45) -> 960.6 | H46: =SUM(H40:H45) -> 1105.62 | I46: =SUM(I40:I45) -> 1032.35 | ... L46: =SUM(L40:L45) -> 0
A47: Total Assets | B47: =B39+B46 -> 5395.91 | C47: =C39+C46 -> 4685.31 | D47: =D39+D46 -> 4109.05 | E47: =E39+E46 -> 3739.33 | F47: =F39+F46 -> 3437.66 | G47: =G39+G46 -> 2982.89 | H47: =H39+H46 -> 2958.55 | I47: =I39+I46 -> 2605.51 | ... L47: =L39+L46 -> 0
A48: OTHER ADDITIONAL INFORMATION
A49: CONTINGENT LIABILITIES, COMMITMENTS
A50: Contingent Liabilities | B50: 230.05 | C50: 125.18 | D50: 541.61 | E50: 705.9 | F50: 331.52 | G50: 252.24 | H50: 312.23 | I50: 356.98 | J50: 236.7 | K50: 258.22
A51: CIF VALUE OF IMPORTS
A52: Raw Materials | G52: 0 | H52: 0 | I52: 0 | J52: 0 | K52: 289.35
A53: Trade/Other Goods | G53: 0 | H53: 0 | I53: 0 | J53: 0 | K53: 13.37
A54: Capital Goods | G54: 0 | H54: 0 | I54: 0 | J54: 0 | K54: 43.1
A55: EXPENDITURE IN FOREIGN EXCHANGE | B55: 679.87 | C55: 368.2 | D55: 346.13 | E55: 318 | F55: 279.23 | G55: 328.53 | H55: 434.2 | I55: 417.12 | J55: 0 | K55: 11.52
A56: REMITTANCES IN FOREIGN CURRENCIES FOR DIVIDENDS
A57: Dividend Remittance In Foreign Currency
A58: EARNINGS IN FOREIGN EXCHANGE
A59: FOB Value Of Goods | B59: - | C59: - | D59: - | E59: - | F59: - | G59: - | H59: - | I59: - | J59: - | K59: 139.52
A60: Other Earnings | B60: 171.02 | C60: 177.5 | D60: 140.39 | E60: 162.35 | F60: 114.05 | G60: 120.58 | H60: 143.56 | I60: 170.51 | J60: - | K60: 0.07
A61: BONUS DETAILS
A62: Bonus Equity Share Capital | B62: 123.66 | C62: 123.66 | D62: 123.66 | E62: 123.66 | F62: 123.66 | G62: 123.66 | H62: 123.66 | I62: 123.66 | J62: 123.66 | K62: 0.58
A63: NON-CURRENT INVESTMENTS
A64: Non-Current Investments Quoted Market Value | B64: - | C64: - | D64: - | E64: - | F64: 0 | G64: 0 | H64: 0 | I64: 0 | J64: 0.01 | K64: 0.01
A65: Non-Current Investments Unquoted Book Value | B65: 5.88 | C65: 3.36 | D65: 3.19 | E65: 1.15 | F65: 1.15 | G65: 1.15 | H65: 1.24 | I65: 364.77 | J65: 364.7 | K65: 364.66
A66: CURRENT INVESTMENTS
A67: Current Investments Quoted Market Value | B67: - | C67: - | D67: - | E67: - | F67: - | G67: - | H67: - | I67: - | J67: - | K67: -
A68: Current Investments Unquoted Book Value | B68: - | C68: - | D68: - | E68: - | F68: 169.93 | G68: 37.32 | H68: 34.82 | I68: 44.91 | J68: 31.64 | K68: 45.58
A70: Standalone Profit & Loss account
A72: INCOME | B72: Mar 25 | C72: Mar 24 | D72: 45016 | E72: 44651 | F72: 44286 | G72: 43921 | H72: 43555 | I72: 43190 | J72: 42825 | K72: 42460 | L72: 42094
A73: Revenue From Operations [Gross] | B73: 8730.32 | C73: 7757.77 | D73: 6674.81 | E73: 5604.43 | F73: 4658.97 | G73: 4820.16 | H73: 5341.43 | I73: 4680.17 | J73: 4194.28 | K73: 3987.37
A74: Less: Excise/Sevice Tax/Other Levies | G74: 0 | H74: 0 | I74: 127.91 | J74: 400.33 | K74: 387.25
A75: Revenue From Operations [Net] | B75: =(B73-B74) -> 8730.32 | C75: =(C73-C74) -> 7757.77 | D75: =D73-D74 -> 6674.81 | E75: =E73-E74 -> 5604.43 | F75: =F73-F74 -> 4658.97 | G75: =G73-G74 -> 4820.16 | H75: =H73-H74 -> 5341.43 | I75: =I73-I74 -> 4552.26 | J75: =J73-J74 -> 3793.95 | K75: =K73-K74 -> 3600.12 | L75: =L73-L74 -> 0
A76: Other Operating Revenues | B76: 115.83 | C76: 113.23 | D76: 92.7 | E76: 92.66 | F76: 114.07 | G76: 118.41 | H76: 76.03 | I76: 88.85 | J76: 85.87 | K76: 73.78
A77: Total Operating Revenues | B77: =SUM(B75:B76) -> 8846.15 | C77: =SUM(C75:C76) -> 7871 | D77: =SUM(D75:D76) -> 6767.51 | E77: =SUM(E75:E76) -> 5697.09 | F77: =SUM(F75:F76) -> 4773.04 | G77: =SUM(G75:G76) -> 4938.57 | H77: =SUM(H75:H76) -> 5417.46 | I77: =SUM(I75:I76) -> 4641.11 | ... L77: =SUM(L75:L76) -> 0
A78: Other Income | B78: 66.58 | C78: 49.47 | D78: 28.2 | E78: 24.39 | F78: 13.55 | G78: 36.19 | H78: 16.22 | I78: 18.39 | J78: 12.55 | K78: 21.98
A79: Total Revenue | B79: =B77+B78 -> 8912.73 | C79: =C77+C78 -> 7920.47 | D79: =D77+D78 -> 6795.71 | E79: =E77+E78 -> 5721.48 | F79: =F77+F78 -> 4786.59 | G79: =G77+G78 -> 4974.76 | H79: =H77+H78 -> 5433.68 | I79: =I77+I78 -> 4659.5 | ... L79: =L77+L78 -> 0
A80: EXPENSES
A81: COGS | B81: 5686.35 | C81: 5086.76 | D81: 4511.09 | E81: 3745.18 | F81: 2969.19 | G81: 3000.67 | H81: 3508.03 | I81: 3011.06 | J81: 2511.41 | K81: 2392.5
A82: Purchase Of Stock-In Trade | B82: 70.67 | C82: 60.38 | D82: 63.91 | E82: 54.07 | F82: 44.6 | G82: 27.84 | H82: 23.08 | I82: 9.09 | J82: 9.81 | K82: 7.86
A83: Changes In Inventories Of FG,WIP And Stock-In Trade | B83: -28.57 | C83: -6.44 | D83: -42.4 | E83: -40.93 | F83: -44.43 | G83: 18.81 | H83: -7.38 | I83: 9.43 | J83: -43.22 | K83: -16.2
A84: Employee Benefit Expenses | B84: 435.78 | C84: 380.12 | D84: 324.18 | E84: 290.31 | F84: 286.56 | G84: 296.13 | H84: 277.74 | I84: 254.7 | J84: 242.18 | K84: 207.71
A85: Finance Costs | B85: 2.56 | C85: 2.99 | D85: 4.27 | E85: 1.82 | F85: 4.8 | G85: 10.82 | H85: 17.07 | I85: 10.25 | J85: 17.86 | K85: 32.55
A86: Depreciation And Amortisation Expenses | B86: 289.65 | C86: 262.52 | D86: 240.71 | E86: 203.74 | F86: 203.42 | G86: 199.25 | H86: 175.7 | I86: 169.63 | J86: 166.86 | K86: 150.48
A87: Other Expenses | B87: 1530.87 | C87: 1343.86 | D87: 1131.49 | E87: 919.79 | F87: 785.53 | G87: 861.06 | H87: 895.9 | I87: 766.46 | J87: 688.6 | K87: 639.78
A88: Less: Amounts Transfer To Capital Accounts | G88: -8.26 | H88: -11.92 | I88: 0 | J88: 0 | K88: 0
A89: Total Expenses | B89: =SUM(B81:B88) -> 7987.31 | C89: =SUM(C81:C88) -> 7130.19 | D89: =SUM(D81:D88) -> 6233.25 | E89: =SUM(E81:E88) -> 5173.98 | F89: =SUM(F81:F88) -> 4249.67 | G89: =SUM(G81:G88) -> 4406.32 | H89: =SUM(H81:H88) -> 4878.22 | I89: =SUM(I81:I88) -> 4230.62 | ... L89: =SUM(L81:L88) -> 0
A91: Profit/Loss Before Exceptional, ExtraOrdinary Items And Tax | B91: =B79-B89 -> 925.42 | C91: =C79-C89 -> 790.28 | D91: =D79-D89 -> 562.46 | E91: =E79-E89 -> 547.5 | F91: =F79-F89 -> 536.92 | G91: =G79-G89 -> 568.44 | H91: =H79-H89 -> 555.46 | I91: =I79-I89 -> 428.88 | ... L91: =L79-L89 -> 0
A92: Exceptional Items | B92: -17.36 | C92: 0 | D92: -10.29 | E92: -31.45 | F92: -11.23 | G92: 0 | H92: -20.8 | I92: -26.88 | J92: 0 | K92: 0
A93: Profit/Loss Before Tax | B93: =B91+B92 -> 908.06 | C93: =C91+C92 -> 790.28 | D93: =D91+D92 -> 552.17 | E93: =E91+E92 -> 516.05 | F93: =F91+F92 -> 525.69 | G93: =G91+G92 -> 568.44 | H93: =H91+H92 -> 534.66 | I93: =I91+I92 -> 402 | ... L93: =L91+L92 -> 0
A94: Current Tax | B94: 229.68 | C94: 194.76 | D94: 141.4 | E94: 136.59 | F94: 142.59 | G94: 147.53 | H94: 159.5 | I94: 126.12 | J94: 75.78 | K94: 71.3
A95: Less: MAT Credit Entitlement
A96: Tax For Earlier Years | B96: -2.16 | C96: -11.75 | D96: 0 | E96: 0 | F96: 0 | G96: 0 | H96: 1.51 | I96: -6.4 | J96: 0.13 | K96: 0
A97: Deferred Tax | B97: 1.88 | C97: 19.46 | D97: 1.86 | E97: -2.29 | F97: -9.09 | G97: -6.78 | H97: 15.79 | I97: 10.67 | J97: 1.48 | K97: 4.33
A98: Total Tax Expenses | B98: =SUM(B94:B97) -> 229.4 | C98: =SUM(C94:C97) -> 202.47 | D98: =SUM(D94:D97) -> 143.26 | E98: =SUM(E94:E97) -> 134.3 | F98: =SUM(F94:F97) -> 133.5 | G98: =SUM(G94:G97) -> 140.75 | H98: =SUM(H94:H97) -> 176.8 | I98: =SUM(I94:I97) -> 130.39 | ... L98: =SUM(L94:L97) -> 0
A99: Profit/Loss After Tax And Before ExtraOrdinary Items | B99: =B93-B98 -> 678.66 | C99: =C93-C98 -> 587.81 | D99: =D93-D98 -> 408.91 | E99: =E93-E98 -> 381.75 | F99: =F93-F98 -> 392.19 | G99: =G93-G98 -> 427.69 | H99: =H93-H98 -> 357.86 | I99: =I93-I98 -> 271.61 | ... L99: =L93-L98 -> 0
A100: Extraordinary Items
A101: Profit/Loss From Continuing Operations | B101: =B99 -> 678.66 | C101: =C99 -> 587.81 | D101: =D99 -> 408.91 | E101: =E99 -> 381.75 | F101: =F99 -> 392.19 | G101: =G99 -> 427.69 | H101: =H99 -> 357.86 | I101: =I99 -> 271.61 | ... L101: =L99 -> 0
A102: Profit/Loss For The Period | B102: =B101 -> 678.66 | C102: =C101 -> 587.81 | D102: =D101 -> 408.91 | E102: =E101 -> 381.75 | F102: =F101 -> 392.19 | G102: =G101 -> 427.69 | H102: =H101 -> 357.86 | I102: =I101 -> 271.61 | ... L102: =L101 -> 0
A103: OTHER ADDITIONAL INFORMATION
A104: EARNINGS PER SHARE
A105: Basic EPS (Rs.) | B105: 48.25 | C105: 41.79 | D105: 29.07 | E105: 27.14 | F105: 27.88 | G105: 30.41 | H105: 25.44 | I105: 19.31 | J105: 15.75 | K105: 14.62 | N105: =H102*10000000/H117 -> 25.44149
A106: Diluted EPS (Rs.) | B106: 48.25 | C106: 41.79 | D106: 29.07 | E106: 27.14 | F106: 27.88 | G106: 30.41 | H106: 25.44 | I106: 19.31 | J106: 15.75 | K106: 14.62
...

Sheet Standalone bs
A1: Endurance Technologies | B1: Previous Years � | G1: � Next Years Previous Years �
A2: Standalone Balance Sheet | B2: ------------------- in Rs. Cr. ------------------- | G2: ------------------- in Rs. Cr. -------------------
B3: Mar 25 | C3: 45352 | D3: 44986 | E3: 44621 | F3: 44256 | G3: Mar 20 | H3: 43525 | I3: 43160 | J3: 42795 | K3: 42430
A4: #VALUE!
B5: 12 mths | C5: 12 mths | D5: 12 mths | E5: 12 mths | F5: 12 mths | G5: 12 mths | H5: 12 mths | I5: 12 mths | J5: 12 mths | K5: 12 mths
A6: #VALUE!
A7: EQUITIES AND LIABILITIES
A8: SHAREHOLDER'S FUNDS
A9: Equity Share Capital | B9: 140.66 | C9: 140.66 | D9: 140.66 | E9: 140.66 | F9: 140.66 | G9: 140.66 | H9: 140.66 | I9: 140.66 | J9: 140.66 | K9: 17.58
A10: Total Share Capital | B10: 140.66 | C10: 140.66 | D10: 140.66 | E10: 140.66 | F10: 140.66 | G10: 140.66 | H10: 140.66 | I10: 140.66 | J10: 140.66 | K10: 17.58
A11: Reserves and Surplus | B11: 4207.35 | C11: 3664.66 | D11: 3190.28 | E11: 2866.19 | F11: 2567.59 | G11: 2176.1 | H11: 1939.29 | I11: 1651.6 | J11: 1422.4 | K11: 1324.88
A12: Total Reserves and Surplus | B12: 4207.35 | C12: 3664.66 | D12: 3190.28 | E12: 2866.19 | F12: 2567.59 | G12: 2176.1 | H12: 1939.29 | I12: 1651.6 | J12: 1422.4 | K12: 1324.88
A13: Total Shareholders Funds | B13: 4348.01 | C13: 3805.32 | D13: 3330.94 | E13: 3006.85 | F13: 2708.26 | G13: 2316.76 | H13: 2079.95 | I13: 1792.26 | J13: 1563.06 | K13: 1342.46
A14: NON-CURRENT LIABILITIES
A15: Long Term Borrowings | B15: 0 | C15: 0 | D15: 0 | E15: 0 | F15: 2.73 | G15: 4.28 | H15: 2.98 | I15: 4.96 | J15: 19.85 | K15: 78.02
A16: Deferred Tax Liabilities [Net] | B16: 13.35 | C16: 13.8 | D16: 0 | E16: 0 | F16: 0 | G16: 7.37 | H16: 15.61 | I16: 1.08 | J16: 0 | K16: 0
A17: Other Long Term Liabilities | B17: 32.77 | C17: 18.79 | D17: 31.94 | E17: 29.94 | F17: 8.96 | G17: 10.75 | H17: 4.68 | I17: 3.08 | J17: 2.26 | K17: 2.79
A18: Long Term Provisions | B18: 3.6 | C18: 4.07 | D18: 6.04 | E18: 8.85 | F18: 21.07 | G18: 15.82 | H18: 6.28 | I18: 2.16 | J18: 16.54 | K18: 22.65
A19: Total Non-Current Liabilities | B19: 49.72 | C19: 36.67 | D19: 37.98 | E19: 38.78 | F19: 32.76 | G19: 38.22 | H19: 29.54 | I19: 11.28 | J19: 38.64 | K19: 103.46
A20: CURRENT LIABILITIES
A21: Short Term Borrowings | B21: 0 | C21: 0 | D21: 20 | E21: 31.7 | F21: 45 | G21: 146.1 | H21: 212 | I21: 178.27 | J21: 142.49 | K21: 68.78
A22: Trade Payables | B22: 815.01 | C22: 676.21 | D22: 566.45 | E22: 529.93 | F22: 526.84 | G22: 395.6 | H22: 520.76 | I22: 483.23 | J22: 347.95 | K22: 312.1
A23: Other Current Liabilities | B23: 157.15 | C23: 142.91 | D23: 121.04 | E23: 103.83 | F23: 94.9 | G23: 56.93 | H23: 91.27 | I23: 121.43 | J23: 135.67 | K23: 148.43
A24: Short Term Provisions | B24: 26.01 | C24: 24.21 | D24: 32.64 | E24: 28.25 | F24: 29.89 | G24: 29.25 | H24: 25.03 | I24: 19.04 | J24: 22.28 | K24: 16.5
A25: Total Current Liabilities | B25: 998.17 | C25: 843.32 | D25: 740.13 | E25: 693.71 | F25: 696.63 | G25: 627.88 | H25: 849.06 | I25: 801.97 | J25: 648.39 | K25: 545.81
A26: Total Capital And Liabilities | B26: 5395.9 | C26: 4685.3 | D26: 4109.05 | E26: 3739.34 | F26: 3437.65 | G26: 2982.87 | H26: 2958.55 | I26: 2605.51 | J26: 2250.1 | K26: 1991.73
A27: ASSETS
A28: NON-CURRENT ASSETS
A29: Tangible Assets | B29: 1964.46 | C29: 1756.7 | D29: 1624.85 | E29: 1508.39 | F29: 1368.37 | G29: 1455.65 | H29: 1157.49 | I29: 957.13 | J29: 838.81 | K29: 916.52
A30: Intangible Assets | B30: 60.85 | C30: 44.45 | D30: 51.47 | E30: 56.56 | F30: 26.67 | G30: 3.25 | H30: 4.16 | I30: 5.7 | J30: 7.45 | K30: 6.83
A31: Capital Work-In-Progress | B31: 206.97 | C31: 102.27 | D31: 119.11 | E31: 83.78 | F31: 88.92 | G31: 61.22 | H31: 89.78 | I31: 50.52 | J31: 33.22 | K31: 46.39
A32: Intangible Assets Under Development | B32: 2.82 | C32: 17.69 | D32: 12.38 | E32: 5.4 | F32: 3.17 | G32: 19.5 | H32: 11.5 | I32: 4.78 | J32: 0.4 | K32: 0.55
A33: Fixed Assets | B33: 2235.09 | C33: 1921.11 | D33: 1807.81 | E33: 1654.14 | F33: 1487.12 | G33: 1539.61 | H33: 1262.94 | I33: 1018.13 | J33: 879.88 | K33: 970.28
A34: Non-Current Investments | B34: 521.97 | C34: 533.82 | D34: 524.82 | E34: 364.91 | F34: 364.91 | G34: 364.91 | H34: 365 | I34: 364.77 | J34: 364.71 | K34: 364.67
A35: Deferred Tax Assets [Net] | B35: 0 | C35: 0 | D35: 1.11 | E35: 3.82 | F35: 1.96 | G35: 0 | H35: 0 | I35: 0 | J35: 9.54 | K35: 10.53
A36: Long Term Loans And Advances | B36: 13.7 | C36: 10 | D36: 0 | E36: 0 | F36: 0 | G36: 0 | H36: 0 | I36: 0 | J36: 0 | K36: 26.09
A37: Other Non-Current Assets | B37: 76.06 | C37: 53.31 | D37: 48.67 | E37: 50.08 | F37: 37.25 | G37: 117.76 | H37: 225 | I37: 190.26 | J37: 171.41 | K37: 0.64
A38: Total Non-Current Assets | B38: 2846.82 | C38: 2518.24 | D38: 2382.41 | E38: 2072.95 | F38: 1891.23 | G38: 2022.28 | H38: 1852.94 | I38: 1573.15 | J38: 1425.54 | K38: 1372.21
A39: CURRENT ASSETS
A40: Current Investments | B40: 518.37 | C40: 402.22 | D40: 267.87 | E40: 209.45 | F40: 169.93 | G40: 37.32 | H40: 34.82 | I40: 44.91 | J40: 31.64 | K40: 45.58
A41: Inventories | B41: 562.08 | C41: 481.71 | D41: 428.92 | E41: 366.68 | F41: 329.53 | G41: 265.83 | H41: 282.98 | I41: 246.62 | J41: 249.07 | K41: 195.31
A42: Trade Receivables | B42: 1132.25 | C42: 1068.44 | D42: 848.8 | E42: 801.09 | F42: 812.51 | G42: 473.76 | H42: 694.76 | I42: 706.57 | J42: 484.64 | K42: 316.51
A43: Cash And Cash Equivalents | B43: 92.19 | C43: 15.74 | D43: 42.73 | E43: 103.14 | F43: 34.29 | G43: 125.33 | H43: 30.43 | I43: 8.69 | J43: 2.98 | K43: 7.58
A44: Short Term Loans And Advances | B44: 3.36 | C44: 2 | D44: 1.48 | E44: 1.1 | F44: 1.26 | G44: 2.01 | H44: 2.1 | I44: 1.3 | J44: 1.62 | K44: 41.25
A45: OtherCurrentAssets | B45: 240.83 | C45: 196.96 | D45: 136.84 | E45: 184.93 | F45: 198.89 | G45: 56.35 | H45: 60.53 | I45: 24.26 | J45: 54.61 | K45: 13.3
A46: Total Current Assets | B46: 2549.08 | C46: 2167.07 | D46: 1726.64 | E46: 1666.39 | F46: 1546.41 | G46: 960.59 | H46: 1105.61 | I46: 1032.36 | J46: 824.56 | K46: 619.52
A47: Total Assets | B47: 5395.9 | C47: 4685.3 | D47: 4109.05 | E47: 3739.34 | F47: 3437.65 | G47: 2982.87 | H47: 2958.55 | I47: 2605.51 | J47: 2250.1 | K47: 1991.73
A48: OTHER ADDITIONAL INFORMATION
A49: CONTINGENT LIABILITIES, COMMITMENTS
A50: Contingent Liabilities | B50: 230.05 | C50: 125.18 | D50: 541.61 | E50: 705.9 | F50: 331.52 | G50: 252.24 | H50: 312.23 | I50: 356.98 | J50: 236.7 | K50: 258.22
A51: CIF VALUE OF IMPORTS
G52: 0 | H52: 0 | I52: 0 | J52: 0 | K52: 289.35
G53: 0 | H53: 0 | I53: 0 | J53: 0 | K53: 13.37
G54: 0 | H54: 0 | I54: 0 | J54: 0 | K54: 43.1
A55: EXPENDITURE IN FOREIGN EXCHANGE
A56: Expenditure In Foreign Currency | B56: 679.87 | C56: 368.2 | D56: 346.13 | E56: 318 | F56: 279.23 | G56: 328.53 | H56: 434.2 | I56: 417.12 | J56: 0 | K56: 11.52
A57: REMITTANCES IN FOREIGN CURRENCIES FOR DIVIDENDS
A58: Dividend Remittance In Foreign Currency | B58: - | C58: - | D58: - | E58: - | F58: - | G58: - | H58: - | I58: - | J58: - | K58: -
A59: EARNINGS IN FOREIGN EXCHANGE
A60: FOB Value Of Goods | B60: - | C60: - | D60: - | E60: - | F60: - | G60: - | H60: - | I60: - | J60: - | K60: 139.52
A61: Other Earnings | B61: 171.02 | C61: 177.5 | D61: 140.39 | E61: 162.35 | F61: 114.05 | G61: 120.58 | H61: 143.56 | I61: 170.51 | J61: - | K61: 0.07
A62: BONUS DETAILS
A63: Bonus Equity Share Capital | B63: 123.66 | C63: 123.66 | D63: 123.66 | E63: 123.66 | F63: 123.66 | G63: 123.66 | H63: 123.66 | I63: 123.66 | J63: 123.66 | K63: 0.58
A64: NON-CURRENT INVESTMENTS
A65: Non-Current Investments Quoted Market Value | B65: - | C65: - | D65: - | E65: - | F65: 0 | G65: 0 | H65: 0 | I65: 0 | J65: 0.01 | K65: 0.01
A66: Non-Current Investments Unquoted Book Value | B66: 5.88 | C66: 3.36 | D66: 3.19 | E66: 1.15 | F66: 1.15 | G66: 1.15 | H66: 1.24 | I66: 364.77 | J66: 364.7 | K66: 364.66
A67: CURRENT INVESTMENTS
A68: Current Investments Quoted Market Value | B68: - | C68: - | D68: - | E68: - | F68: - | G68: - | H68: - | I68: - | J68: - | K68: -
A69: Current Investments Unquoted Book Value | B69: - | C69: - | D69: - | E69: - | F69: 169.93 | G69: 37.32 | H69: 34.82 | I69: 44.91 | J69: 31.64 | K69: 45.58
A72: #VALUE!
A73: #VALUE!

Sheet Sheet2
A1: Endurance Technologies | B1: Previous Years � | G1: � Next Years Previous Years �
A2: Standalone Profit & Loss account | B2: ------------------- in Rs. Cr. ------------------- | G2: ------------------- in Rs. Cr. -------------------
B3: Mar 25 | C3: 45352 | D3: 44986 | E3: 44621 | F3: 44256 | G3: Mar 20 | H3: 43525 | I3: 43160 | J3: 42795 | K3: 42430
A4: #VALUE!
B5: 12 mths | C5: 12 mths | D5: 12 mths | E5: 12 mths | F5: 12 mths | G5: 12 mths | H5: 12 mths | I5: 12 mths | J5: 12 mths | K5: 12 mths
A6: #VALUE!
A7: INCOME
A8: Revenue From Operations [Gross] | B8: 8730.32 | C8: 7757.77 | D8: 6674.81 | E8: 5604.43 | F8: 4658.97 | G8: 4820.16 | H8: 5341.43 | I8: 4680.17 | J8: 4194.28 | K8: 3987.37
A9: Less: Excise/Sevice Tax/Other Levies | G9: 0 | H9: 0 | I9: 127.91 | J9: 400.33 | K9: 387.25
A10: Revenue From Operations [Net] | B10: 8730.32 | C10: 7757.77 | D10: 6674.81 | E10: 5604.43 | F10: 4658.97 | G10: 4820.16 | H10: 5341.43 | I10: 4552.25 | J10: 3793.95 | K10: 3600.13
A11: Other Operating Revenues | B11: 115.83 | C11: 113.23 | D11: 92.7 | E11: 92.66 | F11: 114.07 | G11: 118.41 | H11: 76.03 | I11: 88.85 | J11: 85.87 | K11: 73.78
A12: Total Operating Revenues | B12: 8846.15 | C12: 7871 | D12: 6767.51 | E12: 5697.09 | F12: 4773.03 | G12: 4938.57 | H12: 5417.46 | I12: 4641.1 | J12: 3879.82 | K12: 3673.91
A13: Other Income | B13: 66.58 | C13: 49.47 | D13: 28.2 | E13: 24.39 | F13: 13.55 | G13: 36.19 | H13: 16.22 | I13: 18.39 | J13: 12.55 | K13: 21.98
A14: Total Revenue | B14: 8912.73 | C14: 7920.47 | D14: 6795.71 | E14: 5721.48 | F14: 4786.58 | G14: 4974.76 | H14: 5433.68 | I14: 4659.49 | J14: 3892.37 | K14: 3695.89
A15: EXPENSES
A16: Cost Of Materials Consumed | B16: 5686.35 | C16: 5086.76 | D16: 4511.09 | E16: 3745.18 | F16: 2969.19 | G16: 3000.67 | H16: 3508.03 | I16: 3011.06 | J16: 2511.41 | K16: 2392.5
A17: Purchase Of Stock-In Trade | B17: 70.67 | C17: 60.38 | D17: 63.91 | E17: 54.07 | F17: 44.6 | G17: 27.84 | H17: 23.08 | I17: 9.09 | J17: 9.81 | K17: 7.86
A18: Changes In Inventories Of FG,WIP And Stock-In Trade | B18: -28.57 | C18: -6.44 | D18: -42.4 | E18: -40.93 | F18: -44.43 | G18: 18.81 | H18: -7.38 | I18: 9.43 | J18: -43.22 | K18: -16.2
A19: Employee Benefit Expenses | B19: 435.78 | C19: 380.12 | D19: 324.18 | E19: 290.31 | F19: 286.56 | G19: 296.13 | H19: 277.74 | I19: 254.7 | J19: 242.18 | K19: 207.71
A20: Finance Costs | B20: 2.56 | C20: 2.99 | D20: 4.27 | E20: 1.82 | F20: 4.8 | G20: 10.82 | H20: 17.07 | I20: 10.25 | J20: 17.86 | K20: 32.55
A21: Depreciation And Amortisation Expenses | B21: 289.65 | C21: 262.52 | D21: 240.71 | E21: 203.74 | F21: 203.42 | G21: 199.25 | H21: 175.7 | I21: 169.63 | J21: 166.86 | K21: 150.48
A22: Other Expenses | B22: 1530.87 | C22: 1343.86 | D22: 1131.49 | E22: 919.79 | F22: 785.53 | G22: 861.06 | H22: 895.9 | I22: 766.46 | J22: 688.6 | K22: 639.78
A23: Less: Amounts Transfer To Capital Accounts | G23: 8.26 | H23: 11.92 | I23: 0 | J23: 0 | K23: 0
A24: Total Expenses | B24: 7987.31 | C24: 7130.2 | D24: 6233.25 | E24: 5173.99 | F24: 4249.66 | G24: 4406.32 | H24: 4878.22 | I24: 4230.61 | J24: 3593.49 | K24: 3414.66
B25: 45717 | C25: 45352 | D25: 44986 | E25: 44621 | F25: 44256 | G25: 43891 | H25: 43525 | I25: 43160 | J25: 42795 | K25: 42430
A26: #VALUE!
B27: 12 mths | C27: 12 mths | D27: 12 mths | E27: 12 mths | F27: 12 mths | G27: 12 mths | H27: 12 mths | I27: 12 mths | J27: 12 mths | K27: 12 mths
A28: #VALUE!
A29: Profit/Loss Before Exceptional, ExtraOrdinary Items And Tax | B29: 925.42 | C29: 790.27 | D29: 562.46 | E29: 547.49 | F29: 536.92 | G29: 568.44 | H29: 555.46 | I29: 428.88 | J29: 298.88 | K29: 281.22
A30: Exceptional Items | B30: -17.36 | C30: 0 | D30: -10.29 | E30: -31.45 | F30: -11.23 | G30: 0 | H30: -20.8 | I30: -26.88 | J30: 0 | K30: 0
A31: Profit/Loss Before Tax | B31: 908.06 | C31: 790.27 | D31: 552.17 | E31: 516.04 | F31: 525.7 | G31: 568.44 | H31: 534.66 | I31: 402 | J31: 298.88 | K31: 281.22
A32: Tax Expenses-Continued Operations
A33: Current Tax | B33: 229.68 | C33: 194.76 | D33: 141.4 | E33: 136.59 | F33: 142.59 | G33: 147.53 | H33: 159.5 | I33: 126.12 | J33: 75.78 | K33: 71.3
A34: Deferred Tax | B34: 1.88 | C34: 19.46 | D34: 1.86 | E34: -2.29 | F34: -9.09 | G34: -6.78 | H34: 15.79 | I34: 10.67 | J34: 1.48 | K34: 4.33
A35: Tax For Earlier Years | B35: -2.16 | C35: -11.75 | D35: 0 | E35: 0 | F35: 0 | G35: 0 | H35: 1.51 | I35: -6.4 | J35: 0.13 | K35: 0
A36: Total Tax Expenses | B36: 229.4 | C36: 202.48 | D36: 143.25 | E36: 134.3 | F36: 133.5 | G36: 140.75 | H36: 176.8 | I36: 130.4 | J36: 77.38 | K36: 75.63
A37: Profit/Loss After Tax And Before ExtraOrdinary Items | B37: 678.66 | C37: 587.79 | D37: 408.92 | E37: 381.74 | F37: 392.2 | G37: 427.69 | H37: 357.86 | I37: 271.6 | J37: 221.5 | K37: 205.6
A38: Profit/Loss From Continuing Operations | B38: 678.66 | C38: 587.79 | D38: 408.92 | E38: 381.74 | F38: 392.2 | G38: 427.69 | H38: 357.86 | I38: 271.6 | J38: 221.5 | K38: 205.6
A39: Profit/Loss For The Period | B39: 678.66 | C39: 587.79 | D39: 408.92 | E39: 381.74 | F39: 392.2 | G39: 427.69 | H39: 357.86 | I39: 271.6 | J39: 221.5 | K39: 205.6
B40: 45717 | C40: 45352 | D40: 44986 | E40: 44621 | F40: 44256 | G40: 43891 | H40: 43525 | I40: 43160 | J40: 42795 | K40: 42430
A41: #VALUE!
B42: 12 mths | C42: 12 mths | D42: 12 mths | E42: 12 mths | F42: 12 mths | G42: 12 mths | H42: 12 mths | I42: 12 mths | J42: 12 mths | K42: 12 mths
A43: #VALUE!
A44: OTHER ADDITIONAL INFORMATION
A45: EARNINGS PER SHARE
A46: Basic EPS (Rs.) | B46: 48.25 | C46: 41.79 | D46: 29.07 | E46: 27.14 | F46: 27.88 | G46: 30.41 | H46: 25.44 | I46: 19.31 | J46: 15.75 | K46: 14.62
A47: Diluted EPS (Rs.) | B47: 48.25 | C47: 41.79 | D47: 29.07 | E47: 27.14 | F47: 27.88 | G47: 30.41 | H47: 25.44 | I47: 19.31 | J47: 15.75 | K47: 14.62
A48: VALUE OF IMPORTED AND INDIGENIOUS RAW MATERIALS
A49: Imported Raw Materials | G49: 0 | H49: 0 | I49: 0 | J49: 0 | K49: 314.82
A50: Indigenous Raw Materials | G50: 0 | H50: 0 | I50: 0 | J50: 0 | K50: 2087.09
A51: STORES, SPARES AND LOOSE TOOLS
A52: Imported Stores And Spares | G52: 0 | H52: 0 | I52: 0 | J52: 0 | K52: 17.6
A53: Indigenous Stores And Spares | G53: 0 | H53: 0 | I53: 0 | J53: 0 | K53: 56.24
A54: DIVIDEND AND DIVIDEND PERCENTAGE
A55: Equity Share Dividend | B55: 119.56 | C55: 98.46 | D55: 87.91 | E55: 84.4 | F55: 0 | G55: 154.73 | H55: 56.27 | I55: 35.17 | J55: 5.28 | K55: 17.58
A56: Tax On Dividend | G56: 31.81 | H56: 11.57 | I56: 7.16 | J56: 1.07 | K56: 3.58
A57: Equity Dividend Rate (%) | B57: 100 | C57: 85 | D57: 70 | E57: 63 | F57: 60 | G57: 55 | H57: 55 | I57: 40 | J57: 25 | K57: 74

Sheet Financials_Consol
A1: Endurance Technologies
A3: Consol Balance Sheet
A5: EQUITIES AND LIABILITIES
A6: SHAREHOLDER'S FUNDS | B6: Mar 25 | C6: Mar 24 | D6: 45016 | E6: 44651 | F6: 44286 | G6: 43921 | H6: 43555 | I6: 43190 | J6: 42825 | K6: 42460 | L6: 42094
A7: Equity Share Capital | B7: 140.66 | C7: 140.66 | D7: 140.66 | E7: 140.66 | F7: 140.66 | G7: 140.66 | H7: 140.66 | I7: 140.66 | J7: 140.66 | K7: 17.58
A8: Total Share Capital | B8: =SUM(B7) -> 140.66 | C8: =SUM(C7) -> 140.66 | D8: =SUM(D7) -> 140.66 | E8: =SUM(E7) -> 140.66 | F8: =SUM(F7) -> 140.66 | G8: =SUM(G7) -> 140.66 | H8: =SUM(H7) -> 140.66 | I8: =SUM(I7) -> 140.66 | ... L8: =SUM(L7) -> 0
A9: Reserves and Surplus | B9: 5576.75 | C9: 4836.78 | D9: 4271.47 | E9: 3779.33 | F9: 3421.45 | G9: 2865.38 | H9: 2424.02 | I9: 2032.19 | J9: 1588.67 | K9: 1432.23
A10: Total Reserves and Surplus | B10: =SUM(B8:B9) -> 5717.41 | C10: =SUM(C8:C9) -> 4977.44 | D10: =SUM(D8:D9) -> 4412.13 | E10: =SUM(E8:E9) -> 3919.99 | F10: =SUM(F8:F9) -> 3562.11 | G10: =SUM(G8:G9) -> 3006.04 | H10: =SUM(H8:H9) -> 2564.68 | I10: =SUM(I8:I9) -> 2172.85 | ... L10: =SUM(L8:L9) -> 0
A11: Employees Stock Options
A12: Total Shareholders Funds | B12: =SUM(B10:B11) -> 5717.41 | C12: =SUM(C10:C11) -> 4977.44 | D12: =SUM(D10:D11) -> 4412.13 | E12: =SUM(E10:E11) -> 3919.99 | F12: =SUM(F10:F11) -> 3562.11 | G12: =SUM(G10:G11) -> 3006.04 | H12: =SUM(H10:H11) -> 2564.68 | I12: =SUM(I10:I11) -> 2172.85 | ... L12: =SUM(L10:L11) -> 0
A13: Minority Interest | B13: 0 | C13: 0 | D13: 0 | E13: 0 | F13: 0.02
A14: NON-CURRENT LIABILITIES
A15: Long Term Borrowings | B15: 594.64 | C15: 480.25 | D15: 278.15 | E15: 193.92 | F15: 379.18 | G15: 402.09 | H15: 346.4 | I15: 380.33 | J15: 342.23 | K15: 416.27
A16: Deferred Tax Liabilities [Net] | B16: 13.35 | C16: 14.43 | D16: 0.52 | E16: 0.63 | F16: 0.51 | G16: 7.87 | H16: 16.13 | I16: 1.73 | J16: 0.78 | K16: 1.1
A17: Other Long Term Liabilities | B17: 48.6 | C17: 115.97 | D17: 116.4 | E17: 26.73 | F17: 8.98 | G17: 11.82 | H17: 8.42 | I17: 9.58 | J17: 6.35 | K17: 8.48
A18: Long Term Provisions | B18: 73.46 | C18: 60.18 | D18: 64.53 | E18: 59.15 | F18: 73.36 | G18: 77.67 | H18: 66.11 | I18: 19.65 | J18: 30.7 | K18: 30.31
A19: Total Non-Current Liabilities | B19: =SUM(B15:B18) -> 730.05 | C19: =SUM(C15:C18) -> 670.83 | D19: =SUM(D15:D18) -> 459.6 | E19: =SUM(E15:E18) -> 280.43 | F19: =SUM(F15:F18) -> 462.03 | G19: =SUM(G15:G18) -> 499.45 | H19: =SUM(H15:H18) -> 437.06 | I19: =SUM(I15:I18) -> 411.29 | ... L19: =SUM(L15:L18) -> 0
A20: CURRENT LIABILITIES
A21: Short Term Borrowings | B21: 309.22 | C21: 259.53 | D21: 205.18 | E21: 205.53 | F21: 45 | G21: 146.1 | H21: 212 | I21: 178.27 | J21: 173.59 | K21: 186.91
A22: Trade Payables | B22: 1974.26 | C22: 1604.47 | D22: 1425.74 | E22: 1241.35 | F22: 1278.33 | G22: 1066.23 | H22: 1173.46 | I22: 1128.42 | J22: 864.19 | K22: 738.53
A23: Other Current Liabilities | B23: 381.98 | C23: 348.98 | D23: 267.08 | E23: 182.07 | F23: 370.16 | G23: 318.69 | H23: 369.92 | I23: 431.35 | J23: 341.7 | K23: 434.38
A24: Short Term Provisions | B24: 26.35 | C24: 24.45 | D24: 32.74 | E24: 28.25 | F24: 29.89 | G24: 33.41 | H24: 28.92 | I24: 19.1 | J24: 22.38 | K24: 16.08
A25: Total Current Liabilities | B25: =SUM(B21:B24) -> 2691.81 | C25: =SUM(C21:C24) -> 2237.43 | D25: =SUM(D21:D24) -> 1930.74 | E25: =SUM(E21:E24) -> 1657.2 | F25: =SUM(F21:F24) -> 1723.38 | G25: =SUM(G21:G24) -> 1564.43 | H25: =SUM(H21:H24) -> 1784.3 | I25: =SUM(I21:I24) -> 1757.14 | ... L25: =SUM(L21:L24) -> 0
A26: Total Capital And Liabilities | B26: =B12+B13+B19+B25 -> 9139.27 | C26: =C12+C13+C19+C25 -> 7885.7 | D26: =D12+D13+D19+D25 -> 6802.47 | E26: =E12+E13+E19+E25 -> 5857.62 | F26: =F12+F13+F19+F25 -> 5747.54 | G26: =G12+G13+G19+G25 -> 5069.92 | H26: =H12+H13+H19+H25 -> 4786.04 | I26: =I12+I13+I19+I25 -> 4341.28 | ... L26: =L12+L13+L19+L25 -> 0
A28: ASSETS
A29: NON-CURRENT ASSETS
A30: Tangible Assets | B30: 3612.46 | C30: 3133.65 | D30: 2634.68 | E30: 2455.82 | F30: 2350.93 | G30: 2410.42 | H30: 1994.58 | I30: 1670.62 | J30: 1473.43 | K30: 1432.27
A31: Intangible Assets | B31: 105.18 | C31: 104.29 | D31: 118.16 | E31: 83.18 | F31: 77.66 | G31: 33.44 | H31: 16.57 | I31: 22.62 | J31: 24.78 | K31: 7.67
A32: Capital Work-In-Progress | B32: 290.15 | C32: 156.72 | D32: 168.36 | E32: 119.05 | F32: 92.99 | G32: 106.45 | H32: 106.29 | I32: 54.39 | J32: 43.42 | K32: 93.48
A33: Intangible Assets Under Development | B33: 2.82 | C33: 2.55 | D33: 2.53 | E33: 0.26 | F33: 3.17 | G33: 19.5 | H33: 11.51 | I33: 4.78 | J33: 0.4 | K33: 9.92
A34: Fixed Assets | B34: =SUM(B30:B33) -> 4010.61 | C34: =SUM(C30:C33) -> 3397.21 | D34: =SUM(D30:D33) -> 2923.73 | E34: =SUM(E30:E33) -> 2658.31 | F34: =SUM(F30:F33) -> 2524.75 | G34: =SUM(G30:G33) -> 2569.81 | H34: =SUM(H30:H33) -> 2128.95 | I34: =SUM(I30:I33) -> 1752.41 | ... L34: =SUM(L30:L33) -> 0
A35: Goodwill
A36: Non-Current Investments | B36: 15.68 | C36: 27.52 | D36: 25.47 | E36: 1.19 | F36: 1.2 | G36: 1.19 | H36: 1.28 | I36: 1.01 | J36: 1.02 | K36: 1.02
A37: Deferred Tax Assets [Net] | B37: 69.51 | C37: 78.27 | D37: 71.98 | E37: 75.14 | F37: 60.24 | G37: 32.08 | H37: 31.13 | I37: 11.99 | J37: 18.95 | K37: 19.65
A38: Long Term Loans And Advances | B38: 0 | C38: 0 | D38: 0 | E38: 0 | F38: 2.68 | G38: 156.83 | H38: 307.19 | I38: 268.03 | J38: 212.15 | K38: 228.76
A39: Other Non-Current Assets | B39: 109.07 | C39: 200.47 | D39: 199.38 | E39: 97.92 | F39: 80.5
A40: Total Non-Current Assets | B40: =SUM(B34:B39) -> 4204.87 | C40: =SUM(C34:C39) -> 3703.47 | D40: =SUM(D34:D39) -> 3220.56 | E40: =SUM(E34:E39) -> 2832.56 | F40: =SUM(F34:F39) -> 2669.37 | G40: =SUM(G34:G39) -> 2759.91 | H40: =SUM(H34:H39) -> 2468.55 | I40: =SUM(I34:I39) -> 2033.44 | ... L40: =SUM(L34:L39) -> 0
A41: CURRENT ASSETS
A42: Current Investments | B42: 787.93 | C42: 765.07 | D42: 646.37 | E42: 485.59 | F42: 443.14 | G42: 164.83 | H42: 34.82 | I42: 44.91 | J42: 31.64 | K42: 47.16
A43: Inventories | B43: 936.37 | C43: 872.21 | D43: 820.58 | E43: 701.14 | F43: 611.85 | G43: 550.1 | H43: 540.01 | I43: 493.85 | J43: 443.83 | K43: 409.86
A44: Trade Receivables | B44: 1418.58 | C44: 1262.38 | D44: 1162.03 | E44: 970.37 | F44: 1040.98 | G44: 672.74 | H44: 925.14 | I44: 968.82 | J44: 760.87 | K44: 592.79
A45: Cash And Cash Equivalents | B45: 1018.9 | C45: 504.68 | D45: 287.71 | E45: 402.64 | F45: 513.33 | G45: 620.95 | H45: 537.9 | I45: 502.72 | J45: 219.93 | K45: 167.42
A46: Short Term Loans And Advances | B46: 3.36 | C46: 2 | D46: 1.65 | E46: 3.72 | F46: 5.32 | G46: 2.01 | H46: 2.1 | I46: 1.3 | J46: 1.62 | K46: 0
A47: Other Current assets | B47: 428.77 | C47: 383.6 | D47: 273.53 | E47: 285.9 | F47: 289.61 | G47: 136.93 | H47: 125.56 | I47: 138.51 | J47: 143.72 | K47: 124.94
A48: Total Current Assets | B48: =SUM(B42:B47) -> 4593.91 | C48: =SUM(C42:C47) -> 3789.94 | D48: =SUM(D42:D47) -> 3191.87 | E48: =SUM(E42:E47) -> 2849.36 | F48: =SUM(F42:F47) -> 2904.23 | G48: =SUM(G42:G47) -> 2147.56 | H48: =SUM(H42:H47) -> 2165.53 | I48: =SUM(I42:I47) -> 2150.11 | ... L48: =SUM(L42:L47) -> 0
A49: Total Assets | B49: =B40+B48 -> 8798.78 | C49: =C40+C48 -> 7493.41 | D49: =D40+D48 -> 6412.43 | E49: =E40+E48 -> 5681.92 | F49: =F40+F48 -> 5573.6 | G49: =G40+G48 -> 4907.47 | H49: =H40+H48 -> 4634.08 | I49: =I40+I48 -> 4183.55 | ... L49: =L40+L48 -> 0 | M49: 556.71 | N49: 485.56 | O49: 461.07
M50: =B49-M49 -> 8242.07 | N50: =C49-N49 -> 7007.85 | O50: =D49-O49 -> 5951.36
A51: OTHER ADDITIONAL INFORMATION
A52: CONTINGENT LIABILITIES, COMMITMENTS
A53: Contingent Liabilities | B53: 401.04 | C53: 331.99 | D53: 837.19 | E53: 830.71 | F53: 480.42 | G53: 321.54 | H53: 448.36 | I53: 420.01 | J53: 188.83 | K53: 359.94
A54: CIF VALUE OF IMPORTS
A55: EXPENDITURE IN FOREIGN EXCHANGE
A56: REMITTANCES IN FOREIGN CURRENCIES FOR DIVIDENDS
A57: Dividend Remittance In Foreign Currency
A58: EARNINGS IN FOREIGN EXCHANGE
A59: FOB Value Of Goods
A60: Other Earnings
A61: BONUS DETAILS
A62: Bonus Equity Share Capital | B62: 123.66 | C62: 123.66 | D62: 123.66 | E62: 123.66 | F62: 123.66 | G62: 123.66 | H62: 123.66 | I62: 123.66 | J62: 123.66 | K62: 0.58
A63: NON-CURRENT INVESTMENTS
A64: Non-Current Investments Quoted Market Value | B64: 9.77 | C64: 24.13 | D64: 0 | E64: 0 | F64: 0 | G64: 0 | H64: 0 | I64: 0 | J64: 0.01 | K64: 0.01
A65: Non-Current Investments Unquoted Book Value | B65: 5.91 | C65: 3.39 | D65: 3.22 | E65: 1.19 | F65: 1.19 | G65: 1.19 | H65: 1.28 | I65: 1.01 | J65: 1.01 | K65: 1.01
A66: CURRENT INVESTMENTS
A67: Current Investments Quoted Market Value
A68: Current Investments Unquoted Book Value | B68: 53.7 | C68: 0 | D68: 0 | E68: 0 | F68: 443.14 | G68: 164.83 | H68: 34.82 | I68: 44.91 | J68: 31.64 | K68: 47.16
A70: Consol Profit & Loss account
A72: INCOME | B72: Mar 25 | C72: Mar 24 | D72: 45016 | E72: 44651 | F72: 44286 | G72: 43921 | H72: 43555 | I72: 43190 | J72: 42825 | K72: 42460 | L72: 42094
A73: Revenue From Operations [Gross] | B73: 11371.37 | C73: 10082.5 | D73: 8676.06 | E73: 7424.4 | F73: 6405.48 | G73: 6775.39 | H73: 7411.06 | I73: 6422.92 | J73: 5887.65 | K73: 5528.94
A74: Less: Excise/Sevice Tax/Other Levies | G74: 0 | H74: 0 | I74: -127.91 | J74: -400.33 | K74: -387.25
A75: Revenue From Operations [Net] | B75: =SUM(B73:B74) -> 11371.37 | C75: =SUM(C73:C74) -> 10082.5 | D75: =SUM(D73:D74) -> 8676.06 | E75: =SUM(E73:E74) -> 7424.4 | F75: =SUM(F73:F74) -> 6405.48 | G75: =SUM(G73:G74) -> 6775.39 | H75: =SUM(H73:H74) -> 7411.06 | I75: =SUM(I73:I74) -> 6295.01 | ... L75: =SUM(L73:L74) -> 0
A76: Other Operating Revenues | B76: 189.44 | C76: 158.37 | D76: 127.99 | E76: 124.75 | F76: 141.54 | G76: 142.31 | H76: 99.44 | I76: 56.37 | J76: 103.55 | K76: 88.68
A77: Total Operating Revenues | B77: =SUM(B75:B76) -> 11560.81 | C77: =SUM(C75:C76) -> 10240.87 | D77: =SUM(D75:D76) -> 8804.05 | E77: =SUM(E75:E76) -> 7549.15 | F77: =SUM(F75:F76) -> 6547.02 | G77: =SUM(G75:G76) -> 6917.7 | H77: =SUM(H75:H76) -> 7510.5 | I77: =SUM(I75:I76) -> 6351.38 | ... L77: =SUM(L75:L76) -> 0
A78: Other Income | B78: 116.97 | C78: 85.62 | D78: 45.43 | E78: 41.04 | F78: 30.71 | G78: 47.6 | H78: 27.05 | I78: 23.47 | J78: 29.07 | K78: 32.96
A79: Total Revenue | B79: =SUM(B77:B78) -> 11677.78 | C79: =SUM(C77:C78) -> 10326.49 | D79: =SUM(D77:D78) -> 8849.48 | E79: =SUM(E77:E78) -> 7590.19 | F79: =SUM(F77:F78) -> 6577.73 | G79: =SUM(G77:G78) -> 6965.3 | H79: =SUM(H77:H78) -> 7537.55 | I79: =SUM(I77:I78) -> 6374.85 | ... L79: =SUM(L77:L78) -> 0
A80: EXPENSES
A81: COGS | B81: 6504.87 | C81: 5922.96 | D81: 5320.19 | E81: 4428.43 | F81: 3497.65 | G81: 3704.52 | H81: 4327.84 | I81: 3669.95 | J81: 3257.16 | K81: 3139.97
A82: Purchase Of Stock-In Trade | B82: 111.75 | C82: 140.91 | D82: 103.97 | E82: 86.38 | F82: 89.62 | G82: 27.84 | H82: 23.08 | I82: 9.09 | J82: 9.81 | K82: 7.86
A83: Changes In Inventories Of FG,WIP And Stock-In Trade | B83: -13.51 | C83: -13.29 | D83: -94.64 | E83: -94.66 | F83: -16.71 | G83: 2.85 | H83: -1.47 | I83: -18.13 | J83: -41.02 | K83: -33.7
A84: Employee Benefit Expenses | B84: 1007.35 | C84: 879.9 | D84: 763.61 | E84: 694.36 | F84: 676.06 | G84: 677.33 | H84: 652.74 | I84: 580.93 | J84: 545.52 | K84: 482.3
A85: Finance Costs | B85: 46.81 | C85: 42.66 | D85: 20.58 | E85: 6.35 | F85: 13.76 | G85: 17.54 | H85: 25.73 | I85: 23.52 | J85: 32.25 | K85: 48.96
A86: Depreciation And Amortisation Expenses | B86: 538.71 | C86: 473.99 | D86: 421.58 | E86: 381.73 | F86: 399.14 | G86: 414.28 | H86: 376.21 | I86: 321.59 | J86: 290.51 | K86: 243.17
A87: Other Expenses | B87: 2399.27 | C87: 1982.42 | D87: 1674.65 | E87: 1470 | F87: 1260.19 | G87: 1382.66 | H87: 1391.45 | I87: 1181.68 | J87: 1061.08 | K87: 954.43
A88: Less: Amounts Transfer To Capital Accounts | G88: -8.26 | H88: -11.92 | I88: 0 | J88: 0 | K88: 0
A89: Total Expenses | B89: =SUM(B81:B88) -> 10595.25 | C89: =SUM(C81:C88) -> 9429.55 | D89: =SUM(D81:D88) -> 8209.94 | E89: =SUM(E81:E88) -> 6972.59 | F89: =SUM(F81:F88) -> 5919.71 | G89: =SUM(G81:G88) -> 6218.76 | H89: =SUM(H81:H88) -> 6783.66 | I89: =SUM(I81:I88) -> 5768.63 | ... L89: =SUM(L81:L88) -> 0
N90: 0.141367
A91: Profit/Loss Before Exceptional, ExtraOrdinary Items And Tax | B91: =B79-B89 -> 1082.53 | C91: =C79-C89 -> 896.94 | D91: =D79-D89 -> 639.54 | E91: =E79-E89 -> 617.6 | F91: =F79-F89 -> 658.02 | G91: =G79-G89 -> 746.54 | H91: =H79-H89 -> 753.89 | I91: =I79-I89 -> 606.22 | ... L91: =L79-L89 -> 0 | M91: =C91/L91*100 -> #DIV/0! | N91: =L91*(1+N90)^10 -> 0
A92: Exceptional Items | B92: 12.18 | C92: 0 | D92: -10.29 | E92: -31.45 | F92: -11.23 | G92: 0 | H92: -20.8 | I92: -26.88 | J92: 0 | K92: 0
A93: Profit/Loss Before Tax | B93: =SUM(B91:B92) -> 1094.71 | C93: =SUM(C91:C92) -> 896.94 | D93: =SUM(D91:D92) -> 629.25 | E93: =SUM(E91:E92) -> 586.15 | F93: =SUM(F91:F92) -> 646.79 | G93: =SUM(G91:G92) -> 746.54 | H93: =SUM(H91:H92) -> 733.09 | I93: =SUM(I91:I92) -> 579.34 | ... L93: =SUM(L91:L92) -> 0
A94: Current Tax | B94: 247.49 | C94: 209.68 | D94: 153.55 | E94: 147.4 | F94: 156.3 | G94: 188.31 | H94: 233.94 | I94: 186.53 | J94: 135.5 | K94: 116.9
A95: Less: MAT Credit Entitlement
A96: Tax For Earlier Years | B96: -2.16 | C96: -12.51 | D96: -3.27 | E96: 0.05 | F96: 0 | G96: -1.28 | H96: 0.82 | I96: -7.47 | J96: -1.78 | K96: 0
A97: Deferred Tax | B97: 13.03 | C97: 19.29 | D97: -0.61 | E97: -22.01 | F97: -29.07 | G97: -6.02 | H97: 3.32 | I97: 9.52 | J97: 0.62 | K97: 2.98
A98: Total Tax Expenses | B98: =B93-SUM(B94:B97) -> 836.35 | C98: =C93-SUM(C94:C97) -> 680.48 | D98: =D93-SUM(D94:D97) -> 479.58 | E98: =E93-SUM(E94:E97) -> 460.71 | F98: =F93-SUM(F94:F97) -> 519.56 | G98: =G93-SUM(G94:G97) -> 565.53 | H98: =H93-SUM(H94:H97) -> 495.01 | I98: =I93-SUM(I94:I97) -> 390.76 | ... L98: =L93-SUM(L94:L97) -> 0
A99: Profit/Loss After Tax And Before ExtraOrdinary Items | B99: =B98 -> 836.35 | C99: =C98 -> 680.48 | D99: =D98 -> 479.58 | E99: =E98 -> 460.71 | F99: =F98 -> 519.56 | G99: =G98 -> 565.53 | H99: =H98 -> 495.01 | I99: =I98 -> 390.76 | ... L99: =L98 -> 0
A100: Extraordinary Items
A101: Profit/Loss From Continuing Operations | B101: =SUM(B99:B100) -> 836.35 | C101: =SUM(C99:C100) -> 680.48 | D101: =SUM(D99:D100) -> 479.58 | E101: =SUM(E99:E100) -> 460.71 | F101: =SUM(F99:F100) -> 519.56 | G101: =SUM(G99:G100) -> 565.53 | H101: =SUM(H99:H100) -> 495.01 | I101: =SUM(I99:I100) -> 390.76 | ... L101: =SUM(L99:L100) -> 0
A102: Profit/Loss For The Period | B102: =SUM(B101) -> 836.35 | C102: =SUM(C101) -> 680.48 | D102: =SUM(D101) -> 479.58 | E102: =SUM(E101) -> 460.71 | F102: =SUM(F101) -> 519.56 | G102: =SUM(G101) -> 565.53 | H102: =SUM(H101) -> 495.01 | I102: =SUM(I101) -> 390.76 | ... L102: =SUM(L101) -> 0
A103: Minority Interest | B103: 0 | C103: 0 | D103: 0 | E103: 0 | F103: 0.14 | G103: 0 | H103: 0 | I103: 0 | J103: 0 | K103: -1.09
A104: Share Of Profit/Loss Of Associates
A105: Consolidated Profit/Loss After MI And Associates | B105: =SUM(B102:B104) -> 836.35 | C105: =SUM(C102:C104) -> 680.48 | D105: =SUM(D102:D104) -> 479.58 | E105: =SUM(E102:E104) -> 460.71 | F105: =SUM(F102:F104) -> 519.7 | G105: =SUM(G102:G104) -> 565.53 | H105: =SUM(H102:H104) -> 495.01 | I105: =SUM(I102:I104) -> 390.76 | ... L105: =SUM(L102:L104) -> 0 | M105: =C105/L105*100 -> #DIV/0!
...

Sheet Sheet3
A1: Endurance Technologies | B1: Previous Years �
A2: Consolidated Balance Sheet | B2: ------------------- in Rs. Cr. -------------------
B3: Mar 25 | C3: 45352 | D3: 44986 | E3: 44621 | F3: 44256
A4: #VALUE!
B5: 12 mths | C5: 12 mths | D5: 12 mths | E5: 12 mths | F5: 12 mths
A6: #VALUE!
A7: EQUITIES AND LIABILITIES
A8: SHAREHOLDER'S FUNDS
A9: Equity Share Capital | B9: 140.66 | C9: 140.66 | D9: 140.66 | E9: 140.66 | F9: 140.66
A10: Total Share Capital | B10: 140.66 | C10: 140.66 | D10: 140.66 | E10: 140.66 | F10: 140.66
A11: Reserves and Surplus | B11: 5576.75 | C11: 4836.78 | D11: 4271.47 | E11: 3779.33 | F11: 3421.45
A12: Total Reserves and Surplus | B12: 5576.75 | C12: 4836.78 | D12: 4271.47 | E12: 3779.33 | F12: 3421.45
A13: Total Shareholders Funds | B13: 5717.42 | C13: 4977.44 | D13: 4412.13 | E13: 3919.99 | F13: 3562.12
A14: Minority Interest | B14: 0 | C14: 0 | D14: 0 | E14: 0 | F14: 0.02
A15: NON-CURRENT LIABILITIES
A16: Long Term Borrowings | B16: 594.64 | C16: 480.25 | D16: 278.15 | E16: 193.92 | F16: 379.18
A17: Deferred Tax Liabilities [Net] | B17: 13.35 | C17: 14.43 | D17: 0.52 | E17: 0.63 | F17: 0.51
A18: Other Long Term Liabilities | B18: 48.6 | C18: 115.97 | D18: 116.4 | E18: 26.73 | F18: 8.98
A19: Long Term Provisions | B19: 73.46 | C19: 60.18 | D19: 64.53 | E19: 59.15 | F19: 73.36
A20: Total Non-Current Liabilities | B20: 730.05 | C20: 670.83 | D20: 459.59 | E20: 280.43 | F20: 462.03
A21: CURRENT LIABILITIES
A22: Short Term Borrowings | B22: 309.22 | C22: 259.53 | D22: 205.18 | E22: 205.53 | F22: 45
A23: Trade Payables | B23: 1974.26 | C23: 1604.47 | D23: 1425.74 | E23: 1241.35 | F23: 1278.33
A24: Other Current Liabilities | B24: 381.98 | C24: 348.98 | D24: 267.08 | E24: 182.07 | F24: 370.16
A25: Short Term Provisions | B25: 26.35 | C25: 24.45 | D25: 32.74 | E25: 28.25 | F25: 29.89
A26: Total Current Liabilities | B26: 2691.81 | C26: 2237.43 | D26: 1930.73 | E26: 1657.19 | F26: 1723.38
A27: Total Capital And Liabilities | B27: 9139.28 | C27: 7885.69 | D27: 6802.45 | E27: 5857.62 | F27: 5747.55
A28: ASSETS
A29: NON-CURRENT ASSETS
A30: Tangible Assets | B30: 3612.46 | C30: 3133.65 | D30: 2634.68 | E30: 2455.82 | F30: 2350.93
A31: Intangible Assets | B31: 105.18 | C31: 104.29 | D31: 118.16 | E31: 83.18 | F31: 77.66
A32: Capital Work-In-Progress | B32: 290.15 | C32: 156.72 | D32: 168.36 | E32: 119.05 | F32: 92.99
A33: Intangible Assets Under Development | B33: 2.82 | C33: 2.55 | D33: 2.53 | E33: 0.26 | F33: 3.17
A34: Fixed Assets | B34: 4010.6 | C34: 3397.21 | D34: 2923.74 | E34: 2658.32 | F34: 2524.74
A35: Non-Current Investments | B35: 15.68 | C35: 27.52 | D35: 25.47 | E35: 1.19 | F35: 1.2
A36: Deferred Tax Assets [Net] | B36: 69.51 | C36: 78.27 | D36: 71.98 | E36: 75.14 | F36: 60.24
A37: Long Term Loans And Advances | B37: 0 | C37: 0 | D37: 0 | E37: 0 | F37: 2.68
A38: Other Non-Current Assets | B38: 109.07 | C38: 200.47 | D38: 199.38 | E38: 97.92 | F38: 80.5
A39: Total Non-Current Assets | B39: 4545.38 | C39: 4095.76 | D39: 3610.58 | E39: 3008.26 | F39: 2843.34
A40: CURRENT ASSETS
A41: Current Investments | B41: 787.93 | C41: 765.07 | D41: 646.37 | E41: 485.59 | F41: 443.14
A42: Inventories | B42: 936.37 | C42: 872.21 | D42: 820.58 | E42: 701.14 | F42: 611.85
A43: Trade Receivables | B43: 1418.58 | C43: 1262.38 | D43: 1162.03 | E43: 970.37 | F43: 1040.98
A44: Cash And Cash Equivalents | B44: 1018.9 | C44: 504.68 | D44: 287.71 | E44: 402.64 | F44: 513.33
A45: Short Term Loans And Advances | B45: 3.36 | C45: 2 | D45: 1.65 | E45: 3.72 | F45: 5.32
A46: OtherCurrentAssets | B46: 428.77 | C46: 383.6 | D46: 273.53 | E46: 285.9 | F46: 289.61
A47: Total Current Assets | B47: 4593.9 | C47: 3789.93 | D47: 3191.88 | E47: 2849.36 | F47: 2904.21
A48: Total Assets | B48: 9139.28 | C48: 7885.69 | D48: 6802.45 | E48: 5857.62 | F48: 5747.55
A49: OTHER ADDITIONAL INFORMATION
A50: CONTINGENT LIABILITIES, COMMITMENTS
A51: Contingent Liabilities | B51: 401.04 | C51: 331.99 | D51: 837.19 | E51: 830.71 | F51: 480.42
A52: BONUS DETAILS
A53: Bonus Equity Share Capital | B53: 123.66 | C53: 123.66 | D53: 123.66 | E53: 123.66 | F53: 123.66
A54: NON-CURRENT INVESTMENTS
A55: Non-Current Investments Quoted Market Value | B55: 9.77 | C55: 24.13 | D55: 0 | E55: 0 | F55: 0
A56: Non-Current Investments Unquoted Book Value | B56: 5.91 | C56: 3.39 | D56: 3.22 | E56: 1.19 | F56: 1.19
A57: CURRENT INVESTMENTS
A58: Current Investments Unquoted Book Value | B58: 53.7 | C58: 0 | D58: 0 | E58: 0 | F58: 443.14
A61: Endurance Technologies | B61: Previous Years � | G61: � Next Years Previous Years �
A62: Consolidated Profit & Loss account | B62: ------------------- in Rs. Cr. ------------------- | G62: ------------------- in Rs. Cr. -------------------
B63: Mar 25 | C63: 45352 | D63: 44986 | E63: 44621 | F63: 44256 | G63: Mar 20 | H63: 43525 | I63: 43160 | J63: 42795 | K63: 42430
A64: #VALUE!
B65: 12 mths | C65: 12 mths | D65: 12 mths | E65: 12 mths | F65: 12 mths | G65: 12 mths | H65: 12 mths | I65: 12 mths | J65: 12 mths | K65: 12 mths
A66: #VALUE!
A67: INCOME
A68: Revenue From Operations [Gross] | B68: 11371.37 | C68: 10082.5 | D68: 8676.06 | E68: 7424.4 | F68: 6405.48 | G68: 6775.39 | H68: 7411.06 | I68: 6422.92 | J68: 5887.65 | K68: 5528.94
A69: Less: Excise/Sevice Tax/Other Levies | G69: 0 | H69: 0 | I69: 127.91 | J69: 400.33 | K69: 387.25
A70: Revenue From Operations [Net] | B70: 11371.37 | C70: 10082.5 | D70: 8676.06 | E70: 7424.4 | F70: 6405.48 | G70: 6775.39 | H70: 7411.06 | I70: 6295.01 | J70: 5487.32 | K70: 5141.7
A71: Other Operating Revenues | B71: 189.44 | C71: 158.37 | D71: 127.99 | E71: 124.75 | F71: 141.54 | G71: 142.31 | H71: 99.44 | I71: 56.37 | J71: 103.55 | K71: 88.68
A72: Total Operating Revenues | B72: 11560.81 | C72: 10240.87 | D72: 8804.05 | E72: 7549.14 | F72: 6547.02 | G72: 6917.71 | H72: 7510.5 | I72: 6351.38 | J72: 5590.87 | K72: 5230.37
A73: Other Income | B73: 116.97 | C73: 85.62 | D73: 45.43 | E73: 41.04 | F73: 30.71 | G73: 47.6 | H73: 27.05 | I73: 23.47 | J73: 29.07 | K73: 32.96
A74: Total Revenue | B74: 11677.78 | C74: 10326.49 | D74: 8849.47 | E74: 7590.18 | F74: 6577.73 | G74: 6965.3 | H74: 7537.55 | I74: 6374.85 | J74: 5619.94 | K74: 5263.33
A75: EXPENSES
A76: Cost Of Materials Consumed | B76: 6504.87 | C76: 5922.96 | D76: 5320.19 | E76: 4428.43 | F76: 3497.65 | G76: 3704.52 | H76: 4327.84 | I76: 3669.95 | J76: 3257.16 | K76: 3139.97
A77: Purchase Of Stock-In Trade | B77: 111.75 | C77: 140.91 | D77: 103.97 | E77: 86.38 | F77: 89.62 | G77: 27.84 | H77: 23.08 | I77: 9.09 | J77: 9.81 | K77: 7.86
A78: Changes In Inventories Of FG,WIP And Stock-In Trade | B78: -13.51 | C78: -13.29 | D78: -94.64 | E78: -94.66 | F78: -16.71 | G78: 2.85 | H78: -1.47 | I78: -18.13 | J78: -41.02 | K78: -33.7
A79: Employee Benefit Expenses | B79: 1007.35 | C79: 879.9 | D79: 763.61 | E79: 694.36 | F79: 676.06 | G79: 677.33 | H79: 652.74 | I79: 580.93 | J79: 545.52 | K79: 482.3
A80: Finance Costs | B80: 46.81 | C80: 42.66 | D80: 20.58 | E80: 6.35 | F80: 13.76 | G80: 17.54 | H80: 25.73 | I80: 23.52 | J80: 32.25 | K80: 48.96
A81: Depreciation And Amortisation Expenses | B81: 538.71 | C81: 473.99 | D81: 421.58 | E81: 381.73 | F81: 399.14 | G81: 414.28 | H81: 376.21 | I81: 321.59 | J81: 290.51 | K81: 243.17
A82: Other Expenses | B82: 2399.27 | C82: 1982.42 | D82: 1674.65 | E82: 1470 | F82: 1260.19 | G82: 1382.66 | H82: 1391.45 | I82: 1181.68 | J82: 1061.08 | K82: 954.43
A83: Less: Amounts Transfer To Capital Accounts | G83: -8.26 | H83: -11.92 | I83: 0 | J83: 0 | K83: 0
A84: Total Expenses | B84: 10595.25 | C84: 9429.54 | D84: 8209.94 | E84: 6972.58 | F84: 5919.7 | G84: 6218.76 | H84: 6783.67 | I84: 5768.63 | J84: 5155.29 | K84: 4843.01
A85: Profit/Loss Before Exceptional, ExtraOrdinary Items And Tax | B85: 1082.53 | C85: 896.95 | D85: 639.54 | E85: 617.6 | F85: 658.03 | G85: 746.55 | H85: 753.88 | I85: 606.22 | J85: 464.65 | K85: 420.33
A86: Exceptional Items | B86: 12.18 | C86: 0 | D86: -10.29 | E86: -31.45 | F86: -11.23 | G86: 0 | H86: -20.8 | I86: -26.88 | J86: 0 | K86: 0
A87: Profit/Loss Before Tax | B87: 1094.71 | C87: 896.95 | D87: 629.25 | E87: 586.15 | F87: 646.8 | G87: 746.55 | H87: 733.08 | I87: 579.34 | J87: 464.65 | K87: 420.33
A88: Tax Expenses-Continued Operations
A89: Current Tax | B89: 247.49 | C89: 209.68 | D89: 153.55 | E89: 147.4 | F89: 156.3 | G89: 188.31 | H89: 233.94 | I89: 186.53 | J89: 135.5 | K89: 116.9
A90: Deferred Tax | B90: 13.03 | C90: 19.29 | D90: -0.61 | E90: -22.01 | F90: -29.07 | G90: -6.02 | H90: 3.32 | I90: 9.52 | J90: 0.62 | K90: 2.98
A91: Tax For Earlier Years | B91: -2.16 | C91: -12.51 | D91: -3.27 | E91: 0.05 | F91: 0 | G91: -1.28 | H91: 0.82 | I91: -7.47 | J91: -1.78 | K91: 0
A92: Total Tax Expenses | B92: 258.36 | C92: 216.46 | D92: 149.68 | E92: 125.44 | F92: 127.23 | G92: 181.01 | H92: 238.07 | I92: 188.58 | J92: 134.34 | K92: 119.88
A93: Profit/Loss After Tax And Before ExtraOrdinary Items | B93: 836.35 | C93: 680.49 | D93: 479.58 | E93: 460.71 | F93: 519.57 | G93: 565.53 | H93: 495.01 | I93: 390.76 | J93: 330.31 | K93: 300.45
A94: Profit/Loss From Continuing Operations | B94: 836.35 | C94: 680.49 | D94: 479.58 | E94: 460.71 | F94: 519.57 | G94: 565.53 | H94: 495.01 | I94: 390.76 | J94: 330.31 | K94: 300.45
A95: Profit/Loss For The Period | B95: 836.35 | C95: 680.49 | D95: 479.58 | E95: 460.71 | F95: 519.57 | G95: 565.53 | H95: 495.01 | I95: 390.76 | J95: 330.31 | K95: 300.45
A96: Minority Interest | B96: 0 | C96: 0 | D96: 0 | E96: 0 | F96: 0.14 | G96: 0 | H96: 0 | I96: 0 | J96: 0 | K96: -1.09
A97: Consolidated Profit/Loss After MI And Associates | B97: 836.35 | C97: 680.49 | D97: 479.58 | E97: 460.71 | F97: 519.71 | G97: 565.53 | H97: 495.01 | I97: 390.76 | J97: 330.31 | K97: 299.36
A98: OTHER ADDITIONAL INFORMATION
A99: EARNINGS PER SHARE
A100: Basic EPS (Rs.) | B100: 59 | C100: 48 | D100: 34 | E100: 33 | F100: 37 | G100: 40 | H100: 35 | I100: 28 | J100: 23 | K100: 21
A101: Diluted EPS (Rs.) | B101: 59 | C101: 48 | D101: 34 | E101: 33 | F101: 37 | G101: 40 | H101: 35 | I101: 28 | J101: 23 | K101: 21
A102: DIVIDEND AND DIVIDEND PERCENTAGE
...

Sheet Common Size Analysis - PL_Conso
A1: Endurance Technologies | I1: Endurance Technologies
A2: Income Statement | I2: Common-Size Income Statement
A3: (Rs Crore) | B3: 45717 | C3: 45352 | D3: 44986 | E3: 44621 | F3: 44256 | G3: 43891 | J3: 45717 | K3: 45352 | L3: 44986 | M3: 44621 | N3: 44256 | O3: 43891
A4: Revenue from Operations | I4: Revenue from Operations
A5: Gross Sales of Products | B5: =Financials_Consol!B73 -> 11371.37 | C5: =Financials_Consol!C73 -> 10082.5 | D5: =Financials_Consol!D73 -> 8676.06 | E5: =Financials_Consol!E73 -> 7424.4 | F5: =Financials_Consol!F73 -> 6405.48 | G5: =Financials_Consol!G73 -> 6775.39 | I5: Gross Sales of Products | J5: 1 | K5: 1 | L5: 1 | M5: 1 | N5: 1 | O5: 1
A6: Less - Excise Duty | B6: =Financials_Consol!B74 -> 0 | C6: =Financials_Consol!C74 -> 0 | D6: =Financials_Consol!D74 -> 0 | E6: =Financials_Consol!E74 -> 0 | F6: =Financials_Consol!F74 -> 0 | G6: =Financials_Consol!G74 -> 0 | I6: Less - Excise Duty | J6: =B6/B$5 -> 0 | K6: =C6/C$5 -> 0 | L6: =D6/D$5 -> 0 | M6: =E6/E$5 -> 0 | N6: =F6/F$5 -> 0 | O6: =G6/G$5 -> 0
A7: Other Operating Revenue | B7: =Financials_Consol!B76 -> 189.44 | C7: =Financials_Consol!C76 -> 158.37 | D7: =Financials_Consol!D76 -> 127.99 | E7: =Financials_Consol!E76 -> 124.75 | F7: =Financials_Consol!F76 -> 141.54 | G7: =Financials_Consol!G76 -> 142.31 | I7: Other Operating Revenue | J7: =B7/B$5 -> 0.016659382 | K7: =C7/C$5 -> 0.015707414 | L7: =D7/D$5 -> 0.014752088 | M7: =E7/E$5 -> 0.016802705 | N7: =F7/F$5 -> 0.022096705 | O7: =G7/G$5 -> 0.021003957
A8: Net Revenue from Operations (A) | B8: =B5-B6+B7 -> 11560.81 | C8: =C5-C6+C7 -> 10240.87 | D8: =D5-D6+D7 -> 8804.05 | E8: =E5-E6+E7 -> 7549.15 | F8: =F5-F6+F7 -> 6547.02 | G8: =G5-G6+G7 -> 6917.7 | I8: Net Revenue from Operations (A) | J8: =B8/B$8 -> 1 | K8: =C8/C$8 -> 1 | L8: =D8/D$8 -> 1 | M8: =E8/E$8 -> 1 | N8: =F8/F$8 -> 1 | O8: =G8/G$8 -> 1
A10: Other Income (B) | B10: =Financials_Consol!B78 -> 116.97 | C10: =Financials_Consol!C78 -> 85.62 | D10: =Financials_Consol!D78 -> 45.43 | E10: =Financials_Consol!E78 -> 41.04 | F10: =Financials_Consol!F78 -> 30.71 | G10: =Financials_Consol!G78 -> 47.6 | I10: Other Income (B) | J10: =B10/B$5 -> 0.01028636 | K10: =C10/C$5 -> 0.0084919415 | L10: =D10/D$5 -> 0.0052362478 | M10: =E10/E$5 -> 0.0055277194 | N10: =F10/F$5 -> 0.0047943324 | O10: =G10/G$5 -> 0.0070254258
A12: Less: Expenses | I12: Less: Expenses
A13: COGS | B13: =Financials_Consol!B81 -> 6504.87 | C13: =Financials_Consol!C81 -> 5922.96 | D13: =Financials_Consol!D81 -> 5320.19 | E13: =Financials_Consol!E81 -> 4428.43 | F13: =Financials_Consol!F81 -> 3497.65 | G13: =Financials_Consol!G81 -> 3704.52 | I13: Cost of Materials Consumed | J13: =B13/B$8 -> 0.56266559 | K13: =C13/C$8 -> 0.57836492 | L13: =D13/D$8 -> 0.60428894 | M13: =E13/E$8 -> 0.58661306 | N13: =F13/F$8 -> 0.53423542 | O13: =G13/G$8 -> 0.53551325
A14: Purchase Of Stock-In Trade | B14: =Financials_Consol!B82 -> 111.75 | C14: =Financials_Consol!C82 -> 140.91 | D14: =Financials_Consol!D82 -> 103.97 | E14: =Financials_Consol!E82 -> 86.38 | F14: =Financials_Consol!F82 -> 89.62 | G14: =Financials_Consol!G82 -> 27.84 | I14: Purchase Of Stock-In Trade | J14: =B14/B$8 -> 0.0096662777 | K14: =C14/C$8 -> 0.013759573 | L14: =D14/D$8 -> 0.011809338 | M14: =E14/E$8 -> 0.011442348 | N14: =F14/F$8 -> 0.013688671 | O14: =G14/G$8 -> 0.004024459
A15: Changes In Inventories Of FG,WIP And Stock-In Trade | B15: =Financials_Consol!B83 -> -13.51 | C15: =Financials_Consol!C83 -> -13.29 | D15: =Financials_Consol!D83 -> -94.64 | E15: =Financials_Consol!E83 -> -94.66 | F15: =Financials_Consol!F83 -> -16.71 | G15: =Financials_Consol!G83 -> 2.85 | I15: Changes in Inventories | J15: =B15/B$8 -> -0.0011686032 | K15: =C15/C$8 -> -0.0012977413 | L15: =D15/D$8 -> -0.010749598 | M15: =E15/E$8 -> -0.01253916 | N15: =F15/F$8 -> -0.0025523062 | O15: =G15/G$8 -> 0.00041198664
A16: Employee Benefit Expenses | B16: =Financials_Consol!B84 -> 1007.35 | C16: =Financials_Consol!C84 -> 879.9 | D16: =Financials_Consol!D84 -> 763.61 | E16: =Financials_Consol!E84 -> 694.36 | F16: =Financials_Consol!F84 -> 676.06 | G16: =Financials_Consol!G84 -> 677.33 | I16: Employee Benefits Expenses | J16: =B16/B$8 -> 0.087134898 | K16: =C16/C$8 -> 0.085920434 | L16: =D16/D$8 -> 0.086733946 | M16: =E16/E$8 -> 0.091978567 | N16: =F16/F$8 -> 0.10326225 | O16: =G16/G$8 -> 0.097912601
A17: Finance Costs | B17: =Financials_Consol!B85 -> 46.81 | C17: =Financials_Consol!C85 -> 42.66 | D17: =Financials_Consol!D85 -> 20.58 | E17: =Financials_Consol!E85 -> 6.35 | F17: =Financials_Consol!F85 -> 13.76 | G17: =Financials_Consol!G85 -> 17.54 | I17: Finance costs | J17: =B17/B$8 -> 0.0040490242 | K17: =C17/C$8 -> 0.0041656617 | L17: =D17/D$8 -> 0.0023375606 | M17: =E17/E$8 -> 0.0008411543 | N17: =F17/F$8 -> 0.0021017196 | O17: =G17/G$8 -> 0.0025355248
A18: Depreciation And Amortisation Expenses | B18: =Financials_Consol!B86 -> 538.71 | C18: =Financials_Consol!C86 -> 473.99 | D18: =Financials_Consol!D86 -> 421.58 | E18: =Financials_Consol!E86 -> 381.73 | F18: =Financials_Consol!F86 -> 399.14 | G18: =Financials_Consol!G86 -> 414.28 | I18: Depreciation and Amortisation Expenses | J18: =B18/B$8 -> 0.046597946 | K18: =C18/C$8 -> 0.046284154 | L18: =D18/D$8 -> 0.04788478 | M18: =E18/E$8 -> 0.050565958 | N18: =F18/F$8 -> 0.060965141 | O18: =G18/G$8 -> 0.059886957
A19: Other Expenses | B19: =Financials_Consol!B87 -> 2399.27 | C19: =Financials_Consol!C87 -> 1982.42 | D19: =Financials_Consol!D87 -> 1674.65 | E19: =Financials_Consol!E87 -> 1470 | F19: =Financials_Consol!F87 -> 1260.19 | G19: =Financials_Consol!G87 -> 1382.66 | I19: Other expenses | J19: =B19/B$8 -> 0.20753477 | K19: =C19/C$8 -> 0.19357926 | L19: =D19/D$8 -> 0.19021359 | M19: =E19/E$8 -> 0.19472391 | N19: =F19/F$8 -> 0.19248299 | O19: =G19/G$8 -> 0.19987279
A20: Less: Amounts Transfer To Capital Accounts | B20: =Financials_Consol!B88 -> 0 | C20: =Financials_Consol!C88 -> 0 | D20: =Financials_Consol!D88 -> 0 | E20: =Financials_Consol!E88 -> 0 | F20: =Financials_Consol!F88 -> 0 | G20: =Financials_Consol!G88 -> -8.26
A21: Total Expenses (C) | B21: =SUM(B13:B20) -> 10595.25 | C21: =SUM(C13:C20) -> 9429.55 | D21: =SUM(D13:D20) -> 8209.94 | E21: =SUM(E13:E20) -> 6972.59 | F21: =SUM(F13:F20) -> 5919.71 | G21: =SUM(G13:G20) -> 6218.76 | I21: Total Expenses (C) | J21: =B21/B$8 -> 0.9164799 | K21: =C21/C$8 -> 0.92077626 | L21: =D21/D$8 -> 0.93251856 | M21: =E21/E$8 -> 0.92362584 | N21: =F21/F$8 -> 0.90418389 | O21: =G21/G$8 -> 0.89896353
A23: Profit before Taxes (D = A+B-C) | B23: =B8+B10-B21 -> 1082.53 | C23: =C8+C10-C21 -> 896.94 | D23: =D8+D10-D21 -> 639.54 | E23: =E8+E10-E21 -> 617.6 | F23: =F8+F10-F21 -> 658.02 | G23: =G8+G10-G21 -> 746.54 | I23: Profit before Taxes (D = A+B-C) | J23: =B23/B$8 -> 0.093637903 | K23: =C23/C$8 -> 0.087584356 | L23: =D23/D$8 -> 0.072641568 | M23: =E23/E$8 -> 0.081810535 | N23: =F23/F$8 -> 0.1005068 | O23: =G23/G$8 -> 0.10791737
A25: Less: Taxes (E) | B25: =SUM(Financials_Consol!B94:B97) -> 258.36 | C25: =SUM(Financials_Consol!C94:C97) -> 216.46 | D25: =SUM(Financials_Consol!D94:D97) -> 149.67 | E25: =SUM(Financials_Consol!E94:E97) -> 125.44 | F25: =SUM(Financials_Consol!F94:F97) -> 127.23 | G25: =SUM(Financials_Consol!G94:G97) -> 181.01 | I25: Less: Taxes (E) | J25: =B25/B$8 -> 0.022347915 | K25: =C25/C$8 -> 0.021136876 | L25: =D25/D$8 -> 0.017000131 | M25: =E25/E$8 -> 0.01661644 | N25: =F25/F$8 -> 0.019433269 | O25: =G25/G$8 -> 0.026166211
A26: Extraordinary Items | B26: =Financials_Consol!B92 -> 12.18 | C26: =Financials_Consol!C92 -> 0 | D26: =Financials_Consol!D92 -> -10.29 | E26: =Financials_Consol!E92 -> -31.45 | F26: =Financials_Consol!F92 -> -11.23 | G26: =Financials_Consol!G92 -> 0 | I26: Extraordinary Items | J26: =B26/B$8 -> 0.0010535594 | K26: =C26/C$8 -> 0 | L26: =D26/D$8 -> -0.0011687803 | M26: =E26/E$8 -> -0.0041660319 | N26: =F26/F$8 -> -0.0017152842 | O26: =G26/G$8 -> 0
A28: Profit for the Year / Net Profit (D-E) | B28: =B23-B25+B26 -> 836.35 | C28: =C23-C25+C26 -> 680.48 | D28: =D23-D25+D26 -> 479.58 | E28: =E23-E25+E26 -> 460.71 | F28: =F23-F25+F26 -> 519.56 | G28: =G23-G25+G26 -> 565.53 | I28: Profit for the Year / Net Profit (D-E) | J28: =B28/B$8 -> 0.072343547 | K28: =C28/C$8 -> 0.06644748 | L28: =D28/D$8 -> 0.054472657 | M28: =E28/E$8 -> 0.061028063 | N28: =F28/F$8 -> 0.079358242 | O28: =G28/G$8 -> 0.08175116
B30: =Financials_Consol!B101 -> 836.35 | C30: =Financials_Consol!C101 -> 680.48 | D30: =Financials_Consol!D101 -> 479.58 | E30: =Financials_Consol!E101 -> 460.71 | F30: =Financials_Consol!F101 -> 519.56 | G30: =Financials_Consol!G101 -> 565.53
B31: =B28-B30 -> 0 | C31: =C28-C30 -> 0 | D31: =D28-D30 -> 0 | E31: =E28-E30 -> 0 | F31: =F28-F30 -> 0 | G31: =G28-G30 -> 0

Sheet Common Size Analysis - PL
A1: Endurance Technologies | I1: Endurance Technologies
A2: Income Statement | I2: Common-Size Income Statement
A3: (Rs lakhs) | B3: 45717 | C3: 45352 | D3: 44986 | E3: 44621 | F3: 44256 | G3: 43891 | J3: 45717 | K3: 45352 | L3: 44986 | M3: 44621 | N3: 44256 | O3: 43891
A4: Revenue from Operations | I4: Revenue from Operations
A5: Gross Sales of Products | B5: =Financials_Standalone!B73 -> 8730.32 | C5: =Financials_Standalone!C73 -> 7757.77 | D5: =Financials_Standalone!D73 -> 6674.81 | E5: =Financials_Standalone!E73 -> 5604.43 | F5: =Financials_Standalone!F73 -> 4658.97 | G5: =Financials_Standalone!G73 -> 4820.16 | I5: Gross Sales of Products | J5: 1 | K5: 1 | L5: 1 | M5: 1 | N5: 1 | O5: 1 | P5: =C5*12/9 -> 10343.693 | Q5: =P5/G5 -> 2.1459232
A6: Less - Excise Duty | B6: =Financials_Standalone!B74 -> 0 | C6: =Financials_Standalone!C74 -> 0 | D6: =Financials_Standalone!D74 -> 0 | E6: =Financials_Standalone!E74 -> 0 | F6: =Financials_Standalone!F74 -> 0 | G6: =Financials_Standalone!G74 -> 0 | I6: Less - Excise Duty | J6: =B6/B$5 -> 0 | K6: =C6/C$5 -> 0 | L6: =D6/D$5 -> 0 | M6: =E6/E$5 -> 0 | N6: =F6/F$5 -> 0 | O6: =G6/G$5 -> 0
A7: Other Operating Revenue | B7: =Financials_Standalone!B76 -> 115.83 | C7: =Financials_Standalone!C76 -> 113.23 | D7: =Financials_Standalone!D76 -> 92.7 | E7: =Financials_Standalone!E76 -> 92.66 | F7: =Financials_Standalone!F76 -> 114.07 | G7: =Financials_Standalone!G76 -> 118.41 | I7: Other Operating Revenue | J7: =B7/B$5 -> 0.013267555 | K7: =C7/C$5 -> 0.014595689 | L7: =D7/D$5 -> 0.013888036 | M7: =E7/E$5 -> 0.01653335 | N7: =F7/F$5 -> 0.024483952 | O7: =G7/G$5 -> 0.024565575
A8: Net Revenue from Operations (A) | B8: =B5-B6+B7 -> 8846.15 | C8: =C5-C6+C7 -> 7871 | D8: =D5-D6+D7 -> 6767.51 | E8: =E5-E6+E7 -> 5697.09 | F8: =F5-F6+F7 -> 4773.04 | G8: =G5-G6+G7 -> 4938.57 | I8: Net Revenue from Operations (A) | J8: =B8/B$8 -> 1 | K8: =C8/C$8 -> 1 | L8: =D8/D$8 -> 1 | M8: =E8/E$8 -> 1 | N8: =F8/F$8 -> 1 | O8: =G8/G$8 -> 1
A10: Other Income (B) | B10: =Financials_Standalone!B78 -> 66.58 | C10: =Financials_Standalone!C78 -> 49.47 | D10: =Financials_Standalone!D78 -> 28.2 | E10: =Financials_Standalone!E78 -> 24.39 | F10: =Financials_Standalone!F78 -> 13.55 | G10: =Financials_Standalone!G78 -> 36.19 | I10: Other Income (B) | J10: =B10/B$5 -> 0.0076262955 | K10: =C10/C$5 -> 0.0063768325 | L10: =D10/D$5 -> 0.0042248394 | M10: =E10/E$5 -> 0.0043519145 | N10: =F10/F$5 -> 0.0029083682 | O10: =G10/G$5 -> 0.0075080495
A12: Less: Expenses | I12: Less: Expenses
A13: COGS | B13: =Financials_Standalone!B81 -> 5686.35 | C13: =Financials_Standalone!C81 -> 5086.76 | D13: =Financials_Standalone!D81 -> 4511.09 | E13: =Financials_Standalone!E81 -> 3745.18 | F13: =Financials_Standalone!F81 -> 2969.19 | G13: =Financials_Standalone!G81 -> 3000.67 | I13: Cost of Materials Consumed | J13: =B13/B$8 -> 0.64280506 | K13: =C13/C$8 -> 0.64626604 | L13: =D13/D$8 -> 0.66658047 | M13: =E13/E$8 -> 0.65738474 | N13: =F13/F$8 -> 0.62207524 | O13: =G13/G$8 -> 0.60759896
A14: Purchase Of Stock-In Trade | B14: =Financials_Standalone!B82 -> 70.67 | C14: =Financials_Standalone!C82 -> 60.38 | D14: =Financials_Standalone!D82 -> 63.91 | E14: =Financials_Standalone!E82 -> 54.07 | F14: =Financials_Standalone!F82 -> 44.6 | G14: =Financials_Standalone!G82 -> 27.84 | I14: Purchase Of Stock-In Trade | J14: =B14/B$8 -> 0.0079887861 | K14: =C14/C$8 -> 0.0076711981 | L14: =D14/D$8 -> 0.0094436506 | M14: =E14/E$8 -> 0.0094908102 | N14: =F14/F$8 -> 0.0093441496 | O14: =G14/G$8 -> 0.0056372594
A15: Changes In Inventories Of FG,WIP And Stock-In Trade | B15: =Financials_Standalone!B83 -> -28.57 | C15: =Financials_Standalone!C83 -> -6.44 | D15: =Financials_Standalone!D83 -> -42.4 | E15: =Financials_Standalone!E83 -> -40.93 | F15: =Financials_Standalone!F83 -> -44.43 | G15: =Financials_Standalone!G83 -> 18.81 | I15: Changes in Inventories | J15: =B15/B$8 -> -0.0032296536 | K15: =C15/C$8 -> -0.00081819337 | L15: =D15/D$8 -> -0.006265229 | M15: =E15/E$8 -> -0.0071843696 | N15: =F15/F$8 -> -0.0093085329 | O15: =G15/G$8 -> 0.0038087949
A16: Employee Benefit Expenses | B16: =Financials_Standalone!B84 -> 435.78 | C16: =Financials_Standalone!C84 -> 380.12 | D16: =Financials_Standalone!D84 -> 324.18 | E16: =Financials_Standalone!E84 -> 290.31 | F16: =Financials_Standalone!F84 -> 286.56 | G16: =Financials_Standalone!G84 -> 296.13 | I16: Employee Benefits Expenses | J16: =B16/B$8 -> 0.049262108 | K16: =C16/C$8 -> 0.048293737 | L16: =D16/D$8 -> 0.047902404 | M16: =E16/E$8 -> 0.050957594 | N16: =F16/F$8 -> 0.060037209 | O16: =G16/G$8 -> 0.059962702
A17: Finance Costs | B17: =Financials_Standalone!B85 -> 2.56 | C17: =Financials_Standalone!C85 -> 2.99 | D17: =Financials_Standalone!D85 -> 4.27 | E17: =Financials_Standalone!E85 -> 1.82 | F17: =Financials_Standalone!F85 -> 4.8 | G17: =Financials_Standalone!G85 -> 10.82 | I17: Finance costs | J17: =B17/B$8 -> 0.00028939143 | K17: =C17/C$8 -> 0.00037987549 | L17: =D17/D$8 -> 0.00063095585 | M17: =E17/E$8 -> 0.00031946134 | N17: =F17/F$8 -> 0.0010056484 | O17: =G17/G$8 -> 0.0021909176
A18: Depreciation And Amortisation Expenses | B18: =Financials_Standalone!B86 -> 289.65 | C18: =Financials_Standalone!C86 -> 262.52 | D18: =Financials_Standalone!D86 -> 240.71 | E18: =Financials_Standalone!E86 -> 203.74 | F18: =Financials_Standalone!F86 -> 203.42 | G18: =Financials_Standalone!G86 -> 199.25 | I18: Depreciation and Amortisation Expenses | J18: =B18/B$8 -> 0.032743058 | K18: =C18/C$8 -> 0.033352814 | L18: =D18/D$8 -> 0.035568473 | M18: =E18/E$8 -> 0.035762117 | N18: =F18/F$8 -> 0.042618541 | O18: =G18/G$8 -> 0.040345687
A19: Other Expenses | B19: =Financials_Standalone!B87 -> 1530.87 | C19: =Financials_Standalone!C87 -> 1343.86 | D19: =Financials_Standalone!D87 -> 1131.49 | E19: =Financials_Standalone!E87 -> 919.79 | F19: =Financials_Standalone!F87 -> 785.53 | G19: =Financials_Standalone!G87 -> 861.06 | I19: Other expenses | J19: =B19/B$8 -> 0.17305494 | K19: =C19/C$8 -> 0.17073561 | L19: =D19/D$8 -> 0.16719443 | M19: =E19/E$8 -> 0.16144909 | N19: =F19/F$8 -> 0.16457645 | O19: =G19/G$8 -> 0.17435411
A20: Less: Amounts Transfer To Capital Accounts | B20: =Financials_Standalone!B88 -> 0 | C20: =Financials_Standalone!C88 -> 0 | D20: =Financials_Standalone!D88 -> 0 | E20: =Financials_Standalone!E88 -> 0 | F20: =Financials_Standalone!F88 -> 0 | G20: =Financials_Standalone!G88 -> -8.26 | J20: =B20/B$8 -> 0 | K20: =C20/C$8 -> 0 | L20: =D20/D$8 -> 0 | M20: =E20/E$8 -> 0 | N20: =F20/F$8 -> 0 | O20: =G20/G$8 -> -0.0016725489
A21: Total Expenses (C) | B21: =SUM(B13:B20) -> 7987.31 | C21: =SUM(C13:C20) -> 7130.19 | D21: =SUM(D13:D20) -> 6233.25 | E21: =SUM(E13:E20) -> 5173.98 | F21: =SUM(F13:F20) -> 4249.67 | G21: =SUM(G13:G20) -> 4406.32 | I21: Total Expenses (C) | J21: =B21/B$8 -> 0.9029137 | K21: =C21/C$8 -> 0.90588108 | L21: =D21/D$8 -> 0.92105516 | M21: =E21/E$8 -> 0.90817944 | N21: =F21/F$8 -> 0.89034871 | O21: =G21/G$8 -> 0.89222589
A23: Profit before Taxes (D = A+B-C) | B23: =B8+B10-B21 -> 925.42 | C23: =C8+C10-C21 -> 790.28 | D23: =D8+D10-D21 -> 562.46 | E23: =E8+E10-E21 -> 547.5 | F23: =F8+F10-F21 -> 536.92 | G23: =G8+G10-G21 -> 568.44 | I23: Profit before Taxes (D = A+B-C) | J23: =B23/B$8 -> 0.10461274 | K23: =C23/C$8 -> 0.10040401 | L23: =D23/D$8 -> 0.083111809 | M23: =E23/E$8 -> 0.096101694 | N23: =F23/F$8 -> 0.11249015 | O23: =G23/G$8 -> 0.11510214
A25: Less: Taxes (E) | B25: =Financials_Standalone!B98 -> 229.4 | C25: =Financials_Standalone!C98 -> 202.47 | D25: =Financials_Standalone!D98 -> 143.26 | E25: =Financials_Standalone!E98 -> 134.3 | F25: =Financials_Standalone!F98 -> 133.5 | G25: =Financials_Standalone!G98 -> 140.75 | I25: Less: Taxes (E) | J25: =B25/B$8 -> 0.025932185 | K25: =C25/C$8 -> 0.025723542 | L25: =D25/D$8 -> 0.02116879 | M25: =E25/E$8 -> 0.023573438 | N25: =F25/F$8 -> 0.027969596 | O25: =G25/G$8 -> 0.028500153
A26: Extraordinary Items | B26: =Financials_Standalone!B92 -> -17.36 | C26: =Financials_Standalone!C92 -> 0 | D26: =Financials_Standalone!D92 -> -10.29 | E26: =Financials_Standalone!E92 -> -31.45 | F26: =Financials_Standalone!F92 -> -11.23 | G26: =Financials_Standalone!G92 -> 0 | I26: Extraordinary Items | J26: =B26/B$8 -> -0.0019624356 | K26: =C26/C$8 -> 0 | L26: =D26/D$8 -> -0.0015205002 | M26: =E26/E$8 -> -0.0055203621 | N26: =F26/F$8 -> -0.0023527982 | O26: =G26/G$8 -> 0
A28: Profit for the Year / Net Profit (D-E) | B28: =B23-B25+B26 -> 678.66 | C28: =C23-C25+C26 -> 587.81 | D28: =D23-D25+D26 -> 408.91 | E28: =E23-E25+E26 -> 381.75 | F28: =F23-F25+F26 -> 392.19 | G28: =G23-G25+G26 -> 427.69 | I28: Profit for the Year / Net Profit (D-E) | J28: =B28/B$8 -> 0.07671812 | K28: =C28/C$8 -> 0.074680473 | L28: =D28/D$8 -> 0.060422519 | M28: =E28/E$8 -> 0.067007894 | N28: =F28/F$8 -> 0.082167759 | O28: =G28/G$8 -> 0.086601992
B30: =Financials_Standalone!B101 -> 678.66 | C30: =Financials_Standalone!C101 -> 587.81 | D30: =Financials_Standalone!D101 -> 408.91 | E30: =Financials_Standalone!E101 -> 381.75 | F30: =Financials_Standalone!F101 -> 392.19 | G30: =Financials_Standalone!G101 -> 427.69
B31: =B28-B30 -> 0 | C31: =C28-C30 -> 0 | D31: =D28-D30 -> 0 | E31: =E28-E30 -> 0 | F31: =F28-F30 -> 0 | G31: =G28-G30 -> 0
G34: =C28*1.25/G28 -> 1.7179791

Sheet Common Size Analysis - BS_conso
A1: Endurance Technologies | I1: Endurance Technologies
A2: Balance Sheet | I2: Common-Size Balance Sheet
B3: 45717 | C3: 45352 | D3: 44986 | E3: 44621 | F3: 44256 | G3: 43891 | J3: 45717 | K3: 45352 | L3: 44986 | M3: 44621 | N3: 44256 | O3: 43891
A4: Assets | I4: Assets
A5: Non-Current Assets | B5: =B6+B13+B15+B16+B14+B12 -> 4204.87 | C5: =C6+C13+C15+C16+C14+C12 -> 3703.47 | D5: =D6+D13+D15+D16+D14+D12 -> 3220.56 | E5: =E6+E13+E15+E16+E14+E12 -> 2832.56 | F5: =F6+F13+F15+F16+F14+F12 -> 2669.37 | G5: =G6+G13+G15+G16+G14+G12 -> 2759.91 | I5: Non-Current Assets | J5: =B5/B$24 -> 0.47789239 | K5: =C5/C$24 -> 0.49423026 | L5: =D5/D$24 -> 0.50223706 | M5: =E5/E$24 -> 0.49852163 | N5: =F5/F$24 -> 0.47893103 | O5: =G5/G$24 -> 0.56238958
A6: Fixed Assets | B6: =SUM(B7:B10) -> 4010.61 | C6: =SUM(C7:C10) -> 3397.21 | D6: =SUM(D7:D10) -> 2923.73 | E6: =SUM(E7:E10) -> 2658.31 | F6: =SUM(F7:F10) -> 2524.75 | G6: =SUM(G7:G10) -> 2569.81 | I6: Fixed Assets | J6: =B6/B$24 -> 0.45581433 | K6: =C6/C$24 -> 0.45335969 | L6: =D6/D$24 -> 0.45594728 | M6: =E6/E$24 -> 0.46785418 | N6: =F6/F$24 -> 0.45298371 | O6: =G6/G$24 -> 0.52365272
A7: Tangible Assets | B7: =Financials_Consol!B30 -> 3612.46 | C7: =Financials_Consol!C30 -> 3133.65 | D7: =Financials_Consol!D30 -> 2634.68 | E7: =Financials_Consol!E30 -> 2455.82 | F7: =Financials_Consol!F30 -> 2350.93 | G7: =Financials_Consol!G30 -> 2410.42 | I7: Tangible Assets | J7: =B7/B$24 -> 0.41056374 | K7: =C7/C$24 -> 0.41818745 | L7: =D7/D$24 -> 0.41087076 | M7: =E7/E$24 -> 0.43221657 | N7: =F7/F$24 -> 0.4217974 | O7: =G7/G$24 -> 0.49117366
A8: Intangible Assets | B8: =Financials_Consol!B31 -> 105.18 | C8: =Financials_Consol!C31 -> 104.29 | D8: =Financials_Consol!D31 -> 118.16 | E8: =Financials_Consol!E31 -> 83.18 | F8: =Financials_Consol!F31 -> 77.66 | G8: =Financials_Consol!G31 -> 33.44 | I8: Intangible Assets | J8: =B8/B$24 -> 0.01195393 | K8: =C8/C$24 -> 0.013917562 | L8: =D8/D$24 -> 0.018426712 | M8: =E8/E$24 -> 0.014639418 | N8: =F8/F$24 -> 0.013933544 | O8: =G8/G$24 -> 0.0068141018
A9: Capital Work-In-Progress | B9: =Financials_Consol!B32 -> 290.15 | C9: =Financials_Consol!C32 -> 156.72 | D9: =Financials_Consol!D32 -> 168.36 | E9: =Financials_Consol!E32 -> 119.05 | F9: =Financials_Consol!F32 -> 92.99 | G9: =Financials_Consol!G32 -> 106.45 | I9: Intangible Assets under development | J9: =B9/B$24 -> 0.032976163 | K9: =C9/C$24 -> 0.020914377 | L9: =D9/D$24 -> 0.026255257 | M9: =E9/E$24 -> 0.020952425 | N9: =F9/F$24 -> 0.01668401 | O9: =G9/G$24 -> 0.021691421
A10: Intangible Assets Under Development | B10: =Financials_Consol!B33 -> 2.82 | C10: =Financials_Consol!C33 -> 2.55 | D10: =Financials_Consol!D33 -> 2.53 | E10: =Financials_Consol!E33 -> 0.26 | F10: =Financials_Consol!F33 -> 3.17 | G10: =Financials_Consol!G33 -> 19.5 | I10: Capital Work-in-Progress | J10: =B10/B$24 -> 0.00032049898 | K10: =C10/C$24 -> 0.00034029901 | L10: =D10/D$24 -> 0.00039454622 | M10: =E10/E$24 -> 4.575918e-05 | N10: =F10/F$24 -> 0.00056875269 | O10: =G10/G$24 -> 0.0039735342
A11: Other assets | B11: =Financials_Consol!B33 -> 2.82 | C11: =Financials_Consol!C33 -> 2.55 | D11: =Financials_Consol!D33 -> 2.53 | E11: =Financials_Consol!E33 -> 0.26 | F11: =Financials_Consol!F33 -> 3.17 | G11: =Financials_Consol!G33 -> 19.5 | I11: Other assets | J11: =B11/B$24 -> 0.00032049898 | K11: =C11/C$24 -> 0.00034029901 | L11: =D11/D$24 -> 0.00039454622 | M11: =E11/E$24 -> 4.575918e-05 | N11: =F11/F$24 -> 0.00056875269 | O11: =G11/G$24 -> 0.0039735342
A12: Goodwill on consolidation | B12: =Financials_Consol!B35 -> 0 | C12: =Financials_Consol!C35 -> 0 | D12: =Financials_Consol!D35 -> 0 | E12: =Financials_Consol!E35 -> 0 | F12: =Financials_Consol!F35 -> 0 | G12: =Financials_Consol!G35 -> 0 | I12: Goodwill on consolidation | J12: =B12/B$24 -> 0 | K12: =C12/C$24 -> 0 | L12: =D12/D$24 -> 0 | M12: =E12/E$24 -> 0 | N12: =F12/F$24 -> 0 | O12: =G12/G$24 -> 0
A13: Long-Term Investments | B13: =Financials_Consol!B36 -> 15.68 | C13: =Financials_Consol!C36 -> 27.52 | D13: =Financials_Consol!D36 -> 25.47 | E13: =Financials_Consol!E36 -> 1.19 | F13: =Financials_Consol!F36 -> 1.2 | G13: =Financials_Consol!G36 -> 1.19 | I13: Long-Term Investments | J13: =B13/B$24 -> 0.0017820652 | K13: =C13/C$24 -> 0.0036725603 | L13: =D13/D$24 -> 0.0039719732 | M13: =E13/E$24 -> 0.00020943625 | N13: =F13/F$24 -> 0.0002153007 | O13: =G13/G$24 -> 0.00024248747
A14: Deferred Tax Assets [Net] | B14: =Financials_Consol!B37 -> 69.51 | C14: =Financials_Consol!C37 -> 78.27 | D14: =Financials_Consol!D37 -> 71.98 | E14: =Financials_Consol!E37 -> 75.14 | F14: =Financials_Consol!F37 -> 60.24 | G14: =Financials_Consol!G37 -> 32.08 | I14: Deferred Tax Assets [Net] | J14: =B14/B$24 -> 0.0078999589 | K14: =C14/C$24 -> 0.010445178 | L14: =D14/D$24 -> 0.011225074 | M14: =E14/E$24 -> 0.013224403 | N14: =F14/F$24 -> 0.010808095 | O14: =G14/G$24 -> 0.0065369732
A15: Long-Term Loans & Advances | B15: =Financials_Consol!B38 -> 0 | C15: =Financials_Consol!C38 -> 0 | D15: =Financials_Consol!D38 -> 0 | E15: =Financials_Consol!E38 -> 0 | F15: =Financials_Consol!F38 -> 2.68 | G15: =Financials_Consol!G38 -> 156.83 | I15: Long-Term Loans & Advances | J15: =B15/B$24 -> 0 | K15: =C15/C$24 -> 0 | L15: =D15/D$24 -> 0 | M15: =E15/E$24 -> 0 | N15: =F15/F$24 -> 0.00048083824 | O15: =G15/G$24 -> 0.031957404
A16: Other Non-Current Assets | B16: =Financials_Consol!B39 -> 109.07 | C16: =Financials_Consol!C39 -> 200.47 | D16: =Financials_Consol!D39 -> 199.38 | E16: =Financials_Consol!E39 -> 97.92 | F16: =Financials_Consol!F39 -> 80.5 | G16: =Financials_Consol!G39 -> 0 | I16: Other Non-Current Assets | J16: =B16/B$24 -> 0.012396037 | K16: =C16/C$24 -> 0.02675284 | L16: =D16/D$24 -> 0.031092737 | M16: =E16/E$24 -> 0.017233611 | N16: =F16/F$24 -> 0.014443089 | O16: =G16/G$24 -> 0
A17: Current Assets | B17: =SUM(B18:B23) -> 4593.91 | C17: =SUM(C18:C23) -> 3789.94 | D17: =SUM(D18:D23) -> 3191.87 | E17: =SUM(E18:E23) -> 2849.36 | F17: =SUM(F18:F23) -> 2904.23 | G17: =SUM(G18:G23) -> 2147.56 | I17: Current Assets | J17: =B17/B$24 -> 0.52210761 | K17: =C17/C$24 -> 0.50576974 | L17: =D17/D$24 -> 0.49776294 | M17: =E17/E$24 -> 0.50147837 | N17: =F17/F$24 -> 0.52106897 | O17: =G17/G$24 -> 0.43761042
A18: Current Investments | B18: =Financials_Consol!B42 -> 787.93 | C18: =Financials_Consol!C42 -> 765.07 | D18: =Financials_Consol!D42 -> 646.37 | E18: =Financials_Consol!E42 -> 485.59 | F18: =Financials_Consol!F42 -> 443.14 | G18: =Financials_Consol!G42 -> 164.83 | I18: Current Investments | J18: =B18/B$24 -> 0.089549915 | K18: =C18/C$24 -> 0.10209904 | L18: =D18/D$24 -> 0.10079954 | M18: =E18/E$24 -> 0.085462309 | N18: =F18/F$24 -> 0.079506961 | O18: =G18/G$24 -> 0.033587572
A19: Inventories | B19: =Financials_Consol!B43 -> 936.37 | C19: =Financials_Consol!C43 -> 872.21 | D19: =Financials_Consol!D43 -> 820.58 | E19: =Financials_Consol!E43 -> 701.14 | F19: =Financials_Consol!F43 -> 611.85 | G19: =Financials_Consol!G43 -> 550.1 | I19: Inventories | J19: =B19/B$24 -> 0.10642044 | K19: =C19/C$24 -> 0.11639694 | L19: =D19/D$24 -> 0.12796709 | M19: =E19/E$24 -> 0.12339843 | N19: =F19/F$24 -> 0.10977645 | O19: =G19/G$24 -> 0.11209442
A20: Trade Receivables | B20: =Financials_Consol!B44 -> 1418.58 | C20: =Financials_Consol!C44 -> 1262.38 | D20: =Financials_Consol!D44 -> 1162.03 | E20: =Financials_Consol!E44 -> 970.37 | F20: =Financials_Consol!F44 -> 1040.98 | G20: =Financials_Consol!G44 -> 672.74 | I20: Trade Receivables | J20: =B20/B$24 -> 0.16122462 | K20: =C20/C$24 -> 0.16846536 | L20: =D20/D$24 -> 0.18121523 | M20: =E20/E$24 -> 0.17078206 | N20: =F20/F$24 -> 0.18676977 | O20: =G20/G$24 -> 0.13708489
A21: Cash and Cash Equivalents | B21: =Financials_Consol!B45 -> 1018.9 | C21: =Financials_Consol!C45 -> 504.68 | D21: =Financials_Consol!D45 -> 287.71 | E21: =Financials_Consol!E45 -> 402.64 | F21: =Financials_Consol!F45 -> 513.33 | G21: =Financials_Consol!G45 -> 620.95 | I21: Cash and Cash Equivalents | J21: =B21/B$24 -> 0.11580015 | K21: =C21/C$24 -> 0.067349845 | L21: =D21/D$24 -> 0.044867546 | M21: =E21/E$24 -> 0.07086337 | N21: =F21/F$24 -> 0.092100258 | O21: =G21/G$24 -> 0.12653159
A22: Short-Term Loans & Advances | B22: =Financials_Consol!B46 -> 3.36 | C22: =Financials_Consol!C46 -> 2 | D22: =Financials_Consol!D46 -> 1.65 | E22: =Financials_Consol!E46 -> 3.72 | F22: =Financials_Consol!F46 -> 5.32 | G22: =Financials_Consol!G46 -> 2.01 | I22: Short-Term Loans & Advances | J22: =B22/B$24 -> 0.00038187112 | K22: =C22/C$24 -> 0.00026690118 | L22: =D22/D$24 -> 0.00025731275 | M22: =E22/E$24 -> 0.00065470827 | N22: =F22/F$24 -> 0.00095449978 | O22: =G22/G$24 -> 0.00040957968
A23: Other Current Assets | B23: =Financials_Consol!B47 -> 428.77 | C23: =Financials_Consol!C47 -> 383.6 | D23: =Financials_Consol!D47 -> 273.53 | E23: =Financials_Consol!E47 -> 285.9 | F23: =Financials_Consol!F47 -> 289.61 | G23: =Financials_Consol!G47 -> 136.93 | I23: Other Current Assets | J23: =B23/B$24 -> 0.048730619 | K23: =C23/C$24 -> 0.051191647 | L23: =D23/D$24 -> 0.042656216 | M23: =E23/E$24 -> 0.050317498 | N23: =F23/F$24 -> 0.051961031 | O23: =G23/G$24 -> 0.027902361
A24: Total Assets | B24: =B5+B17 -> 8798.78 | C24: =C5+C17 -> 7493.41 | D24: =D5+D17 -> 6412.43 | E24: =E5+E17 -> 5681.92 | F24: =F5+F17 -> 5573.6 | G24: =G5+G17 -> 4907.47 | I24: Total Assets | J24: =J5+J17 -> 1 | K24: =K5+K17 -> 1 | L24: =L5+L17 -> 1 | M24: =M5+M17 -> 1 | N24: =N5+N17 -> 1 | O24: =O5+O17 -> 1
A25: Equity and Liabilities | I25: Equity and Liabilities
A26: Shareholders' Funds | B26: =B27+B28+B29 -> 5717.41 | C26: =C27+C28+C29 -> 4977.44 | D26: =D27+D28+D29 -> 4412.13 | E26: =E27+E28+E29 -> 3919.99 | F26: =F27+F28+F29 -> 3562.11 | G26: =G27+G28+G29 -> 3006.04 | I26: Shareholders' Funds | J26: =B26/B$41 -> 0.62558716 | K26: =C26/C$41 -> 0.63119824 | L26: =D26/D$41 -> 0.64860705 | M26: =E26/E$41 -> 0.66921207 | N26: =F26/F$41 -> 0.61976254 | O26: =G26/G$41 -> 0.59291665
A27: Share Capital | B27: =Financials_Consol!B7 -> 140.66 | C27: =Financials_Consol!C7 -> 140.66 | D27: =Financials_Consol!D7 -> 140.66 | E27: =Financials_Consol!E7 -> 140.66 | F27: =Financials_Consol!F7 -> 140.66 | G27: =Financials_Consol!G7 -> 140.66 | I27: Share Capital | J27: =B27/B$41 -> 0.015390726 | K27: =C27/C$41 -> 0.017837351 | L27: =D27/D$41 -> 0.020677783 | M27: =E27/E$41 -> 0.024013166 | N27: =F27/F$41 -> 0.024473079 | O27: =G27/G$41 -> 0.027744028
A28: Reserves & Surplus | B28: =Financials_Consol!B9 -> 5576.75 | C28: =Financials_Consol!C9 -> 4836.78 | D28: =Financials_Consol!D9 -> 4271.47 | E28: =Financials_Consol!E9 -> 3779.33 | F28: =Financials_Consol!F9 -> 3421.45 | G28: =Financials_Consol!G9 -> 2865.38 | I28: Reserves & Surplus | J28: =B28/B$41 -> 0.61019644 | K28: =C28/C$41 -> 0.61336089 | L28: =D28/D$41 -> 0.62792927 | M28: =E28/E$41 -> 0.6451989 | N28: =F28/F$41 -> 0.59528946 | O28: =G28/G$41 -> 0.56517263
A29: =Financials_Standalone!$A$11 -> Employees Stock Options/ share application money pending allotment | B29: =Financials_Consol!B11 -> 0 | C29: =Financials_Consol!C11 -> 0 | D29: =Financials_Consol!D11 -> 0 | E29: =Financials_Consol!E11 -> 0 | F29: =Financials_Consol!F11 -> 0 | G29: =Financials_Consol!G11 -> 0 | I29: Employees Stock Options | J29: =B29/B$41 -> 0 | K29: =C29/C$41 -> 0
A30: Non-Current Liabilities | B30: =SUM(B31:B35) -> 730.05 | C30: =SUM(C31:C35) -> 670.83 | D30: =SUM(D31:D35) -> 459.6 | E30: =SUM(E31:E35) -> 280.43 | F30: =SUM(F31:F35) -> 462.05 | G30: =SUM(G31:G35) -> 499.45 | I30: Non-Current Liabilities | J30: =B30/B$41 -> 0.079880559 | K30: =C30/C$41 -> 0.085069176 | L30: =D30/D$41 -> 0.067563694 | M30: =E30/E$41 -> 0.047874393 | N30: =F30/F$41 -> 0.080390915 | O30: =G30/G$41 -> 0.098512403
A31: Long-Term Liabilities | B31: =Financials_Consol!B17 -> 48.6 | C31: =Financials_Consol!C17 -> 115.97 | D31: =Financials_Consol!D17 -> 116.4 | E31: =Financials_Consol!E17 -> 26.73 | F31: =Financials_Consol!F17 -> 8.98 | G31: =Financials_Consol!G17 -> 11.82 | I31: Long-Term Liabilities | J31: =B31/B$41 -> 0.0053177114 | K31: =C31/C$41 -> 0.014706367 | L31: =D31/D$41 -> 0.017111432 | M31: =E31/E$41 -> 0.0045632868 | N31: =F31/F$41 -> 0.0015624076 | O31: =G31/G$41 -> 0.0023313977
A32: Minority Interest | B32: =Financials_Consol!B13 -> 0 | C32: =Financials_Consol!C13 -> 0 | D32: =Financials_Consol!D13 -> 0 | E32: =Financials_Consol!E13 -> 0 | F32: =Financials_Consol!F13 -> 0.02 | G32: =Financials_Consol!G13 -> 0 | I32: Minority Interest | J32: =B32/B$41 -> 0 | K32: =C32/C$41 -> 0 | L32: =D32/D$41 -> 0 | M32: =E32/E$41 -> 0 | N32: =F32/F$41 -> 3.4797496e-06 | O32: =G32/G$41 -> 0
A33: Long Term Borrowings | B33: =Financials_Consol!B15 -> 594.64 | C33: =Financials_Consol!C15 -> 480.25 | D33: =Financials_Consol!D15 -> 278.15 | E33: =Financials_Consol!E15 -> 193.92 | F33: =Financials_Consol!F15 -> 379.18 | G33: =Financials_Consol!G15 -> 402.09 | I33: Long Term Borrowings | J33: =B33/B$41 -> 0.065064278 | K33: =C33/C$41 -> 0.060901378 | L33: =D33/D$41 -> 0.040889559 | M33: =E33/E$41 -> 0.033105596 | N33: =F33/F$41 -> 0.065972573 | O33: =G33/G$41 -> 0.079308944
A34: Defered Tax Liabilities (Net) | B34: =Financials_Consol!B16 -> 13.35 | C34: =Financials_Consol!C16 -> 14.43 | D34: =Financials_Consol!D16 -> 0.52 | E34: =Financials_Consol!E16 -> 0.63 | F34: =Financials_Consol!F16 -> 0.51 | G34: =Financials_Consol!G16 -> 7.87 | I34: Defered Tax Liabilities (Net) | J34: =B34/B$41 -> 0.0014607294 | K34: =C34/C$41 -> 0.0018298946 | L34: =D34/D$41 -> 7.6442822e-05 | M34: =E34/E$41 -> 0.00010755221 | N34: =F34/F$41 -> 8.8733615e-05 | O34: =G34/G$41 -> 0.0015522927
A35: Long-Term Provisions | B35: =Financials_Consol!B18 -> 73.46 | C35: =Financials_Consol!C18 -> 60.18 | D35: =Financials_Consol!D18 -> 64.53 | E35: =Financials_Consol!E18 -> 59.15 | F35: =Financials_Consol!F18 -> 73.36 | G35: =Financials_Consol!G18 -> 77.67 | I35: Long-Term Provisions | J35: =B35/B$41 -> 0.0080378411 | K35: =C35/C$41 -> 0.0076315356 | L35: =D35/D$41 -> 0.0094862601 | M35: =E35/E$41 -> 0.010097958 | N35: =F35/F$41 -> 0.012763722 | O35: =G35/G$41 -> 0.015319768
A36: Current Liabilities | B36: =SUM(B37:B40) -> 2691.81 | C36: =SUM(C37:C40) -> 2237.43 | D36: =SUM(D37:D40) -> 1930.74 | E36: =SUM(E37:E40) -> 1657.2 | F36: =SUM(F37:F40) -> 1723.38 | G36: =SUM(G37:G40) -> 1564.43 | I36: Current Liabilities | J36: =B36/B$41 -> 0.29453228 | K36: =C36/C$41 -> 0.28373258 | L36: =D36/D$41 -> 0.28382926 | M36: =E36/E$41 -> 0.28291354 | N36: =F36/F$41 -> 0.29984654 | O36: =G36/G$41 -> 0.30857094
A37: Trade Payables | B37: =Financials_Consol!B22 -> 1974.26 | C37: =Financials_Consol!C22 -> 1604.47 | D37: =Financials_Consol!D22 -> 1425.74 | E37: =Financials_Consol!E22 -> 1241.35 | F37: =Financials_Consol!F22 -> 1278.33 | G37: =Financials_Consol!G22 -> 1066.23 | I37: Trade Payables | J37: =B37/B$41 -> 0.21601944 | K37: =C37/C$41 -> 0.20346577 | L37: =D37/D$41 -> 0.20959152 | M37: =E37/E$41 -> 0.21192054 | N37: =F37/F$41 -> 0.22241342 | O37: =G37/G$41 -> 0.21030509
A38: Short Term Borrowings | B38: =Financials_Consol!B21 -> 309.22 | C38: =Financials_Consol!C21 -> 259.53 | D38: =Financials_Consol!D21 -> 205.18 | E38: =Financials_Consol!E21 -> 205.53 | F38: =Financials_Consol!F21 -> 45 | G38: =Financials_Consol!G21 -> 146.1 | I38: Short Term Borrowings | J38: =B38/B$41 -> 0.033834212 | K38: =C38/C$41 -> 0.032911473 | L38: =D38/D$41 -> 0.030162573 | M38: =E38/E$41 -> 0.035087629 | N38: =F38/F$41 -> 0.0078294366 | O38: =G38/G$41 -> 0.028817023
A39: Other Current Liabilities | B39: =Financials_Consol!B23 -> 381.98 | C39: =Financials_Consol!C23 -> 348.98 | D39: =Financials_Consol!D23 -> 267.08 | E39: =Financials_Consol!E23 -> 182.07 | F39: =Financials_Consol!F23 -> 370.16 | G39: =Financials_Consol!G23 -> 318.69 | I39: Other Current Liabilities | J39: =B39/B$41 -> 0.041795461 | K39: =C39/C$41 -> 0.04425479 | L39: =D39/D$41 -> 0.039262209 | M39: =E39/E$41 -> 0.03108259 | N39: =F39/F$41 -> 0.064403206 | O39: =G39/G$41 -> 0.06285898
A40: Short-Term Provisions | B40: =Financials_Consol!B24 -> 26.35 | C40: =Financials_Consol!C24 -> 24.45 | D40: =Financials_Consol!D24 -> 32.74 | E40: =Financials_Consol!E24 -> 28.25 | F40: =Financials_Consol!F24 -> 29.89 | G40: =Financials_Consol!G24 -> 33.41 | I40: Short-Term Provisions | J40: =B40/B$41 -> 0.0028831624 | K40: =C40/C$41 -> 0.0031005491 | L40: =D40/D$41 -> 0.0048129576 | M40: =E40/E$41 -> 0.0048227779 | N40: =F40/F$41 -> 0.0052004858 | O40: =G40/G$41 -> 0.0065898476
A41: Total Equity and Liabilities | B41: =B26+B30+B36 -> 9139.27 | C41: =C26+C30+C36 -> 7885.7 | D41: =D26+D30+D36 -> 6802.47 | E41: =E26+E30+E36 -> 5857.62 | F41: =F26+F30+F36 -> 5747.54 | G41: =G26+G30+G36 -> 5069.92 | I41: Total Equity and Liabilities | J41: =J26+J30+J36 -> 1 | K41: =K26+K30+K36 -> 1 | L41: =L26+L30+L36 -> 1 | M41: =M26+M30+M36 -> 1 | N41: =N26+N30+N36 -> 1 | O41: =O26+O30+O36 -> 1
B43: =Financials_Consol!B26 -> 9139.27 | C43: =Financials_Consol!C26 -> 7885.7 | D43: =Financials_Consol!D26 -> 6802.47 | E43: =Financials_Consol!E26 -> 5857.62 | F43: =Financials_Consol!F26 -> 5747.54 | G43: =Financials_Consol!G26 -> 5069.92
A44: With Assets | B44: =B24-B43 -> -340.49 | C44: =C24-C43 -> -392.29 | D44: =D24-D43 -> -390.04 | E44: =E24-E43 -> -175.7 | F44: =F24-F43 -> -173.94 | G44: =G24-G43 -> -162.45
A45: With Liabilities | B45: =B41-B43 -> 0 | C45: =C41-C43 -> 0 | D45: =D41-D43 -> 0 | E45: =E41-E43 -> 0 | F45: =F41-F43 -> 0 | G45: =G41-G43 -> 0
B47: =B24-B41 -> -340.49 | C47: =C24-C41 -> -392.29 | D47: =D24-D41 -> -390.04 | E47: =E24-E41 -> -175.7 | F47: =F24-F41 -> -173.94 | G47: =G24-G41 -> -162.45

Sheet Common Size Analysis - BS
A1: Endurance Technologies | I1: Endurance Technologies
A2: Balance Sheet | I2: Common-Size Balance Sheet
B3: 45717 | C3: 45352 | D3: 44986 | E3: 44621 | F3: 44256 | G3: 43891 | J3: 45717 | K3: 45352 | L3: 44986 | M3: 44621 | N3: 44256 | O3: 43891
A4: Assets | I4: Assets
A5: Non-Current Assets | B5: =B6+B11+B13+B14+B12 -> 2846.83 | C5: =C6+C11+C13+C14+C12 -> 2518.24 | D5: =D6+D11+D13+D14+D12 -> 2382.41 | E5: =E6+E11+E13+E14+E12 -> 2072.94 | F5: =F6+F11+F13+F14+F12 -> 1891.25 | G5: =G6+G11+G13+G14+G12 -> 2022.29 | I5: Non-Current Assets | J5: =B5/B$22 -> 0.52759034 | K5: =C5/C$22 -> 0.53747564 | L5: =D5/D$22 -> 0.57979582 | M5: =E5/E$22 -> 0.55436134 | N5: =F5/F$22 -> 0.55015621 | O5: =G5/G$22 -> 0.67796332
A6: Fixed Assets | B6: =SUM(B7:B10) -> 2235.1 | C6: =SUM(C7:C10) -> 1921.11 | D6: =SUM(D7:D10) -> 1807.81 | E6: =SUM(E7:E10) -> 1654.13 | F6: =SUM(F7:F10) -> 1487.13 | G6: =SUM(G7:G10) -> 1539.62 | I6: Fixed Assets | J6: =B6/B$22 -> 0.41422114 | K6: =C6/C$22 -> 0.41002837 | L6: =D6/D$22 -> 0.43995814 | M6: =E6/E$22 -> 0.44235999 | N6: =F6/F$22 -> 0.4325995 | O6: =G6/G$22 -> 0.51615044
A7: Tangible Assets | B7: =Financials_Standalone!B29 -> 1964.46 | C7: =Financials_Standalone!C29 -> 1756.7 | D7: =Financials_Standalone!D29 -> 1624.85 | E7: =Financials_Standalone!E29 -> 1508.39 | F7: =Financials_Standalone!F29 -> 1368.37 | G7: =Financials_Standalone!G29 -> 1455.65 | I7: Tangible Assets | J7: =B7/B$22 -> 0.36406463 | K7: =C7/C$22 -> 0.37493784 | L7: =D7/D$22 -> 0.39543203 | M7: =E7/E$22 -> 0.4033851 | N7: =F7/F$22 -> 0.39805275 | O7: =G7/G$22 -> 0.48799989
A8: Intangible Assets | B8: =Financials_Standalone!B30 -> 60.85 | C8: =Financials_Standalone!C30 -> 44.45 | D8: =Financials_Standalone!D30 -> 51.47 | E8: =Financials_Standalone!E30 -> 56.56 | F8: =Financials_Standalone!F30 -> 26.67 | G8: =Financials_Standalone!G30 -> 3.25 | I8: Intangible Assets | J8: =B8/B$22 -> 0.01127706 | K8: =C8/C$22 -> 0.009487099 | L8: =D8/D$22 -> 0.01252601 | M8: =E8/E$22 -> 0.015125704 | N8: =F8/F$22 -> 0.0077581843 | O8: =G8/G$22 -> 0.0010895474
A9: Capital Work-In-Progress | B9: =Financials_Standalone!B31 -> 206.97 | C9: =Financials_Standalone!C31 -> 102.27 | D9: =Financials_Standalone!D31 -> 119.11 | E9: =Financials_Standalone!E31 -> 83.78 | F9: =Financials_Standalone!F31 -> 88.92 | G9: =Financials_Standalone!G31 -> 61.22 | I9: Intangible Assets under development | J9: =B9/B$22 -> 0.03835683 | K9: =C9/C$22 -> 0.021827798 | L9: =D9/D$22 -> 0.028987235 | M9: =E9/E$22 -> 0.022405083 | N9: =F9/F$22 -> 0.025866432 | O9: =G9/G$22 -> 0.02052372
A10: Intangible Assets Under Development | B10: =Financials_Standalone!B32 -> 2.82 | C10: =Financials_Standalone!C32 -> 17.69 | D10: =Financials_Standalone!D32 -> 12.38 | E10: =Financials_Standalone!E32 -> 5.4 | F10: =Financials_Standalone!F32 -> 3.17 | G10: =Financials_Standalone!G32 -> 19.5 | I10: Capital Work-in-Progress | J10: =B10/B$22 -> 0.00052261806 | K10: =C10/C$22 -> 0.0037756306 | L10: =D10/D$22 -> 0.0030128619 | M10: =E10/E$22 -> 0.001444109 | N10: =F10/F$22 -> 0.0009221389 | O10: =G10/G$22 -> 0.0065372843
A11: Long-Term Investments | B11: =Financials_Standalone!B34 -> 521.97 | C11: =Financials_Standalone!C34 -> 533.82 | D11: =Financials_Standalone!D34 -> 524.82 | E11: =Financials_Standalone!E34 -> 364.91 | F11: =Financials_Standalone!F34 -> 364.91 | G11: =Financials_Standalone!G34 -> 364.91 | I11: Long-Term Investments | J11: =B11/B$22 -> 0.096734378 | K11: =C11/C$22 -> 0.11393483 | L11: =D11/D$22 -> 0.12772295 | M11: =E11/E$22 -> 0.097587001 | N11: =F11/F$22 -> 0.1061507 | O11: =G11/G$22 -> 0.12233438
A12: Deferred Tax Assets [Net] | B12: =Financials_Standalone!B35 -> 0 | C12: =Financials_Standalone!C35 -> 0 | D12: =Financials_Standalone!D35 -> 1.11 | E12: =Financials_Standalone!E35 -> 3.82 | F12: =Financials_Standalone!F35 -> 1.96 | G12: =Financials_Standalone!G35 -> 0 | I12: Deferred Tax Assets [Net] | J12: =B12/B$22 -> 0 | K12: =C12/C$22 -> 0 | L12: =D12/D$22 -> 0.00027013543 | M12: =E12/E$22 -> 0.0010215734 | N12: =F12/F$22 -> 0.00057015528 | O12: =G12/G$22 -> 0
A13: Long-Term Loans & Advances | B13: =Financials_Standalone!B36 -> 13.7 | C13: =Financials_Standalone!C36 -> 10 | D13: =Financials_Standalone!D36 -> 0 | E13: =Financials_Standalone!E36 -> 0 | F13: =Financials_Standalone!F36 -> 0 | G13: =Financials_Standalone!G36 -> 0 | I13: Long-Term Loans & Advances | J13: =B13/B$22 -> 0.0025389601 | K13: =C13/C$22 -> 0.0021343305 | L13: =D13/D$22 -> 0 | M13: =E13/E$22 -> 0 | N13: =F13/F$22 -> 0 | O13: =G13/G$22 -> 0
A14: Other Non-Current Assets | B14: =Financials_Standalone!B37 -> 76.06 | C14: =Financials_Standalone!C37 -> 53.31 | D14: =Financials_Standalone!D37 -> 48.67 | E14: =Financials_Standalone!E37 -> 50.08 | F14: =Financials_Standalone!F37 -> 37.25 | G14: =Financials_Standalone!G37 -> 117.76 | I14: Other Non-Current Assets | J14: =B14/B$22 -> 0.014095861 | K14: =C14/C$22 -> 0.011378116 | L14: =D14/D$22 -> 0.011844587 | M14: =E14/E$22 -> 0.013392774 | N14: =F14/F$22 -> 0.010835859 | O14: =G14/G$22 -> 0.039478492
A15: Current Assets | B15: =SUM(B16:B21) -> 2549.08 | C15: =SUM(C16:C21) -> 2167.07 | D15: =SUM(D16:D21) -> 1726.64 | E15: =SUM(E16:E21) -> 1666.39 | F15: =SUM(F16:F21) -> 1546.41 | G15: =SUM(G16:G21) -> 960.6 | I15: Current Assets | J15: =B15/B$22 -> 0.47240966 | K15: =C15/C$22 -> 0.46252436 | L15: =D15/D$22 -> 0.42020418 | M15: =E15/E$22 -> 0.44563866 | N15: =F15/F$22 -> 0.44984379 | O15: =G15/G$22 -> 0.32203668
A16: Current Investments | B16: =Financials_Standalone!B40 -> 518.37 | C16: =Financials_Standalone!C40 -> 402.22 | D16: =Financials_Standalone!D40 -> 267.87 | E16: =Financials_Standalone!E40 -> 209.45 | F16: =Financials_Standalone!F40 -> 169.93 | G16: =Financials_Standalone!G40 -> 37.32 | I16: Current Investments | J16: =B16/B$22 -> 0.096067206 | K16: =C16/C$22 -> 0.085847041 | L16: =D16/D$22 -> 0.065190251 | M16: =E16/E$22 -> 0.056012708 | N16: =F16/F$22 -> 0.049431881 | O16: =G16/G$22 -> 0.012511356
A17: Inventories | B17: =Financials_Standalone!B41 -> 562.08 | C17: =Financials_Standalone!C41 -> 481.71 | D17: =Financials_Standalone!D41 -> 428.92 | E17: =Financials_Standalone!E41 -> 366.68 | F17: =Financials_Standalone!F41 -> 329.53 | G17: =Financials_Standalone!G41 -> 265.83 | I17: Inventories | J17: =B17/B$22 -> 0.10416779 | K17: =C17/C$22 -> 0.10281283 | L17: =D17/D$22 -> 0.10438423 | M17: =E17/E$22 -> 0.098060348 | N17: =F17/F$22 -> 0.095858811 | O17: =G17/G$22 -> 0.089118271
A18: Trade Receivables | B18: =Financials_Standalone!B42 -> 1132.25 | C18: =Financials_Standalone!C42 -> 1068.44 | D18: =Financials_Standalone!D42 -> 848.8 | E18: =Financials_Standalone!E42 -> 801.09 | F18: =Financials_Standalone!F42 -> 812.51 | G18: =Financials_Standalone!G42 -> 473.76 | I18: Trade Receivables | J18: =B18/B$22 -> 0.20983486 | K18: =C18/C$22 -> 0.22804041 | L18: =D18/D$22 -> 0.20656843 | M18: =E18/E$22 -> 0.21423357 | N18: =F18/F$22 -> 0.23635554 | O18: =G18/G$22 -> 0.15882584
A19: Cash and Cash Equivalents | B19: =Financials_Standalone!B43 -> 92.19 | C19: =Financials_Standalone!C43 -> 15.74 | D19: =Financials_Standalone!D43 -> 42.73 | E19: =Financials_Standalone!E43 -> 103.14 | F19: =Financials_Standalone!F43 -> 34.29 | G19: =Financials_Standalone!G43 -> 125.33 | I19: Cash and Cash Equivalents | J19: =B19/B$22 -> 0.017085163 | K19: =C19/C$22 -> 0.0033594362 | L19: =D19/D$22 -> 0.010398997 | M19: =E19/E$22 -> 0.027582481 | N19: =F19/F$22 -> 0.0099748084 | O19: =G19/G$22 -> 0.0420163
A20: Short-Term Loans & Advances | B20: =Financials_Standalone!B44 -> 3.36 | C20: =Financials_Standalone!C44 -> 2 | D20: =Financials_Standalone!D44 -> 1.48 | E20: =Financials_Standalone!E44 -> 1.1 | F20: =Financials_Standalone!F44 -> 1.26 | G20: =Financials_Standalone!G44 -> 2.01 | I20: Short-Term Loans & Advances | J20: =B20/B$22 -> 0.00062269386 | K20: =C20/C$22 -> 0.0004268661 | L20: =D20/D$22 -> 0.00036018058 | M20: =E20/E$22 -> 0.00029417035 | N20: =F20/F$22 -> 0.00036652839 | O20: =G20/G$22 -> 0.00067384315
A21: Other Current Assets | B21: =Financials_Standalone!B45 -> 240.83 | C21: =Financials_Standalone!C45 -> 196.96 | D21: =Financials_Standalone!D45 -> 136.84 | E21: =Financials_Standalone!E45 -> 184.93 | F21: =Financials_Standalone!F45 -> 198.89 | G21: =Financials_Standalone!G45 -> 56.35 | I21: Other Current Assets | J21: =B21/B$22 -> 0.044631953 | K21: =C21/C$22 -> 0.042037773 | L21: =D21/D$22 -> 0.033302101 | M21: =E21/E$22 -> 0.049455384 | N21: =F21/F$22 -> 0.057856216 | O21: =G21/G$22 -> 0.018891075
A22: Total Assets | B22: =B5+B15 -> 5395.91 | C22: =C5+C15 -> 4685.31 | D22: =D5+D15 -> 4109.05 | E22: =E5+E15 -> 3739.33 | F22: =F5+F15 -> 3437.66 | G22: =G5+G15 -> 2982.89 | I22: Total Assets | J22: =J5+J15 -> 1 | K22: =K5+K15 -> 1 | L22: =L5+L15 -> 1 | M22: =M5+M15 -> 1 | N22: =N5+N15 -> 1 | O22: =O5+O15 -> 1
A23: Equity and Liabilities | I23: Equity and Liabilities
A24: Shareholders' Funds | B24: =B25+B26+B27 -> 4348.01 | C24: =C25+C26+C27 -> 3805.32 | D24: =D25+D26+D27 -> 3330.94 | E24: =E25+E26+E27 -> 3006.85 | F24: =F25+F26+F27 -> 2708.25 | G24: =G25+G26+G27 -> 2316.76 | I24: Shareholders' Funds | J24: =B24/B$38 -> 0.80579885 | K24: =C24/C$38 -> 0.81218105 | L24: =D24/D$38 -> 0.81063506 | M24: =E24/E$38 -> 0.80411034 | N24: =F24/F$38 -> 0.78782246 | O24: =G24/G$38 -> 0.77669083
A25: Share Capital | B25: =Financials_Standalone!B7 -> 140.66 | C25: =Financials_Standalone!C7 -> 140.66 | D25: =Financials_Standalone!D7 -> 140.66 | E25: =Financials_Standalone!E7 -> 140.66 | F25: =Financials_Standalone!F7 -> 140.66 | G25: =Financials_Standalone!G7 -> 140.66 | I25: Share Capital | J25: =B25/B$38 -> 0.02606794 | K25: =C25/C$38 -> 0.030021493 | L25: =D25/D$38 -> 0.034231757 | M25: =E25/E$38 -> 0.037616163 | N25: =F25/F$38 -> 0.040917606 | O25: =G25/G$38 -> 0.047156085
A26: Reserves & Surplus | B26: =Financials_Standalone!B9 -> 4207.35 | C26: =Financials_Standalone!C9 -> 3664.66 | D26: =Financials_Standalone!D9 -> 3190.28 | E26: =Financials_Standalone!E9 -> 2866.19 | F26: =Financials_Standalone!F9 -> 2567.59 | G26: =Financials_Standalone!G9 -> 2176.1 | I26: Reserves & Surplus | J26: =B26/B$38 -> 0.77973091 | K26: =C26/C$38 -> 0.78215956 | L26: =D26/D$38 -> 0.7764033 | M26: =E26/E$38 -> 0.76649418 | N26: =F26/F$38 -> 0.74690485 | O26: =G26/G$38 -> 0.72953474
A27: =Financials_Standalone!$A$11 -> Employees Stock Options/ share application money pending allotment | B27: =Financials_Standalone!B11 -> 0 | C27: =Financials_Standalone!C11 -> 0 | D27: =Financials_Standalone!D11 -> 0 | E27: =Financials_Standalone!E11 -> 0 | F27: =Financials_Standalone!F11 -> 0 | G27: =Financials_Standalone!G11 -> 0 | I27: Employees Stock Options | J27: =B27/B$38 -> 0 | K27: =C27/C$38 -> 0 | L27: =D27/D$38 -> 0 | M27: =E27/E$38 -> 0 | N27: =F27/F$38 -> 0 | O27: =G27/G$38 -> 0
A28: Non-Current Liabilities | B28: =SUM(B29:B32) -> 49.72 | C28: =SUM(C29:C32) -> 36.66 | D28: =SUM(D29:D32) -> 37.98 | E28: =SUM(E29:E32) -> 38.79 | F28: =SUM(F29:F32) -> 32.76 | G28: =SUM(G29:G32) -> 38.22 | I28: Non-Current Liabilities | J28: =B28/B$38 -> 0.0092144035 | K28: =C28/C$38 -> 0.0078244556 | L28: =D28/D$38 -> 0.0092430124 | M28: =E28/E$38 -> 0.010373461 | N28: =F28/F$38 -> 0.0095297937 | O28: =G28/G$38 -> 0.012813206
A29: Long-Term Liabilities | B29: =Financials_Standalone!B16 -> 32.77 | C29: =Financials_Standalone!C16 -> 18.79 | D29: =Financials_Standalone!D16 -> 31.94 | E29: =Financials_Standalone!E16 -> 29.94 | F29: =Financials_Standalone!F16 -> 8.96 | G29: =Financials_Standalone!G16 -> 10.75 | I29: Long-Term Liabilities | J29: =B29/B$38 -> 0.0060731296 | K29: =C29/C$38 -> 0.004010407 | L29: =D29/D$38 -> 0.0077730862 | M29: =E29/E$38 -> 0.0080067391 | N29: =F29/F$38 -> 0.0026064393 | O29: =G29/G$38 -> 0.0036039238
A30: Long Term Borrowings | B30: =Financials_Standalone!B14 -> 0 | C30: =Financials_Standalone!C14 -> 0 | D30: =Financials_Standalone!D14 -> 0 | E30: =Financials_Standalone!E14 -> 0 | F30: =Financials_Standalone!F14 -> 2.73 | G30: =Financials_Standalone!G14 -> 4.28 | I30: Long Term Borrowings | J30: =B30/B$38 -> 0 | K30: =C30/C$38 -> 0 | L30: =D30/D$38 -> 0 | M30: =E30/E$38 -> 0 | N30: =F30/F$38 -> 0.00079414947 | O30: =G30/G$38 -> 0.0014348645
A31: Defered Tax Liabilities (Net) | B31: =Financials_Standalone!B15 -> 13.35 | C31: =Financials_Standalone!C15 -> 13.8 | D31: =Financials_Standalone!D15 -> 0 | E31: =Financials_Standalone!E15 -> 0 | F31: =Financials_Standalone!F15 -> 0 | G31: =Financials_Standalone!G15 -> 7.37 | I31: Defered Tax Liabilities (Net) | J31: =B31/B$38 -> 0.0024741007 | K31: =C31/C$38 -> 0.0029453761 | L31: =D31/D$38 -> 0 | M31: =E31/E$38 -> 0 | N31: =F31/F$38 -> 0 | O31: =G31/G$38 -> 0.0024707831
A32: Long-Term Provisions | B32: =Financials_Standalone!B17 -> 3.6 | C32: =Financials_Standalone!C17 -> 4.07 | D32: =Financials_Standalone!D17 -> 6.04 | E32: =Financials_Standalone!E17 -> 8.85 | F32: =Financials_Standalone!F17 -> 21.07 | G32: =Financials_Standalone!G17 -> 15.82 | I32: Long-Term Provisions | J32: =B32/B$38 -> 0.00066717322 | K32: =C32/C$38 -> 0.00086867251 | L32: =D32/D$38 -> 0.0014699261 | M32: =E32/E$38 -> 0.0023667215 | N32: =F32/F$38 -> 0.0061292049 | O32: =G32/G$38 -> 0.0053036348
A33: Current Liabilities | B33: =SUM(B34:B37) -> 998.17 | C33: =SUM(C34:C37) -> 843.33 | D33: =SUM(D34:D37) -> 740.13 | E33: =SUM(E34:E37) -> 693.71 | F33: =SUM(F34:F37) -> 696.63 | G33: =SUM(G34:G37) -> 627.88 | I33: Current Liabilities | J33: =B33/B$38 -> 0.18498675 | K33: =C33/C$38 -> 0.17999449 | L33: =D33/D$38 -> 0.18012193 | M33: =E33/E$38 -> 0.1855162 | N33: =F33/F$38 -> 0.20264775 | O33: =G33/G$38 -> 0.21049597
A34: Trade Payables | B34: =Financials_Standalone!B21 -> 815.01 | C34: =Financials_Standalone!C21 -> 676.21 | D34: =Financials_Standalone!D21 -> 566.45 | E34: =Financials_Standalone!E21 -> 529.93 | F34: =Financials_Standalone!F21 -> 526.84 | G34: =Financials_Standalone!G21 -> 395.6 | I34: Trade Payables | J34: =B34/B$38 -> 0.15104246 | K34: =C34/C$38 -> 0.14432556 | L34: =D34/D$38 -> 0.13785425 | M34: =E34/E$38 -> 0.14171714 | N34: =F34/F$38 -> 0.1532563 | O34: =G34/G$38 -> 0.13262439
A35: Short Term Borrowings | B35: =Financials_Standalone!B20 -> 0 | C35: =Financials_Standalone!C20 -> 0 | D35: =Financials_Standalone!D20 -> 20 | E35: =Financials_Standalone!E20 -> 31.7 | F35: =Financials_Standalone!F20 -> 45 | G35: =Financials_Standalone!G20 -> 146.1 | I35: Short Term Borrowings | J35: =B35/B$38 -> 0 | K35: =C35/C$38 -> 0 | L35: =D35/D$38 -> 0.0048673051 | M35: =E35/E$38 -> 0.0084774092 | N35: =F35/F$38 -> 0.013090376 | O35: =G35/G$38 -> 0.048979838
A36: Other Current Liabilities | B36: =Financials_Standalone!B22 -> 157.15 | C36: =Financials_Standalone!C22 -> 142.91 | D36: =Financials_Standalone!D22 -> 121.04 | E36: =Financials_Standalone!E22 -> 103.83 | F36: =Financials_Standalone!F22 -> 94.9 | G36: =Financials_Standalone!G22 -> 56.93 | I36: Other Current Liabilities | J36: =B36/B$38 -> 0.029123964 | K36: =C36/C$38 -> 0.030501717 | L36: =D36/D$38 -> 0.02945693 | M36: =E36/E$38 -> 0.027766858 | N36: =F36/F$38 -> 0.027606148 | O36: =G36/G$38 -> 0.01908571
A37: Short-Term Provisions | B37: =Financials_Standalone!B23 -> 26.01 | C37: =Financials_Standalone!C23 -> 24.21 | D37: =Financials_Standalone!D23 -> 32.64 | E37: =Financials_Standalone!E23 -> 28.25 | F37: =Financials_Standalone!F23 -> 29.89 | G37: =Financials_Standalone!G23 -> 29.25 | I37: Short-Term Provisions | J37: =B37/B$38 -> 0.0048203265 | K37: =C37/C$38 -> 0.0051672141 | L37: =D37/D$38 -> 0.0079434419 | M37: =E37/E$38 -> 0.0075547889 | N37: =F37/F$38 -> 0.0086949186 | O37: =G37/G$38 -> 0.0098060251
A38: Total Equity and Liabilities | B38: =B24+B28+B33 -> 5395.9 | C38: =C24+C28+C33 -> 4685.31 | D38: =D24+D28+D33 -> 4109.05 | E38: =E24+E28+E33 -> 3739.35 | F38: =F24+F28+F33 -> 3437.64 | G38: =G24+G28+G33 -> 2982.86 | I38: Total Equity and Liabilities | J38: =J24+J28+J33 -> 1 | K38: =K24+K28+K33 -> 1 | L38: =L24+L28+L33 -> 1 | M38: =M24+M28+M33 -> 1 | N38: =N24+N28+N33 -> 1 | O38: =O24+O28+O33 -> 1
B40: =Financials_Standalone!B25 -> 5395.9 | C40: =Financials_Standalone!C25 -> 4685.31 | D40: =Financials_Standalone!D25 -> 4109.05 | E40: =Financials_Standalone!E25 -> 3739.35 | F40: =Financials_Standalone!F25 -> 3437.64 | G40: =Financials_Standalone!G25 -> 2982.86
A41: With Assets | B41: =B22-B40 -> 0.01 | C41: =C22-C40 -> 0 | D41: =D22-D40 -> 0 | E41: =E22-E40 -> -0.02 | F41: =F22-F40 -> 0.02 | G41: =G22-G40 -> 0.03
A42: With Liabilities | B42: =B38-B40 -> 0 | C42: =C38-C40 -> 0 | D42: =D38-D40 -> 0 | E42: =E38-E40 -> 0 | F42: =F38-F40 -> 0 | G42: =G38-G40 -> 0
B44: =B22-B38 -> 0.01 | C44: =C22-C38 -> 0 | D44: =D22-D38 -> 0 | E44: =E22-E38 -> -0.02 | F44: =F22-F38 -> 0.02 | G44: =G22-G38 -> 0.03

Sheet Common Size Analysis - CFS_Cons
A1: Endurance Technologies | I1: Endurance Technologies
A2: Cash Flow Statement | I2: Common-Size Cash Flow Statement
B3: 45717 | C3: 45352 | D3: 44986 | E3: 44621 | F3: 44256 | G3: 43891 | J3: 45717 | K3: 45352 | L3: 44986 | M3: 44621 | N3: 44256 | O3: 43891
A4: Revenue from Operations | C4: ='Common Size Analysis - PL_Conso'!C8 -> 10240.87 | D4: ='Common Size Analysis - PL_Conso'!D8 -> 8804.05 | E4: ='Common Size Analysis - PL_Conso'!E8*10000000 -> 75491500000 | F4: ='Common Size Analysis - PL_Conso'!F8*10000000 -> 6.54702e+10 | G4: ='Common Size Analysis - PL_Conso'!G8*10000000 -> 69177000000 | I4: Revenue from Operations | J4: 1 | K4: 1 | L4: 1 | M4: 1 | N4: 1 | O4: 1
A5: Cash Flow from Operating Activities | I5: Cash Flow from Operating Activities
A6: Net Profit Before Tax | B6: =Financials_Consol!B93 -> 1094.71 | C6: =Financials_Consol!C93 -> 896.94 | D6: =Financials_Consol!D93 -> 629.25 | E6: =Financials_Consol!E93 -> 586.15 | F6: =Financials_Consol!F93 -> 646.79 | G6: =Financials_Consol!G93 -> 746.54 | I6: Net Profit Before Tax | J6: =B6/B$4 -> #DIV/0! | K6: =C6/C$4 -> 0.087584356 | L6: =D6/D$4 -> 0.071472788 | M6: =E6/E$4 -> 7.7644503e-09 | N6: =F6/F$4 -> 9.8791511e-09 | O6: =G6/G$4 -> 1.0791737e-08
A7: Add: Depreciation & Amortization | I7: Add: Depreciation & Amortization | J7: =B7/B$4 -> #DIV/0! | K7: =C7/C$4 -> 0 | L7: =D7/D$4 -> 0 | M7: =E7/E$4 -> 0 | N7: =F7/F$4 -> 0 | O7: =G7/G$4 -> 0
A8: Interest received | I8: Interest received | J8: =B8/B$4 -> #DIV/0! | K8: =C8/C$4 -> 0 | L8: =D8/D$4 -> 0 | M8: =E8/E$4 -> 0 | N8: =F8/F$4 -> 0 | O8: =G8/G$4 -> 0
A9: Interest expense | I9: Interest expense | J9: =B9/B$4 -> #DIV/0! | K9: =C9/C$4 -> 0 | L9: =D9/D$4 -> 0 | M9: =E9/E$4 -> 0 | N9: =F9/F$4 -> 0 | O9: =G9/G$4 -> 0
A10: Government incentive scheme | I10: Government incentive scheme | J10: =B10/B$4 -> #DIV/0! | K10: =C10/C$4 -> 0 | L10: =D10/D$4 -> 0 | M10: =E10/E$4 -> 0 | N10: =F10/F$4 -> 0 | O10: =G10/G$4 -> 0
A11: Gratuity | I11: Gratuity | J11: =B11/B$4 -> #DIV/0! | K11: =C11/C$4 -> 0 | L11: =D11/D$4 -> 0 | M11: =E11/E$4 -> 0 | N11: =F11/F$4 -> 0 | O11: =G11/G$4 -> 0
A12: leave encashment | I12: leave encashment | J12: =B12/B$4 -> #DIV/0! | K12: =C12/C$4 -> 0 | L12: =D12/D$4 -> 0 | M12: =E12/E$4 -> 0 | N12: =F12/F$4 -> 0 | O12: =G12/G$4 -> 0
A13: Expense regcognised in respect of equity based payments | I13: Expense regcognised in respect of equity based payments | J13: =B13/B$4 -> #DIV/0! | K13: =C13/C$4 -> 0 | L13: =D13/D$4 -> 0 | M13: =E13/E$4 -> 0 | N13: =F13/F$4 -> 0 | O13: =G13/G$4 -> 0
A14: Litigations
A15: Profit on sale of fixed assets | I15: Profit on sale of fixed assets | J15: =B15/B$4 -> #DIV/0! | K15: =C15/C$4 -> 0 | L15: =D15/D$4 -> 0 | M15: =E15/E$4 -> 0 | N15: =F15/F$4 -> 0 | O15: =G15/G$4 -> 0
A16: Dividend received | I16: Dividend received | J16: =B16/B$4 -> #DIV/0! | K16: =C16/C$4 -> 0 | L16: =D16/D$4 -> 0 | M16: =E16/E$4 -> 0 | N16: =F16/F$4 -> 0 | O16: =G16/G$4 -> 0
A17: Profit from sale of investments | I17: Profit from sale of investments | J17: =B17/B$4 -> #DIV/0! | K17: =C17/C$4 -> 0 | L17: =D17/D$4 -> 0 | M17: =E17/E$4 -> 0 | N17: =F17/F$4 -> 0 | O17: =G17/G$4 -> 0
A18: Unrealised loss/ gain from derivative instruements | I18: Unrealised loss/ gain from derivative instruements | J18: =B18/B$4 -> #DIV/0! | K18: =C18/C$4 -> 0 | L18: =D18/D$4 -> 0 | M18: =E18/E$4 -> 0 | N18: =F18/F$4 -> 0 | O18: =G18/G$4 -> 0
A19: Share of Profit of associate | I19: Share of Profit of associate | J19: =B19/B$4 -> #DIV/0! | K19: =C19/C$4 -> 0 | L19: =D19/D$4 -> 0 | M19: =E19/E$4 -> 0 | N19: =F19/F$4 -> 0 | O19: =G19/G$4 -> 0
A20: Profit on redemtion of mutual funds | I20: Profit on redemtion of mutual funds | J20: =B20/B$4 -> #DIV/0! | K20: =C20/C$4 -> 0 | L20: =D20/D$4 -> 0 | M20: =E20/E$4 -> 0 | N20: =F20/F$4 -> 0 | O20: =G20/G$4 -> 0
A21: Profit from sale of subsidaries | I21: Profit from sale of subsidaries | J21: =B21/B$4 -> #DIV/0! | K21: =C21/C$4 -> 0 | L21: =D21/D$4 -> 0 | M21: =E21/E$4 -> 0 | N21: =F21/F$4 -> 0 | O21: =G21/G$4 -> 0
A22: Bad Debts | I22: Bad Debts | J22: =B22/B$4 -> #DIV/0! | K22: =C22/C$4 -> 0 | L22: =D22/D$4 -> 0 | M22: =E22/E$4 -> 0 | N22: =F22/F$4 -> 0 | O22: =G22/G$4 -> 0
A23: Sundry balance written off | I23: Sundry balance written off | J23: =B23/B$4 -> #DIV/0! | K23: =C23/C$4 -> 0 | L23: =D23/D$4 -> 0 | M23: =E23/E$4 -> 0 | N23: =F23/F$4 -> 0 | O23: =G23/G$4 -> 0
A24: Impairment loss recognised in Fixed assets | I24: Impairment loss recognised in Fixed assets | J24: =B24/B$4 -> #DIV/0! | K24: =C24/C$4 -> 0 | L24: =D24/D$4 -> 0 | M24: =E24/E$4 -> 0 | N24: =F24/F$4 -> 0 | O24: =G24/G$4 -> 0
A25: Deferred compensation payable | I25: Deferred compensation payable | J25: =B25/B$4 -> #DIV/0! | K25: =C25/C$4 -> 0 | L25: =D25/D$4 -> 0 | M25: =E25/E$4 -> 0 | N25: =F25/F$4 -> 0 | O25: =G25/G$4 -> 0
A26: Provisions/ Liability no longer required written back | I26: Provisions/ Liability no longer required written back | J26: =B26/B$4 -> #DIV/0! | K26: =C26/C$4 -> 0 | L26: =D26/D$4 -> 0 | M26: =E26/E$4 -> 0 | N26: =F26/F$4 -> 0 | O26: =G26/G$4 -> 0
... A29: Operating Profit before Working Capital Changes | I29: Operating Profit before Working Capital Changes | J29: =B29/B$4 -> #DIV/0! | K29: =C29/C$4 -> 0 | L29: =D29/D$4 -> 0 | M29: =E29/E$4 -> 0 | N29: =F29/F$4 -> 0 | O29: =G29/G$4 -> 0
A31: Changes in Working Capital: | I31: Changes in Working Capital:
A32: Other advances and receivables | I32: Other advances and receivables | J32: =B32/B$4 -> #DIV/0! | K32: =C32/C$4 -> 0 | L32: =D32/D$4 -> 0 | M32: =E32/E$4 -> 0 | N32: =F32/F$4 -> 0 | O32: =G32/G$4 -> 0
A33: Trade Receivables | I33: Trade Receivables | J33: =B33/B$4 -> #DIV/0! | K33: =C33/C$4 -> 0 | L33: =D33/D$4 -> 0 | M33: =E33/E$4 -> 0 | N33: =F33/F$4 -> 0 | O33: =G33/G$4 -> 0
A34: Inventory | I34: Inventory | J34: =B34/B$4 -> #DIV/0! | K34: =C34/C$4 -> 0 | L34: =D34/D$4 -> 0 | M34: =E34/E$4 -> 0 | N34: =F34/F$4 -> 0 | O34: =G34/G$4 -> 0
A35: Other Current assets | I35: Other Current assets | J35: =B35/B$4 -> #DIV/0! | K35: =C35/C$4 -> 0 | L35: =D35/D$4 -> 0 | M35: =E35/E$4 -> 0 | N35: =F35/F$4 -> 0 | O35: =G35/G$4 -> 0
A36: Non-current assets | I36: Non-current assets | J36: =B36/B$4 -> #DIV/0! | K36: =C36/C$4 -> 0 | L36: =D36/D$4 -> 0 | M36: =E36/E$4 -> 0 | N36: =F36/F$4 -> 0 | O36: =G36/G$4 -> 0
A37: Trade Payables | I37: Trade Payables | J37: =B37/B$4 -> #DIV/0! | K37: =C37/C$4 -> 0 | L37: =D37/D$4 -> 0 | M37: =E37/E$4 -> 0 | N37: =F37/F$4 -> 0 | O37: =G37/G$4 -> 0
A38: Margin money | I38: Margin money | J38: =B38/B$4 -> #DIV/0! | K38: =C38/C$4 -> 0 | L38: =D38/D$4 -> 0 | M38: =E38/E$4 -> 0 | N38: =F38/F$4 -> 0 | O38: =G38/G$4 -> 0
A39: Share in minority interest | I39: Share in minority interest | J39: =B39/B$4 -> #DIV/0! | K39: =C39/C$4 -> 0 | L39: =D39/D$4 -> 0 | M39: =E39/E$4 -> 0 | N39: =F39/F$4 -> 0 | O39: =G39/G$4 -> 0
A40: Short-Term Provisions | I40: Short-Term Provisions | J40: =B40/B$4 -> #DIV/0! | K40: =C40/C$4 -> 0 | L40: =D40/D$4 -> 0 | M40: =E40/E$4 -> 0 | N40: =F40/F$4 -> 0 | O40: =G40/G$4 -> 0
A41: Long-Term Provisions | I41: Long-Term Provisions | J41: =B41/B$4 -> #DIV/0! | K41: =C41/C$4 -> 0 | L41: =D41/D$4 -> 0 | M41: =E41/E$4 -> 0 | N41: =F41/F$4 -> 0 | O41: =G41/G$4 -> 0
A42: Total Changes in Working Capital | I42: Total Changes in Working Capital | J42: =B42/B$4 -> #DIV/0! | K42: =C42/C$4 -> 0 | L42: =D42/D$4 -> 0 | M42: =E42/E$4 -> 0 | N42: =F42/F$4 -> 0 | O42: =G42/G$4 -> 0
A43: Cash Generated from Operations | I43: Cash Generated from Operations | J43: =B43/B$4 -> #DIV/0! | K43: =C43/C$4 -> 0 | L43: =D43/D$4 -> 0 | M43: =E43/E$4 -> 0 | N43: =F43/F$4 -> 0 | O43: =G43/G$4 -> 0
A44: Less: Direct Taxes Paid | I44: Less: Direct Taxes Paid | J44: =B44/B$4 -> #DIV/0! | K44: =C44/C$4 -> 0 | L44: =D44/D$4 -> 0 | M44: =E44/E$4 -> 0 | N44: =F44/F$4 -> 0 | O44: =G44/G$4 -> 0
A45: Net Cash from Operating Activities | B45: 1532 | C45: 1057 | D45: 862 | E45: 742 | F45: 621 | I45: Net Cash from Operating Activities | J45: =B45/B$4 -> #DIV/0! | K45: =C45/C$4 -> 0.10321389 | L45: =D45/D$4 -> 0.097909485 | M45: =E45/E$4 -> 9.8289211e-09 | N45: =F45/F$4 -> 9.4852314e-09 | O45: =G45/G$4 -> 0
A46: =AVERAGE(C46:G46) -> 0.95486994 | B46: =B45/B6 -> 1.3994574 | C46: =C45/C6 -> 1.1784512 | D46: =D45/D6 -> 1.3698848 | E46: =E45/E6 -> 1.2658876 | F46: =F45/F6 -> 0.96012616 | G46: =G45/G6 -> 0
A47: Cash Flow from Investing Activities | I47: Cash Flow from Investing Activities
A48: Add: Proceeds from Sale of Fixed Assets | B48: 47 | C48: 15 | D48: 15 | E48: 10 | F48: 64 | I48: Add: Proceeds from Sale of Fixed Assets | J48: =B48/B$4 -> #DIV/0! | K48: =C48/C$4 -> 0.0014647193 | L48: =D48/D$4 -> 0.0017037613 | M48: =E48/E$4 -> 1.3246524e-10 | N48: =F48/F$4 -> 9.7754398e-10 | O48: =G48/G$4 -> 0
A49: Rental income | I49: Rental income | J49: =B49/B$4 -> #DIV/0! | K49: =C49/C$4 -> 0 | L49: =D49/D$4 -> 0 | M49: =E49/E$4 -> 0 | N49: =F49/F$4 -> 0 | O49: =G49/G$4 -> 0
A50: Investment in FDs with banks/Investments/MF | I50: Investment in FDs with banks/Investments/MF | J50: =B50/B$4 -> #DIV/0! | K50: =C50/C$4 -> 0 | L50: =D50/D$4 -> 0 | M50: =E50/E$4 -> 0 | N50: =F50/F$4 -> 0 | O50: =G50/G$4 -> 0
A51: Proceeds from FDs with banks | I51: Proceeds from FDs with banks | J51: =B51/B$4 -> #DIV/0! | K51: =C51/C$4 -> 0 | L51: =D51/D$4 -> 0 | M51: =E51/E$4 -> 0 | N51: =F51/F$4 -> 0 | O51: =G51/G$4 -> 0
A52: Proceeds from redemption of debentures | I52: Proceeds from redemption of debentures | J52: =B52/B$4 -> #DIV/0! | K52: =C52/C$4 -> 0 | L52: =D52/D$4 -> 0 | M52: =E52/E$4 -> 0 | N52: =F52/F$4 -> 0 | O52: =G52/G$4 -> 0
A53: Acquisition of subsidary | I53: Acquisition of subsidary | J53: =B53/B$4 -> #DIV/0! | K53: =C53/C$4 -> 0 | L53: =D53/D$4 -> 0 | M53: =E53/E$4 -> 0 | N53: =F53/F$4 -> 0 | O53: =G53/G$4 -> 0
A54: Sale of subsidary | I54: Sale of subsidary | J54: =B54/B$4 -> #DIV/0! | K54: =C54/C$4 -> 0 | L54: =D54/D$4 -> 0 | M54: =E54/E$4 -> 0 | N54: =F54/F$4 -> 0 | O54: =G54/G$4 -> 0
A55: Investment in Mutual fund | I55: Investment in Mutual fund | J55: =B55/B$4 -> #DIV/0! | K55: =C55/C$4 -> 0 | L55: =D55/D$4 -> 0 | M55: =E55/E$4 -> 0 | N55: =F55/F$4 -> 0 | O55: =G55/G$4 -> 0
A56: Proceeds from mutual fund | I56: Proceeds from mutual fund | J56: =B56/B$4 -> #DIV/0! | K56: =C56/C$4 -> 0 | L56: =D56/D$4 -> 0 | M56: =E56/E$4 -> 0 | N56: =F56/F$4 -> 0 | O56: =G56/G$4 -> 0
A57: Payment of deferred consideration | I57: Payment of deferred consideration | J57: =B57/B$4 -> #DIV/0! | K57: =C57/C$4 -> 0 | L57: =D57/D$4 -> 0 | M57: =E57/E$4 -> 0 | N57: =F57/F$4 -> 0 | O57: =G57/G$4 -> 0
A58: Investment in Long term FDs with Bank | I58: Investment in Long term FDs with Bank | J58: =B58/B$4 -> #DIV/0! | K58: =C58/C$4 -> 0 | L58: =D58/D$4 -> 0 | M58: =E58/E$4 -> 0 | N58: =F58/F$4 -> 0 | O58: =G58/G$4 -> 0
A59: Proceeds from Long term Fds with bank | I59: Proceeds from Long term Fds with bank | J59: =B59/B$4 -> #DIV/0! | K59: =C59/C$4 -> 0 | L59: =D59/D$4 -> 0 | M59: =E59/E$4 -> 0 | N59: =F59/F$4 -> 0 | O59: =G59/G$4 -> 0
A60: Increase in Fixed deposits | I60: Increase in Fixed deposits | J60: =B60/B$4 -> #DIV/0! | K60: =C60/C$4 -> 0 | L60: =D60/D$4 -> 0 | M60: =E60/E$4 -> 0 | N60: =F60/F$4 -> 0 | O60: =G60/G$4 -> 0
... A64: Divided received | I64: Divided received | J64: =B64/B$4 -> #DIV/0! | K64: =C64/C$4 -> 0 | L64: =D64/D$4 -> 0 | M64: =E64/E$4 -> 0 | N64: =F64/F$4 -> 0 | O64: =G64/G$4 -> 0
A65: Less: Capital Expenditure/ purchase of fixed assets | B65: -1053 | C65: -835 | D65: -636 | E65: -529 | F65: -375 | I65: Less: Capital Expenditure/ purchase of fixed assets | J65: =B65/B$4 -> #DIV/0! | K65: =C65/C$4 -> -0.081536041 | L65: =D65/D$4 -> -0.072239481 | M65: =E65/E$4 -> -7.0074114e-09 | N65: =F65/F$4 -> -5.7277968e-09 | O65: =G65/G$4 -> 0
A66: Purchase of long term Investments | I66: Purchase of long term Investments | J66: =B66/B$4 -> #DIV/0! | K66: =C66/C$4 -> 0 | L66: =D66/D$4 -> 0 | M66: =E66/E$4 -> 0 | N66: =F66/F$4 -> 0 | O66: =G66/G$4 -> 0
A67: Sale of long term Investments | I67: Sale of long term Investments | J67: =B67/B$4 -> #DIV/0! | K67: =C67/C$4 -> 0 | L67: =D67/D$4 -> 0 | M67: =E67/E$4 -> 0 | N67: =F67/F$4 -> 0 | O67: =G67/G$4 -> 0
A68: Income from investment activity | I68: Income from investment activity | J68: =B68/B$4 -> #DIV/0! | K68: =C68/C$4 -> 0 | L68: =D68/D$4 -> 0 | M68: =E68/E$4 -> 0 | N68: =F68/F$4 -> 0 | O68: =G68/G$4 -> 0
A69: Interest income | I69: Interest income | J69: =B69/B$4 -> #DIV/0! | K69: =C69/C$4 -> 0 | L69: =D69/D$4 -> 0 | M69: =E69/E$4 -> 0 | N69: =F69/F$4 -> 0 | O69: =G69/G$4 -> 0
A70: Net Cash (used) in Investing Activities | B70: -988 | C70: -945 | D70: -905 | E70: -550 | F70: -586 | I70: Net Cash (used) in Investing Activities | J70: =B70/B$4 -> #DIV/0! | K70: =C70/C$4 -> -0.092277316 | L70: =D70/D$4 -> -0.1027936 | M70: =E70/E$4 -> -7.2855884e-09 | N70: =F70/F$4 -> -8.9506371e-09 | O70: =G70/G$4 -> 0
A72: Cash Flow from Financing Activities | I72: Cash Flow from Financing Activities
A73: Interest Paid | I73: Interest Paid | J73: =B73/B$4 -> #DIV/0! | K73: =C73/C$4 -> 0 | L73: =D73/D$4 -> 0 | M73: =E73/E$4 -> 0 | N73: =F73/F$4 -> 0 | O73: =G73/G$4 -> 0
A74: Proceeds from other non-current assets | I74: Proceeds from other non-current assets | J74: =B74/B$4 -> #DIV/0! | K74: =C74/C$4 -> 0 | L74: =D74/D$4 -> 0 | M74: =E74/E$4 -> 0 | N74: =F74/F$4 -> 0 | O74: =G74/G$4 -> 0
A75: Payment towards reduction of outstanding lease liability | I75: Payment towards reduction of outstanding lease liability | J75: =B75/B$4 -> #DIV/0! | K75: =C75/C$4 -> 0 | L75: =D75/D$4 -> 0 | M75: =E75/E$4 -> 0 | N75: =F75/F$4 -> 0 | O75: =G75/G$4 -> 0
A76: NCD Interest | I76: NCD Interest | J76: =B76/B$4 -> #DIV/0! | K76: =C76/C$4 -> 0 | L76: =D76/D$4 -> 0 | M76: =E76/E$4 -> 0 | N76: =F76/F$4 -> 0 | O76: =G76/G$4 -> 0
A77: Dividend Paid | I77: Dividend Paid | J77: =B77/B$4 -> #DIV/0! | K77: =C77/C$4 -> 0 | L77: =D77/D$4 -> 0 | M77: =E77/E$4 -> 0 | N77: =F77/F$4 -> 0 | O77: =G77/G$4 -> 0
A78: Dividend tax | I78: Dividend tax | J78: =B78/B$4 -> #DIV/0! | K78: =C78/C$4 -> 0 | L78: =D78/D$4 -> 0 | M78: =E78/E$4 -> 0 | N78: =F78/F$4 -> 0 | O78: =G78/G$4 -> 0
A79: Issue of share warrants/ shares | I79: Issue of share warrants/ shares | J79: =B79/B$4 -> #DIV/0! | K79: =C79/C$4 -> 0 | L79: =D79/D$4 -> 0 | M79: =E79/E$4 -> 0 | N79: =F79/F$4 -> 0 | O79: =G79/G$4 -> 0
A80: Amount used in Buy back | I80: Amount used in Buy back | J80: =B80/B$4 -> #DIV/0! | K80: =C80/C$4 -> 0 | L80: =D80/D$4 -> 0 | M80: =E80/E$4 -> 0 | N80: =F80/F$4 -> 0 | O80: =G80/G$4 -> 0
A81: QIB/ Debenture issue expenses | I81: QIB/ Debenture issue expenses | J81: =B81/B$4 -> #DIV/0! | K81: =C81/C$4 -> 0 | L81: =D81/D$4 -> 0 | M81: =E81/E$4 -> 0 | N81: =F81/F$4 -> 0 | O81: =G81/G$4 -> 0
A82: Share of minority interest | I82: Share of minority interest | J82: =B82/B$4 -> #DIV/0! | K82: =C82/C$4 -> 0 | L82: =D82/D$4 -> 0 | M82: =E82/E$4 -> 0 | N82: =F82/F$4 -> 0 | O82: =G82/G$4 -> 0
A83: Receipt of borrowings/ NCDs | I83: Receipt of borrowings/ NCDs | J83: =B83/B$4 -> #DIV/0! | K83: =C83/C$4 -> 0 | L83: =D83/D$4 -> 0 | M83: =E83/E$4 -> 0 | N83: =F83/F$4 -> 0 | O83: =G83/G$4 -> 0
A84: Proceeds from borrowings | I84: Proceeds from borrowings | J84: =B84/B$4 -> #DIV/0! | K84: =C84/C$4 -> 0 | L84: =D84/D$4 -> 0 | M84: =E84/E$4 -> 0 | N84: =F84/F$4 -> 0 | O84: =G84/G$4 -> 0
... A86: Repayment of Short term borrowings | I86: Repayment of borrowings/ NCDs | J86: =B86/B$4 -> #DIV/0! | K86: =C86/C$4 -> 0 | L86: =D86/D$4 -> 0 | M86: =E86/E$4 -> 0 | N86: =F86/F$4 -> 0 | O86: =G86/G$4 -> 0
A87: Net Cash (used) in Financing Activities | B87: -29 | C87: 105 | D87: -72 | E87: -302 | F87: -143 | I87: Net Cash (used) in Financing Activities | J87: =B87/B$4 -> #DIV/0! | K87: =C87/C$4 -> 0.010253035 | L87: =D87/D$4 -> -0.0081780544 | M87: =E87/E$4 -> -4.0004504e-09 | N87: =F87/F$4 -> -2.1841998e-09 | O87: =G87/G$4 -> 0
A88: Increase/Decrease in Cash and Cash Equivalents | B88: =B45+B70+B87 -> 515 | C88: =C45+C70+C87 -> 217 | D88: =D45+D70+D87 -> -115 | E88: =E45+E70+E87 -> -110 | F88: =F45+F70+F87 -> -108 | I88: Increase/Decrease in Cash and Cash Equivalents | J88: =B88/B$4 -> #DIV/0! | K88: =C88/C$4 -> 0.021189606 | L88: =D88/D$4 -> -0.01306217 | M88: =E88/E$4 -> -1.4571177e-09 | N88: =F88/F$4 -> -1.6496055e-09 | O88: =G88/G$4 -> 0

Sheet Common Size Analysis - CFS
A1: Endurance Technologies | I1: Endurance Technologies
A2: Cash Flow Statement | I2: Common-Size Cash Flow Statement
B3: 45717 | C3: 45352 | D3: 44986 | E3: 44621 | F3: 44256 | G3: 43891 | J3: 45352 | K3: 44986 | L3: 44621 | M3: 44256 | N3: 43891
A4: Revenue from Operations | B4: ='Common Size Analysis - PL'!B8 -> 8846.15 | C4: ='Common Size Analysis - PL'!C8 -> 7871 | D4: ='Common Size Analysis - PL'!D8 -> 6767.51 | E4: ='Common Size Analysis - PL'!E8 -> 5697.09 | F4: ='Common Size Analysis - PL'!F8 -> 4773.04 | G4: ='Common Size Analysis - PL'!G8 -> 4938.57 | I4: Revenue from Operations | J4: 1 | K4: 1 | L4: 1 | M4: 1 | N4: 1
A5: Cash Flow from Operating Activities | I5: Cash Flow from Operating Activities
A6: Net Profit Before Tax | B6: =Financials_Standalone!B93 -> 908.06 | C6: =Financials_Standalone!C93 -> 790.28 | D6: =Financials_Standalone!D93 -> 552.17 | E6: =Financials_Standalone!E93 -> 516.05 | F6: =Financials_Standalone!F93 -> 525.69 | G6: =Financials_Standalone!G93 -> 568.44 | I6: Net Profit Before Tax | J6: =C6/C$4 -> 0.10040401 | K6: =D6/D$4 -> 0.081591309 | L6: =E6/E$4 -> 0.090581332 | M6: =F6/F$4 -> 0.11013735 | N6: =G6/G$4 -> 0.11510214
A7: Add: Depreciation & Amortization | I7: Add: Depreciation & Amortization | J7: =C7/C$4 -> 0 | K7: =D7/D$4 -> 0 | L7: =E7/E$4 -> 0 | M7: =F7/F$4 -> 0 | N7: =G7/G$4 -> 0
A8: Interest received | I8: Interest received | J8: =C8/C$4 -> 0 | K8: =D8/D$4 -> 0 | L8: =E8/E$4 -> 0 | M8: =F8/F$4 -> 0 | N8: =G8/G$4 -> 0
A9: Interest expense | I9: Interest expense | J9: =C9/C$4 -> 0 | K9: =D9/D$4 -> 0 | L9: =E9/E$4 -> 0 | M9: =F9/F$4 -> 0 | N9: =G9/G$4 -> 0
A10: Rental income from investment property | I10: Rental income from investment property | J10: =C10/C$4 -> 0 | K10: =D10/D$4 -> 0 | L10: =E10/E$4 -> 0 | M10: =F10/F$4 -> 0 | N10: =G10/G$4 -> 0
A11: Interest on Income tax | I11: Interest on Income tax | J11: =C11/C$4 -> 0 | K11: =D11/D$4 -> 0 | L11: =E11/E$4 -> 0 | M11: =F11/F$4 -> 0 | N11: =G11/G$4 -> 0
A12: Liability no longer required written back | I12: Liability no longer required written back | J12: =C12/C$4 -> 0 | K12: =D12/D$4 -> 0 | L12: =E12/E$4 -> 0 | M12: =F12/F$4 -> 0 | N12: =G12/G$4 -> 0
A13: Profit on sale of fixed assets | I13: Profit on sale of fixed assets | J13: =C13/C$4 -> 0 | K13: =D13/D$4 -> 0 | L13: =E13/E$4 -> 0 | M13: =F13/F$4 -> 0 | N13: =G13/G$4 -> 0
A14: Profit from sale of investments | I14: Profit from sale of investments | J14: =C14/C$4 -> 0 | K14: =D14/D$4 -> 0 | L14: =E14/E$4 -> 0 | M14: =F14/F$4 -> 0 | N14: =G14/G$4 -> 0
A15: Profit from sale of mutual funds | I15: Profit from sale of mutual funds | J15: =C15/C$4 -> 0 | K15: =D15/D$4 -> 0 | L15: =E15/E$4 -> 0 | M15: =F15/F$4 -> 0 | N15: =G15/G$4 -> 0
A16: Profit from sale of undertaking | I16: Profit from sale of undertaking | J16: =C16/C$4 -> 0 | K16: =D16/D$4 -> 0 | L16: =E16/E$4 -> 0 | M16: =F16/F$4 -> 0 | N16: =G16/G$4 -> 0
A17: Profit from sale of subsidary | I17: Profit from sale of subsidary | J17: =C17/C$4 -> 0 | K17: =D17/D$4 -> 0 | L17: =E17/E$4 -> 0 | M17: =F17/F$4 -> 0 | N17: =G17/G$4 -> 0
A18: Dividend received from subsidary | I18: Dividend received from subsidary | J18: =C18/C$4 -> 0 | K18: =D18/D$4 -> 0 | L18: =E18/E$4 -> 0 | M18: =F18/F$4 -> 0 | N18: =G18/G$4 -> 0
... A26: Foreign exchange gain / loss | I26: Foreign exchange gain / loss | J26: =C26/C$4 -> 0 | K26: =D26/D$4 -> 0 | L26: =E26/E$4 -> 0 | M26: =F26/F$4 -> 0 | N26: =G26/G$4 -> 0
A27: Operating Profit before Working Capital Changes | H27: =SUM(H6:H26) -> 0 | I27: Operating Profit before Working Capital Changes | J27: =C27/C$4 -> 0 | K27: =D27/D$4 -> 0 | L27: =E27/E$4 -> 0 | M27: =F27/F$4 -> 0 | N27: =G27/G$4 -> 0
A29: Changes in Working Capital: | I29: Changes in Working Capital:
A30: Inventory | I30: Inventory | J30: =C30/C$4 -> 0 | K30: =D30/D$4 -> 0 | L30: =E30/E$4 -> 0 | M30: =F30/F$4 -> 0 | N30: =G30/G$4 -> 0
A31: Trade Receivables | I31: Trade Receivables | J31: =C31/C$4 -> 0 | K31: =D31/D$4 -> 0 | L31: =E31/E$4 -> 0 | M31: =F31/F$4 -> 0 | N31: =G31/G$4 -> 0
A32: Other current assets | I32: Other current assets | J32: =C32/C$4 -> 0 | K32: =D32/D$4 -> 0 | L32: =E32/E$4 -> 0 | M32: =F32/F$4 -> 0 | N32: =G32/G$4 -> 0
A33: Short term loans and advances | I33: Short term loans and advances | J33: =C33/C$4 -> 0 | K33: =D33/D$4 -> 0 | L33: =E33/E$4 -> 0 | M33: =F33/F$4 -> 0 | N33: =G33/G$4 -> 0
A34: Margin money deposits | I34: Margin money deposits | J34: =C34/C$4 -> 0 | K34: =D34/D$4 -> 0 | L34: =E34/E$4 -> 0 | M34: =F34/F$4 -> 0 | N34: =G34/G$4 -> 0
A35: Other non- current assets | I35: Other non- current assets | J35: =C35/C$4 -> 0 | K35: =D35/D$4 -> 0 | L35: =E35/E$4 -> 0 | M35: =F35/F$4 -> 0 | N35: =G35/G$4 -> 0
A36: Trade Payables | I36: Trade Payables | J36: =C36/C$4 -> 0 | K36: =D36/D$4 -> 0 | L36: =E36/E$4 -> 0 | M36: =F36/F$4 -> 0 | N36: =G36/G$4 -> 0
A37: Other Current Liabilities | I37: Other payables | J37: =C37/C$4 -> 0 | K37: =D37/D$4 -> 0 | L37: =E37/E$4 -> 0 | M37: =F37/F$4 -> 0 | N37: =G37/G$4 -> 0
A38: Other Long-Term Liabilities | I38: Other Long-Term Liabilities | J38: =C38/C$4 -> 0 | K38: =D38/D$4 -> 0 | L38: =E38/E$4 -> 0 | M38: =F38/F$4 -> 0 | N38: =G38/G$4 -> 0
A39: Short-Term Provisions | I39: Short-Term Provisions | J39: =C39/C$4 -> 0 | K39: =D39/D$4 -> 0 | L39: =E39/E$4 -> 0 | M39: =F39/F$4 -> 0 | N39: =G39/G$4 -> 0
A40: Other non-current liabilities | I40: Long-Term Provisions | J40: =C40/C$4 -> 0 | K40: =D40/D$4 -> 0 | L40: =E40/E$4 -> 0 | M40: =F40/F$4 -> 0 | N40: =G40/G$4 -> 0
A41: Total Changes in Working Capital | H41: =SUM(H30:H40) -> 0 | I41: Total Changes in Working Capital | J41: =C41/C$4 -> 0 | K41: =D41/D$4 -> 0 | L41: =E41/E$4 -> 0 | M41: =F41/F$4 -> 0 | N41: =G41/G$4 -> 0
A42: Cash Generated from Operations | H42: =H27+H41 -> 0 | I42: Cash Generated from Operations | J42: =C42/C$4 -> 0 | K42: =D42/D$4 -> 0 | L42: =E42/E$4 -> 0 | M42: =F42/F$4 -> 0 | N42: =G42/G$4 -> 0
A43: Less: Direct Taxes Paid | I43: Less: Direct Taxes Paid | J43: =C43/C$4 -> 0 | K43: =D43/D$4 -> 0 | L43: =E43/E$4 -> 0 | M43: =F43/F$4 -> 0 | N43: =G43/G$4 -> 0
A44: Net Cash from Operating Activities | B44: 873 | C44: 605 | D44: 623 | E44: 549 | F44: 297 | H44: =H42+H43 -> 0 | I44: Net Cash from Operating Activities | J44: =C44/C$4 -> 0.076864439 | K44: =D44/D$4 -> 0.092057492 | L44: =E44/E$4 -> 0.096364986 | M44: =F44/F$4 -> 0.062224494 | N44: =G44/G$4 -> 0
A45: =AVERAGE(C45:G45) -> 0.70452986 | B45: =B44/B6 -> 0.96139022 | C45: =C44/C6 -> 0.76555145 | D45: =D44/D6 -> 1.1282757 | E45: =E44/E6 -> 1.0638504 | F45: =F44/F6 -> 0.56497175 | G45: =G44/G6 -> 0
A46: Cash Flow from Investing Activities | I46: Cash Flow from Investing Activities
A47: Add: Proceeds from Sale of Fixed Assets | B47: 23 | C47: 12 | D47: 11 | E47: 6 | F47: 46 | I47: Add: Proceeds from Sale of Fixed Assets | J47: =C47/C$4 -> 0.0015245839 | K47: =D47/D$4 -> 0.0016254132 | L47: =E47/E$4 -> 0.0010531692 | M47: =F47/F$4 -> 0.0096374638 | N47: =G47/G$4 -> 0
A48: Investment in FDs with banks/Investments/MF | I48: Investment in FDs with banks | J48: =C48/C$4 -> 0 | K48: =D48/D$4 -> 0 | L48: =E48/E$4 -> 0 | M48: =F48/F$4 -> 0 | N48: =G48/G$4 -> 0
A49: Proceeds from FDs with banks | I49: Proceeds from FDs with banks | J49: =C49/C$4 -> 0 | K49: =D49/D$4 -> 0 | L49: =E49/E$4 -> 0 | M49: =F49/F$4 -> 0 | N49: =G49/G$4 -> 0
A50: Proceeds from sale of investments | I50: Proceeds from sale of investments | J50: =C50/C$4 -> 0 | K50: =D50/D$4 -> 0 | L50: =E50/E$4 -> 0 | M50: =F50/F$4 -> 0 | N50: =G50/G$4 -> 0
A51: Proceeds from sale of subsidaries | I51: Proceeds from sale of subsidaries | J51: =C51/C$4 -> 0 | K51: =D51/D$4 -> 0 | L51: =E51/E$4 -> 0 | M51: =F51/F$4 -> 0 | N51: =G51/G$4 -> 0
A52: Proceeds from buyback of subsidary share | I52: Proceeds from buyback of subsidary share | J52: =C52/C$4 -> 0 | K52: =D52/D$4 -> 0 | L52: =E52/E$4 -> 0 | M52: =F52/F$4 -> 0 | N52: =G52/G$4 -> 0
A53: Dividend received from subsidary | I53: Dividend received from subsidary | J53: =C53/C$4 -> 0 | K53: =D53/D$4 -> 0 | L53: =E53/E$4 -> 0 | M53: =F53/F$4 -> 0 | N53: =G53/G$4 -> 0
A54: Investment in subsidary | I54: Investment in subsidary | J54: =C54/C$4 -> 0 | K54: =D54/D$4 -> 0 | L54: =E54/E$4 -> 0 | M54: =F54/F$4 -> 0 | N54: =G54/G$4 -> 0
A55: Deferred compensation payable to shareholds of subsidaries | I55: Deferred compensation payable to shareholds of subsidaries | J55: =C55/C$4 -> 0 | K55: =D55/D$4 -> 0 | L55: =E55/E$4 -> 0 | M55: =F55/F$4 -> 0 | N55: =G55/G$4 -> 0
A56: Inter-corporate deposits | I56: Inter-corporate deposits | J56: =C56/C$4 -> 0 | K56: =D56/D$4 -> 0 | L56: =E56/E$4 -> 0 | M56: =F56/F$4 -> 0 | N56: =G56/G$4 -> 0
A57: Investment in Long term FDs | I57: Investment in Long term FDs | J57: =C57/C$4 -> 0 | K57: =D57/D$4 -> 0 | L57: =E57/E$4 -> 0 | M57: =F57/F$4 -> 0 | N57: =G57/G$4 -> 0
A58: Proceeds from Long term FDs | I58: Proceeds from Long term FDs | J58: =C58/C$4 -> 0 | K58: =D58/D$4 -> 0 | L58: =E58/E$4 -> 0 | M58: =F58/F$4 -> 0 | N58: =G58/G$4 -> 0
A59: Share application money paid | I59: Share application money paid | J59: =C59/C$4 -> 0 | K59: =D59/D$4 -> 0 | L59: =E59/E$4 -> 0 | M59: =F59/F$4 -> 0 | N59: =G59/G$4 -> 0
... A63: Rental Income from investment property | I63: Rental Income from investment property | J63: =C63/C$4 -> 0 | K63: =D63/D$4 -> 0 | L63: =E63/E$4 -> 0 | M63: =F63/F$4 -> 0 | N63: =G63/G$4 -> 0
A64: Less: Capital Expenditure/ Purchase of fixed assets | B64: -611 | C64: -383 | D64: -391 | E64: -358 | F64: -200 | I64: Less: Capital Expenditure/ Purchase of fixed assets | J64: =C64/C$4 -> -0.048659637 | K64: =D64/D$4 -> -0.057776051 | L64: =E64/E$4 -> -0.062839099 | M64: =F64/F$4 -> -0.041902016 | N64: =G64/G$4 -> 0
A65: Increase in Non-current investments | I65: Increase in Non-current investments | J65: =C65/C$4 -> 0 | K65: =D65/D$4 -> 0 | L65: =E65/E$4 -> 0 | M65: =F65/F$4 -> 0 | N65: =G65/G$4 -> 0
A66: Investment in Mutual fund | I66: Investment in Mutual fund | J66: =C66/C$4 -> 0 | K66: =D66/D$4 -> 0 | L66: =E66/E$4 -> 0 | M66: =F66/F$4 -> 0 | N66: =G66/G$4 -> 0
A67: Proceeds from sale of Mutual funds | I67: Proceeds from sale of Mutual funds | J67: =C67/C$4 -> 0 | K67: =D67/D$4 -> 0 | L67: =E67/E$4 -> 0 | M67: =F67/F$4 -> 0 | N67: =G67/G$4 -> 0
A68: Loan from / repayment subsidaries | I68: Loan from / repayment subsidaries | J68: =C68/C$4 -> 0 | K68: =D68/D$4 -> 0 | L68: =E68/E$4 -> 0 | M68: =F68/F$4 -> 0 | N68: =G68/G$4 -> 0
A69: Net Cash (used) in Investing Activities | B69: -673 | C69: -509 | D69: -579 | E69: -379 | F69: -280 | H69: =SUM(H47:H68) -> 0 | I69: Net Cash (used) in Investing Activities | J69: =C69/C$4 -> -0.064667768 | K69: =D69/D$4 -> -0.08555584 | L69: =E69/E$4 -> -0.066525191 | M69: =F69/F$4 -> -0.058662823 | N69: =G69/G$4 -> 0
A71: Cash Flow from Financing Activities | I71: Cash Flow from Financing Activities
A72: Interest Paid | I72: Interest Paid | J72: =C72/C$4 -> 0 | K72: =D72/D$4 -> 0 | L72: =E72/E$4 -> 0 | M72: =F72/F$4 -> 0 | N72: =G72/G$4 -> 0
A73: Proceeds from other non-current assets | I73: Proceeds from other non-current assets | J73: =C73/C$4 -> 0 | K73: =D73/D$4 -> 0 | L73: =E73/E$4 -> 0 | M73: =F73/F$4 -> 0 | N73: =G73/G$4 -> 0
A74: Dividend paid | I74: Dividend paid | J74: =C74/C$4 -> 0 | K74: =D74/D$4 -> 0 | L74: =E74/E$4 -> 0 | M74: =F74/F$4 -> 0 | N74: =G74/G$4 -> 0
A75: Others | I75: Tax on dividend paid | J75: =C75/C$4 -> 0 | K75: =D75/D$4 -> 0 | L75: =E75/E$4 -> 0 | M75: =F75/F$4 -> 0 | N75: =G75/G$4 -> 0
A76: Proceeds from issue of Share warrants/ Shares/ QIP | I76: Proceeds from issue of Share warrants/ Shares/ QIP | J76: =C76/C$4 -> 0 | K76: =D76/D$4 -> 0 | L76: =E76/E$4 -> 0 | M76: =F76/F$4 -> 0 | N76: =G76/G$4 -> 0
A77: Security premium | I77: Amount used in Buy back of Shares | J77: =C77/C$4 -> 0 | K77: =D77/D$4 -> 0 | L77: =E77/E$4 -> 0 | M77: =F77/F$4 -> 0 | N77: =G77/G$4 -> 0
A78: NCD Interest | I78: NCD Interest | J78: =C78/C$4 -> 0 | K78: =D78/D$4 -> 0 | L78: =E78/E$4 -> 0 | M78: =F78/F$4 -> 0 | N78: =G78/G$4 -> 0
A79: QIP/ Debenture issue expenses | I79: QIP/ Debenture issue expenses | J79: =C79/C$4 -> 0 | K79: =D79/D$4 -> 0 | L79: =E79/E$4 -> 0 | M79: =F79/F$4 -> 0 | N79: =G79/G$4 -> 0
A80: Issue of non-convertible debentures | I80: Issue of non-convertible debentures | J80: =C80/C$4 -> 0 | K80: =D80/D$4 -> 0 | L80: =E80/E$4 -> 0 | M80: =F80/F$4 -> 0 | N80: =G80/G$4 -> 0
A81: Proceeds from Borrowings | I81: Proceeds from Borrowings | J81: =C81/C$4 -> 0 | K81: =D81/D$4 -> 0 | L81: =E81/E$4 -> 0 | M81: =F81/F$4 -> 0 | N81: =G81/G$4 -> 0
A82: Repayment of Long term and other borrowings | I82: Repayment of Long term and other borrowings | J82: =C82/C$4 -> 0 | K82: =D82/D$4 -> 0 | L82: =E82/E$4 -> 0 | M82: =F82/F$4 -> 0 | N82: =G82/G$4 -> 0
A83: Repayment of borrowings/ non- covertible debentures | I83: Repayment of borrowings/ non- covertible debentures | J83: =C83/C$4 -> 0 | K83: =D83/D$4 -> 0 | L83: =E83/E$4 -> 0 | M83: =F83/F$4 -> 0 | N83: =G83/G$4 -> 0
A84: Net Cash (used) in Financing Activities | B84: -124 | C84: -123 | D84: -104 | E84: -101 | F84: -108 | H84: =SUM(H72:H83) -> 0 | I84: Net Cash (used) in Financing Activities | J84: =C84/C$4 -> -0.015626985 | K84: =D84/D$4 -> -0.015367543 | L84: =E84/E$4 -> -0.017728349 | M84: =F84/F$4 -> -0.022627089 | N84: =G84/G$4 -> 0
A85: Increase/Decrease in Cash and Cash Equivalents | B85: =B44+B69+B84 -> 76 | C85: =C44+C69+C84 -> -27 | D85: =D44+D69+D84 -> -60 | E85: =E44+E69+E84 -> 69 | F85: =F44+F69+F84 -> -91 | G85: =G44+G69+G84 -> 0 | H85: =H44+H69+H84 -> 0 | I85: Increase/Decrease in Cash and Cash Equivalents | J85: =C85/C$4 -> -0.0034303138 | K85: =D85/D$4 -> -0.0088658901 | L85: =E85/E$4 -> 0.012111446 | M85: =F85/F$4 -> -0.019065417 | N85: =G85/G$4 -> 0

Sheet Ratio Analysis_Conso
A1: Endurance Technologies
A3: Ratio Analysis
C5: 45717 | D5: 45352 | E5: 44986 | F5: 44621 | G5: 44256 | H5: 43891 | I5: 43525 | J5: 43160 | K5: 42795 | L5: 42430 | M5: 42064
A6: I | B6: Activity Ratios
A8: 1 | B8: Inventory Turnover ratio | C8: =C9/C10 -> 8.4159506 | D8: =D9/D10 -> 8.1882336 | E8: =E9/E10 -> 8.0082144 | F8: =F9/F10 -> 7.7906305 | G8: =G9/G10 -> 7.3094711 | H8: =H9/H10 -> 8.0955867 | I8: =I9/I10 -> 9.6767261 | J8: =J9/J10 -> 9.0475215 | ... M8: =M9/M10 -> #DIV/0!
B9: Cost of goods sold | C9: =SUM(Financials_Consol!B81:B84) -> 7610.46 | D9: =SUM(Financials_Consol!C81:C84) -> 6930.48 | E9: =SUM(Financials_Consol!D81:D84) -> 6093.13 | F9: =SUM(Financials_Consol!E81:E84) -> 5114.51 | G9: =SUM(Financials_Consol!F81:F84) -> 4246.62 | H9: =SUM(Financials_Consol!G81:G84) -> 4412.54 | I9: =SUM(Financials_Consol!H81:H84) -> 5002.19 | J9: =SUM(Financials_Consol!I81:I84) -> 4241.84 | ... M9: =SUM(Financials_Consol!L81:L84) -> 0
B10: Average Inventory | C10: =AVERAGE(Financials_Consol!B43:C43) -> 904.29 | D10: =AVERAGE(Financials_Consol!C43:D43) -> 846.395 | E10: =AVERAGE(Financials_Consol!D43:E43) -> 760.86 | F10: =AVERAGE(Financials_Consol!E43:F43) -> 656.495 | G10: =AVERAGE(Financials_Consol!F43:G43) -> 580.975 | H10: =AVERAGE(Financials_Consol!G43:H43) -> 545.055 | I10: =AVERAGE(Financials_Consol!H43:I43) -> 516.93 | J10: =AVERAGE(Financials_Consol!I43:J43) -> 468.84 | ... M10: =AVERAGE(Financials_Consol!L43:M43) -> #DIV/0!
A12: =A8+1 -> 2 | B12: Inventory Days | C12: =C13/C14 -> 43.370026 | D12: =D13/D14 -> 44.576159 | E12: =E13/E14 -> 45.703072 | F12: =F13/F14 -> 46.85115 | G12: =G13/G14 -> 49.935213 | H12: =H13/H14 -> 45.086294 | I12: =I13/I14 -> 37.719369 | J12: =J13/J14 -> 40.34254 | ... M12: =M13/M14 -> #DIV/0!
B13: Number of Days | C13: 365 | D13: 365 | E13: 366 | F13: 365 | G13: 365 | H13: 365 | I13: 365 | J13: 365 | K13: 365 | L13: 365 | M13: 365
B14: Inventory Turnover ratio | C14: =C8 -> 8.4159506 | D14: =D8 -> 8.1882336 | E14: =E8 -> 8.0082144 | F14: =F8 -> 7.7906305 | G14: =G8 -> 7.3094711 | H14: =H8 -> 8.0955867 | I14: =I8 -> 9.6767261 | J14: =J8 -> 9.0475215 | ... M14: =M8 -> #DIV/0!
A16: 3 | B16: Receivables Turnover | C16: =C17/C18 -> 8.6243808 | D16: =D17/D18 -> 8.4481338 | E16: =E17/E18 -> 8.2574095 | F16: =F17/F18 -> 7.5065503 | G16: =G17/G18 -> 7.6407114 | H16: =H17/H18 -> 8.6585976 | I16: =I17/I18 -> 7.9310017 | J16: =J17/J18 -> 7.3439518 | ... M16: =M17/M18 -> #DIV/0!
B17: Revenue | C17: =Financials_Consol!B77 -> 11560.81 | D17: =Financials_Consol!C77 -> 10240.87 | E17: =Financials_Consol!D77 -> 8804.05 | F17: =Financials_Consol!E77 -> 7549.15 | G17: =Financials_Consol!F77 -> 6547.02 | H17: =Financials_Consol!G77 -> 6917.7 | I17: =Financials_Consol!H77 -> 7510.5 | J17: =Financials_Consol!I77 -> 6351.38 | ... M17: =Financials_Consol!L77 -> 0
B18: Average Receivables | C18: =AVERAGE(Financials_Consol!B44:C44) -> 1340.48 | D18: =AVERAGE(Financials_Consol!C44:D44) -> 1212.205 | E18: =AVERAGE(Financials_Consol!D44:E44) -> 1066.2 | F18: =AVERAGE(Financials_Consol!E44:F44) -> 1005.675 | G18: =AVERAGE(Financials_Consol!F44:G44) -> 856.86 | H18: =AVERAGE(Financials_Consol!G44:H44) -> 798.94 | I18: =AVERAGE(Financials_Consol!H44:I44) -> 946.98 | J18: =AVERAGE(Financials_Consol!I44:J44) -> 864.845 | ... M18: =AVERAGE(Financials_Consol!L44:M44) -> #DIV/0!
A20: =A16+1 -> 4 | B20: Days of sales outstanding | C20: =C21/C22 -> 42.321879 | D20: =D21/D22 -> 43.204808 | E20: =E21/E22 -> 44.323828 | F20: =F21/F22 -> 48.624199 | G20: =G21/G22 -> 47.770421 | H20: =H21/H22 -> 42.154632 | I20: =I21/I22 -> 46.021929 | J20: =J21/J22 -> 49.700762 | ... M20: =M21/M22 -> #DIV/0!
B21: Number of Days | C21: 365 | D21: 365 | E21: 366 | F21: 365 | G21: 365 | H21: 365 | I21: 365 | J21: 365 | K21: 365 | L21: 365 | M21: 365
B22: Receivables Turnover | C22: =C16 -> 8.6243808 | D22: =D16 -> 8.4481338 | E22: =E16 -> 8.2574095 | F22: =F16 -> 7.5065503 | G22: =G16 -> 7.6407114 | H22: =H16 -> 8.6585976 | I22: =I16 -> 7.9310017 | J22: =J16 -> 7.3439518 | ... M22: =M16 -> #DIV/0!
A24: =A20+1 -> 5 | B24: Payables Turnover | C24: =C25/C26 -> 4.2531624 | D24: =D25/D26 -> 4.5742572 | E24: =E25/E26 -> 4.5691222 | F24: =F25/F26 -> 4.0596504 | G24: =G25/G26 -> 3.6225305 | H24: =H25/H26 -> 3.9403132 | I24: =I25/I26 -> 4.3461779 | J24: =J25/J26 -> 4.2575717 | ... M24: =M25/M26 -> #DIV/0!
B25: Cost of Goods Sold | C25: =C9 -> 7610.46 | D25: =D9 -> 6930.48 | E25: =E9 -> 6093.13 | F25: =F9 -> 5114.51 | G25: =G9 -> 4246.62 | H25: =H9 -> 4412.54 | I25: =I9 -> 5002.19 | J25: =J9 -> 4241.84 | ... M25: =M9 -> 0
B26: Average trade payables | C26: =AVERAGE(Financials_Consol!B22:C22) -> 1789.365 | D26: =AVERAGE(Financials_Consol!C22:D22) -> 1515.105 | E26: =AVERAGE(Financials_Consol!D22:E22) -> 1333.545 | F26: =AVERAGE(Financials_Consol!E22:F22) -> 1259.84 | G26: =AVERAGE(Financials_Consol!F22:G22) -> 1172.28 | H26: =AVERAGE(Financials_Consol!G22:H22) -> 1119.845 | I26: =AVERAGE(Financials_Consol!H22:I22) -> 1150.94 | J26: =AVERAGE(Financials_Consol!I22:J22) -> 996.305 | ... M26: =AVERAGE(Financials_Consol!L22:M22) -> #DIV/0!
A28: =A24+1 -> 6 | B28: Payables days | C28: =C29/C30 -> 85.818495 | D28: =D29/D30 -> 79.794376 | E28: =E29/E30 -> 79.884054 | F28: =F29/F30 -> 89.909219 | G28: =G29/G30 -> 100.7583 | H28: =H29/H30 -> 92.632231 | I28: =I29/I30 -> 83.981836 | J28: =J29/J30 -> 85.729619 | ... M28: =M29/M30 -> #DIV/0!
B29: Number of Days | C29: 365 | D29: 365 | E29: 365 | F29: 365 | G29: 365 | H29: 365 | I29: 365 | J29: 365 | K29: 365 | L29: 365 | M29: 365
B30: Payables Turnover | C30: =C24 -> 4.2531624 | D30: =D24 -> 4.5742572 | E30: =E24 -> 4.5691222 | F30: =F24 -> 4.0596504 | G30: =G24 -> 3.6225305 | H30: =H24 -> 3.9403132 | I30: =I24 -> 4.3461779 | J30: =J24 -> 4.2575717 | ... M30: =M24 -> #DIV/0!
A32: =A24+1 -> 6 | B32: Working Capital Turnover | C32: =C33/C34 -> 6.0779191 | D32: =D33/D34 -> 6.5963311 | E32: =E33/E34 -> 6.9810805 | F32: =F33/F34 -> 6.3323296 | G32: =G33/G34 -> 5.5443282 | H32: =H33/H34 -> 11.863049 | I32: =I33/I34 -> 19.700706 | J32: =J33/J34 -> 16.162506 | ... M32: =M33/M34 -> #DIV/0!
B33: Revenue | C33: =C17 -> 11560.81 | D33: =D17 -> 10240.87 | E33: =E17 -> 8804.05 | F33: =F17 -> 7549.15 | G33: =G17 -> 6547.02 | H33: =H17 -> 6917.7 | I33: =I17 -> 7510.5 | J33: =J17 -> 6351.38 | ... M33: =M17 -> 0
B34: Average working capital | C34: =Financials_Consol!B48-Financials_Consol!B25 -> 1902.1 | D34: =Financials_Consol!C48-Financials_Consol!C25 -> 1552.51 | E34: =Financials_Consol!D48-Financials_Consol!D25 -> 1261.13 | F34: =Financials_Consol!E48-Financials_Consol!E25 -> 1192.16 | G34: =Financials_Consol!F48-Financials_Consol!F25 -> 1180.85 | H34: =Financials_Consol!G48-Financials_Consol!G25 -> 583.13 | I34: =Financials_Consol!H48-Financials_Consol!H25 -> 381.23 | J34: =Financials_Consol!I48-Financials_Consol!I25 -> 392.97 | ... M34: =Financials_Consol!L48-Financials_Consol!L25 -> 0
A36: =A32+1 -> 7 | B36: Fixed Asset Turnover | C36: =C37/C38 -> 3.1212448 | D36: =D37/D38 -> 3.2402997 | E36: =E37/E38 -> 3.1544202 | F36: =F37/F38 -> 2.9130089 | G36: =G37/G38 -> 2.5702004 | H36: =H37/H38 -> 2.944479 | I36: =I37/I38 -> 3.8700352 | J36: =J37/J38 -> 3.8558177 | ... M36: =M37/M38 -> #DIV/0!
B37: Revenue | C37: =C17 -> 11560.81 | D37: =D17 -> 10240.87 | E37: =E17 -> 8804.05 | F37: =F17 -> 7549.15 | G37: =G17 -> 6547.02 | H37: =H17 -> 6917.7 | I37: =I17 -> 7510.5 | J37: =J17 -> 6351.38 | ... M37: =M17 -> 0
B38: Average Net fixed assets | C38: =AVERAGE(Financials_Consol!B34:C34) -> 3703.91 | D38: =AVERAGE(Financials_Consol!C34:D34) -> 3160.47 | E38: =AVERAGE(Financials_Consol!D34:E34) -> 2791.02 | F38: =AVERAGE(Financials_Consol!E34:F34) -> 2591.53 | G38: =AVERAGE(Financials_Consol!F34:G34) -> 2547.28 | H38: =AVERAGE(Financials_Consol!G34:H34) -> 2349.38 | I38: =AVERAGE(Financials_Consol!H34:I34) -> 1940.68 | J38: =AVERAGE(Financials_Consol!I34:J34) -> 1647.22 | ... M38: =AVERAGE(Financials_Consol!L34:M34) -> 0
A40: =A36+1 -> 8 | B40: Total Asset turnover | C40: =C41/C42 -> 1.3581005 | D40: =D41/D42 -> 1.3944378 | E40: =E41/E42 -> 1.3908353 | F40: =F41/F42 -> 1.3009989 | G40: =G41/G42 -> 1.2104542 | H40: =H41/H42 -> 1.4037598 | I40: =I41/I42 -> 1.6457186 | J40: =J41/J42 -> 1.6176646 | ... M40: =M41/M42 -> #DIV/0!
B41: Revenue | C41: =C17 -> 11560.81 | D41: =D17 -> 10240.87 | E41: =E17 -> 8804.05 | F41: =F17 -> 7549.15 | G41: =G17 -> 6547.02 | H41: =H17 -> 6917.7 | I41: =I17 -> 7510.5 | J41: =J17 -> 6351.38 | ... M41: =M17 -> 0
B42: Average total assets | C42: =AVERAGE(Financials_Consol!B26:C26) -> 8512.485 | D42: =AVERAGE(Financials_Consol!C26:D26) -> 7344.085 | E42: =AVERAGE(Financials_Consol!D26:E26) -> 6330.045 | F42: =AVERAGE(Financials_Consol!E26:F26) -> 5802.58 | G42: =AVERAGE(Financials_Consol!F26:G26) -> 5408.73 | H42: =AVERAGE(Financials_Consol!G26:H26) -> 4927.98 | I42: =AVERAGE(Financials_Consol!H26:I26) -> 4563.66 | J42: =AVERAGE(Financials_Consol!I26:J26) -> 3926.265 | ... M42: =AVERAGE(Financials_Consol!L26:M26) -> 0
A45: II | B45: Liquidity Ratios
A47: 1 | B47: Current ratio | C47: =C48/C49 -> 1.7066249 | D47: =D48/D49 -> 1.6938809 | E47: =E48/E49 -> 1.6531848 | F47: =F48/F49 -> 1.7193821 | G47: =G48/G49 -> 1.6851942 | H47: =H48/H49 -> 1.3727428 | I47: =I48/I49 -> 1.213658 | J47: =J48/J49 -> 1.2236418 | ... M47: =M48/M49 -> #DIV/0!
B48: Current assets | C48: =Financials_Consol!B48 -> 4593.91 | D48: =Financials_Consol!C48 -> 3789.94 | E48: =Financials_Consol!D48 -> 3191.87 | F48: =Financials_Consol!E48 -> 2849.36 | G48: =Financials_Consol!F48 -> 2904.23 | H48: =Financials_Consol!G48 -> 2147.56 | I48: =Financials_Consol!H48 -> 2165.53 | J48: =Financials_Consol!I48 -> 2150.11 | ... M48: =Financials_Consol!L48 -> 0
B49: Current liabilities | C49: =Financials_Consol!B25 -> 2691.81 | D49: =Financials_Consol!C25 -> 2237.43 | E49: =Financials_Consol!D25 -> 1930.74 | F49: =Financials_Consol!E25 -> 1657.2 | G49: =Financials_Consol!F25 -> 1723.38 | H49: =Financials_Consol!G25 -> 1564.43 | I49: =Financials_Consol!H25 -> 1784.3 | J49: =Financials_Consol!I25 -> 1757.14 | ... M49: =Financials_Consol!L25 -> 0
A51: =A47+1 -> 2 | B51: Quick Ratio | C51: =C52/C53 -> 1.358766 | D51: =D52/D53 -> 1.3040542 | E51: =E52/E53 -> 1.2281768 | F51: =F52/F53 -> 1.296295 | G51: =G52/G53 -> 1.3301651 | H51: =H52/H53 -> 1.0211131 | I51: =I52/I53 -> 0.91101272 | J51: =J52/J53 -> 0.94258852 | ... M51: =M52/M53 -> #DIV/0!
B52: Current assets - Inventory | C52: =Financials_Consol!B48-Financials_Consol!B43 -> 3657.54 | D52: =Financials_Consol!C48-Financials_Consol!C43 -> 2917.73 | E52: =Financials_Consol!D48-Financials_Consol!D43 -> 2371.29 | F52: =Financials_Consol!E48-Financials_Consol!E43 -> 2148.22 | G52: =Financials_Consol!F48-Financials_Consol!F43 -> 2292.38 | H52: =Financials_Consol!G48-Financials_Consol!G43 -> 1597.46 | I52: =Financials_Consol!H48-Financials_Consol!H43 -> 1625.52 | J52: =Financials_Consol!I48-Financials_Consol!I43 -> 1656.26 | ... M52: =Financials_Consol!L48-Financials_Consol!L43 -> 0
B53: Current liabilities | C53: =Financials_Consol!B25 -> 2691.81 | D53: =Financials_Consol!C25 -> 2237.43 | E53: =Financials_Consol!D25 -> 1930.74 | F53: =Financials_Consol!E25 -> 1657.2 | G53: =Financials_Consol!F25 -> 1723.38 | H53: =Financials_Consol!G25 -> 1564.43 | I53: =Financials_Consol!H25 -> 1784.3 | J53: =Financials_Consol!I25 -> 1757.14 | ... M53: =Financials_Consol!L25 -> 0
A55: =A51+1 -> 3 | B55: Cash Ratio | C55: =C56/C57 -> 0.83176747 | D55: =D56/D57 -> 0.73984438 | E55: =E56/E57 -> 0.62631944 | F55: =F56/F57 -> 0.71074704 | G55: =G56/G57 -> 0.72613121 | H55: =H56/H57 -> 0.59109068 | I55: =I56/I57 -> 0.39252368 | J55: =J56/J57 -> 0.39122665 | ... M55: =M56/M57 -> #DIV/0!
B56: Current assets - Inventory - receivables | C56: =Financials_Consol!B48-Financials_Consol!B43-Financials_Consol!B44 -> 2238.96 | D56: =Financials_Consol!C48-Financials_Consol!C43-Financials_Consol!C44 -> 1655.35 | E56: =Financials_Consol!D48-Financials_Consol!D43-Financials_Consol!D44 -> 1209.26 | F56: =Financials_Consol!E48-Financials_Consol!E43-Financials_Consol!E44 -> 1177.85 | G56: =Financials_Consol!F48-Financials_Consol!F43-Financials_Consol!F44 -> 1251.4 | H56: =Financials_Consol!G48-Financials_Consol!G43-Financials_Consol!G44 -> 924.72 | I56: =Financials_Consol!H48-Financials_Consol!H43-Financials_Consol!H44 -> 700.38 | J56: =Financials_Consol!I48-Financials_Consol!I43-Financials_Consol!I44 -> 687.44 | ... M56: =Financials_Consol!L48-Financials_Consol!L43-Financials_Consol!L44 -> 0
B57: Current liabilities | C57: =Financials_Consol!B25 -> 2691.81 | D57: =Financials_Consol!C25 -> 2237.43 | E57: =Financials_Consol!D25 -> 1930.74 | F57: =Financials_Consol!E25 -> 1657.2 | G57: =Financials_Consol!F25 -> 1723.38 | H57: =Financials_Consol!G25 -> 1564.43 | I57: =Financials_Consol!H25 -> 1784.3 | J57: =Financials_Consol!I25 -> 1757.14 | ... M57: =Financials_Consol!L25 -> 0
A59: =A55+1 -> 4 | B59: Cash conversion cycle | C59: =C60+C61-C62 -> -43.496616 | D59: =D60+D61-D62 -> -36.589567 | E59: =E60+E61-E62 -> -35.560226 | F59: =F60+F61-F62 -> -41.28502 | G59: =G60+G61-G62 -> -52.987876 | H59: =H60+H61-H62 -> -50.477599 | I59: =I60+I61-I62 -> -37.959907 | J59: =J60+J61-J62 -> -36.028857 | ... M59: =M60+M61-M62 -> #DIV/0!
B60: Inventory Days | C60: 0 | D60: 0 | E60: 0 | F60: 0 | G60: 0 | H60: 0 | I60: 0 | J60: 0 | K60: 0 | L60: 0 | M60: 0
B61: Receivable Days | C61: =C20 -> 42.321879 | D61: =D20 -> 43.204808 | E61: =E20 -> 44.323828 | F61: =F20 -> 48.624199 | G61: =G20 -> 47.770421 | H61: =H20 -> 42.154632 | I61: =I20 -> 46.021929 | J61: =J20 -> 49.700762 | ... M61: =M20 -> #DIV/0!
B62: Payable days | C62: =C28 -> 85.818495 | D62: =D28 -> 79.794376 | E62: =E28 -> 79.884054 | F62: =F28 -> 89.909219 | G62: =G28 -> 100.7583 | H62: =H28 -> 92.632231 | I62: =I28 -> 83.981836 | J62: =J28 -> 85.729619 | ... M62: =M28 -> #DIV/0!
A64: III | B64: Solvency Ratios
A66: 1 | B66: Debts- asset ratio ( Both short term and long term) | C66: =C67/C68 -> 0.09889849 | D66: =D67/D68 -> 0.093812851 | E66: =E67/E68 -> 0.071052133 | F66: =F67/F68 -> 0.068193225 | G66: =G67/G68 -> 0.073802009 | H66: =H67/H68 -> 0.10812597 | I66: =I67/I68 -> 0.11667266 | J66: =J67/J68 -> 0.12867173 | ... M66: =M67/M68 -> #DIV/0!
B67: Total Debt (Short- term and long term) | C67: =Financials_Consol!B15+Financials_Consol!B21 -> 903.86 | D67: =Financials_Consol!C15+Financials_Consol!C21 -> 739.78 | E67: =Financials_Consol!D15+Financials_Consol!D21 -> 483.33 | F67: =Financials_Consol!E15+Financials_Consol!E21 -> 399.45 | G67: =Financials_Consol!F15+Financials_Consol!F21 -> 424.18 | H67: =Financials_Consol!G15+Financials_Consol!G21 -> 548.19 | I67: =Financials_Consol!H15+Financials_Consol!H21 -> 558.4 | J67: =Financials_Consol!I15+Financials_Consol!I21 -> 558.6 | ... M67: =Financials_Consol!L15+Financials_Consol!L21 -> 0
B68: Total Assets | C68: =Financials_Consol!B26 -> 9139.27 | D68: =Financials_Consol!C26 -> 7885.7 | E68: =Financials_Consol!D26 -> 6802.47 | F68: =Financials_Consol!E26 -> 5857.62 | G68: =Financials_Consol!F26 -> 5747.54 | H68: =Financials_Consol!G26 -> 5069.92 | I68: =Financials_Consol!H26 -> 4786.04 | J68: =Financials_Consol!I26 -> 4341.28 | ... M68: =Financials_Consol!L26 -> 0
A70: =A66+1 -> 2 | B70: Debts- asset ratio (long term) | C70: =C71/C72 -> 0.065064278 | D70: =D71/D72 -> 0.060901378 | E70: =E71/E72 -> 0.040889559 | F70: =F71/F72 -> 0.033105596 | G70: =G71/G72 -> 0.065972573 | H70: =H71/H72 -> 0.079308944 | I70: =I71/I72 -> 0.072377164 | J70: =J71/J72 -> 0.087607802 | ... M70: =M71/M72 -> #DIV/0!
B71: Total Debt (long term) | C71: =Financials_Consol!B15 -> 594.64 | D71: =Financials_Consol!C15 -> 480.25 | E71: =Financials_Consol!D15 -> 278.15 | F71: =Financials_Consol!E15 -> 193.92 | G71: =Financials_Consol!F15 -> 379.18 | H71: =Financials_Consol!G15 -> 402.09 | I71: =Financials_Consol!H15 -> 346.4 | J71: =Financials_Consol!I15 -> 380.33 | ... M71: =Financials_Consol!L15 -> 0
B72: Total Assets | C72: =Financials_Consol!B26 -> 9139.27 | D72: =Financials_Consol!C26 -> 7885.7 | E72: =Financials_Consol!D26 -> 6802.47 | F72: =Financials_Consol!E26 -> 5857.62 | G72: =Financials_Consol!F26 -> 5747.54 | H72: =Financials_Consol!G26 -> 5069.92 | I72: =Financials_Consol!H26 -> 4786.04 | J72: =Financials_Consol!I26 -> 4341.28 | ... M72: =Financials_Consol!L26 -> 0
A74: =A70+1 -> 3 | B74: Debt to capital | C74: =C75/C76 -> 0.13650856 | D74: =D75/D76 -> 0.12939506 | E74: =E75/E76 -> 0.098730252 | F74: =F75/F76 -> 0.092477266 | G74: =G75/G76 -> 0.10640972 | H74: =H75/H76 -> 0.15423594 | I74: =I75/I76 -> 0.17879785 | J74: =J75/J76 -> 0.20450676 | ... M74: =M75/M76 -> #DIV/0!
B75: Total Debt (Short- term and long term) | C75: =C67 -> 903.86 | D75: =D67 -> 739.78 | E75: =E67 -> 483.33 | F75: =F67 -> 399.45 | G75: =G67 -> 424.18 | H75: =H67 -> 548.19 | I75: =I67 -> 558.4 | J75: =J67 -> 558.6 | ... M75: =M67 -> 0
B76: Total Capital empployed | C76: =Financials_Consol!B12+C75 -> 6621.27 | D76: =Financials_Consol!C12+D75 -> 5717.22 | E76: =Financials_Consol!D12+E75 -> 4895.46 | F76: =Financials_Consol!E12+F75 -> 4319.44 | G76: =Financials_Consol!F12+G75 -> 3986.29 | H76: =Financials_Consol!G12+H75 -> 3554.23 | I76: =Financials_Consol!H12+I75 -> 3123.08 | J76: =Financials_Consol!I12+J75 -> 2731.45 | ... M76: =Financials_Consol!L12+M75 -> 0
A78: =A74+1 -> 4 | B78: Debt to Equity | C78: =C79/C80 -> 0.15808906 | D78: =D79/D80 -> 0.1486266 | E78: =E79/E80 -> 0.10954573 | F78: =F79/F80 -> 0.049469514 | G78: =G79/G80 -> 0.10644814 | H78: =H79/H80 -> 0.1337607 | I78: =I79/I80 -> 0.13506558 | J78: =J79/J80 -> 0.17503739 | ... M78: =M79/M80 -> #DIV/0!
B79: Total Debt (Short- term and long term) | C79: =C67 -> 903.86 | D79: =D67 -> 739.78 | E79: =E67 -> 483.33 | F79: =F71 -> 193.92 | G79: =G71 -> 379.18 | H79: =H71 -> 402.09 | I79: =I71 -> 346.4 | J79: =J71 -> 380.33 | K79: =K71 -> 342.23 | L79: =L71 -> 416.27 | M79: =M71 -> 0
B80: Total Equity | C80: =Financials_Consol!B12 -> 5717.41 | D80: =Financials_Consol!C12 -> 4977.44 | E80: =Financials_Consol!D12 -> 4412.13 | F80: =Financials_Consol!E12 -> 3919.99 | G80: =Financials_Consol!F12 -> 3562.11 | H80: =Financials_Consol!G12 -> 3006.04 | I80: =Financials_Consol!H12 -> 2564.68 | J80: =Financials_Consol!I12 -> 2172.85 | ... M80: =Financials_Consol!L12 -> 0
A82: =A78+1 -> 5 | B82: Financial leverage Ratio | C82: =C83/C84 -> 1.5233678 | D82: =D83/D84 -> 1.4809879 | E82: =E83/E84 -> 1.4515333 | F82: =F83/F84 -> 1.5043263 | G82: =G83/G84 -> 1.5957416 | H82: =H83/H84 -> 1.7128037 | I82: =I83/I84 -> 1.8612294 | J82: =J83/J84 -> 1.9372018 | ... M82: =M83/M84 -> #DIV/0!
B83: Average total assets | C83: =AVERAGE(Financials_Consol!B49:C49) -> 8146.095 | D83: =AVERAGE(Financials_Consol!C49:D49) -> 6952.92 | E83: =AVERAGE(Financials_Consol!D49:E49) -> 6047.175 | F83: =AVERAGE(Financials_Consol!E49:F49) -> 5627.76 | G83: =AVERAGE(Financials_Consol!F49:G49) -> 5240.535 | H83: =AVERAGE(Financials_Consol!G49:H49) -> 4770.775 | I83: =AVERAGE(Financials_Consol!H49:I49) -> 4408.815 | J83: =AVERAGE(Financials_Consol!I49:J49) -> 3779.655 | ... M83: =AVERAGE(Financials_Consol!L49:M49) -> 278.355
B84: Average total Equity | C84: =AVERAGE(Financials_Consol!B12:C12) -> 5347.425 | D84: =AVERAGE(Financials_Consol!C12:D12) -> 4694.785 | E84: =AVERAGE(Financials_Consol!D12:E12) -> 4166.06 | F84: =AVERAGE(Financials_Consol!E12:F12) -> 3741.05 | G84: =AVERAGE(Financials_Consol!F12:G12) -> 3284.075 | H84: =AVERAGE(Financials_Consol!G12:H12) -> 2785.36 | I84: =AVERAGE(Financials_Consol!H12:I12) -> 2368.765 | J84: =AVERAGE(Financials_Consol!I12:J12) -> 1951.09 | ... M84: =AVERAGE(Financials_Consol!L12:M12) -> 0
A86: =A82+1 -> 6 | B86: Interest coverage ratio | C86: =C87/C88 -> 3.0094856 | D86: =D87/D88 -> 2.8923184 | E86: =E87/E88 -> 2.5170074 | F86: =F87/F88 -> 2.6178975 | G86: =G87/G88 -> 2.6485945 | H86: =H87/H88 -> 2.802018 | I86: =I87/I88 -> 3.0039074 | J86: =J87/J88 -> 2.8850711 | ... M86: =M87/M88 -> #DIV/0!
B87: EBIT | C87: =Financials_Consol!B91+Financials_Consol!B86 -> 1621.24 | D87: =Financials_Consol!C91+Financials_Consol!C86 -> 1370.93 | E87: =Financials_Consol!D91+Financials_Consol!D86 -> 1061.12 | F87: =Financials_Consol!E91+Financials_Consol!E86 -> 999.33 | G87: =Financials_Consol!F91+Financials_Consol!F86 -> 1057.16 | H87: =Financials_Consol!G91+Financials_Consol!G86 -> 1160.82 | I87: =Financials_Consol!H91+Financials_Consol!H86 -> 1130.1 | J87: =Financials_Consol!I91+Financials_Consol!I86 -> 927.81 | ... M87: =Financials_Consol!L91+Financials_Consol!L86 -> 0
B88: Interest Cost | C88: =Financials_Consol!B86 -> 538.71 | D88: =Financials_Consol!C86 -> 473.99 | E88: =Financials_Consol!D86 -> 421.58 | F88: =Financials_Consol!E86 -> 381.73 | G88: =Financials_Consol!F86 -> 399.14 | H88: =Financials_Consol!G86 -> 414.28 | I88: =Financials_Consol!H86 -> 376.21 | J88: =Financials_Consol!I86 -> 321.59 | ... M88: =Financials_Consol!L86 -> 0
A91: IV | B91: Profitability Ratios (Return on Sales)
A93: 1 | B93: Gross Profit Ratio | C93: =C94/C95 -> 0.34170184 | D93: =D94/D95 -> 0.32325281 | E93: =E94/E95 -> 0.30791738 | F93: =F94/F95 -> 0.32250518 | G93: =G94/G95 -> 0.35136596 | H93: =H94/H95 -> 0.3621377 | I93: =I94/I95 -> 0.33397377 | J93: =J94/J95 -> 0.33213884 | ... M93: =M94/M95 -> #DIV/0!
B94: Gross Profit | C94: =Financials_Consol!B77-C9 -> 3950.35 | D94: =Financials_Consol!C77-D9 -> 3310.39 | E94: =Financials_Consol!D77-E9 -> 2710.92 | F94: =Financials_Consol!E77-F9 -> 2434.64 | G94: =Financials_Consol!F77-G9 -> 2300.4 | H94: =Financials_Consol!G77-H9 -> 2505.16 | I94: =Financials_Consol!H77-I9 -> 2508.31 | J94: =Financials_Consol!I77-J9 -> 2109.54 | ... M94: =Financials_Consol!L77-M9 -> 0
B95: Sales | C95: =Financials_Consol!B77 -> 11560.81 | D95: =Financials_Consol!C77 -> 10240.87 | E95: =Financials_Consol!D77 -> 8804.05 | F95: =Financials_Consol!E77 -> 7549.15 | G95: =Financials_Consol!F77 -> 6547.02 | H95: =Financials_Consol!G77 -> 6917.7 | I95: =Financials_Consol!H77 -> 7510.5 | J95: =Financials_Consol!I77 -> 6351.38 | ... M95: =Financials_Consol!L77 -> 0
B96: Sales growth | C96: =(C95-D95)/D95 -> 0.12888944 | D96: =(D95-E95)/E95 -> 0.16319989 | E96: =(E95-F95)/F95 -> 0.16623064 | F96: =(F95-G95)/G95 -> 0.15306659 | G96: =(G95-H95)/H95 -> -0.053584284 | H96: =(H95-I95)/I95 -> -0.078929499 | I96: =(I95-J95)/J95 -> 0.18249892 | J96: =(J95-K95)/K95 -> 0.13602713 | ... L96: =(L95-M95)/M95 -> #DIV/0!
A98: =A93+1 -> 2 | B98: Operating profit ratio | C98: =C99/C100 -> 0.34777061 | D98: =D99/D100 -> 0.32744777 | E98: =E99/E100 -> 0.31073994 | F98: =F99/F100 -> 0.3271004 | G98: =G99/G100 -> 0.35395493 | H98: =H99/H100 -> 0.36767712 | I98: =I99/I100 -> 0.33573664 | J98: =J99/J100 -> 0.33213097 | ... M98: =M99/M100 -> #DIV/0!
B99: Operating Profit | C99: =Financials_Consol!B91+Financials_Consol!B86+Financials_Consol!B87 -> 4020.51 | D99: =Financials_Consol!C91+Financials_Consol!C86+Financials_Consol!C87 -> 3353.35 | E99: =Financials_Consol!D91+Financials_Consol!D86+Financials_Consol!D87 -> 2735.77 | F99: =Financials_Consol!E91+Financials_Consol!E86+Financials_Consol!E87 -> 2469.33 | G99: =Financials_Consol!F91+Financials_Consol!F86+Financials_Consol!F87 -> 2317.35 | H99: =Financials_Consol!G91+Financials_Consol!G86+Financials_Consol!G87 -> 2543.48 | I99: =Financials_Consol!H91+Financials_Consol!H86+Financials_Consol!H87 -> 2521.55 | J99: =Financials_Consol!I91+Financials_Consol!I86+Financials_Consol!I87 -> 2109.49 | ... M99: =Financials_Consol!L91+Financials_Consol!L86+Financials_Consol!L87 -> 0
B100: Sales | C100: =Financials_Consol!B77 -> 11560.81 | D100: =Financials_Consol!C77 -> 10240.87 | E100: =Financials_Consol!D77 -> 8804.05 | F100: =Financials_Consol!E77 -> 7549.15 | G100: =Financials_Consol!F77 -> 6547.02 | H100: =Financials_Consol!G77 -> 6917.7 | I100: =Financials_Consol!H77 -> 7510.5 | J100: =Financials_Consol!I77 -> 6351.38 | ... M100: =Financials_Consol!L77 -> 0
A102: =A98+1 -> 3 | B102: Net profit ratio | C102: =C103/C104 -> 0.072343547 | D102: =D103/D104 -> 0.06644748 | E102: =E103/E104 -> 0.054472657 | F102: =F103/F104 -> 0.061028063 | G102: =G103/G104 -> 0.079358242 | H102: =H103/H104 -> 0.08175116 | I102: =I103/I104 -> 0.065909061 | J102: =J103/J104 -> 0.061523637 | ... M102: =M103/M104 -> #DIV/0!
B103: Net Profit | C103: =Financials_Consol!B102 -> 836.35 | D103: =Financials_Consol!C102 -> 680.48 | E103: =Financials_Consol!D102 -> 479.58 | F103: =Financials_Consol!E102 -> 460.71 | G103: =Financials_Consol!F102 -> 519.56 | H103: =Financials_Consol!G102 -> 565.53 | I103: =Financials_Consol!H102 -> 495.01 | J103: =Financials_Consol!I102 -> 390.76 | ... M103: =Financials_Consol!L102 -> 0
B104: Sales | C104: =C100 -> 11560.81 | D104: =D100 -> 10240.87 | E104: =E100 -> 8804.05 | F104: =F100 -> 7549.15 | G104: =G100 -> 6547.02 | H104: =H100 -> 6917.7 | I104: =I100 -> 7510.5 | J104: =J100 -> 6351.38 | ... M104: =M100 -> 0
B105: % growth | C105: =(C103-D103)/D103 -> 0.2290589 | D105: =(D103-E103)/E103 -> 0.41890821 | E105: =(E103-F103)/F103 -> 0.040958521 | F105: =(F103-G103)/G103 -> -0.11326892 | G105: =(G103-H103)/H103 -> -0.081286581 | H105: =(H103-I103)/I103 -> 0.14246177 | I105: =(I103-J103)/J103 -> 0.2667878 | J105: =(J103-K103)/K103 -> 0.18308153 | ... L105: =(L103-M103)/M103 -> #DIV/0!
A107: V | B107: Profitability Ratios (Return on investment)
A109: 1 | B109: Return on assets | C109: =C110/C111 -> 0.17858601 | D109: =D110/D111 -> 0.17610832 | E109: =E110/E111 -> 0.15393168 | F109: =F110/F111 -> 0.15661212 | G109: =G110/G111 -> 0.17819283 | H109: =H110/H111 -> 0.21648631 | I109: =I110/I111 -> 0.22996 | J109: =J110/J111 -> 0.21918368 | ... M109: =M110/M111 -> 0
B110: Net profit + Post tax interest | C110: =Financials_Consol!B91+Financials_Consol!B86*(1-30.9/100) -> 1454.7786 | D110: =Financials_Consol!C91+Financials_Consol!C86*(1-30.9/100) -> 1224.4671 | E110: =Financials_Consol!D91+Financials_Consol!D86*(1-30.9/100) -> 930.85178 | F110: =Financials_Consol!E91+Financials_Consol!E86*(1-30.9/100) -> 881.37543 | G110: =Financials_Consol!F91+Financials_Consol!F86*(1-30.9/100) -> 933.82574 | H110: =Financials_Consol!G91+Financials_Consol!G86*(1-30.9/100) -> 1032.8075 | I110: =Financials_Consol!H91+Financials_Consol!H86*(1-30.9/100) -> 1013.8511 | J110: =Financials_Consol!I91+Financials_Consol!I86*(1-30.9/100) -> 828.43869 | ... M110: =Financials_Consol!L91+Financials_Consol!L86*(1-30.9/100) -> 0
B111: Average total assets | C111: =C83 -> 8146.095 | D111: =D83 -> 6952.92 | E111: =E83 -> 6047.175 | F111: =F83 -> 5627.76 | G111: =G83 -> 5240.535 | H111: =H83 -> 4770.775 | I111: =I83 -> 4408.815 | J111: =J83 -> 3779.655 | ... M111: =M83 -> 278.355
A113: =A109+1 -> 2 | B113: Return on capital employed | C113: =C114/C115 -> 0.24485333 | D113: =D114/D115 -> 0.23978962 | E113: =E114/E115 -> 0.21675593 | F113: =F114/F115 -> 0.23135638 | G113: =G114/G115 -> 0.26519897 | H113: =H114/H115 -> 0.32660239 | I113: =I114/I115 -> 0.36185432 | J113: =J114/J115 -> 0.33967673 | ... M113: =M114/M115 -> #DIV/0!
B114: PBIT | C114: =C87 -> 1621.24 | D114: =D87 -> 1370.93 | E114: =E87 -> 1061.12 | F114: =F87 -> 999.33 | G114: =G87 -> 1057.16 | H114: =H87 -> 1160.82 | I114: =I87 -> 1130.1 | J114: =J87 -> 927.81 | ... M114: =M87 -> 0
B115: DEBT + EQUITY | C115: =Financials_Consol!B10+Financials_Consol!B15+Financials_Consol!B21 -> 6621.27 | D115: =Financials_Consol!C10+Financials_Consol!C15+Financials_Consol!C21 -> 5717.22 | E115: =Financials_Consol!D10+Financials_Consol!D15+Financials_Consol!D21 -> 4895.46 | F115: =Financials_Consol!E10+Financials_Consol!E15+Financials_Consol!E21 -> 4319.44 | G115: =Financials_Consol!F10+Financials_Consol!F15+Financials_Consol!F21 -> 3986.29 | H115: =Financials_Consol!G10+Financials_Consol!G15+Financials_Consol!G21 -> 3554.23 | I115: =Financials_Consol!H10+Financials_Consol!H15+Financials_Consol!H21 -> 3123.08 | J115: =Financials_Consol!I10+Financials_Consol!I15+Financials_Consol!I21 -> 2731.45 | ... M115: =Financials_Consol!L10+Financials_Consol!L15+Financials_Consol!L21 -> 0
A117: =A113+1 -> 3 | B117: Return on equity (PBT) | C117: =C118/C119 -> 0.20471722 | D117: =D118/D119 -> 0.19105028 | E117: =E118/E119 -> 0.15104199 | F117: =F118/F119 -> 0.15668061 | G117: =G118/G119 -> 0.19694739 | H117: =H118/H119 -> 0.2680228 | I117: =I118/I119 -> 0.30948195 | J117: =J118/J119 -> 0.29693146 | ... M117: =M118/M119 -> #DIV/0!
B118: Net profit before tax | C118: =Financials_Consol!B93 -> 1094.71 | D118: =Financials_Consol!C93 -> 896.94 | E118: =Financials_Consol!D93 -> 629.25 | F118: =Financials_Consol!E93 -> 586.15 | G118: =Financials_Consol!F93 -> 646.79 | H118: =Financials_Consol!G93 -> 746.54 | I118: =Financials_Consol!H93 -> 733.09 | J118: =Financials_Consol!I93 -> 579.34 | ... M118: =Financials_Consol!L93 -> 0
B119: Average equity | C119: =AVERAGE(Financials_Consol!B10:C10) -> 5347.425 | D119: =AVERAGE(Financials_Consol!C10:D10) -> 4694.785 | E119: =AVERAGE(Financials_Consol!D10:E10) -> 4166.06 | F119: =AVERAGE(Financials_Consol!E10:F10) -> 3741.05 | G119: =AVERAGE(Financials_Consol!F10:G10) -> 3284.075 | H119: =AVERAGE(Financials_Consol!G10:H10) -> 2785.36 | I119: =AVERAGE(Financials_Consol!H10:I10) -> 2368.765 | J119: =AVERAGE(Financials_Consol!I10:J10) -> 1951.09 | ... M119: =AVERAGE(Financials_Consol!L10:M10) -> 0
A121: =A117+1 -> 4 | B121: Return on equity (PAT) | C121: =C122/C123 -> 0.15412465 | D121: =D122/D123 -> 0.1449438 | E121: =E122/E123 -> 0.11758592 | F121: =F122/F123 -> 0.13155665 | G121: =G122/G123 -> 0.16162542 | H121: =H122/H123 -> 0.20303659 | I121: =I122/I123 -> 0.21775482 | J121: =J122/J123 -> 0.21405471 | ... M121: =M122/M123 -> #DIV/0!
B122: Net profit after tax excluding exceptional items | C122: =Financials_Consol!B99-Financials_Consol!B92 -> 824.17 | D122: =Financials_Consol!C99-Financials_Consol!C92 -> 680.48 | E122: =Financials_Consol!D99-Financials_Consol!D92 -> 489.87 | F122: =Financials_Consol!E99-Financials_Consol!E92 -> 492.16 | G122: =Financials_Consol!F99-Financials_Consol!F92 -> 530.79 | H122: =Financials_Consol!G99-Financials_Consol!G92 -> 565.53 | I122: =Financials_Consol!H99-Financials_Consol!H92 -> 515.81 | J122: =Financials_Consol!I99-Financials_Consol!I92 -> 417.64 | ... M122: =Financials_Consol!L99-Financials_Consol!L92 -> 0
B123: Average equity | C123: =C119 -> 5347.425 | D123: =D119 -> 4694.785 | E123: =E119 -> 4166.06 | F123: =F119 -> 3741.05 | G123: =G119 -> 3284.075 | H123: =H119 -> 2785.36 | I123: =I119 -> 2368.765 | J123: =J119 -> 1951.09 | ... M123: =M119 -> 0
A125: =A121+1 -> 5 | B125: Du Pont model | C125: =C126*C127*C128 -> 0.14967059 | D125: =D126*D127*D128 -> 0.13722372 | E125: =E126*E127*E128 -> 0.10997179 | F125: =F126*F127*F128 -> 0.11943966 | G125: =G126*G127*G128 -> 0.15328617 | H125: =H126*H127*H128 -> 0.19655962 | I125: =I126*I127*I128 -> 0.20188339 | J125: =J126*J127*J128 -> 0.19279925 | ... M125: =M126*M127*M128 -> #DIV/0!
B126: Net profit Margin | C126: =C102 -> 0.072343547 | D126: =D102 -> 0.06644748 | E126: =E102 -> 0.054472657 | F126: =F102 -> 0.061028063 | G126: =G102 -> 0.079358242 | H126: =H102 -> 0.08175116 | I126: =I102 -> 0.065909061 | J126: =J102 -> 0.061523637 | ... M126: =M102 -> #DIV/0!
B127: Asset turnover | C127: =C40 -> 1.3581005 | D127: =D40 -> 1.3944378 | E127: =E40 -> 1.3908353 | F127: =F40 -> 1.3009989 | G127: =G40 -> 1.2104542 | H127: =H40 -> 1.4037598 | I127: =I40 -> 1.6457186 | J127: =J40 -> 1.6176646 | ... M127: =M40 -> #DIV/0!
B128: Financial leverage Ratio | C128: =C82 -> 1.5233678 | D128: =D82 -> 1.4809879 | E128: =E82 -> 1.4515333 | F128: =F82 -> 1.5043263 | G128: =G82 -> 1.5957416 | H128: =H82 -> 1.7128037 | I128: =I82 -> 1.8612294 | J128: =J82 -> 1.9372018 | ... M128: =M82 -> #DIV/0!
A130: VI | B130: Calculation of cash flows
A132: 1 | B132: Free Cash flows to Firm (FCFF) | C132: =SUM(C133:C136) -> 526 | D132: =SUM(D133:D136) -> 237 | E132: =SUM(E133:E136) -> 241 | F132: =SUM(F133:F136) -> 223 | G132: =SUM(G133:G136) -> 310 | H132: =SUM(H133:H136) -> 0
B133: Cash flow from operating activities | C133: ='Common Size Analysis - CFS_Cons'!B45 -> 1532 | D133: ='Common Size Analysis - CFS_Cons'!C45 -> 1057 | E133: ='Common Size Analysis - CFS_Cons'!D45 -> 862 | F133: ='Common Size Analysis - CFS_Cons'!E45 -> 742 | G133: ='Common Size Analysis - CFS_Cons'!F45 -> 621 | H133: ='Common Size Analysis - CFS_Cons'!G45 -> 0
B134: Net Capital Expenditure
B135: Purchase of Fixed assets | C135: ='Common Size Analysis - CFS_Cons'!B65 -> -1053 | D135: ='Common Size Analysis - CFS_Cons'!C65 -> -835 | E135: ='Common Size Analysis - CFS_Cons'!D65 -> -636 | F135: ='Common Size Analysis - CFS_Cons'!E65 -> -529 | G135: ='Common Size Analysis - CFS_Cons'!F65 -> -375 | H135: ='Common Size Analysis - CFS_Cons'!G65 -> 0
B136: Sale of fixed assets | C136: ='Common Size Analysis - CFS_Cons'!B48 -> 47 | D136: ='Common Size Analysis - CFS_Cons'!C48 -> 15 | E136: ='Common Size Analysis - CFS_Cons'!D48 -> 15 | F136: ='Common Size Analysis - CFS_Cons'!E48 -> 10 | G136: ='Common Size Analysis - CFS_Cons'!F48 -> 64 | H136: ='Common Size Analysis - CFS_Cons'!G48 -> 0
B137: Growth in FCF | C137: =(C132-D132)/-D132 -> -1.2194093 | D137: =(D132-E132)/E132 -> -0.01659751 | E137: =(E132-F132)/F132 -> 0.080717489 | F137: =(F132-G132)/(-G132) -> 0.28064516 | G137: =(G132-H132)/H132 -> #DIV/0!
...

Sheet Ratio Analysis
A1: Endurance Technologies
A3: Ratio Analysis
C5: 45717 | D5: 45352 | E5: 44986 | F5: 44621 | G5: 44256 | H5: 43891 | I5: 43525 | J5: 43160 | K5: 42795 | L5: 42430 | M5: 42064
A6: I | B6: Activity Ratios
A8: 1 | B8: Inventory Turnover ratio | C8: =C9/C10 -> 10.97625 | D8: =D9/D10 -> 11.290425 | E8: =E9/E10 -> 11.394168 | F8: =F9/F10 -> 10.796513 | G8: =G9/G10 -> 9.9750067 | H8: =H9/H10 -> 11.151549 | I8: =I9/I10 -> 13.307137 | J8: =J9/J10 -> 12.223688 | ... M8: =M9/M10 -> #DIV/0!
B9: Cost of goods sold (Add power and fuel) | C9: =SUM(Financials_Standalone!B81:B83) -> 5728.45 | D9: =SUM(Financials_Standalone!C81:C83) -> 5140.7 | E9: =SUM(Financials_Standalone!D81:D83) -> 4532.6 | F9: =SUM(Financials_Standalone!E81:E83) -> 3758.32 | G9: =SUM(Financials_Standalone!F81:F83) -> 2969.36 | H9: =SUM(Financials_Standalone!G81:G83)+1272.09/100 -> 3060.0409 | I9: =SUM(Financials_Standalone!H81:H83) -> 3523.73 | J9: =SUM(Financials_Standalone!I81:I83) -> 3029.58 | K9: =SUM(Financials_Standalone!J81:J83) -> 2478 | L9: =SUM(Financials_Standalone!K81:K83) -> 2384.16 | M9: =SUM(Financials_Standalone!L81:L83) -> 0
B10: Average Inventory | C10: =AVERAGE(Financials_Standalone!B41:C41) -> 521.895 | D10: =AVERAGE(Financials_Standalone!C41:D41) -> 455.315 | E10: =AVERAGE(Financials_Standalone!D41:E41) -> 397.8 | F10: =AVERAGE(Financials_Standalone!E41:F41) -> 348.105 | G10: =AVERAGE(Financials_Standalone!F41:G41) -> 297.68 | H10: =AVERAGE(Financials_Standalone!G41:H41) -> 274.405 | I10: =AVERAGE(Financials_Standalone!H41:I41) -> 264.8 | J10: =AVERAGE(Financials_Standalone!I41:J41) -> 247.845 | ... M10: =AVERAGE(Financials_Standalone!L41:M41) -> #DIV/0!
A12: =A8+1 -> 2 | B12: Inventory Days | C12: =C13/C14 -> 33.253616 | D12: =D13/D14 -> 32.328277 | E12: =E13/E14 -> 32.121696 | F12: =F13/F14 -> 33.807213 | G12: =G13/G14 -> 36.591454 | H12: =H13/H14 -> 32.730878 | I12: =I13/I14 -> 27.428889 | J12: =J13/J14 -> 29.860055 | ... M12: =M13/M14 -> #DIV/0!
B13: Number of Days | C13: 365 | D13: 365 | E13: 366 | F13: 365 | G13: 365 | H13: 365 | I13: 365 | J13: 365 | K13: 365 | L13: 365 | M13: 365
B14: Inventory Turnover ratio | C14: =C8 -> 10.97625 | D14: =D8 -> 11.290425 | E14: =E8 -> 11.394168 | F14: =F8 -> 10.796513 | G14: =G8 -> 9.9750067 | H14: =H8 -> 11.151549 | I14: =I8 -> 13.307137 | J14: =J8 -> 12.223688 | ... M14: =M8 -> #DIV/0!
A16: 3 | B16: Receivables Turnover | C16: =C17/C18 -> 8.0394331 | D16: =D17/D18 -> 8.2107613 | E16: =E17/E18 -> 8.2035893 | F16: =F17/F18 -> 7.0613411 | G16: =G17/G18 -> 7.4215211 | H16: =H17/H18 -> 8.4526923 | I16: =I17/I18 -> 7.7318833 | J16: =J17/J18 -> 7.7922616 | ... M16: =M17/M18 -> #DIV/0!
B17: Revenue | C17: =Financials_Standalone!B77 -> 8846.15 | D17: =Financials_Standalone!C77 -> 7871 | E17: =Financials_Standalone!D77 -> 6767.51 | F17: =Financials_Standalone!E77 -> 5697.09 | G17: =Financials_Standalone!F77 -> 4773.04 | H17: =Financials_Standalone!G77 -> 4938.57 | I17: =Financials_Standalone!H77 -> 5417.46 | J17: =Financials_Standalone!I77 -> 4641.11 | ... M17: =Financials_Standalone!L77 -> 0
B18: Average Receivables | C18: =AVERAGE(Financials_Standalone!B42:C42) -> 1100.345 | D18: =AVERAGE(Financials_Standalone!C42:D42) -> 958.62 | E18: =AVERAGE(Financials_Standalone!D42:E42) -> 824.945 | F18: =AVERAGE(Financials_Standalone!E42:F42) -> 806.8 | G18: =AVERAGE(Financials_Standalone!F42:G42) -> 643.135 | H18: =AVERAGE(Financials_Standalone!G42:H42) -> 584.26 | I18: =AVERAGE(Financials_Standalone!H42:I42) -> 700.665 | J18: =AVERAGE(Financials_Standalone!I42:J42) -> 595.605 | ... M18: =AVERAGE(Financials_Standalone!L42:M42) -> #DIV/0!
A20: =A16+1 -> 4 | B20: Days of sales outstanding | C20: =C21/C22 -> 45.401211 | D20: =D21/D22 -> 44.453856 | E20: =E21/E22 -> 44.614617 | F20: =F21/F22 -> 51.689898 | G20: =G21/G22 -> 49.181292 | H20: =H21/H22 -> 43.181508 | I20: =I21/I22 -> 47.207128 | J20: =J21/J22 -> 46.841343 | ... M20: =M21/M22 -> #DIV/0!
B21: Number of Days | C21: 365 | D21: 365 | E21: 366 | F21: 365 | G21: 365 | H21: 365 | I21: 365 | J21: 365 | K21: 365 | L21: 365 | M21: 365
B22: Receivables Turnover | C22: =C16 -> 8.0394331 | D22: =D16 -> 8.2107613 | E22: =E16 -> 8.2035893 | F22: =F16 -> 7.0613411 | G22: =G16 -> 7.4215211 | H22: =H16 -> 8.4526923 | I22: =I16 -> 7.7318833 | J22: =J16 -> 7.7922616 | ... M22: =M16 -> #DIV/0!
A24: =A20+1 -> 5 | B24: Payables Turnover | C24: =C25/C26 -> 7.6829039 | D24: =D25/D26 -> 8.2737032 | E24: =E25/E26 -> 8.2683011 | F24: =F25/F26 -> 7.1128439 | G24: =G25/G26 -> 6.4380556 | H24: =H25/H26 -> 6.6786872 | I24: =I25/I26 -> 7.0194524 | J24: =J25/J26 -> 7.2898289 | ... M24: =M25/M26 -> #DIV/0!
B25: Cost of Goods Sold | C25: =C9 -> 5728.45 | D25: =D9 -> 5140.7 | E25: =E9 -> 4532.6 | F25: =F9 -> 3758.32 | G25: =G9 -> 2969.36 | H25: =H9 -> 3060.0409 | I25: =I9 -> 3523.73 | J25: =J9 -> 3029.58 | ... M25: =M9 -> 0
B26: Average trade payables | C26: =AVERAGE(Financials_Standalone!B21:C21) -> 745.61 | D26: =AVERAGE(Financials_Standalone!C21:D21) -> 621.33 | E26: =AVERAGE(Financials_Standalone!D21:E21) -> 548.19 | F26: =AVERAGE(Financials_Standalone!E21:F21) -> 528.385 | G26: =AVERAGE(Financials_Standalone!F21:G21) -> 461.22 | H26: =AVERAGE(Financials_Standalone!G21:H21) -> 458.18 | I26: =AVERAGE(Financials_Standalone!H21:I21) -> 501.995 | J26: =AVERAGE(Financials_Standalone!I21:J21) -> 415.59 | ... M26: =AVERAGE(Financials_Standalone!L21:M21) -> #DIV/0!
A28: =A24+1 -> 6 | B28: Payables days | C28: =C29/C30 -> 47.508078 | D28: =D29/D30 -> 44.115675 | E28: =E29/E30 -> 44.144498 | F28: =F29/F30 -> 51.315621 | G28: =G29/G30 -> 56.694136 | H28: =H29/H30 -> 54.651459 | I28: =I29/I30 -> 51.998358 | J28: =J29/J30 -> 50.069762 | ... M28: =M29/M30 -> #DIV/0!
B29: Number of Days | C29: 365 | D29: 365 | E29: 365 | F29: 365 | G29: 365 | H29: 365 | I29: 365 | J29: 365 | K29: 365 | L29: 365 | M29: 365
B30: Payables Turnover | C30: =C24 -> 7.6829039 | D30: =D24 -> 8.2737032 | E30: =E24 -> 8.2683011 | F30: =F24 -> 7.1128439 | G30: =G24 -> 6.4380556 | H30: =H24 -> 6.6786872 | I30: =I24 -> 7.0194524 | J30: =J24 -> 7.2898289 | ... M30: =M24 -> #DIV/0!
A32: =A24+1 -> 6 | B32: Working Capital Turnover | C32: =C33/C34 -> 6.1545927 | D32: =D33/D34 -> 6.8139812 | E32: =E33/E34 -> 6.9084775 | F32: =F33/F34 -> 6.2520878 | G32: =G33/G34 -> 8.0727949 | H32: =H33/H34 -> 8.3806849 | I32: =I33/I34 -> 11.125519 | J32: =J33/J34 -> 11.415841 | ... M32: =M33/M34 -> #DIV/0!
B33: Revenue | C33: =C17 -> 8846.15 | D33: =D17 -> 7871 | E33: =E17 -> 6767.51 | F33: =F17 -> 5697.09 | G33: =G17 -> 4773.04 | H33: =H17 -> 4938.57 | I33: =I17 -> 5417.46 | J33: =J17 -> 4641.11 | ... M33: =M17 -> 0
B34: Average working capital | C34: =(Financials_Standalone!B46-Financials_Standalone!B24+Financials_Standalone!C46-Financials_Standalone!C24)/2 -> 1437.325 | D34: =(Financials_Standalone!C46-Financials_Standalone!C24+Financials_Standalone!D46-Financials_Standalone!D24)/2 -> 1155.125 | E34: =(Financials_Standalone!D46-Financials_Standalone!D24+Financials_Standalone!E46-Financials_Standalone!E24)/2 -> 979.595 | F34: =(Financials_Standalone!E46-Financials_Standalone!E24+Financials_Standalone!F46-Financials_Standalone!F24)/2 -> 911.23 | G34: =(Financials_Standalone!F46-Financials_Standalone!F24+Financials_Standalone!G46-Financials_Standalone!G24)/2 -> 591.25 | H34: =(Financials_Standalone!G46-Financials_Standalone!G24+Financials_Standalone!H46-Financials_Standalone!H24) -> 589.28 | I34: =(Financials_Standalone!H46-Financials_Standalone!H24+Financials_Standalone!I46-Financials_Standalone!I24) -> 486.94 | J34: =(Financials_Standalone!I46-Financials_Standalone!I24+Financials_Standalone!J46-Financials_Standalone!J24) -> 406.55 | K34: =(Financials_Standalone!J46-Financials_Standalone!J24+Financials_Standalone!K46-Financials_Standalone!K24) -> 249.89 | L34: =(Financials_Standalone!K46-Financials_Standalone!K24+Financials_Standalone!L46-Financials_Standalone!L24) -> 73.72 | M34: =(Financials_Standalone!L46-Financials_Standalone!L24+Financials_Standalone!M46-Financials_Standalone!M24) -> 0
A36: =A32+1 -> 7 | B36: Fixed Asset Turnover | C36: =C37/C38 -> 4.256835 | D36: =D37/D38 -> 4.2215977 | E36: =E37/E38 -> 3.9096634 | F36: =F37/F38 -> 3.6272642 | G36: =G37/G38 -> 3.1539044 | H36: =H37/H38 -> 3.5243403 | I36: =I37/I38 -> 4.7499496 | J36: =J37/J38 -> 4.8905011 | ... M36: =M37/M38 -> #DIV/0!
B37: Revenue | C37: =C17 -> 8846.15 | D37: =D17 -> 7871 | E37: =E17 -> 6767.51 | F37: =F17 -> 5697.09 | G37: =G17 -> 4773.04 | H37: =H17 -> 4938.57 | I37: =I17 -> 5417.46 | J37: =J17 -> 4641.11 | ... M37: =M17 -> 0
B38: Average Net fixed assets | C38: =AVERAGE(Financials_Standalone!B33:C33) -> 2078.105 | D38: =AVERAGE(Financials_Standalone!C33:D33) -> 1864.46 | E38: =AVERAGE(Financials_Standalone!D33:E33) -> 1730.97 | F38: =AVERAGE(Financials_Standalone!E33:F33) -> 1570.63 | G38: =AVERAGE(Financials_Standalone!F33:G33) -> 1513.375 | H38: =AVERAGE(Financials_Standalone!G33:H33) -> 1401.275 | I38: =AVERAGE(Financials_Standalone!H33:I33) -> 1140.53 | J38: =AVERAGE(Financials_Standalone!I33:J33) -> 949.005 | ... M38: =AVERAGE(Financials_Standalone!L33:M33) -> 0
A40: =A36+1 -> 8 | B40: Total Asset turnover | C40: =C41/C42 -> 1.7549761 | D40: =D41/D42 -> 1.7900109 | E40: =E41/E42 -> 1.7245623 | F40: =F41/F42 -> 1.5875987 | G40: =G41/G42 -> 1.486801 | H40: =H41/H42 -> 1.6624152 | I40: =I41/I42 -> 1.9473047 | J40: =J41/J42 -> 1.9116486 | ... M40: =M41/M42 -> #DIV/0!
B41: Revenue | C41: =C17 -> 8846.15 | D41: =D17 -> 7871 | E41: =E17 -> 6767.51 | F41: =F17 -> 5697.09 | G41: =G17 -> 4773.04 | H41: =H17 -> 4938.57 | I41: =I17 -> 5417.46 | J41: =J17 -> 4641.11 | ... M41: =M17 -> 0
B42: Average total assets | C42: =AVERAGE(Financials_Standalone!B47:C47) -> 5040.61 | D42: =AVERAGE(Financials_Standalone!C47:D47) -> 4397.18 | E42: =AVERAGE(Financials_Standalone!D47:E47) -> 3924.19 | F42: =AVERAGE(Financials_Standalone!E47:F47) -> 3588.495 | G42: =AVERAGE(Financials_Standalone!F47:G47) -> 3210.275 | H42: =AVERAGE(Financials_Standalone!G47:H47) -> 2970.72 | I42: =AVERAGE(Financials_Standalone!H47:I47) -> 2782.03 | J42: =AVERAGE(Financials_Standalone!I47:J47) -> 2427.805 | ... M42: =AVERAGE(Financials_Standalone!L47:M47) -> 0
A45: II | B45: Liquidity Ratios
A47: 1 | B47: Current ratio | C47: =C48/C49 -> 2.5537534 | D47: =D48/D49 -> 2.5696584 | E47: =E48/E49 -> 2.3328875 | F47: =F48/F49 -> 2.4021421 | G47: =G48/G49 -> 2.2198441 | H47: =H48/H49 -> 1.5299102 | I47: =I48/I49 -> 1.3021695 | J47: =J48/J49 -> 1.2872676 | ... M47: =M48/M49 -> #DIV/0!
B48: Current assets | C48: =Financials_Standalone!B46 -> 2549.08 | D48: =Financials_Standalone!C46 -> 2167.07 | E48: =Financials_Standalone!D46 -> 1726.64 | F48: =Financials_Standalone!E46 -> 1666.39 | G48: =Financials_Standalone!F46 -> 1546.41 | H48: =Financials_Standalone!G46 -> 960.6 | I48: =Financials_Standalone!H46 -> 1105.62 | J48: =Financials_Standalone!I46 -> 1032.35 | ... M48: =Financials_Standalone!L46 -> 0
B49: Current liabilities | C49: =Financials_Standalone!B24 -> 998.17 | D49: =Financials_Standalone!C24 -> 843.33 | E49: =Financials_Standalone!D24 -> 740.13 | F49: =Financials_Standalone!E24 -> 693.71 | G49: =Financials_Standalone!F24 -> 696.63 | H49: =Financials_Standalone!G24 -> 627.88 | I49: =Financials_Standalone!H24 -> 849.06 | J49: =Financials_Standalone!I24 -> 801.97 | ... M49: =Financials_Standalone!L24 -> 0
A51: =A47+1 -> 2 | B51: Quick Ratio | C51: =C52/C53 -> 1.9906429 | D51: =D52/D53 -> 1.9984585 | E51: =E52/E53 -> 1.7533677 | F51: =F52/F53 -> 1.8735639 | G51: =G52/G53 -> 1.7468096 | H51: =H52/H53 -> 1.1065331 | I51: =I52/I53 -> 0.96888324 | J51: =J52/J53 -> 0.97974987 | ... M51: =M52/M53 -> #DIV/0!
B52: Current assets - Inventory | C52: =Financials_Standalone!B46-Financials_Standalone!B41 -> 1987 | D52: =Financials_Standalone!C46-Financials_Standalone!C41 -> 1685.36 | E52: =Financials_Standalone!D46-Financials_Standalone!D41 -> 1297.72 | F52: =Financials_Standalone!E46-Financials_Standalone!E41 -> 1299.71 | G52: =Financials_Standalone!F46-Financials_Standalone!F41 -> 1216.88 | H52: =Financials_Standalone!G46-Financials_Standalone!G41 -> 694.77 | I52: =Financials_Standalone!H46-Financials_Standalone!H41 -> 822.64 | J52: =Financials_Standalone!I46-Financials_Standalone!I41 -> 785.73 | ... M52: =Financials_Standalone!L46-Financials_Standalone!L41 -> 0
B53: Current liabilities | C53: =Financials_Standalone!B24 -> 998.17 | D53: =Financials_Standalone!C24 -> 843.33 | E53: =Financials_Standalone!D24 -> 740.13 | F53: =Financials_Standalone!E24 -> 693.71 | G53: =Financials_Standalone!F24 -> 696.63 | H53: =Financials_Standalone!G24 -> 627.88 | I53: =Financials_Standalone!H24 -> 849.06 | J53: =Financials_Standalone!I24 -> 801.97 | ... M53: =Financials_Standalone!L24 -> 0
A55: =A51+1 -> 3 | B55: Cash Ratio | C55: =C56/C57 -> 0.85631706 | D55: =D56/D57 -> 0.73152858 | E55: =E56/E57 -> 0.60654209 | F55: =F56/F57 -> 0.71877297 | G55: =G56/G57 -> 0.58046596 | H55: =H56/H57 -> 0.35199401 | I55: =I56/I57 -> 0.15061362 | J55: =J56/J57 -> 0.098706934 | ... M55: =M56/M57 -> #DIV/0!
B56: Current assets - Inventory - receivables | C56: =Financials_Standalone!B46-Financials_Standalone!B41-Financials_Standalone!B42 -> 854.75 | D56: =Financials_Standalone!C46-Financials_Standalone!C41-Financials_Standalone!C42 -> 616.92 | E56: =Financials_Standalone!D46-Financials_Standalone!D41-Financials_Standalone!D42 -> 448.92 | F56: =Financials_Standalone!E46-Financials_Standalone!E41-Financials_Standalone!E42 -> 498.62 | G56: =Financials_Standalone!F46-Financials_Standalone!F41-Financials_Standalone!F42 -> 404.37 | H56: =Financials_Standalone!G46-Financials_Standalone!G41-Financials_Standalone!G42 -> 221.01 | I56: =Financials_Standalone!H46-Financials_Standalone!H41-Financials_Standalone!H42 -> 127.88 | J56: =Financials_Standalone!I46-Financials_Standalone!I41-Financials_Standalone!I42 -> 79.16 | ... M56: =Financials_Standalone!L46-Financials_Standalone!L41-Financials_Standalone!L42 -> 0
B57: Current liabilities | C57: =Financials_Standalone!B24 -> 998.17 | D57: =Financials_Standalone!C24 -> 843.33 | E57: =Financials_Standalone!D24 -> 740.13 | F57: =Financials_Standalone!E24 -> 693.71 | G57: =Financials_Standalone!F24 -> 696.63 | H57: =Financials_Standalone!G24 -> 627.88 | I57: =Financials_Standalone!H24 -> 849.06 | J57: =Financials_Standalone!I24 -> 801.97 | ... M57: =Financials_Standalone!L24 -> 0
A59: =A55+1 -> 4 | B59: Cash conversion cycle | C59: =C60+C61-C62 -> 31.146749 | D59: =D60+D61-D62 -> 32.666458 | E59: =E60+E61-E62 -> 32.591816 | F59: =F60+F61-F62 -> 34.18149 | G59: =G60+G61-G62 -> 29.07861 | H59: =H60+H61-H62 -> 21.260927 | I59: =I60+I61-I62 -> 22.637659 | J59: =J60+J61-J62 -> 26.631636 | ... M59: =M60+M61-M62 -> #DIV/0!
B60: Inventory Days | C60: =C12 -> 33.253616 | D60: =D12 -> 32.328277 | E60: =E12 -> 32.121696 | F60: =F12 -> 33.807213 | G60: =G12 -> 36.591454 | H60: =H12 -> 32.730878 | I60: =I12 -> 27.428889 | J60: =J12 -> 29.860055 | ... M60: =M12 -> #DIV/0!
B61: Receivable Days | C61: =C20 -> 45.401211 | D61: =D20 -> 44.453856 | E61: =E20 -> 44.614617 | F61: =F20 -> 51.689898 | G61: =G20 -> 49.181292 | H61: =H20 -> 43.181508 | I61: =I20 -> 47.207128 | J61: =J20 -> 46.841343 | ... M61: =M20 -> #DIV/0!
B62: Payable days | C62: =C28 -> 47.508078 | D62: =D28 -> 44.115675 | E62: =E28 -> 44.144498 | F62: =F28 -> 51.315621 | G62: =G28 -> 56.694136 | H62: =H28 -> 54.651459 | I62: =I28 -> 51.998358 | J62: =J28 -> 50.069762 | ... M62: =M28 -> #DIV/0!
A64: III | B64: Solvency Ratios
A66: 1 | B66: Debts- asset ratio ( Both short term and long term) | C66: =C67/C68 -> 0 | D66: =D67/D68 -> 0 | E66: =E67/E68 -> 0.0048673051 | F66: =F67/F68 -> 0.0084774092 | G66: =G67/G68 -> 0.013884525 | H66: =H67/H68 -> 0.050414703 | I66: =I67/I68 -> 0.072663728 | J66: =J67/J68 -> 0.070324044 | ... M66: =M67/M68 -> #DIV/0!
B67: Total Debt (Short- term and long term) | C67: =Financials_Standalone!B14+Financials_Standalone!B20 -> 0 | D67: =Financials_Standalone!C14+Financials_Standalone!C20 -> 0 | E67: =Financials_Standalone!D14+Financials_Standalone!D20 -> 20 | F67: =Financials_Standalone!E14+Financials_Standalone!E20 -> 31.7 | G67: =Financials_Standalone!F14+Financials_Standalone!F20 -> 47.73 | H67: =Financials_Standalone!G14+Financials_Standalone!G20 -> 150.38 | I67: =Financials_Standalone!H14+Financials_Standalone!H20 -> 214.98 | J67: =Financials_Standalone!I14+Financials_Standalone!I20 -> 183.23 | ... M67: =Financials_Standalone!L14+Financials_Standalone!L20 -> 0
B68: Total Assets | C68: =Financials_Standalone!B25 -> 5395.9 | D68: =Financials_Standalone!C25 -> 4685.31 | E68: =Financials_Standalone!D25 -> 4109.05 | F68: =Financials_Standalone!E25 -> 3739.35 | G68: =Financials_Standalone!F25 -> 3437.64 | H68: =Financials_Standalone!G25 -> 2982.86 | I68: =Financials_Standalone!H25 -> 2958.56 | J68: =Financials_Standalone!I25 -> 2605.51 | ... M68: =Financials_Standalone!L25 -> 0
A70: =A66+1 -> 2 | B70: Debts- asset ratio (long term) | C70: =C71/C72 -> 0 | D70: =D71/D72 -> 0 | E70: =E71/E72 -> 0 | F70: =F71/F72 -> 0 | G70: =G71/G72 -> 0.00079414947 | H70: =H71/H72 -> 0.0014348645 | I70: =I71/I72 -> 0.0010072468 | J70: =J71/J72 -> 0.001903658 | ... M70: =M71/M72 -> #DIV/0!
B71: Total Debt (long term) | C71: =Financials_Standalone!B14 -> 0 | D71: =Financials_Standalone!C14 -> 0 | E71: =Financials_Standalone!D14 -> 0 | F71: =Financials_Standalone!E14 -> 0 | G71: =Financials_Standalone!F14 -> 2.73 | H71: =Financials_Standalone!G14 -> 4.28 | I71: =Financials_Standalone!H14 -> 2.98 | J71: =Financials_Standalone!I14 -> 4.96 | ... M71: =Financials_Standalone!L14 -> 0
B72: Total Assets | C72: =Financials_Standalone!B25 -> 5395.9 | D72: =Financials_Standalone!C25 -> 4685.31 | E72: =Financials_Standalone!D25 -> 4109.05 | F72: =Financials_Standalone!E25 -> 3739.35 | G72: =Financials_Standalone!F25 -> 3437.64 | H72: =Financials_Standalone!G25 -> 2982.86 | I72: =Financials_Standalone!H25 -> 2958.56 | J72: =Financials_Standalone!I25 -> 2605.51 | ... M72: =Financials_Standalone!L25 -> 0
A74: =A70+1 -> 3 | B74: Debt to capital | C74: =C75/C76 -> 0 | D74: =D75/D76 -> 0 | E74: =E75/E76 -> 0.0059684745 | F74: =F75/F76 -> 0.010432608 | G74: =G75/G76 -> 0.017318703 | H74: =H75/H76 -> 0.060953168 | I74: =I75/I76 -> 0.09367606 | J74: =J75/J76 -> 0.092751672 | ... M74: =M75/M76 -> #DIV/0!
B75: Total Debt (Short- term and long term) | C75: =Financials_Standalone!B14+Financials_Standalone!B20 -> 0 | D75: =Financials_Standalone!C14+Financials_Standalone!C20 -> 0 | E75: =Financials_Standalone!D14+Financials_Standalone!D20 -> 20 | F75: =Financials_Standalone!E14+Financials_Standalone!E20 -> 31.7 | G75: =Financials_Standalone!F14+Financials_Standalone!F20 -> 47.73 | H75: =Financials_Standalone!G14+Financials_Standalone!G20 -> 150.38 | I75: =Financials_Standalone!H14+Financials_Standalone!H20 -> 214.98 | J75: =Financials_Standalone!I14+Financials_Standalone!I20 -> 183.23 | ... M75: =Financials_Standalone!L14+Financials_Standalone!L20 -> 0
