Workbook

Sheet 01_Client_Info
A1: SW INDIA - FINANCIAL STATEMENT PREPARATION ENGAGEMENT METADATA
A3: Client / Entity Name | B3: Apex Engineering Industries Limited
A4: Entity Classification | B4: Private Limited Company
A5: Current Reporting Period | B5: 31st March 2026
A6: Previous Year Period | B6: 31st March 2025
A7: Reporting Currency & Denomination | B7: INR (in Lakhs)
A8: Accounting Framework | B8: IGAAP
A9: Schedule Format | B9: Schedule III Division I
A10: Prepared By (Audit Staff) | B10: Amit Kumar (CA Audit Lead)
A11: Reviewed By (Audit Partner) | B11: R. K. Sharma (Audit Partner)
A12: Workbook Generation Timestamp | B12: 2026-08-13 13:51:59
A13: Localhost System Security | B13: 100% Confidential (Zero External Egress)

Sheet 02_Trial_Balance
A1: Ledger Code | B1: Ledger Name | C1: Original Group | D1: Current Year Amount | E1: Previous Year Amount | F1: Type
A2: 1001 | B2: Equity Share Capital | C2: Share Capital | D2: -500 | E2: -500 | F2: Credit
A3: 1002 | B3: General Reserve | C3: Reserves & Surplus | D3: -250 | E3: -200 | F3: Credit
A4: 1003 | B4: Retained Earnings P&L | C4: Reserves & Surplus | D4: -320 | E4: -180 | F4: Credit
A5: 2001 | B5: HDFC Bank Term Loan | C5: Long Term Borrowings | D5: -400 | E5: -450 | F5: Credit
A6: 2002 | B6: ICICI Cash Credit | C6: Short Term Borrowings | D6: -150 | E6: -120 | F6: Credit
A7: 2003 | B7: Trade Creditors for Goods | C7: Trade Payables | D7: -280 | E7: -240 | F7: Credit
A8: 2004 | B8: GST Payable & Statutory Dues | C8: Other Current Liabilities | D8: -45 | E8: -35 | F8: Credit
A9: 3001 | B9: Factory Building & Land | C9: Property Plant Equipment | D9: 750 | E9: 700 | F9: Debit
A10: 3002 | B10: Plant and Machinery | C10: Property Plant Equipment | D10: 420 | E10: 380 | F10: Debit
A11: 3003 | B11: Capital Work in Progress - Plant Expansion | C11: CWIP | D11: 110 | E11: 60 | F11: Debit
A12: 3004 | B12: Inventories - Raw Material & Finished Goods | C12: Inventories | D12: 210 | E12: 190 | F12: Debit
A13: 3005 | B13: Trade Debtors / Customers | C13: Trade Receivables | D13: 340 | E13: 280 | F13: Debit
... A22: 5006 | B22: Current Tax Expense | C22: Tax Expense | D22: 70 | E22: 50 | F22: Debit

Sheet 03_Mapping
A1: Ledger Code | B1: Ledger Name | C1: Original Group | D1: Current Year Amount | E1: Previous Year Amount | F1: Suggested Classification | G1: Final Classification | H1: Financial Statement | I1: Note Number | J1: Current / Non-current | K1: User Override
A2: 1001 | B2: Equity Share Capital | C2: Share Capital | D2: -500 | E2: -500 | F2: Share Capital | G2: Share Capital | H2: Balance Sheet | I2: 4 | J2: Shareholders' Funds | K2: Yes
A3: 1002 | B3: General Reserve | C3: Reserves & Surplus | D3: -250 | E3: -200 | F3: Reserves and Surplus | G3: Reserves and Surplus | H3: Balance Sheet | I3: 5 | J3: Shareholders' Funds | K3: No
A4: 1003 | B4: Retained Earnings P&L | C4: Reserves & Surplus | D4: -320 | E4: -180 | F4: Reserves and Surplus | G4: Reserves and Surplus | H4: Balance Sheet | I4: 5 | J4: Shareholders' Funds | K4: No
A5: 2001 | B5: HDFC Bank Term Loan | C5: Long Term Borrowings | D5: -400 | E5: -450 | F5: Long-term Borrowings | G5: Long-term Borrowings | H5: Balance Sheet | I5: 10 | J5: Non-Current | K5: No
A6: 2002 | B6: ICICI Cash Credit | C6: Short Term Borrowings | D6: -150 | E6: -120 | F6: Short-term Borrowings | G6: Short-term Borrowings | H6: Balance Sheet | I6: 10 | J6: Current | K6: No
A7: 2003 | B7: Trade Creditors for Goods | C7: Trade Payables | D7: -280 | E7: -240 | F7: Trade Payables | G7: Trade Payables | H7: Balance Sheet | I7: 11 | J7: Current | K7: No
A8: 2004 | B8: GST Payable & Statutory Dues | C8: Other Current Liabilities | D8: -45 | E8: -35 | F8: Other Current Liabilities | G8: Other Current Liabilities | H8: Balance Sheet | I8: 11 | J8: Current | K8: No
A9: 3001 | B9: Factory Building & Land | C9: Property Plant Equipment | D9: 750 | E9: 700 | F9: Property, Plant and Equipment | G9: Property, Plant and Equipment | H9: Balance Sheet | I9: 6 | J9: Non-Current | K9: No
A10: 3002 | B10: Plant and Machinery | C10: Property Plant Equipment | D10: 420 | E10: 380 | F10: Property, Plant and Equipment | G10: Property, Plant and Equipment | H10: Balance Sheet | I10: 6 | J10: Non-Current | K10: No
A11: 3003 | B11: Capital Work in Progress - Plant Expansion | C11: CWIP | D11: 110 | E11: 60 | F11: Capital Work-in-Progress | G11: Capital Work-in-Progress | H11: Balance Sheet | I11: 7 | J11: Non-Current | K11: No
A12: 3004 | B12: Inventories - Raw Material & Finished Goods | C12: Inventories | D12: 210 | E12: 190 | F12: Inventories | G12: Inventories | H12: Balance Sheet | I12: 9 | J12: Current | K12: No
A13: 3005 | B13: Trade Debtors / Customers | C13: Trade Receivables | D13: 340 | E13: 280 | F13: Trade Receivables | G13: Trade Receivables | H13: Balance Sheet | I13: 8 | J13: Current | K13: No
... A22: 5006 | B22: Current Tax Expense | C22: Tax Expense | D22: 70 | E22: 50 | F22: Tax Expense | G22: Tax Expense | H22: Profit & Loss | I22: 12 | J22: P&L Tax | K22: No

Sheet 04_AR_Ageing
A1: Customer Code | B1: Customer Name | C1: Related Party Yes/No | D1: Outstanding Amount | E1: Not Due | F1: Less Than 6 Months | G1: 6 Months to 1 Year | H1: 1 to 2 Years | I1: 2 to 3 Years | J1: More Than 3 Years | K1: Disputed Yes/No | L1: Considered Good/Doubtful | M1: Previous Year Outstanding
A2: C001 | B2: Apex Engineering Ltd | C2: No | D2: 150 | E2: 90 | F2: 40 | G2: 20 | H2: 0 | I2: 0 | J2: 0 | K2: No | L2: Considered Good | M2: 120
A3: C002 | B3: Zenith Infra Infra Corp | C3: No | D3: 110 | E3: 40 | F3: 30 | G3: 25 | H3: 15 | I3: 0 | J3: 0 | K3: No | L3: Considered Good | M3: 90
A4: C003 | B4: Global Logistics Pvt Ltd (Related Party) | C4: Yes | D4: 80 | E4: 30 | F4: 20 | G4: 15 | H4: 15 | I4: 0 | J4: 0 | K4: No | L4: Considered Good | M4: 70

Sheet 05_AP_Ageing
A1: Vendor Code | B1: Vendor Name | C1: MSME Yes/No | D1: Related Party Yes/No | E1: Outstanding Amount | F1: Not Due | G1: Less Than 1 Year | H1: 1 to 2 Years | I1: 2 to 3 Years | J1: More Than 3 Years | K1: Disputed Yes/No | L1: Previous Year Outstanding
A2: V001 | B2: Bharat Steel Suppliers (MSME) | C2: Yes | D2: No | E2: 120 | F2: 80 | G2: 35 | H2: 5 | I2: 0 | J2: 0 | K2: No | L2: 100
A3: V002 | B3: National Chemicals Ltd | C3: No | D3: No | E3: 160 | F3: 110 | G3: 50 | H3: 0 | I3: 0 | J3: 0 | K3: No | L3: 140

Sheet 06_CWIP_Ageing
A1: Project Name | B1: Opening CWIP | C1: Additions During Year | D1: Capitalised During Year | E1: Closing CWIP | F1: Less Than 1 Year | G1: 1 to 2 Years | H1: 2 to 3 Years | I1: More Than 3 Years | J1: Completion Status | K1: Reason for Delay
A2: Phase II Factory Unit Expansion | B2: 60 | C2: 50 | D2: 0 | E2: 110 | F2: 50 | G2: 35 | H2: 25 | I2: 0 | J2: In Progress | K2: Environmental approval delay from local authorities

Sheet 07_Related_Party
A1: Related Party Name | B1: Relationship | C1: Nature of Transaction | D1: Opening Balance | E1: Debit Transactions | F1: Credit Transactions | G1: Closing Balance | H1: Receivable/Payable/Income/Expense | I1: Terms and Conditions | J1: Previous Year Closing Balance
A2: Global Logistics Pvt Ltd | B2: Associate Enterprise | C2: Freight & Warehousing Services | D2: 70 | E2: 120 | F2: 110 | G2: 80 | H2: Receivable | I2: Arm's Length Basis | J2: 70

Sheet 08_Borrowings
A1: Lender Name | B1: Loan Type | C1: Secured/Unsecured | D1: Current/Non-current | E1: Opening Balance | F1: Additions | G1: Repayments | H1: Closing Balance | I1: Interest Rate | J1: Security Details | K1: Repayment Terms | L1: Default Yes/No | M1: Default Amount | N1: Previous Year Closing Balance
A2: HDFC Bank Ltd | B2: Term Loan | C2: Secured | D2: Non-current | E2: 450 | F2: 0 | G2: 50 | H2: 400 | I2: 8.50% p.a. | J2: Hypothecation of Factory Building & Machinery | K2: 60 monthly installments | L2: No | M2: 0 | N2: 450
A3: ICICI Bank Ltd | B3: Cash Credit | C3: Secured | D3: Current | E3: 120 | F3: 30 | G3: 0 | H3: 150 | I3: 9.25% p.a. | J3: Hypothecation of Stock & Receivables | K3: On Demand | L3: No | M3: 0 | N3: 120

Sheet 09_Contingencies
A1: Nature of Contingency | B1: Forum/Authority | C1: Current Year Amount | D1: Previous Year Amount | E1: Management Assessment | F1: Whether Provision Required | G1: Remarks
A2: Disputed GST Penalty Assessment | B2: GST Appellate Authority | C2: 35 | D2: 35 | E2: High probability of favorable decision based on legal counsel opinion | F2: No | G2: Contested matter pending hearing

Sheet 10_Balance_Sheet
A1: Apex Engineering Industries Limited - BALANCE SHEET AS AT 31st March 2026
A2: (Schedule III Division I - Figures in INR (in Lakhs) | Generated: 2026-08-13 13:51:59)
A3: Particulars | B3: Note No. | C3: As at 31st March 2026 | D3: As at 31st March 2025
A4: EQUITY AND LIABILITIES
A5: 1. Shareholders' Funds | C5: =C5+C6 | D5: =D5+D6
A6: (a) Share Capital | B6: 4 | C6: =ABS(SUMIFS('03_Mapping'!D:D, '03_Mapping'!G:G, "Share Capital")) | D6: =ABS(SUMIFS('03_Mapping'!E:E, '03_Mapping'!G:G, "Share Capital"))
A7: (b) Reserves and Surplus | B7: 5 | C7: =ABS(SUMIFS('03_Mapping'!D:D, '03_Mapping'!G:G, "Reserves and Surplus"))+'11_Profit_and_Loss'!C18 | D7: =ABS(SUMIFS('03_Mapping'!E:E, '03_Mapping'!G:G, "Reserves and Surplus"))+'11_Profit_and_Loss'!D18
A8: 2. Non-Current Liabilities | C8: =C8+C9 | D8: =D8+D9
A9: (a) Long-term Borrowings | B9: 10 | C9: =ABS(SUMIFS('03_Mapping'!D:D, '03_Mapping'!G:G, "Long-term Borrowings")) | D9: =ABS(SUMIFS('03_Mapping'!E:E, '03_Mapping'!G:G, "Long-term Borrowings"))
A10: (b) Long-term Provisions | B10: 12 | C10: =ABS(SUMIFS('03_Mapping'!D:D, '03_Mapping'!G:G, "Long-term Provisions")) | D10: =ABS(SUMIFS('03_Mapping'!E:E, '03_Mapping'!G:G, "Long-term Provisions"))
A11: 3. Current Liabilities | C11: =C11+C12+C13+C14 | D11: =D11+D12+D13+D14
A12: (a) Short-term Borrowings | B12: 10 | C12: =ABS(SUMIFS('03_Mapping'!D:D, '03_Mapping'!G:G, "Short-term Borrowings")) | D12: =ABS(SUMIFS('03_Mapping'!E:E, '03_Mapping'!G:G, "Short-term Borrowings"))
A13: (b) Trade Payables | B13: 11 | C13: =ABS(SUMIFS('03_Mapping'!D:D, '03_Mapping'!G:G, "Trade Payables")) | D13: =ABS(SUMIFS('03_Mapping'!E:E, '03_Mapping'!G:G, "Trade Payables"))
A14: (c) Other Current Liabilities | B14: 11 | C14: =ABS(SUMIFS('03_Mapping'!D:D, '03_Mapping'!G:G, "Other Current Liabilities")) | D14: =ABS(SUMIFS('03_Mapping'!E:E, '03_Mapping'!G:G, "Other Current Liabilities"))
A15: (d) Short-term Provisions | B15: 12 | C15: =ABS(SUMIFS('03_Mapping'!D:D, '03_Mapping'!G:G, "Short-term Provisions")) | D15: =ABS(SUMIFS('03_Mapping'!E:E, '03_Mapping'!G:G, "Short-term Provisions"))
A16: TOTAL EQUITY AND LIABILITIES | C16: =C4+C7+C10 | D16: =D4+D7+D10
A17: ASSETS
A18: 1. Non-Current Assets | C18: =C17+C18+C19+C20+C21 | D18: =D17+D18+D19+D20+D21
A19: (a) Property, Plant and Equipment | B19: 6 | C19: =SUMIFS('03_Mapping'!D:D, '03_Mapping'!G:G, "Property, Plant and Equipment") | D19: =SUMIFS('03_Mapping'!E:E, '03_Mapping'!G:G, "Property, Plant and Equipment")
A20: (b) Capital Work-in-Progress | B20: 7 | C20: =SUMIFS('03_Mapping'!D:D, '03_Mapping'!G:G, "Capital Work-in-Progress") | D20: =SUMIFS('03_Mapping'!E:E, '03_Mapping'!G:G, "Capital Work-in-Progress")
A21: (c) Non-current Investments | B21: 9 | C21: =SUMIFS('03_Mapping'!D:D, '03_Mapping'!G:G, "Non-current Investments") | D21: =SUMIFS('03_Mapping'!E:E, '03_Mapping'!G:G, "Non-current Investments")
A22: (d) Long-term Loans and Advances | B22: 9 | C22: =SUMIFS('03_Mapping'!D:D, '03_Mapping'!G:G, "Long-term Loans and Advances") | D22: =SUMIFS('03_Mapping'!E:E, '03_Mapping'!G:G, "Long-term Loans and Advances")
A23: (e) Other Non-current Assets | B23: 9 | C23: =SUMIFS('03_Mapping'!D:D, '03_Mapping'!G:G, "Other Non-current Assets") | D23: =SUMIFS('03_Mapping'!E:E, '03_Mapping'!G:G, "Other Non-current Assets")
A24: 2. Current Assets | C24: =C23+C24+C25+C26+C27 | D24: =D23+D24+D25+D26+D27
A25: (a) Inventories | B25: 9 | C25: =SUMIFS('03_Mapping'!D:D, '03_Mapping'!G:G, "Inventories") | D25: =SUMIFS('03_Mapping'!E:E, '03_Mapping'!G:G, "Inventories")
A26: (b) Trade Receivables | B26: 8 | C26: =SUMIFS('03_Mapping'!D:D, '03_Mapping'!G:G, "Trade Receivables") | D26: =SUMIFS('03_Mapping'!E:E, '03_Mapping'!G:G, "Trade Receivables")
A27: (c) Cash and Bank Balances | B27: 9 | C27: =SUMIFS('03_Mapping'!D:D, '03_Mapping'!G:G, "Cash and Bank Balances") | D27: =SUMIFS('03_Mapping'!E:E, '03_Mapping'!G:G, "Cash and Bank Balances")
A28: (d) Short-term Loans and Advances | B28: 9 | C28: =SUMIFS('03_Mapping'!D:D, '03_Mapping'!G:G, "Short-term Loans and Advances") | D28: =SUMIFS('03_Mapping'!E:E, '03_Mapping'!G:G, "Short-term Loans and Advances")
A29: (e) Other Current Assets | B29: 9 | C29: =SUMIFS('03_Mapping'!D:D, '03_Mapping'!G:G, "Other Current Assets") | D29: =SUMIFS('03_Mapping'!E:E, '03_Mapping'!G:G, "Other Current Assets")
A30: TOTAL ASSETS | C30: =C16+C22 | D30: =D16+D22

Sheet 11_Profit_and_Loss
A1: Apex Engineering Industries Limited - STATEMENT OF PROFIT AND LOSS FOR THE YEAR ENDED 31st March 2026
A2: (Schedule III Division I - Figures in INR (in Lakhs) | Generated: 2026-08-13 13:51:59)
A3: Particulars | B3: Note No. | C3: Year ended 31st March 2026 | D3: Year ended 31st March 2025
A4: I. Revenue from Operations | B4: 13 | C4: =ABS(SUMIFS('03_Mapping'!D:D, '03_Mapping'!G:G, "Revenue from Operations")) | D4: =ABS(SUMIFS('03_Mapping'!E:E, '03_Mapping'!G:G, "Revenue from Operations"))
A5: II. Other Income | B5: 13 | C5: =ABS(SUMIFS('03_Mapping'!D:D, '03_Mapping'!G:G, "Other Income")) | D5: =ABS(SUMIFS('03_Mapping'!E:E, '03_Mapping'!G:G, "Other Income"))
A6: III. Total Income (I + II) | C6: =C4+C5 | D6: =D4+D5
A7: IV. Expenses:
A8: Cost of Materials Consumed | B8: 16 | C8: =SUMIFS('03_Mapping'!D:D, '03_Mapping'!G:G, "Cost of Materials Consumed") | D8: =SUMIFS('03_Mapping'!E:E, '03_Mapping'!G:G, "Cost of Materials Consumed")
A9: Purchases of Stock-in-Trade | B9: 16 | C9: =SUMIFS('03_Mapping'!D:D, '03_Mapping'!G:G, "Purchases of Stock-in-Trade") | D9: =SUMIFS('03_Mapping'!E:E, '03_Mapping'!G:G, "Purchases of Stock-in-Trade")
A10: Changes in Inventories | B10: 16 | C10: =SUMIFS('03_Mapping'!D:D, '03_Mapping'!G:G, "Changes in Inventories") | D10: =SUMIFS('03_Mapping'!E:E, '03_Mapping'!G:G, "Changes in Inventories")
A11: Employee Benefit Expenses | B11: 14 | C11: =SUMIFS('03_Mapping'!D:D, '03_Mapping'!G:G, "Employee Benefit Expenses") | D11: =SUMIFS('03_Mapping'!E:E, '03_Mapping'!G:G, "Employee Benefit Expenses")
A12: Finance Costs | B12: 15 | C12: =SUMIFS('03_Mapping'!D:D, '03_Mapping'!G:G, "Finance Costs") | D12: =SUMIFS('03_Mapping'!E:E, '03_Mapping'!G:G, "Finance Costs")
A13: Depreciation and Amortisation Expense | B13: 6 | C13: =SUMIFS('03_Mapping'!D:D, '03_Mapping'!G:G, "Depreciation and Amortisation Expense") | D13: =SUMIFS('03_Mapping'!E:E, '03_Mapping'!G:G, "Depreciation and Amortisation Expense")
A14: Other Expenses | B14: 16 | C14: =SUMIFS('03_Mapping'!D:D, '03_Mapping'!G:G, "Other Expenses") | D14: =SUMIFS('03_Mapping'!E:E, '03_Mapping'!G:G, "Other Expenses")
A15: Total Expenses (IV) | C15: =SUM(C8:C14) | D15: =SUM(D8:D14)
A16: V. Profit Before Tax (III - IV) | C16: =C6-C15 | D16: =D6-D15
A17: VI. Tax Expense | B17: 12 | C17: =SUMIFS('03_Mapping'!D:D, '03_Mapping'!G:G, "Tax Expense") | D17: =SUMIFS('03_Mapping'!E:E, '03_Mapping'!G:G, "Tax Expense")
A18: VII. Profit After Tax (V - VI) | C18: =C16-C17 | D18: =D16-D17

Sheet 12_Notes_Index
A1: Note Number | B1: Note Title | C1: Status
A2: 1 | B2: Corporate Information | C2: Draft Auto-Generated
A3: 2 | B3: Basis of Preparation | C3: Draft Auto-Generated
A4: 3 | B4: Significant Accounting Policies | C4: Draft Auto-Generated
A5: 4 | B5: Share Capital | C5: Draft Auto-Generated
A6: 5 | B6: Reserves and Surplus | C6: Draft Auto-Generated
A7: 6 | B7: Property, Plant and Equipment | C7: Draft Auto-Generated
A8: 7 | B8: Capital Work-in-Progress Ageing | C8: Modified by Auditor
A9: 8 | B9: Trade Receivables Ageing | C9: Draft Auto-Generated
A10: 9 | B10: Cash and Bank Balances | C10: Draft Auto-Generated
A11: 10 | B11: Borrowings | C11: Draft Auto-Generated
A12: 11 | B12: Trade Payables Ageing | C12: Draft Auto-Generated
... A21: 20 | B21: Previous Year Regrouping | C21: Draft Auto-Generated

Sheet 13_Notes_to_Accounts
A1: Note No. | B1: Note Title | C1: Auditor Draft Note Text | D1: Supporting Schedule Total Formula Link
A2: 1 | B2: Corporate Information | C2: The Company is a private limited company incorporated and domiciled in India under the provisions of the Companies Act. The registered office of the company is situated in India. The Company is primarily engaged in manufacturing and trading operations.
A3: 2 | B3: Basis of Preparation | C3: These financial statements have been prepared in accordance with the Generally Accepted Accounting Principles in India (Indian GAAP) under the historical cost convention on an accrual basis. The financial statements comply in all material respects with the Accounting Standards specified under Section 133 of the Companies Act, 2013 read with Rule 7 of the Companies (Accounts) Rules, 2014 and Schedule III Division I of the Companies Act, 2013.
A4: 3 | B4: Significant Accounting Policies | C4: a) Revenue Recognition: Revenue from sale of goods is recognized on transfer of significant risks and rewards of ownership to the buyer. b) Property, Plant & Equipment: Stated at cost less accumulated depreciation. Depreciation is provided on SLM/WDV basis over useful life. c) Inventories: Valued at lower of cost and net realizable value. d) Employee Benefits: Short-term benefits are recognized as an expense in P&L for the year.
A5: 4 | B5: Share Capital | C5: Authorised Share Capital: Equity Shares of Rs 10/- each. Issued, Subscribed and Fully Paid Up Share Capital: Equity Shares held by promoters and shareholders. Reconciliation of number of shares outstanding at beginning and end of reporting period shows no change.
A6: 5 | B6: Reserves and Surplus | C6: Reserves & Surplus comprises General Reserve and Surplus in Statement of Profit & Loss. Closing balance includes profits transferred for the current reporting financial year.
A7: 6 | B7: Property, Plant and Equipment | C7: Schedule of Property, Plant and Equipment comprises Land, Buildings, Plant & Machinery, Furniture & Fixtures and Vehicles. Gross block, additions, disposals, accumulated depreciation and net block are reconciled as per Schedule III requirements.
A8: 7 | B8: Capital Work-in-Progress Ageing | C8: Capital Work-in-Progress (CWIP) comprises ongoing capital projects for expansion. CWIP ageing is classified into Less than 1 year, 1-2 years, 2-3 years, and More than 3 years. --- SUGGESTED RULE-BASED FOOTNOTES --- Footnote Note 7: Project 'Phase II Factory Unit Expansion' has been in progress for over 2 years (Closing balance: Rs 110.00 Lakhs). Management Note: Environmental approval delay from local authorities. [AUDITOR REMARK: Verified physical inspection of CWIP site on 10-Apr-2026]. | D8: =SUM('06_CWIP_Ageing'!E:E)
A9: 8 | B9: Trade Receivables Ageing | C9: Trade Receivables ageing schedule includes amounts outstanding for Undisputed Considered Good, Undisputed Considered Doubtful, and Disputed Receivables, categorized into Less than 6 months, 6M-1Y, 1-2Y, 2-3Y, and More than 3Y. --- SUGGESTED RULE-BASED FOOTNOTES --- Footnote Note 8: Trade Receivables outstanding for more than 6 months aggregate to Rs 90.00 Lakhs. Management considers these balances fully recoverable and good. | D9: =SUM('04_AR_Ageing'!D:D)
A10: 9 | B10: Cash and Bank Balances | C10: Cash and bank balances consist of cash in hand, balances with scheduled banks in current accounts, and fixed deposits with original maturity of less than 12 months.
A11: 10 | B11: Borrowings | C11: Long-term and Short-term borrowings from banks and financial institutions are secured against hypothecation of tangible fixed assets, stocks and book debts, and personal guarantees of directors. --- SUGGESTED RULE-BASED FOOTNOTES --- Footnote Note 10: The Company has not defaulted in repayment of principal or interest to any bank or financial institution during the year. | D11: =SUM('08_Borrowings'!H:H)
A12: 11 | B12: Trade Payables Ageing | C12: Trade Payables ageing schedule displays outstanding dues to MSME and Non-MSME vendors across Undisputed and Disputed categories for Less than 1 year, 1-2 years, 2-3 years, and More than 3 years. --- SUGGESTED RULE-BASED FOOTNOTES --- Footnote Note 11/12: The Company has outstanding dues of Rs 120.00 Lakhs payable to Micro and Small Enterprises as of reporting date. No interest is payable under MSMED Act 2006. | D12: =SUM('05_AP_Ageing'!E:E)
A13: 12 | B13: MSME Disclosure Placeholder | C13: Disclosures required under Micro, Small and Medium Enterprises Development (MSMED) Act, 2006 regarding principal amount due, interest paid/payable, and interest accrued. --- SUGGESTED RULE-BASED FOOTNOTES --- Footnote Note 11/12: The Company has outstanding dues of Rs 120.00 Lakhs payable to Micro and Small Enterprises as of reporting date. No interest is payable under MSMED Act 2006.
A14: 13 | B14: Revenue from Operations | C14: Revenue from operations comprises sale of products, sale of services, and other operating revenues net of trade discounts and returns.
A15: 14 | B15: Employee Benefit Expenses | C15: Employee benefit expenses include Salaries, Wages & Bonus, Contribution to Provident and Other Funds, and Staff Welfare Expenses.
A16: 15 | B16: Finance Costs | C16: Finance costs consist of interest expense on term loans, working capital facilities, bank charges, and loan processing fees.
A17: 16 | B17: Other Expenses | C17: Other expenses comprise Cost of Raw Materials Consumed, Power & Fuel, Rent, Repairs & Maintenance, Legal & Professional Fees, Payment to Auditors, and Miscellaneous Administrative Expenses.
A18: 17 | B18: Related Party Transactions | C18: Disclosures as per AS 18 Related Party Disclosures: Related party relationships, transactions during the year (purchases, sales, services), and closing balances at year end. --- SUGGESTED RULE-BASED FOOTNOTES --- Footnote Note 17: Related Party transactions were executed during the year with Global Logistics Pvt Ltd on an arm's length basis in ordinary course of business. | D18: =SUM('07_Related_Party'!G:G)
A19: 18 | B19: Contingent Liabilities | C19: Contingent liabilities not provided for in respect of disputed statutory claims, guarantees given, and pending litigations against the company. --- SUGGESTED RULE-BASED FOOTNOTES --- Footnote Note 18: Contingent Liabilities in respect of disputed demands total Rs 35.00 Lakhs. Management expects favorable outcome in appellate forums.
A20: 19 | B20: Ratios | C20: Key financial ratios as mandated under Schedule III Division I (Current Ratio, Debt Equity, Net Profit Margin, Return on Equity, Inventory Turnover, Trade Receivable Turnover, Trade Payable Turnover) along with variance analysis.
A21: 20 | B21: Previous Year Regrouping | C21: Previous year figures have been regrouped, reclassified and rearranged wherever necessary to correspond with current year's classification.

Sheet 14_Ratio_Analysis
A1: Ratio Code | B1: Ratio Name | C1: Formula Definition | D1: CY (31st March 2026) | E1: PY (31st March 2025) | F1: Unit | G1: Movement | H1: SW India Audit Commentary
A2: R01 | B2: Current Ratio | C2: Current Assets / Current Liabilities | D2: 1.67 | E2: 1.76 | F2: times | G2: -5.1% | H2: Satisfactory liquidity buffer (ideal benchmark is 1.5 - 2.0).
A3: R02 | B3: Debt Equity Ratio | C3: Total Debt / Shareholders' Equity | D3: 0.46 | E3: 0.62 | F3: times | G3: -25.8% | H3: Comfortable leverage levels well within benchmark threshold of 2.0.
A4: R03 | B4: Net Profit Ratio | C4: (Net Profit After Tax / Revenue) * 100 | D4: 7.03 | E4: 2.67 | F4: % | G4: +163.3% | H4: Healthy net profit margin of 7.03% driven by cost controls.
A5: R04 | B5: EBITDA Margin | C5: (EBITDA / Revenue) * 100 | D5: 16.92 | E5: 13.47 | F5: % | G5: +25.6% | H5: Strong operating cash margin of 16.92%.
A6: R05 | B6: Return on Equity | C6: (Net Profit After Tax / Equity) * 100 | D6: 10.83 | E6: 4.35 | F6: % | G6: +149.0% | H6: Return on equity is 10.83%.
A7: R06 | B7: Trade Receivable Days | C7: (Trade Receivables / Revenue) * 365 | D7: 67.08 | E7: 68.13 | F7: days | G7: -1.5% | H7: Average collection period is 67.08 days. Prompt collection cycle.
A8: R07 | B8: Trade Payable Days | C8: (Trade Payables / COGS) * 365 | D8: 111.09 | E8: 112.31 | F8: days | G8: -1.1% | H8: Vendor payment turnaround is 111.09 days.
A9: R08 | B9: Inventory Days | C9: (Inventories / COGS) * 365 | D9: 83.32 | E9: 88.91 | F9: days | G9: -6.3% | H9: Inventory holding cycle of 83.32 days.

Sheet 15_Validation_Checks
A1: Check Code | B1: Check Name | C1: Category | D1: Status | E1: Observation Summary | F1: Detailed Audit Trace
A2: V01 | B2: Required Upload Columns Present | C2: Upload | D2: Passed | E2: All mandatory Trial Balance columns identified successfully. | F2: Total 21 ledger lines parsed from upload.
A3: V02 | B3: Blank Ledger Names | C3: Upload | D3: Passed | E3: No blank ledger names found in Trial Balance. | F3: All Trial Balance rows have valid ledger names.
A4: V03 | B4: Unmapped / Fallback Ledgers | C4: Accounting | D4: Warning | E4: 1 ledgers mapped to default fallback. | F4: Verify mapping for unclassified ledgers.
A5: V04 | B5: Balance Sheet Tally Check | C5: Financial | D5: Passed | E5: Total Equity & Liabilities equals Total Assets. | F5: Difference: Rs 0.00 Lakhs.
A6: V05 | B6: Balance Sheet Note Numbers | C6: Disclosure | D6: Passed | E6: All Balance Sheet line items have note references assigned. | F6: All line items mapped to notes.
A7: V06 | B7: Profit & Loss Note Numbers | C7: Disclosure | D7: Passed | E7: All P&L line items have note references assigned. | F7: All line items mapped to notes.
A8: V07 | B8: Previous Year Comparatives Available | C8: Financial | D8: Passed | E8: Previous year comparative figures are populated. | F8: 21 of 21 ledgers have PY figures.
A9: V08 | B9: AR Ageing Schedule Reconciliation | C9: Upload | D9: Passed | E9: AR Ageing schedule uploaded and linked. | F9: AR schedule records: 3.
A10: V09 | B10: AP Ageing Schedule Reconciliation | C10: Upload | D10: Passed | E10: AP Ageing schedule uploaded and linked. | F10: AP schedule records: 2.
A11: V10 | B11: CWIP Ageing Schedule Reconciliation | C11: Upload | D11: Passed | E11: CWIP Ageing schedule uploaded and linked. | F11: CWIP projects: 1.
A12: V11 | B12: Related Party Schedule Uploaded | C12: Upload | D12: Passed | E12: Related Party schedule uploaded. | F12: Related party entries: 1.
... A28: V27 | B28: Raw Material Consumed Mapped to Inventories | C28: Mapping Exception | D28: Passed | E28: No raw material consumed ledgers mapped to Inventories. | F28: Material consumed ledgers must map to P&L Cost of Materials Consumed.

Sheet 16_Management_Queries
A1: Query ID | B1: Category | C1: Audit Observation / Management Query | D1: Management Response / Target Resolution | E1: Status
A2: MQ-01 | B2: CWIP | C2: CWIP project Phase II pending > 2 years. Provide updated project completion schedule and impairment assessment. | E2: Pending
A3: MQ-02 | B3: MSME | C3: Confirm if any interest liability is accrued under MSMED Act 2006 for Bharat Steel Suppliers. | E3: Pending
A4: MQ-03 | B4: RPT | C4: Confirm whether Global Logistics freight service contract is covered under TP documentation and at Arm's length. | E4: Pending
A5: MQ-04 | B5: Receivables | C5: Confirm recoverability of overdue Trade Receivables > 6 months (Rs 80.00 Lakhs). | E5: Pending
